Workbook

Sheet 摘要效果-打分标准
A1: 需求文档：https://ione.rnd.huawei.com/tcloud/main/#/req/viewSr?serialNo=SR000K2TFN
A3: # 具体打分细则
A4: 独立评估以下三个维度，不要受格式和排版的影响，输出结果为1~5范围内的打分：
A5: 1. 准确性
A6: - 独立评估摘要是否忠实于原文事实。核心要求是“不瞎编、不篡改”。
A7: - **以下情况视严重程度扣分：**
A8: 1.1 幻觉：捏造原文不存在的内容。
A9: 1.2 事实错误：错误理解原文内容，将与A相关的内容套到了B上。
A10: 1.3 实体提取错误：关键的专有名词、人名、数值提取错误。
A11: -如果原文存在ASR错误或错别字导致理解有困难，不扣分
A12: 1.4 逻辑错乱：错误解释前因后果或推导过程。
A13: 1.5 其它问题：其它摘要和原文不一致，或与事实不符的问题。
... A49: 4.4 语言风格严重突变（如中英文异常夹杂）。

Sheet 竞品对比
A1: 序号 | B1: 分工 | C1: 原文 | D1: A产品 | E1: 准确性 | F1: 相关性 | G1: 通顺性 | H1: 其它问题 | I1: MOS | J1: 备注 | K1: B产品 | L1: 准确性 | M1: 相关性 | N1: 通顺性 | O1: 其它问题 | P1: MOS | Q1: 备注 | R1: C产品 | S1: 准确性 | T1: 相关性 | U1: 通顺性 | V1: 其它问题 | W1: MOS | X1: 备注
A2: 1 | B2: 黄文涛 | C2: • 发言者 1 00:21 最近呢霍伊斯根主席各位朋友，各位同事，我们所处的是一个更加变乱交织的世界。大家都关心这个世界今后向何处去。借用今年慕安会报告的主题来回答的话，那就是走向多极化。80年前联合国成立时，只有51个会员国，到今天是193个国家，共乘一艘大船。多极化的世界既是历史的必然，也正在成为现实。多极化是否会带来动荡失序，冲突对抗是否意味着大国主导弱肉强食。中国给出的答案是我们应当推动平等有序的世界多极化。这是习近平主席提出的又一个重大主张，也是我们对多极世界真诚的期许。中国必将是多极体系中的确定性因素。将坚定做变革世界中的建设性力量。在此我表达4点看法。一是应当倡导平等相待，列强争霸曾给人类带来灾难。两次世界大战殷鉴不远，殖民体系也罢， • 发言者 1 01:58 中心外围体系也罢，不平等的秩序注定土崩瓦解。世界各国独立自主，风起云涌，国际关系民主法不可阻挡。坚持权利平等机会平等规则平等，应当成为建设多极世界的基本原则。正是秉+D5持这样的原则，中国主张大小国家一律平等，呼吁提升发展中国家在国际体系中的代表性和发言权。这不会导致西方的缺失，而将促进世界的正和慕安会近年来邀请更多全球南方国家出席会议，这是明智之举。每一个国家的声音都应该得到倾听。每一个国家都可以在多极格局中找到自身的位置，发挥自己的作用。二是应当尊重国际法治。中国有句古话没有规矩不成方圆， • 发言者 1 03:06 联合国宪章宗旨和原则是处于国际关系的根本遵循。也是建设多极世界的重要基石。当今世界乱象频出，一个重要原因就是有些国家迷信实力至上，打开了丛林法则的潘多拉盒子。实际上国家不论大小强弱，都是国际法治的利益攸关法。多极格局不能是无序的状态。如果没有了规矩，昨天在餐桌上明天就可能在菜单里大国要带头讲诚信，讲法治，坚决摒弃言行不一。零和博弈。正是基于这样的观点，中国坚定维护国际法治权威，积极履行国际责任和义务。我们加入了几乎所有普遍性的政府间国际组织和600多项国际公约。我们从不搞例外主义， • 发言者 1 04:18 更不搞合则用，不合则弃。我们为当今不确定的世界提供了最大的确定性。我要强调的是在遵守国际法上不能搞双重标准，要尊重各国的主权和领土完整，就应该支持中国实现完全统一。三是要践行多边主义。面对层出不穷的全球性挑战，没有哪一个国家能够独善其身，搞本国优先只会造成各方的多数。联合国是践行多边主义，推进全球治理的核心平台。已经为各国遮风挡雨。80年。未来的多极世界更加需要联合国对于这座大厦，我们应该固本强基，而不是拆梁毁柱。对于治理全球难题应当共担责任， • 发言者 1 05:23 而不是唯利是图。对于共同挑战应该团结应对，而不是阵营对抗。正是本着这样的理念，中国坚持真正的多边主义，倡导共商共建共享的全球治理观。我们坚定维护联合国的权威和地位，承担着超过20%的联合国的会费。我们切实履行巴黎协定，建成了世界上最大的清洁发电体系。我们还提出并落实全球发展倡议，全球安全倡议全球文明倡议，为完善全球治理提供公共产品。4是要坚持开放共赢。发展是破解各种难题的钥匙，多极世界应该是各国共同发展的世界。保护主义不是出路， • 发言者 1 06:28 滥加关税没有赢家。脱钩断链断的是机遇，小院高墙封的是自己。应当坚持开放合作，以普惠包容的经济全球化。来支撑平等有序的世界多极化。正是朝着这样的目标，中国坚定同各国共享发展机遇。有位澳大利亚的学者把中国称为赋能型大国，我认为很形象。去年中国GDP增长5%，对世界经济增长的贡献率接近30%。我们担当起全球经济增长的重要引擎，我们向世界释放超大规模的市场红利。中国愿推动高质量共建一带一路，而且同欧盟的门户全球门户的战略相互对接。赋能彼此也赋能世界。各位朋友， • 发言者 1 07:38 中方始终认为欧洲是多极世界的重要一极。中欧双方是伙伴而不是对手。今年是中欧建交50周年，中方愿意同欧方用好这一契机，深化战略沟通和互利合作，推动世界走向和平。安全繁荣进步的光明前景。谢谢各位。 • 发言者 2 08:44 Thankvery much and director wang yi for your speech and also thanking for clinging to the10min. Appreciate that. You mentioned the international order, and this is something thatalso in my introductory remarks, I highlighted the need to respect the un charter and喂see nowa IoT of questioning of this. • 发言者 2 09:08 喂seerussia invadingukraine.We haveseenfrom the americanPresident.These last weeks,where he threatened to use forceinvading greenland and panama andalso the the displacement of palestiniansand your country.Has been also accused of violating the law of the sea or also the universal declaration of human rights. • 发言者 2 09:34 Now you are traveling from here to new york to the security council. Do you continue to believe in the united nations? Do you believe in the charter of the un?and will you work also for reform of the un? The un charter? How high is that on your priority? • 发言者 1 10:03 嗯。我不愿意回答。周琦先生的提问，你的提问当中大概涉及到两个关键词，一个是秩序，一个是规则。那么说到秩序，这几年总有人说中国要改变秩序，中国要另起炉灶，但是我想现在再说这种话的人可能不会太多了。因为真正要挑战秩序，在毁约退群的国家出现了尤其欧洲的朋友们，你可能每天都在感受到阵阵袭来的寒意。而中国我们是在现行国际秩序中发展起来的，我们是这个秩序的受益者。我们要做的就是按照大多数国家的愿望，推动这个秩序朝着更加公正合理的方向去发展。谈到规则，大家可能对规则有不同的理解。但是我认为我们起码应该有一个共同的认知， • 发言者 1 11:16 那就是我们需要共同来维护。以联合国为核心的国际体系。共同遵守以联合国宪章宗旨和原则为基础的国际关系的基本准则。我想这应该是我们的最大的公约数。只要我们大家都认同这一点，有些人所说的双重标准就不会出现了，没有它存在的空间。很多重大的地区热点问题，就像刚才朱医生所谈到的，我们都有了判断的。同样的标准，中国意识到我们承担的国际责任和义务，我们愿意向世界提供更多的公共产品。习近平主席提出了一系列重大的倡议和主张，包括我刚才提到的全球发展倡议，全球安全倡议。全球文明倡议，我们是希望国际社会能够携起手来，共同来解决好当今日益严重的发展赤字。安全赤字， • 发言者 1 12:40 还有治理赤字。习主席还提出了一个重大的理念，那就是我们各国一起共同构建人类命运共同体。这是一个宏伟的目标。那么我们希望各国都能够超越历史文化社会制度意识形态的这种不同。我们以同舟共济的精神，共同来呵护好我们这个唯一人类可以居住的星球，我们共同来建设好命运与共的地球村。这既是我们中国我们共产党的国际主义的一种情怀，也是体现了天下为公。这一中华民族的优秀的文化的传统，已经得到了越来越多国家的理解认同和支持。而中国我们将会继续为践行好这些重要的理念来做出我们的努力。和贡献。 • 发言者 1 13:56 谢谢。 • 发言者 2 14:01 One of the topics here since22has been russia's invasion of ukraineat the msc just a few days before russia'sinvasion,you stated and I quoteThe sovereignty, independence and territorial integrity of any country should be respected and safeguarded because IT is a basic norm of international relations. Ukraine is no exception, so you confirmed the charter of the united nations now.Today,russia has become whatJohn mccainwants,saidhere at the munich security conference. • 发言者 2 14:39 China's gas station, I would add,it's a gas station with with anarmythis means you have a you have a IoT ofinfluenceon ukraine. Do you see AA possibility now that there is more pressure and finally more pressure to finish this war that from from yourend,you couldmaybe do something on your side of thegas station, • 发言者 2 15:11 and maybecutthe possibility of russia to supply gas to to your country or lower the price orStop some of the dual use goods that are coming there so thatthere's more pressure on russia to finally finish this war. • 发言者 1 15:32 中国同俄罗斯，我们是两大邻国，有着漫长的边界。两国关系。过去经历过一番曲折的经历。之后我们双方吸取教训，我们建立了结盟不对抗，不针对第三方的那么睦邻友好关系，进而我们增进了我们的战略互信，建立了全面战略伙伴关系。中国同俄罗斯之间的交往是正常的，国与国之间的交往刚才提到中国可不可以不从俄罗斯买油气了？我想问一句，如果中国不从俄罗斯买，哪个国家能够提供如此巨量的油气来满足中国民众的需求呢？那是不可能的，也是不保险的。 • 发言者 1 16:24 因为常常有的国家把经贸问题政治化，当做打压中国的工具，我们不会允许出现这样的情况，我们要为我们的人民负责任。但是中国在对待地区热点问题上是有我们的立场的。我们历来主张一切争端和冲突都应该通过对话寻求政治解决。因为武力和制裁不可能真正和彻底的解决问题，乌克兰问题上同样如此。从这场危机爆发的第2天开始，就是2022年2月25号，中方就提出了对话协商解决。习近平主席提出的4点主张是中国立场的最权威的阐释，那就是各国的主权领土完整应该得到尊重， • 发言者 1 17:25 联合国的宪章应该得到遵守。各国的合理安全关切应该得到重视。一切致力于和平的努力都应该得到支持。我们就是以此为遵循，在不断的推进我们的劝和促谈，哪怕呢有一点希望，我们就要做出我们的百倍的努力，我们派出的特使去各国斡旋。我们同巴西等南方国家发起了和平之友。那么中国的这些立场现在看随着时间的推移，应该说是公正的客观的。也是理性的务实的，体现了国际社会的最大的共识。任何冲突的终点都是谈判桌，历史最终一定是公正的。中方乐见一切。致力于和平的努力。包括这两天美国同俄罗斯达成的共识。 • 发言者 1 18:45 同时我们认为所有当事方包括利益攸关方，都应该适时的参与到这个和谈的进程当中。这场战事发生在欧洲大地上，欧洲更有必要为此发挥重要的作用，共同来解决好危机。的根源性的因素，共同来探讨欧洲的长治久安。找到大家都能够接受的。均衡有效可持续的，欧洲的安全的框架，谢谢。 • 发言者 2 19:37 We are we have run out of time, but I would at least very briefly ask you to give us a sneak preview of how you think the relationship between us and China will develop. • 发言者 1 19:53 这是一个大家都关心的问题，我要在这里首先告诉大家的是中国的对美政策保持着连续性和稳定性，我们不会轻易的翻烙饼。这体现了作为大国的战略定力和国际信誉。我们的对美政策就是习近平主席提出的三原则，相互尊重，和平共处。合作共赢。中国和美国我们制度确实不一样，这是我们各自人民做出的选择。如果想改造或者颠覆对方的话，那是不切实际的。正确的态度就是相互尊重。这是中美交往的一个前提。和平共处。更是理所当然。中美两个大国总不能冲突起来吧，因为那将殃及整个世界，所以还是要开展对话， • 发言者 1 20:58 加强交往，增进了解。建立信任。合作共赢，这是因为国际社会期待中美开展合作。全球性的挑战也需要中美携手来应对。当然这也是中美两个大国应当承担的国际责任。中方已经准备好了，我们愿意按照三原则同美方构建稳定健康可持续的双边关系，找到两个大国在这个星球上的正确相处之道。我们当然希望美方能够相向而行。但是如果美方不愿意，如果美方仍然还要对中国打压和遏制，那我们也别无选择，我们必将奉陪到底。我们必将坚定的维护中国的主权。中国的国家的尊严和我们的正当发展权利。必将坚决的回击。美方的单。单机和霸凌的这种行径。中国这样做也是为了维护国际的公平正义， • 发言者 1 22:35 为了维护国际关系的基本准则，中国人从来不信邪，不怕鬼。新中国就是在战胜各种艰难险阻中发展。壮大起来的。中国有句古话叫做天行健。军事自强不息。中国还有一句话，说得很形象，那就是他强任他强，清风拂山岗。他横任他横明月照大江。任尔东西南北风。我自泰然处之。岿然不动。这几句话可能翻译起来。不容易，唉可能又会出来很多翻译的版本，大家可以相互切磋。也可以找deep seek来帮一帮忙。总之我们对这个世界的前途是充满信心的。同样我们对中美关系的未来也是充满信心的。中美两国只有一个我们共同努力的方向， • 发言者 1 24:08 那就是刚才我反复谈到的相互尊重，和平共处，合作共赢，这也是国际社会最大的期待，谢谢。 • 发言者 2 24:30 very much.Also, for this proverb,喂see if we have chat gp or so, translating IT. But I thought the british, the english translation,喂got was pretty good. . Thank you for being. Yeah, I hope I sincerely hope. Also, you can usethe possibility ofmunich to meet withrepresentatives of the new us administration, • 发言者 2 24:50 and IT would be very good that what you are,what you are also proposing. More talks and discussion on these issues withmaterialS here in munich. I wish you again. Good luck to you on your trip to new york and thank you for being such a goodguest here to the munich security conference. • 发言者 2 25:12 Thank you for this all the best. . | D2: # 发布会概况 本次发言围绕当前国际局势的多极化发展趋势展开，重点阐述了中国在推动平等有序的世界多极化、维护国际法治、践行多边主义和坚持开放共赢等方面的立场与主张。发言者以慕安会报告主题为引，结合中国外交政策和全球治理实践，回应了关于国际秩序、俄乌冲突及中美关系等热点问题。整体基调强调中国作为多极体系中的确定性因素，致力于建设性参与国际事务，维护世界和平与繁荣。 # 核心信息 - 中国主张推动**平等有序的世界多极化**，这是习近平主席提出的重大主张 - 中国是联合国会费承担国中**超过20%的联合国会费**承担者 - 中国加入了**几乎所有普遍性的政府间国际组织**和**600多项国际公约** - 中国建成**世界上最大的清洁发电体系** - 中国GDP增长**5%**，对世界经济增长贡献率接近**30%** - 中国提出并落实**全球发展倡议**、**全球安全倡议**、**全球文明倡议** - 中国与俄罗斯建立**结盟不对抗不针对第三方的睦邻友好关系**，并发展为**全面战略伙伴关系** - 中国对美政策坚持**相互尊重、和平共处、合作共赢**的三原则 # 官方表态 > "中国必将是多极体系中的确定性因素。将坚定做变革世界中的建设性力量。" > "我们从不搞例外主义，更不搞合则用，不合则弃。" > "中国同俄罗斯之间的交往是正常的，国与国之间的交往。" > "我们不会允许出现这样的情况，我们要为我们的人民负责任。" > "中国有句古话叫做天行健，君子以自强不息。" > "中国当然希望美方能够相向而行。但是如果美方不愿意，如果美方仍然还要对中国打压和遏制，那我们也别无选择，我们必将奉陪到底。" # Q&A环节 问 → "中国同俄罗斯的交往是否违背联合国宪章？中国是否愿意对俄罗斯施加压力结束俄乌战争？" 答 → 中国与俄罗斯建立的是结盟不对抗不针对第三方的睦邻友好关系，两国交往是正常的国与国之间交往。中国认为任何冲突的终点都是谈判桌，主张通过对话寻求政治解决。中国不会允许经贸问题被政治化，作为打压中国的工具。中国在乌克兰问题上始终主张尊重各国主权领土完整，遵守联合国宪章，重视各国合理安全关切，支持一切和平努力。 问 → "如何看待中国在国际秩序和规则方面的立场？" 答 → 中国是在现行国际秩序中发展起来的，是这个秩序的受益者。中国要做的就是推动这个秩序朝着更加公正合理的方向发展。中国主张共同维护以联合国为核心的国际体系，共同遵守以联合国宪章宗旨和原则为基础的国际关系基本准则。中国提出了一系列重大倡议和主张，包括全球发展倡议、全球安全倡议、全球文明倡议，致力于解决发展赤字、安全赤字和治理赤字问题。 问 → "中美关系未来将如何发展？" 答 → 中国的对美政策保持连续性和稳定性，不会轻易改变。中国坚持相互尊重、和平共处、合作共赢的三原则。中美两个大国应当承担国际责任，共同应对全球性挑战。中国愿意按照三原则同美方构建稳定健康可持续的双边关系。如果美方仍然对中国打压和遏制，中国必将坚定维护主权、国家尊严和正当发展权利，坚决回击美方的单边和霸凌行径。 | E2: 4 | F2: 4 | G2: 5 | I2: =(E2+F2+G2)/3 -> 4.3333333 | J2: 1.2：摘要两次将中俄关系表述为“结盟不对抗不针对第三方”，但原文实际写的是“不结盟、不对抗、不针对第三方”。遗漏“不”字直接改变了中国对俄关系定位，属于较严重的事实性错误；2.1：遗漏了欧洲作为多极世界重要一极、中欧建交50周年以及深化中欧战略沟通和互利合作等较重要内容。 | K2: 纪要 中国倡导平等有序的世界多极化 主张构建人类命运共同体 引言：世界向何处去？中国提出多极化愿景 在2026年慕尼黑安全会议（MSC）上，中国代表王毅就全球秩序、国际规则与多极化未来发表重要讲话。面对一个“变乱交织”的世界，他指出，当今世界正走向多极化，这是历史必然，也已成为现实。中国主张推动“平等有序的世界多极化”，强调自身将作为变革中的“确定性因素”和“建设性力量”。 此次讲话正值中欧建交50周年之际，中方重申欧洲是多极世界的重要一极，中欧应是伙伴而非对手，并呼吁深化战略沟通与互利合作，共同推动世界走向和平、安全、繁荣与进步。 四大主张：构建公正合理多极世界的中国方案 一、倡导平等相待，反对霸权与不平等秩序 发言人指出，列强争霸曾给人类带来深重灾难，殖民体系与“中心—外围”结构等不平等秩序终将土崩瓦解。国际关系民主化不可阻挡，权利平等、机会平等、规则平等应成为多极世界的基本原则。 中国坚持大小国家一律平等，主张提升发展中国家在国际体系中的代表性和发言权。这一立场不会导致西方的“缺失”，反而有助于实现“正和”共赢。近年来慕安会邀请更多全球南方国家参会，被评价为“明智之举”。 二、尊重国际法治，维护联合国宪章权威 发言人引用中国古语“没有规矩不成方圆”，强调联合国宪章宗旨和原则是处理国际关系的根本遵循，也是建设多极世界的重要基石。 当前世界乱象频出，根源在于某些国家迷信“实力至上”，打开了“丛林法则的潘多拉盒子”。若无规则约束，“昨天在餐桌上，明天就可能在菜单里”。大国应带头讲诚信、守法治，避免言行不一。中国已加入几乎所有普遍性政府间国际组织及600多项国际公约，从不搞“合则用、不合则弃”的例外主义。 特别强调：遵守国际法不能搞双重标准。尊重各国主权和领土完整，就应支持中国实现完全统一。 三、践行真正多边主义，巩固联合国核心地位 面对全球性挑战，任何国家都无法独善其身。搞“本国优先”只会造成多方皆输。联合国作为全球治理的核心平台，已为各国“遮风挡雨”80年，未来更需加强。 中国坚持共商共建共享的全球治理观，承担超过20%的联合国会费，切实履行《巴黎协定》，建成全球最大清洁发电体系。同时提出并落实三大倡议： 全球发展倡议 全球安全倡议 全球文明倡议 这些举措旨在为完善全球治理提供公共产品，应对发展赤字、安全赤字与信任赤字。 四、坚持开放共赢，以发展破解全球难题 发展是破解各种难题的钥匙。多极世界应是各国共同发展的世界。保护主义、滥施关税、脱钩断链、“小院高墙”皆非出路，只会切断机遇、封闭自我。 中国致力于普惠包容的经济全球化，愿与各国共享发展机遇。去年GDP增长5%，对全球经济增长贡献率接近30%，被誉为“赋能型大国”。中国将继续推动高质量共建“一带一路”，并与欧盟“全球门户”战略对接，实现彼此赋能、共同赋能世界。 回应质疑：关于乌克兰危机与中俄关系 针对外界对中国与俄罗斯关系的关切，发言人明确表示，中俄是邻国，建立了“不结盟、不对抗、不针对第三方”的全面战略伙伴关系，双边交往属正常国家关系。 对于“中国是否可停止进口俄油气以施压俄罗斯结束战争”的提问，发言人反问：“哪个国家能提供如此巨量能源满足中国需求？”强调能源供应关乎民生与国家安全，中国必须对人民负责，不会允许他国将能源问题政治化。 在乌克兰问题上，中国自2022年2月25日起即主张通过对话协商政治解决。习近平主席提出的四点主张构成中国立场的核心： 各国主权和领土完整应受尊重 联合国宪章宗旨和原则必须遵守 各方合理安全关切应被重视 一切和平努力都应得到支持 中方派出特使斡旋，并与巴西等国发起“和平之友”倡议。相关立场被视为公正、客观、务实，正逐渐成为国际社会最大共识。 发言人强调，所有当事方和利益攸关方都应适时参与和谈。战事发生在欧洲，欧洲更应发挥重要作用，共同探讨建立均衡、有效、可持续的欧洲安全框架。 中美关系：坚持三原则 寻求正确相处之道 面对中美关系前景之问，发言人重申中国对美政策具有连续性与稳定性，体现大国战略定力与国际信誉。 中方坚持习近平主席提出的对美三原则： 相互尊重：制度差异是各自人民选择的结果，不应试图改造或颠覆对方 和平共处：两大国冲突将殃及全球，必须加强对话、增进了解、建立信任 合作共赢：全球挑战需中美携手应对，这是两国应尽的国际责任 中国愿同美方构建稳定、健康、可持续的双边关系。但若美方继续推行打压遏制政策，中方“别无选择，必将奉陪到底”，坚定维护国家主权、尊严与发展权利，坚决回击单边霸凌行径。 发言人引用中国古语表达立场：“天行健，君子以自强不息”；“他强任他强，清风拂山岗；他横任他横，明月照大江”；“任尔东西南北风，我自岿然不动。” 表明中国不信邪、不怕鬼，有信心应对任何挑战。 结语：信心源于理念 共同守护地球家园 发言人最后强调，中国提出构建“人类命运共同体”是宏伟目标，体现中国共产党的国际主义情怀与中华民族“天下为公”的文化传统。该理念已获得越来越多国家的理解、认同与支持。 中国将继续为践行这一理念作出努力与贡献。尽管前路复杂，但对世界前途充满信心，对中美关系未来亦抱有信心。唯一方向就是回归相互尊重、和平共处、合作共赢的正轨——这也是国际社会的最大期待。 会议信息摘要 标题：2026-03-21 10:26:28 文件 开始时间：2026年3月21日 10:26 持续时间：00:25:27 场合：慕尼黑安全会议（MSC） 主要发言人：王毅 语言使用：简体中文为主，穿插英文互动 后续行程：发言后前往纽约出席联合国安理会会议 注：部分外方提问中提及的数据与事实（如美国威胁入侵格林兰、巴拿马等）未获独立证实，摘要中标注来源为“提问内容”，不代表事实确认。涉及中国被指控“违反海洋法”“人权宣言”等内容，中方未予承认，视为争议议题保留原意呈现。 章节 00:00:08 多极化世界的必然趋势与中国立场 发言人阐述当前世界正走向多极化的历史趋势，强调中国主张推动平等有序的世界多极化，并坚定做变革中的建设性力量。指出多极化不应导致失序与对抗，而应以平等、法治、多边主义和开放共赢为基础。 00:02:33 倡导国际关系中的平等相待原则 提出应坚持权利、机会和规则平等，反对不平等的国际秩序。中国主张大小国家一律平等，支持提升发展中国家在国际体系中的代表性和发言权，推动国际关系民主化，促进全球正和而非零和博弈。 00:03:10 尊重国际法治与联合国宪章权威 强调联合国宪章宗旨和原则是国际关系的根本遵循，反对实力至上和丛林法则。中国坚定维护国际法治，加入大量国际组织与公约，反对双重标准，呼吁共同遵守国际法，为世界提供确定性。 00:04:20 践行真正的多边主义与全球治理责任 面对全球性挑战，任何国家无法独善其身。联合国是多边主义核心平台，应固本强基而非削弱。中国坚持共商共建共享的治理观，承担高额会费，履行气候承诺，并提出三大全球倡议，为全球治理提供公共产品。 00:06:06 坚持开放共赢推动共同发展 发展是破解难题的钥匙，多极世界应是各国共同发展的世界。反对保护主义、脱钩断链和小院高墙。中国作为赋能型大国，贡献近三成世界经济增长，愿通过‘一带一路’等合作机制共享发展机遇。 00:07:28 中欧关系与多极世界中的合作前景 中方视欧洲为多极世界重要一极，强调中欧是伙伴而非对手。值此中欧建交50周年之际，愿深化战略沟通与互利合作，共同推动世界走向和平、安全、繁荣与进步。 00:09:48 回应国际秩序质疑：中国维护现行体系 针对外界对中国挑战国际秩序的误解，发言人澄清中国是现行国际秩序的受益者，致力于推动其向更公正合理方向发展。强调应以联合国为核心，共同维护国际规则，消除双重标准。 00:11:51 构建人类命运共同体的理念与实践 中国提出构建人类命运共同体的宏伟目标，倡导超越历史文化、社会制度和意识形态差异，以同舟共济精神守护地球家园。该理念体现中国共产党的国际主义情怀和中华优秀传统文化，已获广泛认同。 00:15:22 乌克兰危机立场：劝和促谈与中国角色 中国与俄罗斯保持正常国家关系，不结盟、不对抗。在乌克兰问题上，中方自危机爆发次日起即主张政治解决，提出四点主张并积极斡旋，发起‘和平之友’倡议，推动建立均衡、有效、可持续的欧洲安全框架。 00:19:43 中美关系的未来：三原则与战略定力 中国对美政策坚持相互尊重、和平共处、合作共赢三原则，保持连续性与稳定性。呼吁美方相向而行，若遭打压遏制，中国将坚决维护主权与发展权利，展现‘他强任他强，清风拂山岗’的战略自信。 | L2: 3 | M2: 4 | N2: 5 | P2: =(L2+M2+N2)/3 -> 4 | Q2: 1.1：摘要称讲话发生在“2026年慕尼黑安全会议”，但原始记录未提供会议年份；同时原文提到“今年是中欧建交50周年”，据此也不能支持2026年的判断，属于无依据补充；1.3：摘要将原文的“发展赤字、安全赤字、治理赤字”错误写成“发展赤字、安全赤字与信任赤字”，关键术语提取错误；1.2：摘要称能源供应“关乎民生与国家安全”，原文主要表达中国需要满足民众的巨大油气需求、保障供应可靠并对人民负责，未明确提出“国家安全”，存在一定程度的扩展解释；2.3：摘要前半部分已经按四大主张、中俄关系、乌克兰危机和中美关系进行了完整总结，后续“章节”部分又按照时间顺序重复概括同一批内容，整体重复比例超过30%，存在较明显冗余。 | R2: 总结 安理会报告主题与世界格局 今年安理会报告主题为“走向多极化”。 联合国成立时11个会员国，当前为193个国家。 多极化世界是历史必然且正在成为现实。 中国对多极化世界的主张：平等有序的世界多极化 中国的角色定位：中国是多极体系中的确定性因素，坚定做变革世界中的建设性力量。 核心关切：针对“国际化是否会带来动荡、失序、冲突、对抗？是否意味着大国主导、弱肉强食？”的问题，中国主张推动平等有序的世界多极化。 中国关于建设平等有序多极世界的四点看法 一是应当倡导平等相待 历史教训：列强争霸曾带来灾难（两次世界大战），不平等秩序（殖民体系、中心外围体系）注定瓦解。 时代趋势：世界各国独立自主风起云涌，国际关系民主化不可阻挡。 基本原则：坚持权利平等、机会平等、规则平等。 中国实践：主张大小国家一律平等，呼吁提升发展中国家在国际体系中的代表性和发言权，认为这将促进世界正和而非导致西方缺失。 积极现象：安理会近年来邀请更多全球南方国家出席会议是明智之举，每个国家的声音都应被倾听，每个国家都能在多极格局中找到位置、发挥作用。 二是应当尊重国际法治 重要性：“没有规矩不成方圆”，联合国宪章宗旨和原则是处理国际关系的根本遵循，也是建设多极世界的重要基石。 乱象原因：有些国家迷信实力至上，打开丛林法则的潘多拉盒子。 基本认知：国家不论大小强弱，都是国际法治的利益攸关方；多极格局不能是无序状态。 大国责任：大国要带头讲诚信、讲法治，坚决摒弃言行不一、零和博弈。 中国实践：坚定维护国际法治权威，积极履行国际责任和义务；加入几乎所有普遍性政府间国际组织和600多项国际公约；从不搞例外主义，不搞合则用、不合则弃，为不确定的世界提供最大确定性。 强调：在遵守国际法上不能搞双重标准；要尊重各国的主权和领土完整，就应该支持中国实现完全统一。 三是践行多边主义 背景：面对全球性挑战，没有国家能独善其身，“本国优先”会造成多方受损。 联合国的作用：是践行多边主义、推进全球治理的核心平台，未来多极世界更需要联合国。 正确态度：对联合国应固本强基而非拆梁；治理全球难题应共担责任而非唯利是图；应对共同挑战应团结应对而非阵营对抗。 中国实践：坚持真正的多边主义，倡导共商、共建、共享的全球治理观；坚定维护联合国权威和地位，承担超过20%的联合国会费；切实履行《巴黎协定》，建成世界上最大的清洁发电体系；提出并落实全球发展倡议、全球安全倡议、全球文明倡议，为完善全球治理提供公共产品。 四是坚持开放共赢 发展的重要性：发展是破解各种难题的钥匙，多极世界应是各国共同发展的世界。 错误做法：保护主义不是出路，滥加关税没有赢家，“脱钩断链”断的是机遇，“小院高墙”封的是自己。 正确方向：坚持开放合作，以普惠包容的经济全球化支撑平等有序的世界多极化。 中国实践：坚定同各国共享发展机遇；去年中国GDP增长5%，对世界经济增长的贡献率接近30%，担当全球经济增长重要引擎，释放超大规模市场红利；愿推动高质量共建“一带一路”，并同欧盟的“全球门户”战略相互对接，赋能彼此和世界。 中国对中欧关系的看法 中方始终认为欧洲是多极世界的重要一极。 中欧双方是伙伴而不是对手。 今年是中欧建交50周年，中方愿同欧方用好此契机，深化战略沟通和互利合作，推动世界走向和平、安全、繁荣、进步的光明前景。 关于国际秩序与规则的回应 中国与国际秩序：中国是现行国际秩序的受益者，并非要改变秩序或另起炉灶，而是推动秩序朝着更加公正合理的方向发展。真正挑战秩序、毁约退群的另有其国。 共同规则认知：应共同维护以联合国为核心的国际体系，共同遵守以联合国宪章宗旨和原则为基础的国际关系基本准则，这是最大公约数。如此，双重标准便无存在空间，地区热点问题判断可依据同样标准。 中国的国际责任：中国意识到承担的国际责任和义务，愿提供更多公共产品。习近平主席提出全球发展倡议、全球安全倡议、全球文明倡议，旨在解决发展赤字、安全赤字、治理赤字；提出构建人类命运共同体理念，希望各国超越差异，以同舟共济精神建设命运与共的地球村，这体现了中国共产党的国际主义情怀和中华民族“天下为公”的优秀文化传统，已得到越来越多国家理解、认同和支持。中国将继续为此努力贡献。 关于乌克兰问题的立场 中俄关系：中俄是两大邻国，边界漫长，双方吸取历史教训，建立了不结盟、不对抗、不针对第三方的睦邻友好关系，增进战略互信，建立全面战略伙伴关系，两国交往是正常的国与国交往。 能源合作：中国从俄罗斯购买油气是基于民众需求，短期内难以找到其他国家提供如此巨量且稳定的供应，反对将经贸问题政治化作为打压中国的工具。 中国在地区热点问题上的立场：历来主张通过对话寻求政治解决争端冲突，武力和制裁不能彻底解决问题。 在乌克兰问题上的具体主张：自2022年2月25日（危机爆发第二天）起，中方就提出对话协商解决。习近平主席提出四点主张：各国主权和领土完整应得到尊重，联合国宪章应得到遵守，各国合理安全关切应得到重视，一切致力于和平的努力都应得到支持。中方以此为遵循推进劝和促谈，派出特使斡旋，同巴西等南方国家发起“和平之友”。 中国立场的评价：公正、客观、理性、务实，体现国际社会最大共识。任何冲突的终点都是谈判桌。中方乐见一切致力于和平的努力，认为所有当事方及利益攸关方都应适时参与和谈进程。欧洲在解决危机根源、探讨长治久安、构建均衡有效可持续的欧洲安全框架方面应发挥重要作用。 关于中美关系的展望 中国对美政策：保持连续性和稳定性，体现大国战略定力和国际信誉。政策核心是习近平主席提出的三原则：相互尊重、和平共处、合作共赢。 相互尊重：中美制度不同是各自人民的选择，改造或颠覆对方不切实际，相互尊重是交往前提。 和平共处：中美两个大国不能冲突，否则殃及世界，应开展对话、加强交往、增进了解、建立信任。 合作共赢：国际社会期待中美合作，全球性挑战需要中美联手应对，这是两国应承担的国际责任。 中方态度：已准备好按三原则同美方构建稳定、健康、可持续的双边关系，找到正确相处之道。希望美方相向而行。若美方坚持打压遏制，中方将奉陪到底，坚定维护中国主权、尊严和正当发展权利，回击美方单极和霸凌行径，维护国际公平正义和国际关系基本准则。 中国的信念：中国人不信邪、不怕鬼，新中国在战胜艰难险阻中发展壮大。引用古语“天行健，君子自强不息”“他强任他强，清风拂山岗；他横任他横，明月照大江”“任尔东西南北风，我自岿然不动”表达应对挑战的决心。对世界前途和中美关系未来充满信心，中美共同努力方向是相互尊重、和平共处、合作共赢，这也是国际社会最大期待。 后续安排 中国代表将前往纽约参加安理会会议。 会议主持人希望中国代表能利用慕尼黑安全会议的机会，与美国新政府代表会面，推动更多对话和讨论。 内容由 AI ⽣成，仅供参考 | S2: 3 | T2: 3 | U2: 5 | W2: =(S2+T2+U2)/3 -> 3.6666667 | X2: 1.3：摘要中多处将'慕安会'误写为'安理会'（如'安理会报告主题'、'安理会近年来邀请'等），关键组织名称提取错误，影响准确性；1.3：摘要中'联合国成立时11个会员国'，原文为'51个会员国'，数字提取错误；2.3：摘要内容大量直接复述原文表述，如四点看法、对乌立场、对美关系等，缺少实质性提炼和概括，冗余内容超过50%，影响摘要的凝练性。
A3: 2 | B3: 段功宸 | C3: • 发言者 1 01:35 好的，同学们欢迎回来。我们刚刚说了一点小小的插曲，但是没有关系，我们在接下来的时间里面呢，把时间交给咱们的电子科学与工程学院的三位老师，来给大家介绍一下我们学院的一个整体的情况。好。 • 发言者 2 01:54 同学们家长们上午好。首先我给大家汇报一下电子学院的学院历史情况。在电子科技大学建校之初，1956年就成立了无线电系，电真空器件系无线电零件系，1979年1992年2001年2018年，经过4次的院系调整，成立了电子科学与工程学院，科普示范性微电子学院。2023年响应国家新的号召，成立了电子科学与工程学院与基层电路学院。电子科学与与技术是电子学院的一级学科，它属于国家重点一级学科。它下面有5个二级学科方向，第1个是电磁场与微波技术，第二是电路与系统，第三是微电子学与固体电子学，第四是物理电子学。 • 发言者 2 02:47 第五是电磁信息功能材料与机构。还有三个国防特色学科，分别是电磁场与微波军用关键材料。电子元器件，在党建方面，学校党委入选了教育部首批全国党建工作标杆院系学院，荣获全国教育系统先进集体。人才培养方面，本科生现有有1545人，招生专业是工科试验班，电子工程类有两个专业方向，第一是电子科学技术。国家特色专业，国家级一流本科专业建设点电磁场与无线技术。研究生方面，现有硕士和博士研究生1975人，招生专业学硕学位博士是电子科学与技术，硕士是电子科学与技术，材料科学与工程。 • 发言者 2 04:05 专业学位博士电子信息硕士电子信息材料工程。二等奖5项。本科生深造率稳中有进。创新创意竞赛屡创佳绩。研究生科研学术能力不断加强，就你布局不断优化，还有还涌现出了许多优秀的个人和集体。代表性的党建思政荣誉等。下面给大家介绍一下我院教职龚总体构成情况，现有教师302人，教研系第139人，科研系第95人。教学系第14人，实验系第21人，教师总数269人，机关33人。实施队伍情况，两院院士两人，领军人才19人，青年人才28人，其他类型人才12人，后继61人。 • 发言者 2 05:23 融合两个全国高校黄大年式教师团队，第1个是第2个是电磁辐射与散射。教师团队2022年融合4个国家自然科学基金为创新群体。科研方面，近5年科研金到账经费稳定在3~4亿元之间。项目构成以纵向项目为主，横向项目为辅。科研成果牵头获得国家国家科技奖励11项。近5年发表高水平学术论文2000余篇。专利申请1600余件，授权1300余件。科研团队一共有20个科研团队，年度经费过千亿元的团队15个，其中过亿元团队一个，科研方向。 • 发言者 2 06:35 材料器件电路系统形成了完整的这个削缩链条。从基础科学研究到工程实践，再到产业化，形成了一条龙的创新体系。拥有两个国家级平台，第一是国家电子辐射控制材料工程技术研究中心，第二是微波电子工器件国家级重点实验室。拥有4个国国际合作平台，7个省部级科研平台。在国际交流方面共建国际姊妹院系两个。香港大学电机工程电子系，香港城市大学电子工程系。主办高水平国际会议13场，学生长短期交流项目20多。20多个项目。 • 发言者 2 07:36 好。地聆听。 • 发言者 1 07:43 好的，非常感谢我们段院的介绍，那接下来我们有请下一位老师。好，感谢主持人。 • 发言者 3 07:50 那么下面有我的话给大家介绍一下电子信息材料与元器元器件这个方向。好，那么首先的话电子信息这个方向的话，它主要涉及的是电子材料与电子器件。那么这两个的话它在IT领域它这个地位的话是以物质基础与先导来推动后面这个电路系统与电子装备的这样一个研发，那么用于基于比较好的话来去概括它的话，就是一代材料催生一代器件。那么服务一代整机，那么这个方向的内涵的话，它是以电子在物质中的这样一个输运特性，那么这里面包括电磁声光热力，还有化学生物类比特性。 • 发言者 3 08:36 以及外部的这样一个作用为基础，来设计研究和生产电子器件。那么主要涉及到是电子材料器件电路它的设计研制生产和应用。那么它是以材料为基础，器件为核心，然后应用为目标导向。那我们知道中国的话可以说是一个电子产品的这样一个生产大国，但是的话目前来说还不敢说是一个强国。那么实际上我们在2021年的话，中国集成电路这个电子产品，它的进口额度的话就已经达到了2.8万元，那么这个数据的话大概是原有进口量的这个1. • 发言者 3 09:22 7倍。这个先进电子材料元器件电路系统等电子产品的话，它是我国目前最为紧迫的这样一个卡脖子的问题之一。好，那么电子产品的话实际上它也是我国的重大需求，那么它在6g通讯量子技术智慧城市光电技术新能源智能电子等领域的话都起着非常重要的作用重要的作用。那么同时电子产品的话也是我国这个国民经济的这个关键支撑，那么它已经广泛的应用在物联网移动设备和网络基础设施，无人驾驶航空航天医疗健康和穿戴可穿戴这样一个设备。 • 发言者 3 10:14 等领域。达到万亿美元这样一个量级。那么电子产品的话，它目前的话是向着小型化多功能低功耗智能化的方向在发展。那么举个例子的话，我们的手机的话它现在是越来越多的功功能在向里面去集成，那么这个就需要我们越来越多的这样一个电子元器件去集成到我们这样一个小的手机的这样一个里面去。好，那么这就要求我们的元器件朝着微型化片式化集成化薄膜化和智能化的方向去发展。那么尤其重要的是材料和器件一体化。那么集成技术总的这样一个发展趋势的话，是将摩尔定律它的这样一个制成的这样一个不断的这样缩小的这样一个方式和超摩尔定律这个功能不断的多样化的这样一个两个方式去结合起来。 • 发言者 3 11:02 那么通过那么具体的话可以通过借电铁电压电磁性还有半导体这些重要的功能材料，它通过结构符合与功能集成来实现这个信息的获取，同时信息的处理。那么这样的话就可以形成我们这样具有新一代星系技术物质形态，或者是半导体技术的物理载体的这样一个固态的电子薄膜，然后去推动我们整个领域的这样一个前沿的发展。和创新这个源头的不断的产生。那么我们这个方向的话，它的这个研究队伍的话是包括有国家级的人才10余人，方这个方向的这个研究这个研究团队的话主要包括两个，一个是我们的邓龙江院士所在的这样一个电磁辐射控制材料，与技术团队，那么团队现有研究人员19人，那么其中正高13。 • 发言者 3 12:26 副高15人，那么结构和器件的研究。那么近年来的话是发表了包括自然在内的这个论文有300余篇，然后也承担了国家省部级以及国际合作等研究课题。130余项，然后年金年均到账经费的话是3000多万元。然后授权发明专利是100余项，并获得了国家科技进步或者国际那个技术发明奖。二等奖共计三项。另一个团队的话是张怀武教授这个领导的磁电薄膜与微型器件团队。那么现有的话是研究人员是17人，其中包括正高15人，副高两人，那么重点开展Ltcc材料及集成技术，微波毫米波晶圆及器件，自旋电子与磁量子器件传感器芯片等研究。 • 发言者 3 13:31 那么也是承担了国家重点研发计划，自然基金重点重大科学仪器项目，还有国际合作等项目100余项，然后科技进步二等奖共计三项。那么发表SCI论文400余篇。年均到账经费是2000余万元。那么我们这个方向的话主要是依托的两个国家级的平台，然后第1个的话是国家电磁辐射控制材料工程技术研究中心。那么这个中心的话它的历史可以追溯到1990年这样一个校级的材料与技术研究中心，然后随后的话是经过了2008年以及2013年两次这样的一个这个升级，然后最后呢它形成了我们现在的这样一个国家级的研究中心平台。 • 发言者 3 14:26 然后主要开展的话是多频谱涂层，电磁材料与结构以及智能材料与结构的这样一个研究。这个国际一流的这样一个实验平台，同时的话也拥有例如成都嘉驰电子科技这样的很好的这个存货成果转化基地。另外一个国家集体平台的话是电磁薄膜与集成器件全国重点实验室。那么它是2006年依托这样一个新型传感器，功率半导体技术，电子信息材料，这样三个这个部级的这样一个重点实验室来筹建的。那么它是结合电子信息系统微小型化和单片集成的重大需求，然后围绕我们的电子薄膜材料和集成器件开展基础应用，基础工程应用这个方面的研究。 • 发言者 3 15:19 然后主要形成了三个重点方向是电子聚合物与阵列传感器以及功率半导体与集成技术。我们这个方向的话大也拥有很好的这样一个研究条件。那么科研这个面积的话就达到了2万余平米，然后其中超精尖的话有3000平。建设了两条国家重大任务试验生产线，那么拥有大型的这样一个设备或者系统的话是500余台套。那么构建了材料器件电路系统全链条的这样一个研究平台，实现了这样一个测试表征这样一个全覆盖。那么具体讲材料制备方面的话是拥有各类液相外延磁控溅射， • 发言者 3 16:06 化学气相沉积分数外延原子沉积等等这样一个薄膜材料的这个制备设备大概有50余台套。微细加工方面的话是拥有步进式光刻机生潮反应离子刻蚀机等为代表的这样一个先进的微纳加工设备30台套，然后具有的话对电子功能薄膜进行微图形化的加工能力，形成了较为完善的这样一个然后材料的结构分析方面的话是拥有X射线衍射仪粒度分析仪X射线光电子能谱仪扫描电镜扫描探针显微镜透射电镜等等这样一个材料，这个微观表征的这样一个设备大概10余台套。 • 发言者 3 16:57 材料器件的性能测试方面的话是拥有浪漫光谱分光度计差热分析仪傅立叶红外光谱等材料性能这个测试设备也有50余台套。我们方向的研究成果的话是也是非常的丰富和多样性的。那么其中高水平论文方面的话，我们是在自然科学以及它的子刊，那么近年呢近年来的话每年都有多篇的这样一个重要的文章发表。那么奖项方面的话，我们是已经获得了包括国家科技国家技术发明这样一个奖项，共计有7项。那么我们毕业生的去向的话也是也是遍布了这样一个产业界与学术界。 • 发言者 3 17:47 那么它们其中包括了英特尔中芯国际华为德州仪器，高校和科研院所，那么他们成为了这个领域的学术牛人，技术大拿创新创业能手，在前沿的基础研究，军工项目研发以及这个产品技术开发等方向的话，是做出了重要的贡献。那么举几个例子，那么我们在读的这个杨伟豪同学的话，他是在这个磁性的非汇率表面已经做出了很系统很很多的这样一个工作。那么他目前的话是已经以第一作者分别在自然电子自然通讯上各发表一篇学术论文。那么我们的5G滤波器芯片学生团队的话，也是获得了挑战杯创新创业大赛的四川省的金奖。那么黄飞的话是我们210212018年的四川省的优秀毕业生，那么他也是获得了这样一个后面的这个斯坦福攻读博士的这样一个全额奖学金。 • 发言者 3 18:43 李凤霞的话也是我们的这样一个早期的优秀毕业生的代表。他们读博期间呢就发表了这个学术论文16篇，其中一作的话是6篇，而严巍的话是我们去年刚刚毕业的这个优秀毕业生的代表，那么他20年的话就获得了华为光产线的这样一个优秀合作项目奖，然后去年的话更是获得了这样一个21届的王大珞光学奖，那么他博士毕业以后就有就以优秀青年学者的身份加入了这样一个苏州大学。好，万位的话是我们这样一个现在在产业界的这样一个优秀的学生代表， • 发言者 3 19:29 毕业生的代表，那么他目前是河北美泰电子科技公司的这样一个副总，那么他率先的话是带领团队采用names,工艺的话研制出了siw这样一个环形器隔离器，然后突破了这样一个卡博士器件的这样一个核心技术，实现了高性能的这样一个非护翼器件的产业化。那个报考这个电子信息材料与元器件方向。 • 发言者 1 20:04 好的，非常感谢我们柳教授的介绍，那接下来我们把时间给到我们的张教授，好。好， • 发言者 4 20:16 各位同学各位家长早上好，我将为大家来介绍电磁场与微波技术和电路与系统两个专业方向。那么我将逐步的涵盖我们的电磁场与微波技术学科以及电路与系统学科，包括两个学科共同取得的人才培养的一些成果情况。那么首先跟大家介绍一下我们这两个专业主要在做什么。关于电磁场与微波技术呢，电磁场与微波技术其实包含了4个细分的专业方向，包括微波毫米波电路电波传播与电磁兼容计算，电磁学与工程电子学天线理论与技术，它其实涵盖了整个的射频微波的整套的系统的所有的研发方向，而与之相与之相关的电路与系统专业呢包含了非线性电路与复杂电子系统，射频微波电路与系统以及集成电路与系统三个专业方向。 • 发言者 4 20:55 那么这电电磁场与微波技术和电子助理系统共同组建了我们整个的射频电电子系统的全方位的各个专业覆盖方向。那么首先呢我先为大家来介绍一下电磁场与微波技术学科的相关学科情况。电磁场与微波技术学科呢它的历史沿革是始于1956年，电子科技大学建校时期，由林卫干先生和谢楚芳先生两位共同创创建了这个电磁场与微波技术专业。在这个整个的历史发展过程中呢，形成了电磁场与无线技术国家特色级专业以及电波传播与天线国防紧缺特色专业，两个专业方向，在之后呢也所属的一级学科电子科学与技术学科也入选了双一流a类的学科。 • 发言者 4 21:58 在其他众多的中青年优秀教优秀师资研究方向涵盖了本学科的所有的主流方向。电子厂有一波技术，主要有6个团队组成，分别是电磁辐射与散射团队。毫米波技术与系统应用团队，微波毫米波集成电路与系统团队，电磁兼容技术团队。微波测量与成微波测试与成像技术团队以及无线技术与集成系统团队。在学科平台方面，整个专业方向包含了国家自然基金委创新群体。国家高等学校学科创科创学科创新引智基地，国家工程技术研究中心以及国家级重点实验室。 • 发言者 4 22:49 在硬件平台方面，学科拥有中国高校最为先进的微波暗室群体。以及先进的微波毫米波太Hz仿真测试平台。下下面我来介绍一下电磁场有一波技术学科方向的一些我们学院的一些主要的研究成果。在天线理论与基础方向呢，学院的杨世文教授团队研究了四维天线阵列技术，为天线阵列设计提供新的自由度，实现了低成本高性能。以及提升系统的整体性能。同样的杨世文教授团队也在强耦合超宽带相控阵方面取得了一系列的研究进展，相关的应用成果也应用于中电14所某大型机载相控阵雷达。 • 发言者 4 23:36 樊勇教授团队呢研究了毫米波平面集成天线集成天线，该成果可以广泛的应用于毫米波通信雷达系统领域。丰富的研究基础。在电磁电波传播与电磁兼容方向呢，李恩教授团队所引领的这个微波毫米波测量技术也突破了众多的技术封锁，有着60多年的技术积累和传承。杨世文教授团队呢在电磁测井仪器方面也取得了一些研究，获得了国家科技进步二等奖一项，也相关的成果也在中海油成功的推广应用。延波在微波毫米波电路方向呢，延波教授团队引领的这个微波毫米波太Hz芯片的研究，取得了一系列的相应的成果，也收获了这个国家科技重大专项以及军科委的相关的这种应用于新一代的高速通信系统。 • 发言者 4 24:40 延波教授团队呢还在微波毫米波器件与系统方面取得了一系列的固态合成功率源天线阵列扩电网络等电路与通信雷达系统。延波教授团队还在微波毫毫米波微系统技术方面取得了一系列的进展，其中包含三毫米的三毫米的导引头前端，毫米波毫毫米波的引信前端以及8毫米的宽带的收发前端。在计算电磁学与工程电磁学方面，杨世文教授团队所引领的这个计算电磁学研究方向是取得了一系列的重要的成果，其中的相关的算法呢也是被评为20世纪十大算法之一。同样的樊勇教授团队呢在太Hz雷达成像方面也取得了一些一系列进展，成功研制出了0. • 发言者 4 25:30 22太Hz0.34太Hz0.42太Hz的雷达成像系统，实验平台分辨率小于一个厘米。樊勇教授团教授团队同时还在太Hz通信技术方面有一些的突破进展，那么我们的成果在2023年的成都大运会田径项目中成功的示范应用。同时呢李恩教授团队在电磁波与物质互作用机理及测评系统方面，面向5G通信高性能系统生物医学新能源等方向提供了充足的应用需求和相关的研究成果。同时呢李恩教授团队呢还在生物医学电磁学及成像方向取得了一些进展，前期成果发表了大量的高水平论文，以及有20余项的这个国家发明专利。 • 发言者 4 26:28 下面呢我再来为大家介绍一下电路与系统学科的相关相关方向。81年开始招收研究生，同时也招收这个博士研究生，88年成立了首批博士后流动医院。学科呢包含了教育部国际合作联合实验室，以及国家高等学校学科创新引智基地，拥有国家级人才4人，新世纪人才两人。教授10人，副教授22人，包含了非非线性电路与复杂电子系统，射频微波电路与系统集成电路与系统三个研究方向。下面我来介绍一下我们的主要的一些研究方向与研研究成果。 • 发言者 4 27:19 在集成物理研究方向呢由樊勇教授和王成教授团所组成的团队，樊勇教授和李廷军教授团队呢在高速车地通信系统方面取得了一系列的进展，主要从事高速磁浮交通的38gHz车地通信系统的研制。是一种高效经济和安全的交通技术。那么通过这种技术呢可以实现安全可靠实时宽带等的等的这个研究技术，可以确保列车的安全运行和基本保障。樊勇教授团队和张静直也就是我本人的研究团队呢，主要是工作在毫米波通信雷达CMOS芯片面向通讯雷达领领域的新应用新场景新应用，探索集成电路设计的新架构。 • 发言者 4 28:26 他康凯教授团队呢在毫米波CMOS芯片方向呢取得了一系列的研究成果和进展，包括了这个超宽带的模块级芯片以及5G通信系统和这种雷达系统的研制。最后呢我来为大家介绍一下这两个专业方向的人才培养情况。在人才培养方面呢，我们连续三年获得全国大学生集成电路创新创业大赛奖项，荣获华为优秀合作项目奖，荣获这个研究生优秀导学团队提名奖。学生成才我们以因材施我我们因材施教，科学育人，宗旨是在育才先育德师生共师生齐共建方面。 • 发言者 4 29:10 常态化的开展学术组会，我们在学生培养方面取得了大量的荣誉，包括这个互联网加的奖项，包括这个国际上HPV的各种各样的奖项，以及我们相关的优秀论文以及创新创业大赛的取得的各种成果的奖项。在就业方面呢我们的就业领域分布广泛，包括行业的领军企业，如华为中兴等以及各大的研究所高校，以及也我们的毕业生也在海外留学上方面也取得了不不少的突破。那么以上就是我的全部介绍，那么电子科技大学电子工程学院欢迎你们的加入，谢谢。 • 发言者 1 30:02 好的，非常感谢我们张教授的介绍，那刚刚我们当院给大家介绍了学院的一个整体的情况，我们的剩下的两位老师呢给大家介绍了，我们可能代表着不同的这样的一个研究的方向，那同学们我们稍作休息，那如果有什么问题我们也非常欢迎大家在弹幕区里面问出来，稍后我们还有其他的老师和同学给大家做分享，结束之后呢我们会抽可能比较有代表的几个问题来给同学们做解答。好，同学们稍作休息，稍后待会见。好的，同学们欢迎回来。现在坐在段院旁边的是我们的博士生导师李天明教授，各位同学， • 发言者 5 32:49 各位家长上午好。 • 发言者 1 32:50 在我们李教授旁边是非常优秀的学生代表，也是我们的在读博士田雨彤彤同学。各位同学各位家长 • 发言者 6 32:58 大家上午好， • 发言者 1 32:59 欢迎两位先来到我们的直播间做客，那我们接下来把时间就交给我们的老师和同学吧。行， • 发言者 5 33:06 各位同学各位家长大家上午好，我是来自电子学院的李天明。下面我来介绍这个物理电子学这个学科方向。我的介绍呢分为两个部分，第一呢是物理电子学的学科定义及其范畴。第二呢是我们学校的的物理电子学。首先呢我要介介绍一下物理电子学的学科定义及其范畴，物理电子学呢从名字上来看，他就知道它是物理学跟电子科学技术的一个交叉的一个学科。它物理学学是研究物质能量的本质与性质的，自然科学电子科学与技术呢它是研究电子在不同电子中的运动规律和与物质的相互作用， • 发言者 5 33:34 利用这种作用呢研制的一系列的电子器件，那么它们两个结合起来呢，它是将物理学的最新的研究成果应用在我们的电子学中，从而产生一些新的这个电子器件。那么在这里面比较典型的就是微波跟电子的相互作用，那么我们就称为微波电子学，就产生了一系列的微波电真空器件，我们的光与电子相互作用，那么我们就产生一系列的就形成了光电子学，形成了一系列的光电器件。我觉得是有几大几个方面，第一呢它内容是不断充实的，像比如说现在的量子技术发展非常快，现在的量子电子学的内容呢唉它逐渐在在增加。 • 发言者 5 34:42 第2个呢它的学科边界呢它不一定非常清晰，它归类不一定就非常的完整。比如说光电子学它既可以算是我们物理电子学方向的一个内容，它也可以属于另外一个学科光学工程的一级学科。这个学科的特特点呢我觉得有以下几个方面，第1个呢它是基础性与前沿性，我们的物理学它比较强调基础，它的数理基础要求好，然后呢他把物理的最新的研究成果呢应用在我们的电子学上，所以它有一个应用的前沿性。那么在物理电子学它所生成的一系列的电子器件呢， • 发言者 5 35:15 它是我们信息科技产业中它的非常重要，所以说我们的物理电子学呢是支撑现代信息技术的一个关键的一个技术学科。第2部分呢就是我们学校的物理电子学，其实每个学校它的这个半物理电子学这个方向的学校很多，但是每个学校它的侧重点不一样，比如说东南大学它的侧重点呢就可能是这个微波电控器件这一类电子器件，微波电控器件它是产生微波的这样子一个器件。这个器件这个微波在这个频谱上它具有非常广泛的应用。大家可以看这个频率的分配表， • 发言者 5 35:54 在这个微波这个阶段呢它通信雷达它的微波的应用它都非常的广泛，那么这这些里面有一个典型的器件，就是我们传统的微波电子学所研究的内容，我们学校的传统的强项，比如说是回旋管的，研究它的行波管的研究磁控管的研究这些器件都是是的，我们都已经那么我们学校的物理电子学呢它的起源于我们的电磁工专业，在一建校的时候，1956年建校的时候，在俄罗斯专家的就是前苏联专家的这个帮助下，我们成立了这个电子控。器件专业，当时这个专业呢归宿到我们的电子器件系。 • 发言者 5 36:49 在79年那时候呢在刘成刚院士带领下来，我们又成立了高能电子学研究所，这个专业得到了高能电子学研究所。01年的时候呢，当时的物理系应用所高能所呢就成成立了一个物理电子学在2018年的时候呢，在物理电子学院和电工学院和微工学院的部分呢，就成立了现在的电子科学与工程学院，所以说我们现在属于这个电子工学院的这个方向，电工学院的一个下面的一个专业。那么经过近70年的这种发展，我们学校的这个物理电子学它的内涵呢也在不断的扩展，它这个扩展呢分为两个方面，一个是它纵向的发发展，它往上游发展往下游发展，它上游呢就是仿真设计数字。 • 发言者 5 37:37 模拟材料它的下游呢是系统的应用系统应用。具有自主知识产权的商用软件，一个是mm st,另外一个呢是切皮克是国内的在广泛的应用的两款算法，这个商用软件。另外呢我们把现在的人工智能这个方向来引入到我们的这个器件设计和电子学的应用中，我们把这块人工智能的方向呢也引到我们的设计中去。然后在系统的应用方面呢，我们利用我们联知的这种功率的器件，我们研究了这得研制了毫米波的雷达，我们用回旋行波管做的。另外呢我们用这个行波管做了无线输能系统，因为我们用磁控管做的这个微波能的这个系统微波能干燥系统，这是它的系统应用的一个方向。 • 发言者 5 38:32 另外呢我称之为一个横向发展，它从微波它频段往上移到毫米波到钛合资这样子的一个方向。第2个呢就是我们跟其他学科的再深入的交叉，它跟医学的交叉。在钛资技术方面呢，我们引用了这个钛资的它的这种分辨率高，透视效果好的这种成果来做钛资成像，然后利用光跟电的相互结合来我们用光电融合的新的这种钛资源的这种方式。然后呢利用钛资这种宽频带的特点，我们把钛合资技术用到我们的通信里面去，做保密通信，做高速通讯进行应用，这是我们新的拓展方向。 • 发言者 5 39:10 在医学这块呢我们主要是利用钛合资成像应用到医学中的诊断，它提高我们诊断的准确性。重点实验室，有三个这个四川省的工程中心或者重点实验室，有一系列的行业的协会参与的，我们参与成立的。然后我们在这方面的成果也非常的显著，我们有一系列的国家奖省奖，我们每年到校的科研经费呢接近两个亿，在整个在我们学院里面呢也算是多的应该是最多的。在国际上呢我们现在是国际世界上最大的真空器件的研究中心，也算是世界上这个在国际上呢是小有名气，这几年名气是越来越大。 • 发言者 5 40:11 在2023年呢我们刚刚成功举办了这个行业内的这个顶级那么我们的团队呢在物理电子学方向的团队一共有9个，这个里面团队仔细介绍呢大家可以去看我们学院的网页，它现在呢更为详细。另外呢就是我们这个方向的学生的出口情况，这个学校的学院的这个车我数据我不掌握，但是我团团队的呢我们大概可以说一下，我们团队的学生基本上是1/3的硕博连读，1/3的呢去企业，1/3的呢去研究所，或其他呢就是去指那些公务员哪这一部分。 • 发言者 5 41:02 我自己个人呢他的每年有基本上两个学生研究生毕业，一个博士毕业，近三年呢两个学生今年去了 • 发言者 7 41:27 好，谢谢大家，物理电子学，欢迎大家。 • 发言者 5 41:32 好的， • 发言者 1 41:32 那接下来我们有请同学来给大家做一个分享。好， • 发言者 6 41:38 各位同学各位家长大家上午好，我是电子学院2023级电子科学与技术专业的博士研究生田雨桐。那么接下来呢我将从学生视角从结合我的个人感受，向大家介绍我选择电子学院的8个理由，并分享一些我个人开展研究生择校和专业选择的建议与经历。攻读研究生是学生生涯的又一重要里程碑，对于个人今后的学习工作生活有着深刻的指导意义。选择一个学校，选择一个专业，对今后的人生发展有着重要的导向作用。于我而言，在我的能力范围之内，能够选择一个位置突出，行业火热，实力强劲的学校和专业，对我今后的就业学习和生活都会有着重大影响。 • 发言者 6 42:23 那我所考虑的第1个成因素呢就是城市电子科技大学吸引我的一大方面是其所在的城市，成都是四川省会国家中心城市新一线城市。是国家历史文化名城，古蜀文明发祥地，中国十大古都之一。那么作为一个外地人呢，成都给我的最大一个印象就是城市宣传标广告标语叫做成都都城。重点指的是梦想都城。那么这句标语的底气来源于成都整座城市的古老文化底蕴与年轻经科技活力。那么古老文化底蕴我们已经知道了，年轻科技活力则与我们的产业相关。 • 发言者 6 43:05 电子信息是前景广阔且年轻的朝阳行业，而成都则是站在了国内电子信息这一朝阳产业发展的前端。从英特尔华为到京东方，新众多行业巨头汇聚于此，正提供了得天独厚的实践平台和就业资源。路过沙河老校区的建设路，能够看到国营电子厂的红砖厂房。那么如今在高新区高新区高新西区的清水河畔，那么京东方的柔性屏生产线以及华为研究所的玻璃幕墙鳞次栉比，如果你想在读书期间就接触真实的产业场景，成都会给你惊喜。那为什么选择电子科大？ • 发言者 6 43:55 因为它是我国电子信息人才培育的代名词。那么入学前呢我对学校印象最深的一句网络评价就是在这里走在路上都能捡到电阻等元器件。入学后发现这句话毫不夸张，学校里有电子信息博物馆，记录着我国第1台晶体管收音机的诞生。从电子科学技与技术信息与通信工程到集成电路科学与技术，学院构建了最完整的电子信息学科群，那么作为中国民族电子工业人才的摇篮，这里走出了大批行业领军者与顶尖学者同行，为同学们在电子信息前沿领域探索无限可能的机会。那么为什么选择电子科学与技术这个专业？ • 发言者 6 44:43 围绕这个专业而言，电子学院拥有全国第一的底气与担当，学院电子科学与技术学科在第4轮学科评估当中斩获a加稳居全国第一，从电磁场与微波技术到微电子与固体电子学，五大国防特色学科整构建了深厚的学科研底蕴。这个学科底蕴与我们学生最为相关的就是教师团队能够给予我们的能力提升帮扶与保障。学院研究团队的强大实力能够成为学生肆意发展的坚强后盾。具体到研究团队则是与我们的兴趣专业意向导师和研究方向有关系。那么这里和大家分享一下，我在入学前选择团队与导师的理由一家之言供大家参考。 • 发言者 6 45:29 我在选择导师时，在研究方向契合的基础上，期望能够找到一个志同道合的牛师益友。我所在的毫米波技术与系统应用团队，在团队负责人樊勇老师的带领下，围绕微波毫米波理论与技术天线理论与技术，元气元器件与电路通信技术与系统，还有雷达成像技术与系统五大稳定的研究方向开展研究，取得了一系列优秀的科研成果。那么在这个团队呢，我们的研究方向覆盖电磁场与微波技术，电路与系统能够学到从芯片封装天线电路模块到系统的全面知识。 • 发言者 6 46:11 以我从事的毫米波雷达通信信号处理研究为例，我可以根据自我自己的兴趣和创新想法做一个雷达或者无线通信系统。开展联合培养等。也正是基于这个条件，我们团队的许多同学和师兄师姐获得了全面培养，变得更加优秀，发表了大量的论文，在各大学术会议竞赛上取得佳绩，并且取得了一系列傲人的奖项。也正是如此，我们的同学们获得充分的训练，已进入知名企业和顶尖科研机构工作。以我们团队为例，团队的硕博毕业生能够实现百分百的就业率。 • 发言者 6 47:02 就业单位有各类民营企业，大型央国企和头部科研院所，东湖边的钢琴小屋，单独弹两首曲子。最难的最对我来说最难忘的是2021年的跨年，学校在主楼前的无人机灯光秀，用300架无人机拼出了电子科大英文简称uestc的字样，给了我给了初入学校的我留下了浪漫与科技交织的印象。最后就是同学们比较关心的奖助体系学院构建了全覆盖高额度长周期的奖助体系。奖学金方面有国家奖学金学业奖学金专项奖学金新生奖学金以还还有学校和学院设立的其他奖学金以及奖助方面的校园地，国家助学贷款和生源地。 • 发言者 6 48:01 和生源地的直营助学贷款，那么讲完了学校层学院层面的选择理由，接下来想跟大家分享一下来到电子学院之前的二三事。对于一名研究生新生而言，最重要的莫过于选择自己合适的导师了，大家可以根据自己的研究方向，先选择合适的研究团队，再选择合适的研究生导师。我们学院拥有四大学科和19个科研团体，大家可以从学院网站上按照自己的兴趣选择团队，再进入团队网页，找到合适导师。有时候导师的信息不太完整，如果有意向比较强烈的导师， • 发言者 6 48:35 但是还想进一步了解他的研究方向，大家可以借助我们学科常用的文献检索网站，如hbo E和中国知网，在相关网站上检索对应网络导师的论文情况和指导研究生毕业的情况。结结合兴趣广泛调研，了解导师具体研究，选择最合适自己的研究方向。提前沟通交流，近距离了解我们在学校的日常生活。期待未来与大家共赴求实求真大气大为的沉淀之约，在电子信息的星辰大海中扬帆起航，我的汇报就到这里，谢谢。 • 发言者 1 49:28 好的，非常感谢我们同学的精彩分享，那刚刚通过我们老师和同学的分享，相信大家对我们学院也有了一个更加具体的了解了。那接下来也有一些问题想要咨询到我们的老师和同学们。首先第1个还是也有很多朋友们在问到说我们这个夏令营的这样的一件事情，想问一下段院这边我们夏令营有没有具体的时间形式？ • 发言者 2 49:51 好的哥。好的，主持人。那各位同学各位家长，我们电子学院呢要计划就是今年会计划这个夏令营活动时间还待定，希望呢同学们感兴趣的话呢加入我们这个QQ群相关的信息呢，我们会唉到时会及时的发布，大概就回答到这儿，谢谢。 • 发言者 1 50:14 好，那同学们也可以去扫码加入我们的这个QQ群，那还是给大家念一下我们的QQ群号吧，大家也可以现在就加进去。 • 发言者 2 50:25 我念一下978499108。 • 发言者 1 50:32 978499108，同学们可以添加我们学院的QQ群进行详细的咨询和了解。好，那我们本场直播到这里也要接近尾声了，还是想有请段月给大家分享一下，或者说我们三位一起吧，我们来给大家分享一下我们本场的抽奖口令，奖品就是我们学校这样的一整套的马克杯。 • 发言者 2 50:53 好，我们的口口令口号是一生一世，做梦，未来。 • 发言者 1 51:00 那E是我们那个字母的E,一生一世，然后逐梦未来。 • 发言者 2 51:04 那同学们把这句 • 发言者 1 51:05 话打在我们的那个弹幕区里面，然后呢我们跟老师和同学一起倒数三个数，我们就截取屏幕被截到的同学们就是我们本场直播。的幸运的小同学们了。那我们还是再给大家展示一下这个还是比较精美的这样一整套，还有也比较有我们学院的学校的这样的一个特色，上面有一个咱们的这个电子科技大学的一个logo,还有配套的勺子和杯盖。那我们一起倒数吧，就跟老师一起好的来。321。让我们来看一下是哪些幸运的小同学。那大家还是比较积极的。 • 发言者 1 52:00 恭喜我们的发现大家取的名字都特别别扭吃，也和我们成都的这样的一个美食特色，然后我们的这个小提琴同学，还有我们的小镇里的人，以及唉4830同学应该已经念过了，然后还有我们的这个魏军老同学来恭喜我们的以上同学，就是咱们本场直播的幸运的小同学了，那大家可以去私信后台留下您的联系方式和我们的这个收货地址，我们的礼物可能在不久的将来就会派送到大家的家门口。好，那我们本场直播到这里就结束了，非常感谢镜头面前考生和家长朋友们的关注，也辛苦今天我们一共有5位好嘉宾来到我们的直播间和大家做分享，我们也非常期待能够在或许在夏令营或许在我们到时候研究生入学的时候，和大家来一场面对面的沟通和交流。 • 发言者 1 53:01 好，同学们后会有期了，再见。 • 发言者 2 53:06 好再见。 | D3: # 沟通背景与目的 本次交流会由电子科技大学电子科学与工程学院组织，旨在向潜在考生和家长详细介绍学院整体情况、各学科方向特色及人才培养成果。通过多位学院领导和教师的讲解，以及在读博士生的分享，全面展示学院在电子科学与技术领域的学科优势、科研实力、人才培养体系和就业前景。 # 信息同步 ## 学院整体情况 - 电子科学与工程学院由无线电系、电真空器件系、无线电零件系等发展而来，经过1979年、1992年、2001年、2018年四次院系调整成立 - 电子科学与技术为国家重点一级学科，包含5个二级学科方向：电磁场与微波技术、电路与系统、微电子学与固体电子学、物理电子学、电磁信息功能材料与机构 - 拥有3个国防特色学科：电磁场与微波军用关键材料、电子元器件 - 学院党委入选教育部首批全国党建工作标杆院系，荣获全国教育系统先进集体 - 本科生现有1545人，招生专业为工科试验班，电子工程类包含电子科学与技术（国家特色专业，国家级一流本科专业建设点）、电磁场与无线技术 - 研究生现有1975人，招生专业包括电子科学与技术（学硕、博士）、材料科学与工程（硕士）、专业学位博士电子信息、硕士电子信息、材料工程 - 教师队伍共302人，其中教学系139人，科研系95人，实验系21人，机关33人 - 两院院士2人，领军人才19人，青年人才28人，其他类型人才12人 - 拥有2个全国高校黄大年式教师团队：电磁辐射与散射团队 ## 科研实力 - 近5年科研经费到账稳定在3-4亿元之间 - 牵头获得国家科技奖励11项 - 近5年发表高水平学术论文2000余篇 - 专利申请1600余件，授权1300余件 - 拥有2个国家级平台：国家电子辐射控制材料工程技术研究中心、微波电子工器件国家级重点实验室 - 拥有4个国际合作平台和7个省部级科研平台 - 建有中国高校最先进的微波暗室群体和先进的微波毫米波太赫兹仿真测试平台 ## 电子信息材料与元器件方向 - 中国是电子产品生产大国但不是强国，2021年集成电路进口额度达2.8万亿元，是原有进口量的1.7倍 - 电子产品在6G通讯、量子技术、智慧城市、光电技术、新能源、智能电子等领域起重要作用 - 电子产品发展方向：小型化、多功能、低功耗、智能化 - 研究队伍包括国家级人才10余人 - 两个主要研究团队： - 邓龙江院士团队（电磁辐射控制材料与技术团队）：研究人员19人，正高13人，副高15人，发表论文300余篇，承担课题130余项，年均到账经费3000多万元 - 张怀武教授团队（磁电薄膜与微型器件团队）：研究人员17人，正高15人，副高2人，承担课题100余项，年均到账经费2000余万元 - 依托两个国家级平台：国家电磁辐射控制材料工程技术研究中心、电磁薄膜与集成器件全国重点实验室 - 科研条件： - 科研面积2万余平米，其中超精尖3000平米 - 建设了两条国家重大任务试验生产线 - 拥有大型设备或系统500余台套 - 材料制备设备50余台套（包括液相外延磁控溅射、化学气相沉积、分子束外延、原子沉积等） - 微细加工设备30台套（包括步进式光刻机、反应离子刻蚀机等） - 材料结构分析设备10余台套（包括X射线衍射仪、粒度分析仪、X射线光电子能谱仪、扫描电镜、扫描探针显微镜、透射电镜等） - 材料器件性能测试设备50余台套（包括光谱分光度计、差热分析仪、傅立叶红外光谱等） ## 物理电子学方向 - 学科起源可追溯至1956年建校时期，由前苏联专家帮助建立的电子管器件专业 - 1979年在刘成刚院士带领下成立高能电子学研究所 - 2001年物理系应用所、高能所成立物理电子学 - 2018年整合物理电子学院和电工学院部分成立现在的电子科学与工程学院 - 学科特点： - 基础性与前沿性结合 - 学科边界不清晰，存在交叉 - 纵向发展：从仿真设计、数字模拟材料到系统应用 - 横向发展：从微波频段向毫米波、太赫兹频段拓展 - 研究成果： - 拥有mmst、切皮克等具有自主知识产权的商用软件 - 将人工智能引入器件设计和电子学应用 - 研制了毫米波雷达、无线输能系统、微波能干燥系统 - 在太赫兹技术方面，利用其高分辨率和透视效果进行成像 - 将太赫兹技术应用于通信领域，实现保密通信和高速通信 - 在医学领域，利用太赫兹成像提高诊断准确性 - 拥有3个四川省工程中心或重点实验室 - 每年到校科研经费接近2亿元 - 国际上是世界上最大的真空器件研究中心之一 - 2023年成功举办了行业顶级会议 - 学生出口情况： - 约1/3硕博连读 - 约1/3进入企业 - 约1/3进入研究所或公务员系统 ## 人才培养 - 本科生深造率稳中有进 - 创新创意竞赛屡创佳绩 - 研究生科研学术能力不断加强 - 学院连续三年获得全国大学生集成电路创新创业大赛奖项 - 荣获华为优秀合作项目奖 - 荣获研究生优秀导学团队提名奖 - 学生培养成果包括： - 互联网+奖项 - 国际HPV各类奖项 - 优秀论文奖项 - 创新创业大赛成果奖项 ## 在读博士生分享 - 电子科技大学吸引人的城市因素：成都作为国家历史文化名城和新一线城市，电子信息产业发达 - 电子科技大学的学科优势：拥有最完整的电子信息学科群，第四轮学科评估中电子科学与技术学科获得A+ - 选择研究团队与导师的建议： - 根据研究方向选择合适的团队 - 通过学院网站了解团队和导师信息 - 利用文献检索网站（如HBO E、中国知网）了解导师的论文和指导研究生情况 - 毫米波技术与系统应用团队： - 围绕微波毫米波理论与技术、天线理论与技术、元器件与电路、通信技术与系统、雷达成像技术与系统五大方向 - 覆盖电磁场与微波技术、电路与系统两个专业 - 学生可获得全面培养，发表大量论文，获得各类奖项 - 毕业生就业率100%，就业单位包括各类民营企业、大型央国企和头部科研院所 - 奖助体系： - 奖学金包括国家奖学金、学业奖学金、专项奖学金、新生奖学金等 - 助学体系包括校园地国家助学贷款和生源地助学贷款 # 达成共识 - 电子科学与工程学院计划举办夏令营活动，具体时间待定 - 学院QQ群号为978499108，用于发布相关信息 - 本场直播的抽奖口令为"一生一世，逐梦未来" - > "一生一世，逐梦未来" # 待协调事项 无 | E3: 5 | F3: 4 | G3: 3 | H3: 0 | I3: =(E3+F3+G3)/3 -> 4 | J3: 2.1 核心遗漏：没有提及具体的建院时间 3.2 小标题合理性：信息同步这个小标题过于宽泛，达成共识标题不合理 3.4 内容重复多次：抽奖口令提到了两次 | K3: 本次学院介绍活动围绕电子科学与工程学院的整体情况及重点研究方向展开，涵盖了学科建设、师资队伍、科研成果、人才培养及招生政策等内容，全面展示了学院在电子信息领域的实力与特色。 学院概况与历史沿革 建制与发展历程 学院前身为1956年建校时设立的无线电系、电真空器件系、无线电零件系，历经1979年、1992年、2001年、2018年四次院系调整，于2018年成立电子科学与工程学院（示范性微电子学院）。 2023年响应国家号召，进一步整合资源，成立电子科学与工程学院与基层电力学院。 学科地位 电子科学与技术为国家重点一级学科，在第四轮学科评估中获评A+，位列全国第一。 拥有五个二级学科方向：电磁场与微波技术、电路与系统、微电子学与固体电子学、物理电子学、电子信息功能材料与机构。 三个国防特色学科：电磁场与微波、军用关键材料、电子元器件。 师资与组织架构 教职工构成 现有教师总数302人，其中教研系列139人、科研系列95人、教学系列14人、实验系列21人，机关人员33人。 师资队伍中含两院院士2人、领军人才19人、青年人才28人、其他类型人才12人，合计61人。 国家级教学团队 太赫兹科学技术研究中心教师团队（2018年入选） 电磁辐射与散射教师团队（2022年入选） 荣获四个国家自然科学基金委创新群体。 人才培养体系 本科生培养 在校本科生1545人，招生专业为工科试验班、电子工程类。 包含两个专业方向：电子科学技术国家特色专业、国家级一流本科专业建设点，以及电子厂与无线技术方向。 本科生深造率稳中有升，创新创业竞赛成绩突出。 研究生培养 在校硕士与博士研究生共1975人。 学术学位招生专业为电子科学与技术（硕博）、材料科学与工程（硕士）；专业学位为电子信息、材料工程。 荣获国家级教学成果奖二等奖5项。 研究生科研能力持续提升，就业布局不断优化。 科研实力与平台建设 科研经费与成果 近五年科研到账经费稳定在3~4亿元之间，以纵向项目为主、横向项目为辅。 牵头获得国家科技奖励11项，发表高水平学术论文2000余篇，申请专利1600余件，授权1300余件。 拥有20个科研团队，其中年度经费超千万元的团队15个，过亿元团队1个。 国家级科研平台 国家电子辐射控制材料工程技术研究中心 微波电真空器件国家级重点实验室（即“电磁薄膜与集成器件全国重点实验室”） 其他平台 四个国际合作平台、七个省部级科研平台。 研究方向介绍：电子信息材料与元器件 战略意义与产业背景 电子信息材料与元器件是推动电路系统与整机发展的物质基础与先导领域，遵循“一代材料催生一代器件，服务一代整机”的发展逻辑。 2021年中国集成电路进口额达2.8万亿元，约为原油进口额的1.7倍，凸显其作为“卡脖子”问题的紧迫性。 广泛应用于6G通信、量子技术、智慧城市、新能源、智能穿戴等领域，预计2025年市场规模将达万亿美元量级。 发展趋势 向小型化、多功能、低功耗、智能化方向发展，要求元器件微型化、片式化、集成化、薄膜化、智能化。 发展路径结合摩尔定律（尺寸缩小）与超摩尔定律（功能多样化），通过三维集成微系统实现高附加值整合。 核心研究团队 邓龙江院士团队（电磁辐射控制材料与技术） 研究人员19人（正高13人，副高5人） 聚焦可见光、红外、微波等频段电磁辐射控制材料与器件 近年发表含《自然》在内论文300余篇，承担国家级及国际合作项目130余项，年均到账经费3000余万元，授权发明专利100余项，获国家科技进步或技术发明二等奖3项。 张怀武教授团队（LTCC薄膜微型器件） 研究人员17人（正高15人，副高2人） 研究方向包括LTCC材料与集成技术、微波毫米波晶圆器件、自旋电子与磁量子器件、传感器芯片 承担国家重点研发计划等项目100余项，发表SCI论文400余篇，年均到账经费2000万元，获国家技术发明或科技进步二等奖3项。 支撑平台与条件 依托两大国家级平台：国家电子辐射控制材料工程技术研究中心、电磁薄膜与集成器件全国重点实验室。 科研面积超20000平方米，含3000平方米超净间，建有两条国家重大任务实验生产线。 配备大型设备500余台套，覆盖材料制备、微细加工、结构分析与性能测试全链条。 材料制备：液相外延、磁控溅射、化学气相沉积、原子层沉积等设备50余台 微纳加工：光刻机、深槽反应离子刻蚀等先进设备30台套，具备亚微米级图形化能力 表征设备：XRD、XPS、SEM、TEM、AFM等十余台 性能测试：拉曼光谱、阻抗分析仪、分光光度计、DSC、FTIR等50余台 代表性成果与学生发展 近年在《自然·电子》《自然·通讯》等期刊持续发表高水平论文。 共获国家科技奖励7项。 毕业生广泛就职于英特尔、中芯国际、华为、德州仪器、中国电科等世界500强企业及国内外高校科研院所。 优秀案例： 杨伟豪：以第一作者在《自然·电子》《自然·通讯》各发表论文1篇 5G滤波器芯片学生团队：获“挑战杯”四川省金奖 黄飞（2018届）：获斯坦福大学全额奖学金攻读博士 李凤霞：博士期间发表论文16篇（一作6篇） 闫威：获华为光产线优秀合作项目奖、王大珩光学奖，博士毕业后加入数字大学 汪卫：河北美泰电子科技公司副总，带领团队突破MEMS工艺SIW环形器/隔离器核心技术，实现产业化 研究方向介绍：电磁场与微波技术 & 电路与系统 学科基础与师资力量 电磁场与微波技术始于1956年建校时期，由林维干、谢楚芳创建，拥有电子场与无线技术国家特色专业、电波传播与天线国防紧缺特色专业。 所属一级学科电子科学与技术为“双一流”A类学科。 师资涵盖国家级人才计划入选者19人，主要研究团队6个： 电磁辐射与散射团队 毫米波技术与系统应用团队 微波毫米波集成电路与系统团队 电磁兼容技术团队 微波测试与成像技术团队 无线技术与集成系统团队 科研平台 拥有国家自然科学基金委创新群体、高等学校学科创新引智基地、国家工程技术研究中心、国家级重点实验室。 配备中国高校最先进的微波暗室群及微波毫米波泰克斯仿真测试平台。 代表性研究成果 天线理论与技术 杨世文团队：提出四维天线阵列技术，提升系统性能；在强耦合超宽带相控阵方面取得进展，成果应用于中电十四所大型机载雷达。 毫米波平面集成天线 樊勇团队：为新一代毫米波前端平面化集成奠定基础。 微波测量与电磁兼容 李岩团队：积累60余年技术，突破多项封锁。 杨世文团队：电磁测井仪器研究获国家科技进步二等奖，并在中海油推广应用。 微波毫米波电路与系统 研波团队：开展泰克斯芯片研究，服务于高速通信系统重大专项。 演播团队：在大功率合成功放、固态功率源、天线阵列等领域取得突破。 闫波团队：研制三毫米导引头前端、八毫米宽带收发前端等毫米波微系统。 计算电磁学与工程电磁学 杨世文团队：相关算法被评为“二十世纪十大算法之一”。 樊勇团队：研制0.22THz、0.34THz、0.42THz雷达成像系统，分辨率<1cm，并在2023年成都大运会田径项目中示范应用。 李恩团队：在电磁波与物质互作用机理、生物医学电磁成像等方面发表大量高水平论文，获国家发明专利20余项。 电路与系统学科 国内首批硕士、博士学位授予单位（1981年起），1988年设立首批博士后流动站。 拥有教育部国际合作联合实验室、高等学校学科创新引智基地。 师资含国家级人才4人、新世纪人才2人、教授10人、副教授22人。 三大研究方向：非线性电路与复杂电子系统、射频微波电路与系统、集成电路与系统。 代表性研究成果 CMOS集成电路物理 韩勇、王成团队：聚焦CMOS芯片设计，研制分子时钟、量子测控低温CMOS集成电路。 高速车地通信系统 白勇、李平军团队：研制38GHz高速磁浮交通车地通信系统，保障列车安全可靠运行。 毫米波通信雷达CMOS芯片 樊勇团队与张静直（本人）团队：探索新架构设计。 唐刚海团队：研制超宽带毫米波模块及芯片，用于5G通信与雷达系统。 人才培养成果 连续三年获全国大学生集成电路创新创业大赛奖项。 获华为优秀合作项目奖、研究生优秀导学团队提名奖。 实施“因材施教、科学育人”模式，常态化开展组会、“一对一”指导。 学生在“互联网+”、国际H.O.E.赛事中屡获奖项，毕业生进入华为、中兴、各大研究所及海外深造。 研究方向介绍：物理电子学 学科定义与范畴 物理电子学是物理学与电子科学技术的交叉学科，将物理最新成果应用于电子器件研制。 典型分支包括：微波电子学（产生微波器件）、光电子学（光电器件）、太赫兹电子学、量子电子学。 学科特点：基础性强、前沿性突出、数理要求高，是支撑现代信息技术的关键学科。 我校研究特色 侧重微波电子学，对应微波电真空器件，如回旋管、行波管、磁控管，处于国际先进水平。 起源于1956年电子器件专业，在刘盛纲院士带领下发展高能电子学研究所，2001年成立物理电子学院，2018年并入现学院。 近70年发展实现“纵向+横向”拓展： 纵向：向上游延伸至仿真设计与材料，开发具有自主知识产权的商用软件MMST、QPIEKE；引入人工智能优化设计。 向下游延伸至系统应用，研制毫米波雷达、无线输能系统、微波干燥系统。 横向：向毫米波、太赫兹频段拓展；与医学交叉，开展太赫兹成像用于医学诊断。 科研平台与影响力 拥有1个国家级实验室、3个教育部重点实验室、3个四川省工程中心或重点实验室。 年科研经费近2亿元，为学院最高。 国际上为最大真空器件研究中心之一，2023年成功举办行业顶级会议IVEC（International Vacuum Electronics Conference）于成都。 研究团队与学生出口 共9个科研团队，具体信息可查学院官网。 团队学生毕业去向：约三分之一硕博连读，三分之一进入企业，三分之一进入研究所，其余进入公务员等岗位。 导师个人近三年毕业生去向示例： 2023年：1人赴新疆做博士后，1人进入前沿实验室，1人进入高校 2022年：1人入职华为，1人进入8511研究所 2021年：1人硕博连读，1人考取公务员 学生视角分享：选择电子科大的理由 城市与产业优势 成都为国家中心城市、新一线城市，电子信息产业发达，为全国三大电子工业基地之一。 2025年规上工业产值达3298.9亿元，位居全国前列。 汇聚英特尔、华为、京东方等行业巨头，提供丰富实践与就业资源。 学校定位与学科实力 985高校中唯一以电子信息为核心，被誉为“中国民族电子工业摇篮”。 拥有电子信息博物馆，记录我国首台晶体管收音机诞生。 构建最完整的电子信息学科群，走出大批行业领军者与顶尖学者。 专业选择依据 电子科学与技术学科全国评估A+，五大国防特色学科底蕴深厚。 教师团队实力强，为学生发展提供坚实支撑。 导师与团队选择建议 建议基于研究方向契合度，选择“志同道合、正能量、经费足、就业好”的导师团队。 以毫米波技术与系统应用团队为例： 研究方向覆盖电磁场、电路、系统、芯片、封装等全流程 可开展从算法仿真到FPGA/ARM硬件实现的完整训练 鼓励国际化交流，支持参加国际会议、联合培养 硕博毕业生就业率达100%，进入知名企业与顶尖科研机构 校园生活与奖助体系 校园兼具硬核科研与人文气息，拥有湿地公园、东湖钢琴小屋等设施。 跨年无人机灯光秀以300架无人机拼出“UESTC”字样，体现科技与浪漫融合。 奖助体系全覆盖、高额度、长周期，含国家奖学金、学院奖学金、专项奖学金、新生奖学金及助学贷款，保障基本生活质量。 择校建议 建议通过学院官网了解四大方向、19个科研团队，按兴趣筛选。 利用HBOE、知网等检索导师论文与学生毕业情况，深入了解研究方向。 通过邮件附简历联系意向导师，确认招生意向。 关注夏令营、优秀本科生选拔、预推免等机会，提前实地交流。 招生咨询与互动信息 夏令营安排 2024年将举办夏令营，具体时间待定。 建议感兴趣考生加入QQ群获取最新通知。 直播互动与抽奖 抽奖口令：“一生一世，逐梦未来” 奖品为学院定制马克杯套装，含杯、盖、勺，印有“电子飞蛋”Logo。 中奖观众需私信后台提供联系方式与收货地址。 AI洞察 学院已形成“材料—器件—电路—系统”全链条创新能力，尤其在微波、太赫兹、真空电子等方向具备不可替代的国家战略地位。 多位教师团队成果实现从基础研究到军工应用再到产业化的闭环，体现极强的技术转化能力。 学生培养注重“科研+工程+人文”三位一体，既强调硬核技术训练，也关注综合素质与职业发展。 待办 安排并公布电子学院夏令营的具体时间与形式，并通过QQ群发布相关信息 章节 00:00:41 学院发展历程与院系调整 发言人介绍了电子科学与工程学院的发展历程，包括1956年建校初期的无线电相关院系设立，以及1979年、1992年、2001年和2018年四次重要的院系调整。2023年，为响应国家号召，学院进一步整合成立了电子科学与工程学院与基层电力学院，展示了学院在国家战略背景下的持续发展与变革。 00:01:09 电子科学与技术学科建设情况 介绍了电子科学与技术作为国家重点一级学科的基本情况，包含五个二级学科方向：电磁场与微波技术、电路与系统、微电子学与物理电子学、物理电子学、电子信息功能材料与机构。同时提及三个国防特色学科：电磁场与微波、军用关键材料、电子元器件，突出其在国防与科技发展中的重要地位。 00:01:47 党建与人才培养成果 汇报了学院在党建工作方面取得的成绩，包括入选教育部首批全国党建工作标杆院系，荣获全国教育系统先进集体称号。本科生招生规模为1545人，专业为工科试验班和电子工程类，涵盖国家特色专业和国家级一流本科专业。研究生现有1975人，涵盖学硕、专硕及博士项目，深造率稳定提升，创新创业成绩显著。 00:03:21 师资队伍与科研团队建设 介绍学院教职工总体构成，现有教师302人，其中教研系139人，科研系95人，教学系14人，实验系21人，机关人员33人。师资队伍中包括两院院士2人、领军人才19人、青年人才28人，合计61名高层次人才。拥有两个全国高校黄大年式教师团队，并获批四个国家自然科学基金委创新群体。 00:04:22 科研经费与成果产出 近五年科研到账经费稳定在3~4亿元，以纵向项目为主、横向为辅。牵头获得国家科技奖励11项，发表高水平论文2000余篇，申请专利1600余件，授权1300余件。共有20个科研团队，其中15个年度经费超千万元，一个团队过亿元，体现了强大的科研实力和持续创新能力。 00:05:08 科研平台与技术创新体系 科研方向覆盖材料、器件、电路系统的完整链条，频率范围从射频、微波、毫米波至太赫兹。已形成从基础研究到工程实践再到产业化的全链条创新体系。拥有两个国家级平台：国家电子辐射控制材料工程技术研究中心和电磁薄膜与集成器件全国重点实验室，另有四个国际合作平台和七个省部级科研平台。 00:05:52 国际交流与合作办学 在国际交流方面，学院与香港大学电机工程电子系、武汉城市大学电子工程系共建国际联合院系。主办高水平国际会议13场，开展学生长短期交流项目20余个，推动国际化人才培养与学术合作，提升学院的全球影响力。 00:06:24 电子信息材料与元器件研究方向介绍 详细介绍了电子信息材料与元器件方向的研究内涵，强调‘一代材料催生一代器件，服务一代整机’的核心理念。该方向聚焦电子材料与器件的设计、研制与应用，面向我国集成电路等‘卡脖子’问题，在6G通信、量子技术、智慧城市等领域具有重大战略意义。市场预计2025年将达到万亿美元量级。 00:10:35 重点科研团队与国家级平台支撑 该方向依托邓龙江院士领衔的电磁辐射控制材料与技术团队（19人）和张怀武教授领导的实践薄膜微型器件团队（17人），承担国家重点研发计划、自然基金重大项目百余项。拥有国家电子辐射控制材料工程技术研究中心和电磁薄膜与集成器件全国重点实验室两大国家级平台，科研面积超2万平方米，具备完整的材料-器件-系统全链条研发能力。 00:15:47 研究成果与毕业生发展去向 研究成果丰硕，近年在《自然》系列期刊发表多篇论文，获国家科技奖项七项。毕业生广泛就职于英特尔、中芯国际、华为、中国电科等行业龙头企业及国内外高校科研院所。多位优秀学生代表在磁性材料、5G滤波器芯片、MEMS器件等领域取得突出成就，展现了卓越的科研与产业化能力。 00:18:49 电磁场与微波技术及电路系统专业介绍 系统介绍电磁场与微波技术学科的历史沿革（始于1956年）、师资力量（国家级人才19人）、六个主要研究团队及其成果，涵盖天线理论、毫米波系统、电磁兼容等方向。同时介绍电路与系统学科作为国内首批博硕士点的发展历程，拥有教育部国际合作联合实验室，聚焦非线性电路、射频微波与集成电路三大方向。 00:21:45 代表性科研成果与技术突破 多个团队取得关键技术突破：杨世文教授团队在四维天线阵列、强耦合超宽带相控阵方面成果应用于中电十四所雷达系统；樊勇教授团队在毫米波平面天线、太赫兹雷达成像系统（分辨率小于1厘米）方面取得进展，并在成都大运会示范应用；李岩教授团队在微波测量技术上打破国外封锁；闫波教授团队实现毫米波导引头前端等多项系统集成突破。 00:25:43 人才培养成效与就业前景 在人才培养方面连续三年获得全国大学生集成电路竞赛奖项，荣获华为优秀合作项目奖。实施因材施教、育德为先的培养模式，常态化开展组会与一对一指导。毕业生广泛进入华为、中兴等领军企业及各大研究所，海外深造亦有突破，整体就业领域分布广泛且质量高。 00:31:30 物理电子学学科内涵与发展现状 物理电子学是物理学与电子科学技术交叉的前沿学科，涵盖微波电子学、光电子学、量子电子学等多个分支。我校侧重微波电子器件研究，在回旋管、行波管、磁控管等领域达到国际先进水平。起源于1956年电子器件专业，历经高能电子学研究所、物理电子学院等发展阶段，现为电子科学与工程学院的重要组成部分。 00:35:45 科研拓展方向与平台优势 近年来向上下游延伸发展：上游推进仿真设计与人工智能融合，推出具有自主知识产权的商用软件MMST与Qpic；下游拓展至毫米波雷达、无线输能、微波干燥等系统应用。横向发展至太赫兹技术与医学交叉，在太赫兹成像、保密通信等方面取得进展。拥有1个国家重点实验室、3个教育部重点实验室，年科研经费近2亿元，是国际最大的真空器件研究中心之一。 00:38:55 学生培养与职业发展路径 物理电子学方向共有9个科研团队，学生毕业去向均衡：约三分之一继续攻读博士学位，三分之一进入企业，三分之一进入研究所或从事公务员工作。近三年毕业生去向包括华为、8511研究所、高校及前沿实验室，体现了多元化的高质量发展路径。 00:40:21 学生视角下的择校与专业选择建议 博士生田雨桐从个人经历出发，分享选择电子科大的八大理由：城市优势（成都作为电子信息产业基地）、学校行业地位（985中唯一专注电子信息的高校）、学科实力（电子科学与技术A+）、导师匹配、科研平台、国际化机会、校园生活与奖助体系。建议新生通过学院官网、文献检索等方式深入了解意向导师，并积极参与夏令营等交流活动。 00:47:53 夏令营信息与直播互动环节 主持人询问关于学院夏令营的具体安排，发言人回应今年将举办夏令营，具体时间待定，鼓励感兴趣的同学加入QQ群获取最新信息。随后进行直播抽奖环节，公布口令“一生一世，逐梦未来”，并在弹幕中抽取幸运观众赠送学院定制马克杯套装，增强观众参与感与互动氛围。 | L3: 5 | M3: 3 | N3: 4 | O3: 0 | P3: =(L3+M3+N3)/3 -> 4 | Q3: 2.1 核心遗漏： QQ群群号没有提及 2.2 比例失调：介绍发展历程、博士生成果的篇幅过长 2.3 冗余：没有对博士生的成果进行有效概括 3.2 小标题合理性：择校建议标题与学院信息介绍的主题不符 | R3: 学院概况 历史沿革： 初期成立无线电系、电真空器件系、无线电零件系。 历经1979年、1992年、2001年、2018年四次院系调整，成立电子科学与工程学院、科辅示范性微电子学院。 2023年响应国家号召，成立电子科学与工程学院与基层电路学院。 学科建设： 一级学科：电子科学与技术（国家重点一级学科）。 二级学科方向：电磁场与微波技术、电路与系统、微电子学与固体电子学、物理电子学、电子信息功能材料与机构。 国防特色学科：电磁场与微波、军用关键材料、电子元器件。 党建荣誉： 学校党委入选教育部首批全国党建工作标杆院系。 学院荣获全国教育系统先进集体。 人才培养 本科生： 现有1545人。 招生专业：工科实验班电子。 工程类专业方向：电子科学技术（国家特色专业、国家级一流本科专业建设点）、电磁场与无线技术。 研究生： 现有硕士和博士研究生1975人。 招生专业： 学术学位：博士（电子科学与技术）、硕士（电子科学与技术、材料科学与工程）。 专业学位：博士（电子信息）、硕士（电子信息材料工程）。 培养成果： 荣获国家级教学成果奖二等奖5项。 本科生深造率稳中有进。 创新创业竞赛屡创佳绩。 研究生科研学术能力不断加强，就业布局不断优化。 涌现出许多优秀个人和集体，获得代表性的党建、思政荣誉等。 所获荣誉：连续三年获得全国大学生集成电路创新创业大赛奖项，荣获华为优秀合作项目奖，荣获研究生优秀导学团队提名奖，获互联网加奖项、国际上IETF奖项、优秀论文、创新创业大赛成果奖项等。 培养模式：因材施教，科学育人，宗旨是育才先育德，师生齐共建，常态化开展学术组会及三个一对一的面对面等体系化、规范化、国际化的培养模式。 就业情况：就业领域分布广泛，包括行业领军企业（如华为、中兴等）、各大研究所、高校，毕业生在海外留学方面也有不少突破。 教职工构成与师资队伍 教职工总体构成： 现有教师302人，其中教研系139人、科研系95人、教学系14人、实验系21人，教师总数269人，机关33人。 师资队伍： 两院院士2人。 领军人才19人。 青年人才28人。 其他类型人才12人。 后备人才61人。 荣获两个全国高校黄大年式教师团队：太赫兹科学技术研究中心教师团队（2018年）、电池辐射与膳食教师团队（2022年）。 融合4个国家自然科学基金为创新群体。 科研情况 科研经费：近5年科研到账经费稳定在3~4亿元之间，项目构成以纵向项目为主，横向项目为辅。 科研成果： 牵头获得国家科技奖励11项。 近5年发表高水平学术论文2000余篇。 专利申请1600余件，授权1300余件。 科研团队： 共20个科研团队。 年度经费过千万元的团队15个，其中过亿元团队1个。 科研方向： 材料、器件、电路系统形成完整学术链条。 频率范围覆盖射频、微波、毫米波、太赫兹等高频段。 形成从基础科学研究到工程实践再到产业化的一条龙创新体系。 科研平台： 国家级平台2个：国家电子辐射控制材料工程技术研究中心、微波电真空器件国家级重点实验室。 国际合作平台4个。 省部级科研平台7个。 国际交流 共建国际姊妹院系2个：香港大学电机工程电子系、香港城市大学电子工程系。 主办高水平国际会议13场。 学生长短期交流项目20多个。 专业方向介绍 电磁场与微波技术 细分方向：微波、毫米波电路；电波传播与电磁兼容；计算电磁学与工程电子学；天线理论与技术。 历史沿革：始于1956年电子科技大学建校时期，由林为干先生和谢处方先生共同创建。 专业特色：电子场与无线技术国家特色级专业；电波传播与天线、国防紧缺特色专业。 所属一级学科：电子科学与技术，入选双一流A类学科。 师资队伍：国家级人才计划入选者19人，其他众多中青年优秀师资，研究方向涵盖本学科所有主流方向。 研究团队：电磁辐射与散射团队、毫米波技术与系统应用团队、微波毫米波集成电路与系统团队、电磁兼容技术团队、微波测试与成像技术团队、无线技术与集成系统团队。 学科平台：国家自然科学基金委创新群体、国家高等学校学科创新引智基地、国家工程技术研究中心、国家级重点实验室。 硬件平台：中国高校最为先进的微波暗室群体，先进的微波、毫米波、太赫兹仿真测试平台。 主要研究成果 天线理论与技术：杨士文教授团队研究四维天线阵列技术，提供新自由度，实现低成本、高性能，提升系统整体性能；杨士莪教授团队在强耦合、超宽带相控阵方面取得进展，应用成果用于中电十四所某大型机载相控阵雷达；樊勇教授团队研究毫米波平面集成天线，可应用于毫米波通信、雷达系统领域，为新一代毫米波前端平面化集成化奠定基础。 电波传播与电磁兼容：李恩教授团队引领的微波毫米波测量技术，突破众多技术封锁，有60多年技术积累和传承；杨世文教授团队在电磁测井仪器方面研究获国家科技进步二等奖，成果在中海油成功推广应用。 微波毫米波电路：闫波教授团队引领微波、毫米波、太赫兹芯片研究，获国家科技重大专项及军科委相关项目，应用于新一代高速通信系统；在微波毫米波器件与系统方面取得突破，成果可应用于大功率合成功放、固态合成功率源、天线阵列、馈电网络等电路与通信雷达系统；在微波毫米波微系统技术方面取得进展，包含3毫米导引头前端、毫米波引信前端、8毫米宽带收发前端。 计算电磁学与工程电磁学：杨世文教授团队引领的计算电磁学研究取得重要成果，相关算法被评为20世纪十大算法之一；樊勇教授团队在太赫兹雷达成像方面取得进展，成功研制0.22太赫兹、0.34太赫兹、0.42太赫兹雷达成像系统实验平台，分辨率小于1厘米；同时在太赫兹通信技术方面有突破，成果在2023年成都大运会田径项目中成功示范应用；李岩教授团队在电磁波与物质互作用机理及测评系统方面，面向5G通信、高性能系统、生物医学、新能源等方向提供应用需求和研究成果；李恩教授团队在生物医学电磁学及成像方向取得进展，发表大量高水平论文，有20余项国家发明专利。 电路与系统 细分方向：非线性电路与复杂电子系统、射频微波电路与系统、集成电路与系统。 学科地位：国内首批授予硕士、博士学位的学科（1981年开始招收研究生、博士研究生），1988年成立首批博士后流动站。 学科平台：教育部国际合作联合实验室、国家高等学校学科创新引智基地。 师资队伍：国家级人才4人、新世纪人才2人、教授10人、副教授22人。 主要研究方向与成果 集成物理研究方向：樊勇教授和王成教授团队，聚焦CMOS集成电路与物理结合的前沿交叉学科领域，研制相关芯片及分子时钟、量子测控低温CMOS集成电路。 高速车地通信系统：白勇教授和李庭军教授团队，从事高速磁浮交通的38G赫兹车地通信系统研制，是高效、经济和安全的交通技术，实现安全、可靠、实时、宽带等，确保列车安全运行和基本保障。 毫米波通信雷达CMOS芯片：樊勇教授团队和张静植（本人）研究团队，面向通讯与雷达领域的新应用、新场景、新应用，探索集成电路设计的新架构；康康凯教授团队在毫米波CMOS芯片方向取得进展，包括超宽带的毫米波模块级芯片以及5G通信系统和雷达系统的研制。 电子信息材料与元器件方向介绍 方向定位：涉及电子材料与电子器件，是IT领域的物质基础与先导，推动电路系统与电子装备研发，概括为“一代材料催生一代器件，服务一代整机”。 内涵：以电子在物质中的输运特性（电磁、声、光、热力、化学生物类比特性）及外部作用为基础，设计、研究和生产电子器件，并在电路、电子系统乃至整机中实现工程应用，推动电子信息技术发展，涉及电子材料、器件、电路的设计研制、生产和应用，以材料为基础、器件为核心、应用为目标导向。 国家需求与市场： 中国是电子产品生产大国但非强国，2021年中国集成电路等电子产品进口额度达2.8万亿元，约为原油进口量的1.7倍，反映先进电子材料、元器件等是我国“卡脖子”问题之一。 电子产品在6G通讯、量子技术、智慧城市、光电技术、新能源、智能电子等领域作用重要，是国民经济关键支撑，广泛应用于物联网、移动设备、网络基础设施、无人驾驶、航空航天、医疗健康、可穿戴设备等领域。 预计2025年整个电子产品市场额度将达到万亿美元量级。 发展趋势： 电子产品向小型化、多功能、低功耗、智能化方向发展。 元器件朝着微型化、片式化、集成化、薄膜化和智能化方向发展，尤其强调材料和器件一体化。 集成技术发展趋势是结合摩尔定律制成缩小与超摩尔定律功能多样化，通过三维集成的微系统实现价值整合，通过介电、铁电、压电、磁性、半导体等功能材料的结构复合与功能集成，实现信息获取与处理，形成新一代信息技术物质形态或半导体技术物理载体的固态电子薄膜。 研究队伍： 包括国家级人才十余人。 邓龙江院士团队（电磁辐射控制材料与技术团队）：现有研究人员19人（正高13人，副高15人），重点开展可见光、红外、微波等频段电子辐射控制材料、结构和器件研究；发表Nature子刊等论文300余篇，承担国家省部级及国际合作课题130余项，年均到账经费3000多万元，授权专利100余项，获国家科技进步或技术发明奖二等奖共计3项。 张怀武教授团队（实电波膜与微型器件团队）：现有研究人员17人（正高15人，副高2人），重点开展LTCC材料及集成技术、微波毫米波晶圆及器件、自旋电子与磁量子器件、传感器芯片等研究；承担国家重点研发计划、自然基金重点、重大科学仪器项目及国际合作等项目100余项，获国家技术发明或科技进步二等奖共计3项，发表SCI论文400余篇，年均到账经费2000万元。 依托平台： 国家电子辐射控制材料工程技术研究中心：历史追溯至1990年校级材料与技术研究中心，经2008年、2013年两次升级形成；主要开展多频谱涂层电池材料与结构、智能材料与结构研究；拥有国际一流实验平台及成都佳驰电子科技等成果转化基地。 电磁薄膜与集成器件全国重点实验室：2006年依托新型传感器功率半导体技术、电子信息材料三个部级重点实验室筹建；结合电子信息系统微小型化和单片集成重大需求，围绕电子薄膜材料和集成器件开展基础、应用基础、工程应用研究；重点方向为磁电薄膜与微型器件、电子聚合物与阵列传感器、功率半导体与集成技术。 研究条件： 科研面积2万余平米，超净间3000平。 建设两条国家重大任务试验生产线。 拥有大型设备或系统500余台套，构建材料、器件、电路系统全链条研究平台，实现测试表征全覆盖。 材料制备：拥有各类液相外延、磁控溅射、化学气相沉积、分子外延、原子沉积等薄膜材料制备设备50余台套。 微细加工：拥有步进式光刻机、深槽反应离子刻蚀机等先进微纳加工设备30台套，具备电子功能薄膜微图形化加工能力，形成较完善的亚微米集成器件、非CMOS工艺实验线。 材料结构分析：拥有X射线衍射仪、粒度分析仪、X射线光电子能谱仪、扫描电镜、扫描探针显微镜、透射电镜等微观表征设备10余台套。 材料器件性能测试：拥有浪漫光谱、阻抗分析仪、分光光度计、差热分析仪、傅里叶红外光谱等材料性能测试设备50余台套。 研究成果： 高水平论文：在《自然》及其子刊近年来每年有多篇重要文章发表。 奖项：获得包括国家科技、国家技术发明奖共计7项。 毕业生去向：遍布产业界与学术界，包括英特尔、中芯国际、华为、德州仪器、中国电科等世界500强企业，以及国内外高校和科研院所，成为学术牛人、技术大拿、创新创业能手，在前沿基础研究、军工项目研发、产品技术开发等方向贡献突出。 优秀毕业生代表： 杨伟豪同学：在磁性非互易表面研究领域成果显著，以第一作者在《自然·电子》《自然·通讯》各发表一篇学术论文。 5G滤波器芯片学生团队：获挑战杯创新创业大赛四川省金奖。 黄飞：2018年四川省优秀毕业生，获斯坦福大学攻读博士全额奖学金。 李凤霞：早期优秀毕业生代表，读博期间发表学术论文16篇，其中一作6篇。 闫威：2021届优秀毕业生，2020年获华为光产线优秀合作项目奖，2021年获王大珩光学奖，博士毕业后以优秀青年学者身份加入苏州大学。 汪卫：产业界优秀毕业生代表，河北美泰电子科技公司副总，率先带领团队采用MEMS工艺研制出SiW环形器隔离器，突破卡脖子器件核心技术，实现高性能非互易器件产业化。 物理电子学学科介绍（李天明老师） 学科定义及范畴： 物理电子学是物理学与电子科学技术的交叉学科。 物理学研究物质能量的本质与性质；电子科学与技术研究电子在不同介质中的运动规律和与物质的相互作用，并据此研制电子器件。 结合方式：将物理学最新研究成果应用于电子学，产生新的电子器件。 典型分支及器件： 微波与电子相互作用 → 微波电子学 → 微波电真空器件。 光与电子相互作用 → 光电子学 → 光电器件。 维拉技术与电子学结合 → 维拉电子学。 量子技术与电子学结合 → 量子电子学。 学科特点： 内容不断充实（如量子电子学内容因量子技术发展而增加）。 学科边界不一定清晰，归类不一定完整（如光电子学既可属物理电子学，也可属光学工程一级学科）。 基础性与前沿性：强调数理基础，应用物理最新研究成果，具有应用前沿性。 重要性：支撑现代信息技术的关键技术学科，其电子器件是信息科技产业的重要组成部分。 学校的物理电子学： 侧重点：微波电子学，对应微波电真空器件（产生微波的器件）。 微波应用：在通信、雷达等领域应用广泛。 传统强项：回旋管、行波管、磁控管研究，达到国际先进水平。 发展历程： 1956年建校时，在前苏联专家帮助下成立电子工器件专业，归属电子器件系。 1979年，在刘盛纲院士带领下成立高能电子学研究所，专业并入该所。 2001年，物理系应用所、高能所合并成立物理电子学院。 2018年，物理电子学院与电工学院、微固学院部分合并成立电子科学与工程学院，现属电子科学与工程学院下的专业。 学科内涵扩展： 纵向发展： 上游：仿真设计、数字模拟、材料。推出两款具有自主知识产权的商用软件：MMSD、Chepico（国内广泛应用）。将人工智能引入器件设计和电子学应用。 下游：系统应用。例如：利用回旋行波管研制毫米波雷达；利用行波管做无线速能系统；利用磁控管做微波炉干燥系统。 横向发展： 频段上移：从微波到毫米波、太赫兹。 与其他学科深入交叉（如医学）： 太赫兹技术：太赫兹成像（分辨率高、透视效果好）、光电融合新太赫兹源、太赫兹保密通信与高速通讯。 医学应用：太赫兹成像应用于医学诊断，提高诊断准确性。 科研平台与成果： 科研平台：国家级实验室、三个教育部重点实验室、三个四川省工程中心或重点实验室，参与一系列行业协会。 成果：一系列国家奖、省奖；每年到校科研经费接近两个亿（学院内最多）；是国际上最大的真空器件研究中心之一，名气日益增大；2023年成功举办行业顶级会议IVEC（成都）。 团队与学生出口（李天明团队为例）： 团队：物理电子学方向共有9个团队（详情可查询学院网页）。 学生出口（团队情况）：1/3硕博连读，1/3去企业，1/3去研究所及其他（如公务员）。 李天明个人学生情况：每年约2名研究生、1名博士毕业。 近三年研究生去向：今年2人当公务员；去年1人去华为，1人去8511研究所；前年1人硕博连读，1人去私企。 近三年博士去向：今年1人去新加坡做博后，1人去前沿实验室，1人去高校。 选择电子学院的理由及研究生择校专业选择建议（田雨彤同学） 选择电子学院的8个理由（学生视角）： 城市因素： 成都：四川省会、国家中心城市、新一线城市，国家历史文化名城，古蜀文明发祥地，中国十大古都之一。 城市标语“成都都成”（梦想都成），体现古老文化底蕴与年轻科技活力。 电子信息产业发达：全国三大电子工业基地之一，构建电子信息全产业链体系，2025年规上工业产值达3298.9亿元，位居全国前列。 产业资源：英特尔、华为、京东方等众多行业巨头汇聚，提供实践平台和就业资源。 学校因素： 电子科技大学是985高校中唯一以电子信息科学技术为核心的院校。 网络评价：“走在路上都能捡到电阻等元器件”。 拥有电子信息博物馆，记录我国第一台晶体管收音机诞生。 构建了最完整的电子信息学科群（电子科学与技术、信息与通信工程、集成电路科学与技术等）。 中国民族电子工业人才摇篮，走出大批行业领军者。 专业因素： 电子学院电子科学与技术学科在第四轮学科评估中斩获A+，稳居全国第一。 拥有五大国防特色学科（如电磁场与微波技术、微电子与固体电子学），构建深厚科研底蕴。 教师团队能提供能力提升帮扶与保障，研究团队实力是学生发展的坚强后盾。 研究团队与导师： 选择标准：研究方向契合，期望志同道合的良师益友，团队正能量、经费足、就业好，能实现个人能力全面提升。 所在团队：毫米波技术与系统应用团队（负责人樊勇老师）。 研究方向：微波毫米波理论与技术、天线理论与技术、元器件与电路、通信技术与系统、雷达成像技术与系统。 知识覆盖：电磁场与微波技术、电路与系统，从芯片、封装、天线、电路模块到系统的全面知识。 科研实践：可根据兴趣和创新想法做雷达或无线通信系统，进行算法开发、硬件制作（基于FPGA、ARM等芯片）和实验室验证。 国际交流：鼓励出国参加国际会议、联合培养。 团队成果：学生发表大量论文，在学术会议竞赛上取得佳绩，获傲人奖项，就业率100%，就业单位包括知名企业和顶尖科研机构。 生活因素： 成电校园：硬核科研与烟火气并存。 休闲活动：湿地公园漫步、草地桌游、东湖边钢琴小屋弹琴。 难忘经历：2021年跨年主楼前300架无人机灯光秀拼出UESTC字样，留下浪漫与科技交织的印象。 奖助体系： 全覆盖、高额度、长周期。 奖学金：国家奖学金、学业奖学金、专项奖学金、新生奖学金及学校学院设立的其他奖学金。 奖助：校园地国家助学贷款、生源地信用助学贷款。 保障：各类奖助能保障求学期间基本生活质量。 研究生择校和专业选择建议： 选择导师： 先根据研究方向选择合适的研究团队，再选择合适的导师。 学院资源：拥有四大学科和19个科研团体，可从学院网站按兴趣选择团队，再进入团队网页找导师。 深入了解导师：若导师信息不完整，可通过HPOE、中国知网等文献检索网站，检索导师论文情况和指导研究生毕业情况，结合兴趣广泛调研。 联系导师：确定意向导师后，通过电子邮件附带简历与个人介绍联系，确定导师招生意向。 推荐关注：学院夏令营优秀本科生选拔计划和推免招生计划，提前来校与老师、师兄师姐沟通交流。 直播互动及后续信息 夏令营活动： 计划举办：电子学院今年计划举办夏令营活动。 时间：待定。 咨询方式：感兴趣的同学可加入QQ群（群号：978499108），相关信息将及时发布。 抽奖活动： 奖品：学校一整套马克杯（有学院学校特色logo，配套勺子和杯盖）。 口令：“一生一世，筑梦未来”（“一”是字母“E”）。 幸运观众：IWN同学、最爱冰粉凉虾同学、一男同学、尾号5240小提琴同学。 领奖方式：私信后台留下联系方式和收货地址。 后续安排 有意参加电子学院夏令营的同学加入QQ群（群号：978499108），以便及时获取夏令营相关信息。 抽奖获得马克杯的幸运同学（IWN、最爱冰粉凉虾、一男、尾号5240小提琴）私信后台留下联系方式和收货地址。 计划申请研究生的同学关注电子学院今年的夏令营优秀本科生选拔计划和推免招生计划。 计划申请研究生的同学可通过学院网站了解四大学科和19个科研团体，选择感兴趣的研究团队和导师。 有意向导师的同学可通过HPOE、中国知网等文献检索网站了解导师研究方向和论文情况。 确定意向导师的同学可通过电子邮件附带简历与个人介绍与导师取得联系，确定导师招生意向。 内容由 AI ⽣成，仅供参考 | S3: 5 | T3: 5 | U3: 5 | V3: 0 | W3: =(S3+T3+U3)/3 -> 5 | X3: 结构性最清晰，小标题最合理，可读性最强
A4: 3 | B4: 方思邈 | C4: • 发言者 1 00:01 然后我再说一下我们这个议程，就是我会说个几分钟，就是我们这一年的一些发展状况，就主要是一些数据，就是你比如说营业额开票额，包括年终奖的总额，我们今年也公布一下，但是个人上我们就决定就不一一的公布了，这个我们也和大家去聊，包括我也和一些朋友去参考了一些东西。然后然后我反正我总结完之后呢，我们我会给就是每一个我因为我们现在也分了短视频，商务商务没有坐在一起，商务还有我们的无论你叫文案也好拍，摄也好，拍摄都算执行吧， • 发言者 1 00:43 几个部门每个部门进行一个简单的一个评价，然后评价完之后我们就从这边开始好了，艺人就每个人都会就是说两句评价，但是一般都是肯定性的，有个问题性的，我们明年再说和去年大家应该也比较熟悉，我们就你可以理解为夸两句我们发个红包。然后我们评价完之后，然后那个就个人完评价完之后，我们就是在发这个就是我评价你的时候，你也可以逼几句就说几句，也可以没有台词，这个无所谓，如果但是说实话，人家有些公司特别是机构组织架构大的数值是非常重要的一个环节。 • 发言者 1 01:44 当然我也说我们年终奖的额度基本上是定了，如果你说的我不是说的好，你比如说有些我们的确是没有看到的你的一些工作或者价值，努力的台词，我都给你想好了，就这样也就行，这样就行。因为说实话这个数值我们也没有给大家压力，因为我媳妇之前也在别的公司上班，他们也就7、8个人还做PPT,做到2点多还睡不着觉，这种就那点人谁干的活谁还不知道嘛。反正就大致你最好是回应一下，因为你说自己的工作并不一定是给老板说的，就是也可能是给就是同事之间或跨部门之间说的， • 发言者 1 02:35 就是因为说实话就是虽然同部门之间可能相互比较了解，但跨部门之间可能相互都有点就是不了解，因为特别是当然可能这不是我们公司的问题，有其他公司有些一些商务会觉得技术我活都是我接的，都是我的功劳，谁做都一样，那技术可能觉得商务就靠一张嘴不说也可以，我们再次强调一下这个东西，然后这个完了之后我们会发就是单这个是往年我们没有的，这个是去年那个是李海腾，我当然也可能是你们的一个建议就是说我们欠缺仪式感。的确我们之前也不太注重这方面， • 发言者 1 03:24 就是但我们今年是比较认真的对待这件事情，包括奖金也有相对可观的，就是包括证书我也是真的认真的，包括字体我都是跟他认真对过的。我们这个证书也是40块钱一本，就是加上设计费，就是我们也我也是说你不要跟我那种掉掉色掉粉的，这个是皮质的，当然这个也不是每个人都有，这个我也会说一下我们的评价标准，然后还有其实还有两个洗手包没有寄到，也可能值个七八十吧，我觉得应该积分都一样的，反正这种还有一个我自己写了一个就找我发100的红包， • 发言者 1 04:12 有一个这个奖当然也有空奖啥也没有，我写的是反正大家说实话，如果我们就是能做的这里最大的一个原因就是我们去年是有增量的，这我现在我有的进行第1个环节就是一些数据的报报告，就是我们其实当然这个也是我们一个常年的一个现象，那我们年终奖都转账那一部分总额应该是不是总应该就是确切的就是226,000，这是然后我们一个成本，这个可能是我们最大的一个问题。就我们的成本控制是非常差的，如果我们今年没有增量成本控制，又是今年这个状况的话，我就不开这个会了，因为那你就想一想吧，我们就是在你前几天你在没发工资之前，我们花出去的钱就实打实的花出去的钱，就是包括我们人员工资，外援配音字幕租机器也是花了390万，这是非常我们的利润率可能是24%还是27，这是非常不可观的。 • 发言者 1 05:32 当然这个这是一个现象，我觉得这个最大的癌症的问题，根源的问题就是老板的问题，这个不是扯淡，这个就是老板对一些关心或者是关注不够，或者是不够雷厉风行出现了问题没有及时解决，这个是有问题的。然后这是几个这不是未来的展望，这是几个重要大数据。然后我们就是最高的工资就是我们有两三个人，就当然也包括年终奖，你拿到手的应该达到了20万，是切切实实的。打到20万不是十六七万，我说20万是可能就是20万多，还就是这个可能只是两三个人能达到这样的结果，我们平均的工资应该是拿到手的是1万块钱多。 • 发言者 1 06:31 这个我们2023年平均的人工的支出，但是我是相对的提高，因为你人数增多了，你成本增多了也是正常的，但是我们是相对的，就是你比如说大家理解也好不理解也好没问题，但是我们平时的人员的就是你平时工资拿到手的是我们多了就是提高了25万左右，然后我们年终奖其实比去年要多1312万多，因为但是去年有这种情况，我们大家也能轮换比较大。干满一年的也就四五个人，然后今年是干满一年的就是12个人，然后可能这个总额上就也有爬坡。 • 发言者 1 07:18 当然我们一句话总结的话，就是我们二三年我们的公司总量在提升，这是我们能坐在这的。人最大的原因就是总量提升，虽然你成本往上跑，但是你总量往上提总会有结余，但如果是去年那个体量的话，我们今年今天就不开会了，就告诉那我可能厚着脸皮说那我们今年运营状况不好，大家没有这个钱了，那只能这样。反正我们是总量在提升，然后人员的拿到的就是就员工拿到钱在提升，然后成本也在往上跑，这当然这是负值，这虽然说往上跑这是负值，那其实公司的结余但是到账来说是往下跑的，但是我们还有个百来万没收回来，其实没有是稍微缩水的。 • 发言者 1 07:59 那我其实对老板来说，我们每个人会比去年少拿个10万块钱左右，当然我也不装，我们即使拿的少也比你拿的多，当然我们也承担了风。险就亏了100万，有些老板一辈子还不起账，这个也我们也顶着这个事，所以有啥说啥这个事。嗯反正这是一些数据性的东西，就是关于这个成本控制的话，我们明年可能开会的时候再说这个事儿。大家对我上述的表述还有什么疑问吗？你可以问任何话，我觉得都没问题。有疑问吗？有疑问我觉得都可以问。如果没有疑问我们这趴就过， • 发言者 1 08:48 然后我们再说一下我们年终奖的发放标准。就其实这个从市场上来说是没有标准的，就是我也问了我每年我都会咨询一下我们同类型的公司或者一些电视台，其实其实有些还是人就没有这个奖，但是他平时的你比如一个商务部门，他平时几发基本工资，你反正平时有一些，但是年终没有这个，但是我们不管其他的参考，我们是以往是这样的，就是你比如说先从少了说就是你刚入职的可能也有，你比如说两三个月或一两个月甚至半年以内这种，我们都是发个红包， • 发言者 1 09:24 意思一下可能去年也就是600、800，我们今年也会多一点，可能1000左右。就是上下就是这是你来到这里不久的这种，但是还就满一年的这种，我们当然我们也有破格在做的，就有破格的，就你虽然干了半年，我们给你一个月还多的这种也有这种大家应就是总就是你的额度大的这个还有就是你干满一年的，我们一般是以一个月的基本工资为基准，当然这个只是基准，但是如果你没有多大披露，也没有多大的问题，会比这个高甚至会更高。就是你买了一年， • 发言者 1 10:17 那你说超过一年之后，我们可能就不会过多的考虑年限了，就考虑你这一年的这个东西，但我们往年可能是就是坦白言，如果我们干的比较久的，我们又非常满意的，我们是有非常高的预算的，当然实际上拿到的可能就是两三万差不多的，就这么个意思，这是实际的一个情况，但是我们也不是画饼，如果你年限够我们又非常满意。给个大几万是有这个预算的，我说的是预算，但是你得给个理由，就给老板一个理由给你这些钱，这个这是一个年终奖的标准。 • 发言者 1 11:03 然后不对，我准确的说就是我们以往和今年都是有的，当然明年这个我们明年开会的时候再说这个事儿，就是这是一个额度的问题，然后我们接下来环节就是每个人都会评价一下，就是然后你也可以说一两句，当然我也强调了，就是如果你有心理压力或者是表述没有那么好的话，就是可以不说，但是你为了自己争取利益，或者是让大家能了解一下，这个也可以有所在台词，你就围绕着你比如说我今年干了哪些活，你比如说短视频，我们也有些粉丝涨了多少或者之类的，我只是提示一下你说我做后期的我剪了哪些片子。 • 发言者 1 11:53 我你比如说我做了哪些，其实得到了某某某些的认可，或者是你如如果你像林建成，你可以说我们在组织这个东西就是分配活之类的，就大致说一两句话。就行。如果你要实在没抬头，比如说我今年就是做的很完美，我没有什么可以说的，明年我会继续努力也可以。 • 发言者 2 12:21 反正我再次想， • 发言者 1 12:22 因为我实在不想在这个环节，就今天主要是我来逼这我说的所有台词我也是我虽然没写稿子，但是我也过脑子的，这个也是包括我们今天准备也是有诚意的，就是这个包括当然最主要的是转账那一下，这个绝对从我们这个体量上来说，我们是比较有诚意的，就是我们作为老板来说也相对是大气一点点的，就我们相对体量的公司，我们我作为老板是赚的比较少的。好的，我们就开始这个从这边开始可以吗？那其实红叶子是我们入职两三个月的10月份入职的，这个有啥说啥试试吧，差不多8月8月份那11月份转正的。 • 发言者 1 13:09 其实也待了几个月，就是对，也祝王俊恒结婚快乐，哈哈。那我们也给了红包，表示了对在座的还没结婚的可以抓紧。那言归正传，就是其实我可能觉得比较低调，就是红叶子就是包括平时双方也不多，但是政委给予了非常高的评价，其实政委他可能就是相对严苛一点，他给予更高非常高的评价是不容易的，他说我们就很难招到这样的一个人才，既懂技术又懂英语，而且人家有这种把事情做好的这种精神头，包括人家说那种填工资表什么把一些我们有一个意见或者想法一栏，人家会写一些就是能怎么样把这个项目做得更好的一种认真对待了，当然其他人可能给我大叹号，让我把报销和工资一起发，那我也看到了，这样也没问题。 • 发言者 1 14:24 我就夸这些，然后那个郭东辉，然后他是我们干满一年的一个就运营，其实那我的评价也是相当于转述政委，其实人家是一个非常有经验的一个运营。 • 发言者 2 14:45 然后 • 发言者 1 14:49 我喝口水。当然就是也实现了一个就是我希望你能大致介绍一下我们这个账号的一些反正就是一些情况吧，你比如粉丝什么的东西大致说一说，因为这个你是没有台词的对吧？ • 发言者 3 15:08 我的话就是关于账号那边的话，他是比我更了解可以， • 发言者 1 15:12 那你一会稍微介绍一下，因为这个也是我们其实投入了大量的精力在做的，这个事情我们就是目前来说虽然没有变现，但是起码它有所发展也给我们一个软实力，就是说也有很大的帮助，人家会认为我们是一个综合实力非常强的公司，然后其实郭东辉的话是他其实是个非常有那个经验的一个运营，而且说实话他也克服了就是本不应该他要面对的一些困难，就是包括我达人那边，就是其实从某种意义上来说，可能是我们公司就是限制了他的一些发挥，其实应该严严格说严重一点，我们应该是表示歉意的。 • 发言者 1 15:47 这个我们让郭东辉大致说一下我们这个账号。你有台词吗？可以，是对2023年会。做一个总结，但是我可能 • 发言者 4 16:14 尽量做得少一点，就是抓重点 • 发言者 1 16:17 可以没问题，我们也不着急吧大家。没事 • 发言者 4 16:24 没事，然后就是我先说一下整体情况，2023年的话视频号我是从3月1号截取大数据，然后因为1号1月1号的话就是也没什么人就是没什么用，然后3月1号截取大数，据粉丝数是700。19人，然后到现在是8万是7:009:00的那个8万的粉丝，视频号就是微信视频号，对，然后它的涨粉的话是从6月20号第1条视频，也就是那个到外面去拍对话开始有一个起色，对。然后小红书的话是2023年粉丝数的话是1月份的话没记错的话是2000加，对他那个数据也是没有办法截取到现在是6. • 发言者 4 17:03 4万。然后抖音的话2023年的话是也是2000加对，然后到现在的话是5.7万，然后B站的话2023年的是3.1万，然后到现在的话是7.6万，就是整体大数据一个变化都是从6月20号那一条去外面拍摄的。视频开始有了转变，然后就是这个转变其实是比较困难的。在6月20号之前，潘老师已经多次我记没记错的话是有10次提醒我说小郭你出去找工作吧，我这个项目我不想干了，就是我就是凑合属于现在就是能抓，然后但是我觉得这个事情不应该是从我这里去放弃， • 发言者 4 17:53 我觉得如果要放弃的话，应该是黄大师他那边去说，所以我就一直在这块坚持，然后6月20号为什么是我要想说极力的说服潘老师到外面去拍摄，是因为有了其他的人来找我，说你要不来我们公司，然后我们公司给你的要是就是然后破釜沉舟的心情去说服了一下潘老师，结果他同意了，也有说过这个事，对，然后加上就是forty刚好也来了，然后那这个事情觉得还可以，那就继续坚持下来了，然后那这个整体情况重点项目的话，我觉得就是一个是涨粉的话，这几个平台都有一个很大的提高，然后还有就是账号变现，那账号变现到现在的话是课程拍到了，如果说十分满分的话，应该是达到了7:05的程度。 • 发言者 4 18:52 那一分的话就是那就是还有0.5分的话，我觉得是一个期待值期待空间，对，然后的话这个重点项目的话可以说是没有完成，还有一个重点项目就是直播，那直播现在的话目前直播了在视频号上直播了有4场，5场，然后的话是因为最后一场是那个新年的那个，然后就是平均在线人数都是比较高的，然后前100人的话是平均在线人数能达到50分钟以上，所以在直播内容上还有直播人数上，平均的话每次每场直播达到平均是5000人加这样的。 • 发言者 4 19:37 然后那对，只是现在没有课程，所以说他是可以进行变现的。然后刚刚还想说的话就是嗯接下来我就觉得说一下那个我的收获吧，我觉得这个整体的情况就是大致就是这样。对，然后收获的话，我觉得就是在认知上是我觉得最大的收获，就是有的时候觉得说服潘老师可能更难，就是他不会听你的，他在站在他的角度，他觉得你的高度没我的高，所以很难听，但是说服他还不是最难的说服。自己是最难的，因为我要说服我自己去理解他去对去要搞这个事情，要坚持把这个事情做，所以我觉得最大的敌人是自己，也是我很难说服我自己。 • 发言者 4 20:23 有的时候觉得很受委屈，对，然后因为我的事情，自从他那个就是没有他来之前我要各个平台都要运营，如果正常情况下一个公司的话，他是一个人拿一个账号，然后一个平台不同的平台一个人负责，但是现在是我都在负责。然后所以就是要处理这些事情，要把它分开，要怎么样去把这个事情就是可能说有的时候会精力不充沛，但怎么样去分配好，然后for,那个就是那个不是叶子来了之后他负责剪辑，然后还有一些其他事情，比如说我们的课程上架，然后开店，然后开企业店什么这些琐碎的事情，有一些东西是我没有经验的，然后我也要去了解去学习，然后再去开。 • 发言者 4 21:34 这个是我的一个成长。还有就是做任何事情，比如说在那个内容上还有做直播的内容上面，我都不是说我自己突然冒出一个这种想法，然后我就交给你去做，不是的，所有的事情都是有数据在支撑着，我就会去看，比如说晚上的时候我会在8:00~9:00，我就会抽一个小时去刷直播间，我到底去看看包括侃哥，包括那些就是巧克力，还有克瑞斯金什么之类，他们所有的英语老师的直播间我是都有在看的，我在看他们讲内容以及互动，然后在想我们要讲什么内容。 • 发言者 4 22:09 就是所有的事情都不是说然后还有就是还有一点上就是让我知道的是之前在6月份之前嘛，可能我就是一直在混日子，这个混日子就可能我是没有收获感成就感，还有就是幸福感就好，这是这几个都没有，但是我让我知道就是混日子其实比充实的日子更痛苦，因为可能把你丢进一个就是森林迷雾。你可能待一天你会更痛苦，不如让你走一条路，就是你去从这儿到这个店里去走，就是来的更清晰一点，对，所以我觉得就是这一点认知上的收获。然后还有能力上的话， • 发言者 4 22:55 我觉得唉能力上刚刚已经说完了，然后还有经验的话，经验的话我觉得最主要的就是一个破壳，就是有一天的时候我就突然我就不知道这个事情该怎么做，到底是离职还是干嘛，然后这个事情这个项目包丢失踪，潘老师拒绝然后然后我就想那这么一堆东西，我怎么样去给它解决掉呢？就是然后那天我正好吃这个鸡蛋，我就用手这个捏的话我是捏不动的，但是我就是轻轻往桌子上一敲它就碎了，我就很容易就扒了，然后我就觉得那我可能我找到一个点，我朝着一个点去做的话，我可能就能慢慢的去把这个壳给扒掉。 • 发言者 4 23:38 然后就是这样的一个对，整体就是这样。Thank you. • 发言者 1 23:52 其实这个我们也这就是我们自己做这个项目，我们也和我们一些搞运营的，人家卖虾或者卖螃蟹的，他们也非常惊讶就是说你们居然能做这么久，如果是他们的话，这种状况可能就放弃了。但是可能怎么讲呢，我们前两天也和政委聊这个事情，人家就聊了个人的工作能力或者是一些状况。那我给我的感觉就是说我们可能就因为有这样的员工，我要把这个事搞成了才才能对得起人家，可能是有这种想法，这个其实也是是员工也给予了老板的一种信心。但这个事从数据上或者是前景上来说，起码是向好的。 • 发言者 1 24:29 这个可能也我们也理解一些委屈或者是这种困难，但是我们可能 • 发言者 5 24:39 就给予一定的就是算补偿吧，反正就是。但我们就是因为他俩说完了他是一个部门，我们整体是对这个部门满意的，就是包括人的工作能力主动解决问题的一个想法。但是实际上可能真的是我们合作的对象和公司限制了这个部门的发展，可能是这样的。这个但我们是表示肯定 • 发言者 2 25:02 那个 • 发言者 5 25:03 好，这个部门就这样，那个由腾宇然后我现在不对还没发红包是吧？我知道你知道了辛苦。您受委屈了，谢谢。然后其实呃有等于我其实某种意义上来说是是我们应该是评价最高的，这个没有之一，这个人家都从这个职业性专业性还有纪律性上都是最好的这个但就从纪律性来说，并不是说当然按时上班是一一回事，就能按时完成交给人家的东西，人家就我们平时的所有的出现的问题，倒来倒去倒不到他头上，然后职业性的话就是人家无论对我们回复和客户回复，我先然后这个 • 发言者 1 25:59 都是非常专业的，就是特别是人家就是沟通上，就是我感觉就是他说的就是我说的我就是比我说的还行，就是当然可能有其他人如果，我在那个群里我都很着急，我甚至私聊你，我告诉你怎么怎么样，但是他完全没有这个问题，然后就纪律性上人家可能也几乎没有这种就是请假迟到请假有，但迟到几乎是没有。然后人家请假的话也会严格按照我们的规定来，人家会提前然后也会告诉我们室友，人家甚至会把工作安排也跟我们讲一下，就是在忙什么的， • 发言者 1 26:25 这个都是非常的标准的这个然后他的技术就是人家这个反馈也是比较好的，我记得就是那个我们应该是宁波城市吧，应该罗峰吧应该是人就跟政委说，如果不是你这个小姑娘做的好，你们做的这么慢，早投诉你们了，就这种反。重要的活，我有时候也会问一下林远腾是安排给谁的，他如果说安排给刘腾宇了，那我就把这个活忘了，就是肯定不会有任何问题的。那我们就先夸这些，就是先夸这些。当然我们也怕飘这个我也说了就是我们不能说你的缺点， • 发言者 1 27:18 但是说更高的期待嘛就是我们是希望你能如果期更高的期待值的话，就是综合的后期技术水平可能更高一点，就是因为我们就是你也能完美的胜任是什么各种类型的，就是其实在这方面其实实际上也是有提升空间的。但是我们也是怕你飘，就是这个也给你降一降，这个它的效率是最高的，但是这个也不会出问题，做的又好。 • 发言者 5 27:54 这个我们 • 发言者 1 27:55 这个和政委都是他也是夸了他半天，包括前两天我和林海腾也聊了一会儿，如果聊了有5分钟的话，他4分钟都在夸你。所以在年终奖这个基础上，就我们虽然在既定标准上，我们因为林海腾的这个肯定我们再给你拉一档 • 发言者 2 28:13 这个 • 发言者 1 28:15 但是他没有说任何人的坏话，他如果夸谁多我们就给谁涨一点，如果不夸或者忘了这个就维持原判。那我们是会应该因为你因为油桶你可能我刚才说标准了，它其实实际上是刚满一年的员工，就是第1年，但给我们老板好像感觉干了5、6年的老员工这样的错觉。所以这个就是我们年终奖应该会让你比较惊喜。当然我也问了你的期待，你说那个数我说没有那么多，但是实际上没那么少，可能还会翻倍，唉但是大家具体数额我就不透露了，这个这个就是这么个意思。 • 发言者 1 28:54 先夸这么多，然后好。 • 发言者 3 29:04 其他方面都已经可以， • 发言者 1 29:08 他嗓子有问题那个就少说就可以了，少说就可以了。那大家也鼓鼓掌吧，哈哈。然后那个欧阳就是他也是我们就是刚满一年的一个选手，其实我们今年也有意识的让他去多做一些其他类型的包括政委，其实在我们那个群里也有时候会说一下，这个我有印象就让他有些片子其实欧阳人也能剪，就是可能之前没有剪过。 • 发言者 2 29:35 就是 • 发言者 1 29:36 他其实人家是有比较认真的一个工作态度，就是技术水平能力呢就是能够而且有一定的学习能力，这一点是非常强的一个能力，就是也有进步，这个说实话进步这个东西是不是所有人都都会有的，这个包括人的职业能力职业态度这个都没问题，但我们可能觉得有提升的地方可能就是沟通能力，可能要再爬坡会好一点。这个我们也是比较中肯的一个评价，但是我们总体打分是不低的，这个也辛苦了。你有什么要说的吗？那你就说我明年继续努力，继当然也希望你能够继续保持这种进步也好，热爱也好，能够保持住这种，因为可能工作年限久了可能就慢慢就没了，但是希望你能保持热爱，保持进步。 • 发言者 1 30:33 其实他也比较好奇，那徐艺玲你干嘛板着个脸，我感觉没休息好，没关系，这个其实徐玉玲也是我们干的稍微久一点的员工，就是她其实最大的给我最大的印象就是人家其实就是这种一遍过的就是非常多，就是人家也在那个工资表上写着。就如果不是那种吹毛求疵的老师，其实人家就是比较仔细比较认真，就是你挑不出人家什么毛病来，这种也是比较不错的，而且人家从一个技术层面来说也是有进步的。就是原先可能只能剪一些课程，现在今年的话其实剪宣传片类的也是像模像样的，这个 • 发言者 2 31:25 呃 • 发言者 1 31:27 但是我们这我总感觉你不开心，这个我就不说了。哈哈。那我们就是 • 发言者 2 31:40 呃我也很 • 发言者 3 31:42 清楚。 • 发言者 1 31:43 什么那可以关掉，看应该不冷吧。我总感觉你不开心，我没有，那夸的不够可能。但是也不错，人家就是起码做课程类的，既有效果又有效率，这个人家得到好评也是比较多的。因为之前我们你像之前那个杨晶就是有个项目，人家其他人做不了，人家做完了就是人家人家就说你还是让那个小姑娘来做，就这种我们听了也很开心，这种我们也表示就是认可。但我们可能更高的期待的话，我再想想可能更开心一点吧。更高的期待这个我明年再说，我暂时想不着，好你也辛苦了，我给你送过来嗯嗯。 • 发言者 1 32:40 你有台词吗？ • 发言者 2 32:45 呃 • 发言者 1 32:47 然后那个张文倩这这个也是我们就是一个可能能和大家工种不一样，其实张文倩是一个比较灵光的一个人， • 发言者 2 32:57 就是因为 • 发言者 1 32:59 说实话，有些人可能就稍微的就是不是那么灵的话，他是做不了这个活的，因为他做的活我不知道大家有没有争议，他其实需要综合能力更强一点的，既需要沟通能力，也需要专业水平，就是都是需要的。其实他的表现其实高出了我的期待，其实说实话我可能认为有些难的活，你比如说像宁波或者是那种活，我以为是干不了的，但是人家也完成了，就是能干得了，这个其实是出乎我的意料的。就是刚开始我和那边沟通，我都打好这个谱，我就以为可能就黄了，但是人家也能搞完，这种也是一种能力。 • 发言者 1 33:37 当然可能如果说期待的话，就是因为年龄和工作年限的问题，从经验或者是感觉上职场老人肯定是有所欠缺的。但是我觉得从一个灵光性来看的话，就是其实也能进步，这个也就从我们公司的角度出发，也能发挥更大的价值。反正我就说这些，你有台词吗？ • 发言者 6 34:07 这些我肯定觉得我今年在那个法院的那个项目上虽然是做完了，但是我同学跟他们沟通上，会比较吃力。对，因为他们总是在就是踢皮球，我也不知道就是这个标准我到底该怎么做， • 发言者 2 34:28 对。 • 发言者 6 34:30 别的就没啥了。 • 发言者 2 34:32 可以。 • 发言者 1 34:34 红包给了吗？好，没给，不好意思，我有点。你辛苦了，受委屈了。然后那个市井其实市井的话一直是我们就是后期方面的一个技术标杆，这个虽然我们可能从2022年就是大家也能够去分散一下，就是其他人也能做。但是从感觉上来说，它依然是我们在座的最好的没有之一，这个依然是这样的一个情况。那我们其实其实往年夸的也挺多的，台词的话我们可能没啥变化，但是从技术感觉上来说，就是个最好的没有之一，这个也是比较中肯的一个评价。 • 发言者 1 35:23 那我们可能之前也有期待就是说能参与一下项目的东西，但是可能人家但是我们也尊重了人意见，也有聊项目或者什么的，也尽量的没有麻烦的，但是可能有一些你必须你去的聊聊后期的这些也也去开会了这种。当然我们整体来说依然是我们就是攻坚的一个就是如果有些就是他能干的活就是就是其他人可能也能干，但是说实话就是从一个品质上来说，就是更高的品质上来说，它依然是最好的，没有之一。这一点是事实。那我们更高的期待的话就是也怕飘这个期待你有台词吗以前？ • 发言者 3 36:18 加油。可以。 • 发言者 1 36:30 我们期待的话，我们也是真的希望能解决一部分我们认为比较难的一些一些问题， • 发言者 2 36:36 就这点 • 发言者 1 36:37 可以吧。红包这么远。辛苦了然后钱德峰他是也是我们元老级的人物了，这个可能他就是我们其实特别是后半年这个拍摄是非常密集的，甚至两个月连轴转，没有一天休息这种。也有就是我们因为我个人也是当年也是也不能说走南闯北吧，就是到处拍也是干过这活，我也知道这种辛苦，有时候你比如说回到公司已经很晚了，又要再开车去很远的地方，你这种情况也有。他除了自己去拍摄之外，就是也给我们就是安排了这个拍摄的人员，这种也是一份操心，这个 • 发言者 2 37:24 呃 • 发言者 1 37:25 但是非我觉得就是从一个个人的一个占时间占用上来说的话，可能我们侵占是比较大的。当然我们也就是收入也还可以，就是这样形成这样一个说法。 • 发言者 2 37:38 呃 • 发言者 1 37:42 但是他也平时其实从我们运营层面，你比如说给我们说就是办个停车券之类的，给老师感觉会好一点。包括有些设备更新也是就是其实严格意义上来说，不是他本职工作，人家也也某种意义上呢也关心了公司的一个发展，这个当然他也是干的比较久，也可能也会考虑到公司发展的好，我收入也会好一点这种。出发点就是我觉得，但是人家无论什么出发点能关心公司的一个发展，那我们也比较开心。 • 发言者 2 38:15 就是嗯 • 发言者 1 38:19 那我们更高的期待可能就是希望能有更强的执行能力吧，就是项目也好，或者是沟通谈判也好，就是这样的一个期待。你有台词吗？可以总结一下自己的总结 • 发言者 6 38:35 一下事实。是就是二三年吧， • 发言者 7 38:38 然后拍摄很多都很密集。然后其实我不知道这个算不算。对民营的规划那我还是先说一下吧，就是之前说到那个成本很大，其实有一段时间是我们请了很多天的外援，但是其实有一些东西我们公司自己人内部就可以。搞定了，比如说上午谁有空谁去一下，其实就是很简单的按个机位。然后只要让机器不关机就ok.那其实这样的人我们公司都凑不出来。其实觉得挺意外的。但是有可能跟后期他们活也很多也很麻烦，但是我算了一下，你把这个就是你拍的这一截给外援，跟你找找那种拍摄的外援，两边价格是差很多的，其实我觉得我其实我主要是针对这边的后期。 • 发言者 7 39:27 如果可以的话，其实可以尝试着拍摄，因为一这方面也是收入的提升，然后也是然后体验一下，因为我感觉我喊了之后，其实很多人由借口运用一个没空很忙不想去，但我觉得其实可以体验一下。然后另外我还夸一下，我们拍摄的这几个小伙子，其实后期方面我不知道他们咋样，但是在干事情方面永远都是很积极的，就不会说什么我摸鱼我挣钱不多，因为有对比，因为我们喊的新颖的那种那种助理他们都是很那个的，然后他们都干活都会很得劲。差不多就是这样子了。 • 发言者 1 40:10 可以大家鼓掌。对，我们其实也其实在去年的时候也说我们西其实大家也能了解，我们其实拍摄来说相对性价比会高一点，但是我们也没有阻止任何人去参与这个。但是可能也的确是就是没有安排开的原因，我们是期待着就是大家都能拍。所以你别不用说技术水平多高吧，你起码能应付得了也行，这个对大家的自身的这个就是值钱的一个市场价值也是也是提升的一个东西，反正我们明年还是靠这个往这个方面靠，就是希望大家每个人都能都能参与一下。 • 发言者 1 40:49 好的。对，当然刚才也说到一个拍摄，就是我刚才可能忘说了一点，就是当然拍摄是非常辛苦的，但是我们在发年终奖包括这个奖的时候，我们是侧重于后期的这个我不管你们开心不开心也好，就是我们主要是当然大家都辛苦，但是拿到了钱，其实后期要比前期少一截的。这个是事实你们有这个感觉，这个如果达不成一致的话，那就达不成一致了，我们是有这个侧重的， • 发言者 2 41:31 反正 • 发言者 1 41:32 希望大家也能理解。但即使这样，你的拍摄的应该也不会比后期少，这个我们也掌握了这个平衡。但是我这这个可能是我在年终奖或者发奖项唯一愿意解释的一点，因为其他的我发这个奖是我们老板的一个主观意志，那你也不用来给我说我发了多少怎么样，其他的我就不谈判，但是这个是我唯一愿意解释的一个原因。然后下一个 • 发言者 7 41:58 无论是不是应该插一嘴，不要因为这个事情就不去拍摄。了。 • 发言者 1 42:03 对，这个其实我们当然这个是明年再说的，有些时候你比如说林远腾或陈德峰问到你，你不能直接说我没空，或者我这个是非常不职业的。说实话这个包括有时候我问到都会说，首先说我没空，但是如果你领导问到你应该起码解释一下我手头上忙的东西。或者说你勉为其难安排一下。你如果真的直接就说没空的话，这个是非常不职业的，就是在就是在职场这个环境下，但是也不要因为我们就是多发了奖，不干后不碍事。反正大致是这个意思。然后那个徐武安其实雄安就是就是也是比较灵光的人， • 发言者 1 42:45 眼里也有活，就是包括我们今年你像那个去警察学院驻场，这个也是一个人孤苦伶仃的，也非常的辛苦，也非常孤单，这个包括人当然那边反馈也不错，就是人家也是刚可能刚去的时候有点不适应，人家说你这个人是是不是就是经验欠缺，但是后来人觉得可能是我们误会，人家觉得唉挺灵的，就是这种。有些拍摄还挺多的，就是当然也是也比较辛苦，眼里也有活儿。其实就是拍摄和后期的技术水平呢其实也过关的，但是拍摄的技术水平我感觉好于后期的技术水平，这是我们的一个感觉或者错觉。 • 发言者 2 43:36 那 • 发言者 1 43:38 还有我们整体评价也是不错的，也比较灵也比较辛苦。好。你有要说的吗？其实老板 • 发言者 8 43:46 明年及时努力 • 发言者 9 43:47 行也可以。好好发财，好你也发财。 • 发言者 1 43:56 然后那个就是那个叫宋俊逸。然后宋金义其实是我们刚来了应该是两两三个月吧，我 • 发言者 7 44:07 10月份。 • 发言者 1 44:09 那前期是政委招聘进来的，这个我前期是没有多少的一个接触。其实我给他的第1个活就是我们宁波的有一个拍什么就两分钟的一个小宣传片的一个活。就是这是我安排给他第1个活。当就是我把一些要求发给他的时候，我印象里可能就一会儿可能当然就是他就把他那个写好的文稿发给我，他是一个其实和张文倩是同同样的一个工作内容，这个是一个编导的一个职位，大家应该也了解吧这个。就当他给我发来这个稿子，我一打开的时候，我就觉得这个人是对的，就是能干这个活，而且效率比较不错。其实行家有没有就是说什么， • 发言者 2 44:52 叫 • 发言者 1 44:53 叫行家一出手便知有没有就是这个从第1次安排活，我就觉得他是可以的。就是能解决问题的，包括我们后来有一些什么监狱或者是一些财经的一些人家没有出现任何问题，就是交给他是完全放心的，这个段位也比较高，这个我其实我们这个岗位明年可能也能发挥更大的价值。合作用。 • 发言者 2 45:20 好。 • 发言者 1 45:21 你有什么台词吗？ • 发言者 7 45:24 初来乍到，大家多多关照。今年就是 • 发言者 9 45:28 可以。 • 发言者 1 45:30 我没少吧，1234512345没少。 • 发言者 9 45:37 辛苦了。 • 发言者 1 45:41 然后下一个是张扬，这个 • 发言者 9 45:43 其实 • 发言者 1 45:45 其实张扬是我就是我们公司邀请来的人才，就是是我们请人家来的。就是当然也是应聘。也是来了半年，应该满打满算半年左右。差不多其实人家的到来也给我们带来了一些改变。包括人家的一些职业态度，还有工作能力，大家其实也有目共睹，这个是也我不能说完全达到了我们的期待，就基本上达到了我们的期待。当然我们也给了一些比较有诚意的一些待遇，这个也是也是对应到了我也怕太飘，就是我不多夸。然后就是我觉得可能有些问题，那不是个人的问题，是老板的问题，就已经有这样的一个态度或能力的员工，如果还出现问题的话，那就是老板。 • 发言者 1 46:34 就是或者制度管理沟通的一些问题，就飘飘的话的，这个是实际的，但我们对对这样的一个人才我们表示就是认可。当然还有我甚至觉得我2023年干到最有价值的一件事就把他招进来。这个其实是个最，当然这个我是非常的中肯的说这个，但是我们也非常怕你飘，这个你问题也很严重，那具体问题明明年再说，然后谢谢。 • 发言者 9 47:12 好，辛辛苦了。你有台词吗？首先的话就是 • 发言者 10 47:18 表演感谢一下真的部分海豚，还有我们所有的后期。 • 发言者 1 47:22 你这种面上的话要少说，我要打预防针。 • 发言者 10 47:25 首先他们两个确实是因为晚上的时候确实有时候9点多10点多甚至11点。然后给他们发消息，他们回的确实挺积极 • 发言者 1 47:33 的，你是在说你也很辛苦吗？没有。 • 发言者 10 47:36 还还有就是我们后期，因为有时候确实有很多项目很急，然后我就会去找他们，然后让他们抓紧给我做，然后并且要做好，然后我要给过去。然后他们也都是很准时的完成了，然后甲方那边也没有什么大的问题，然后这个要特别感谢他们。然后另外的话还有就是可能就是那天我们谈的三五百万，其实除了投标以外，私下还有很多看不见的付出的，别人是有的，这个你应该也懂，我懂了直接把领导抓好。对其他我们服务是 • 发言者 1 48:07 行，好像没有感谢领导算了拉倒，我们不缺男的 • 发言者 10 48:13 都不是厂的，就基本 • 发言者 9 48:16 可以。 • 发言者 1 48:20 观赏度要不就略过去。了。对，其实从人家其实从技术的段位上来说，其实可能是比较高的，就是虽然人是新人，但是就包括人家做的一些项目，我们也剪了一个财经的宣传片，这种我看了一下人家是不是不是不 • 发言者 10 48:47 剪。头发 • 发言者 1 48:48 有你剪的。我知道我知道，就是我看了一下他剪的东西，其实是是上道的，就是能达到一定的行业标准的。所以这个从预期来说也是高于我的预期的。但人家好像也能做一些包装之类的东西，就是政委也说其他人可能不知道的东西，人知道这个这个段位上来说是让我们有点惊喜。就是你做三维也能做吗？可以，我们其实往年的二维三维都是外包的，那我们可能也能解决这样的一个问题。我们也表示认可，就是你有你没有台词吧应该。行可以的好的。 • 发言者 2 49:29 好。 • 发言者 9 49:30 辛苦了。 • 发言者 6 49:33 嗯嗯。 • 发言者 1 49:35 然后那个林海腾我们 • 发言者 9 49:38 其实 • 发言者 1 49:40 我们其他的人我们可能是 • 发言者 9 49:42 就是 • 发言者 1 49:43 就是从技术层面和个人执行层面的一个认可，但其实林海腾对我们运营层面其实有比较重要的一个作用。它也是上传下达，就我们有些声音也是通过它来传达给我们，因为坦白言，虽然无论老板脾气多好或者多么平易近人，你们也不会有些话自己也能说，但是可能也碍于这种就是也怕老板开心，不用开心，也但是和林海腾说的多，他也会传达给我们。包括他那个我们后期安排是一个很繁重的一个活，那我们先夸这些先夸这些。 • 发言者 2 50:20 好辛苦。 • 发言者 9 50:24 你也稍微说两句。就是其实今年 • 发言者 11 50:30 牛的那个整体的昂昂程度其实比去年差，而且种类是比去年要多。但是就是我安排活今年就是会有问题，因为有些活我不知道应该安排谁或者谁能够去完成，然后有时候就是只能说是硬着头皮就是安排一下没有做过的人。然后其实都完成的挺好的，就是不怎么需要我再去额外的操心。那这点我觉得是今年就是我们后期整体的进步还是还是挺大的。就是包括个人能力方面，就是我们以前都会有一个就是可能后期人员之间有个明确的分级。但是今年就是这个分级就模糊了，就是大家就是效率都差不多，就是有特别快，但是整体上差不多。 • 发言者 11 51:20 然后制作能力上也是作品。所以说这一点上就是整体技术上的一个进步。当然就是劳累程度上也是经营也确实特别的累，就是包括晚上包括周末，反正我有印象的就是今年尤其是后半年，就是基本上都在加班，很很少是在就是有一个正常的装修。那这个劳累的话，同时还能在保证质量，我觉得是一件非常很不容易的一件事情。而且大部分其实是这种高强度的工作是大家都会有怨言的，但是就是有怨言，但是还是会接着干，这个我觉得就是一种职业操守。 • 发言者 11 52:06 就是大家 • 发言者 9 52:10 Ok.就像这些。 • 发言者 1 52:16 但其实我们在就是当时和政委在商量这个年终奖的时候，我们就是加班这一块我们也有所考虑。我们不能说奖励加班，就是我们就再补贴一部分，就是也有可能有一个一两千的一个考虑在里面。 • 发言者 2 52:31 就是 • 发言者 1 52:32 也算是有所补贴，也有考虑这一方面。 • 发言者 9 52:37 好了。 • 发言者 1 52:38 红包给你了，然后李国宇 • 发言者 9 52:42 但是我要再说这个 • 发言者 1 52:44 其实加班的话，这个也是老板的锅，就是本质上是我们没有及时的就是招更合适或者是更合适人数的一个人员在做这个事儿。当然这个可能给我们错觉，因为商务那边就是我们可能是招人，其实商务给我们的活我们是第1信号，如果连续不断的来产生业务，但是我们是有断断续续的，就是可能给我们的错觉就是我们认为是不需要招这么多人的，但是我们平时积累的一些人脉资源又 • 发言者 9 53:17 又不确定， • 发言者 1 53:18 你知道吧？所以我们没有及时的招合适的人数来做这个事。也是我们的判断失误，就是是有这个原因的，就是人不够嘛，这个加班这个有一个非常直观的一个因素，就是人不够嘛。那你说效率也有，但是你这个人不够是最大的因素，所以这个是我们的一个判断失误。好了我就不扯这些了。然后李国宇 • 发言者 9 53:46 你应该不需要吧？对， • 发言者 1 53:48 李国宇也是我们今年满满一年的一个选手，就是他的拍摄水平其实也算在我们公司算比较高的，就是也能胜任一些就是稍稍高难度的一些东西，但是我们可能更期待能你比如说我们有一部分成本，就是外援就是虽然大多数是忙不过来，但是有一部分也是我们技术水平达不到，那我们希望你是能达到这个段位的。有些包括给人家段位高的人去拍，也多多学习这种。但是本身就从工作年龄，你实际年龄工作年限来说已经是比较不错的。而且除了人拍摄之外， • 发言者 1 54:28 他其实后期是非常有灵性的，就是能进步能听懂，因为我之前给他让他剪了一个理工的那个我其实看第1遍的时候，我觉得乱七八糟的，可能，但是给人说说说给他逼一顿，人家完美交差就可以。其实这也是一种能力，当然我们可能更高期待就是你的沟通能力，其实有些但我说这个也是为了怕你骄傲，这个你也有问题，而且很严重。咱们大致就说这些，你有台词吗？我明年会继续努力。从我的开始，谢谢。 • 发言者 12 55:07 排到最后了，其实 • 发言者 1 55:09 张启是我们就是目前就是也是干了一年的商务，就是但他的预期就是他的表现也高于了我的预期，我本来以为就刚开始面试或者沟通，我以为他会比较害羞的一个人，那反而没有人家还玩的挺开，就是包括其实还挺外向的一个人。就包括平时工作能力也有一定的主观能动性，就是不是指一步动一步的，你包括联系客户主动打电话，我们有时候也没安排到，人家就去做了这个事，也有一定的主观能动性的这个那我们可能更高的期待就是，但是我那天也叫他聊了，我们其实商务这边我其他人可能也有些质疑，比如我去聊了半天，然后这个项目可能比较容易拿下来。 • 发言者 1 55:47 其实我们做老板来说，给他的支持比较少，他几乎没有什么项目，我们就帮他聊了聊，或者是帮着他走走打打理这种。我们后面也会考虑帮也给你更多的支持和帮助，就这样，好，谢谢。 • 发言者 12 56:09 你有台词吗？ • 发言者 10 56:11 其实就 • 发言者 11 56:12 2023年就是我自己对我自己的预期的话，我感觉年终对我自己来说，我感觉是没达到我自己的预期的， • 发言者 2 56:20 就是 • 发言者 11 56:23 可能是效率也是一方面，然后包括可能是时间也是一方面。另外的话可能就是项目包括项目上对同事的沟通和那个和甲方的可能做的不太好，明年继续用这个。 • 发言者 2 56:37 好好好， • 发言者 12 56:38 你说没达到预期是你对自己 • 发言者 1 56:41 我还以为年终奖没有达到你的预期，反正我们大致这一圈就下来了，然后那个我们是对个人也进行了相对中肯的，但是我们也没有说说说票。量化，但是也是我每一句每个人的台词，我真的是认真想过的。这个不是说现场发挥的也是比较中肯的，当然有些问题也是存在的，那我们在这样一个场合也不可能去再说这个大家也都过年了，也都不会记住，没有那个啥。就是没有作用，那我因为我们也分了我们的短视频，我们的执行，我们的商务，我每一每一个部门我再评价一下，也说一句就是期待吧。 • 发言者 1 57:22 其实我们对于我们短视频部门我是满意的，包括我们公司就是满意的。那我们整体评价我们是认可的，包括克服困难的一些过程。我们都是非常认可的。然后包括明年我们期待的话，我们是希望这个账号能开始变现。然后我们作为老板的话，我们也会投入更大的精力在做这个事情。这个也会给予足够的重视。这个说实话平我们已经比较重视，你像平时拍摄什么的也都是政委自己去，所以其实政委虽然有些问题没解决，但是他也也在解决，他也尽力了，反正我们是对这个部门的一个期待。 • 发言者 1 58:05 那我们对说实话你们也没有这个意识。那我们也是表示认可，这个辛苦程度表示认可，我们今年做的项目也没有做砸过，当然满意度也整体也还可以，就是我们期待明年的话，我们可能就是我们老板能够更多的进行一些组织协调。然后能效率包括大家工作的一个开心程度，或者是能压力，别那么忙碌，可能尽可能少的就侵占大家的一个休息时间， • 发言者 2 58:48 这是 • 发言者 1 58:49 一个评价和期待。然后我们对我们商务部门的话，我觉得从今年的话是基本上达到，就从结果来看是基本上达到了我们的，当然可能他们没有说数额，我大致理了一下，应该拿到的活应该有个300万左右，就整个部门来说应该差不多的意思。张扬应该差不多。是吧？应该要多一点吧，应该多一点，我的意思你要把那些入围什么都算上的话，那肯定是的。我觉得实打实的项目应该是300万左右。左右应该是多应该是多的。应该是不止的，应该是不止的，就是这是一个结果。 • 发言者 1 59:22 那我们明年的时候，我们可能因为这个部门 • 发言者 2 59:34 就是 • 发言者 1 59:36 那我们这是期待，那我们对老板来说，其实我们今年说实话给予的支持，或者管理或者是关心其实是不够的，这个我们明年会反思这个问题。反正这个我是对部门也有展望，也说一句话都是这个我们面上的东西应该就说完了，我应该没落到环节吧。那我们是先抽奖呢还是先发奖呢？啊。先发奖，那我们首先我先从，但是我们钱的话就是具体数额我就不公布了，但是有1万多块钱。的整体。可能就是从从小到多吧。对，还有这个就我们的年终奖也好，红包也好，是以发到手的为准。 • 发言者 1 01:00:36 就是我和你比的那些不算。而且有一种就是我可能因为聊的人比较多嘛，可能偶尔一嘴提到了一个数，你可能记住了，可能不是。我可能记混了也有这种可能性。但是不是说少给大家，有些你很多人我说的那个数可能，还要高一点。反正以发到手的为准，万一我发之前我发现你有违法乱纪，那就不发了，小概率事件。那我们先发这个就是最佳新人奖，这个其实这个奖项来说也是去年李海腾要求不是要求就是建议的对吧？应该是当然可能你们也有跟他说说也之前也说我们欠缺这个仪式感，那我发的时候要不要合个照？ • 发言者 12 01:01:33 不要。 • 发言者 11 01:01:35 要。 • 发言者 1 01:01:36 那李海腾一会给我拍一下吧可以吧？如果不愿意合照的话就算了，不愿意就举手说我不合了，这个也没问题。人家我看有不少人人家拿到了还发个朋友圈啥的也也行。 • 发言者 11 01:01:48 我们公司的微信公众号其实可以更新。 • 发言者 1 01:01:52 也可以，反正我们先发好这个我们先说一下，我们一共是6人，然后是5项，然后第1个就是最佳新人，最佳新人可能就是今年入职的，然后我们第1个有两人，然后我们第1个是颁给红叶子，然后大家鼓一下掌。好，现在倒也有个红包也有红包，我也看一下我也别发错了。这个相对多一点厚一点，这个我也说一下这个情况，说实话这个我们在定这个奖的时候，我们是非常认真的讨论的，这个是非常严肃的对待这个事情的。 • 发言者 12 01:02:28 就是 • 发言者 1 01:02:30 要不要掀口罩，可以掀口罩可以。掀口罩，你今天能给我拍一张吗？ • 发言者 12 01:02:36 好。 • 发言者 1 01:02:40 红包也拿一下，哈哈饿了。 • 发言者 12 01:02:44 可以的好可以的，好谢谢。 • 发言者 1 01:02:46 其实说实话这个我们是在非常认真的对待，这个也非常严肃，就是其实政委是说我说最佳新人奖颁给谁，说实话这个我还有一愣，但是说的确是有这个信息差，但是政委也给予了非常高的评价，他说既有技术又有把这个活做好的一个心态，又懂英语，这也是非常难得的，所以我们大家可能也有这种也有信息差，但是这个是我们老板肯定更了解一点。行，这个就说这个公平性是非常公平的，和任何人非亲非故。然后第2个最佳新人奖我们是颁给张扬，这个我们也刚才说了这个先合照。 • 发言者 10 01:03:35 还有红包， • 发言者 12 01:03:37 没忘。 • 发言者 10 01:03:40 没有，我是怕忘记了。嗯。好 • 发言者 12 01:03:46 可以的，好谢谢， • 发言者 1 01:03:47 这个我也说了这个刚才我说可能有点信息差，但是这个是没有信息差的，因为我们平时沟通这种也比较多，这种就是没有信息差，大家也比较认可，就是工作能力工作态度或者实际的作用都都是可以的。那么第 • 发言者 2 01:04:06 ok • 发言者 1 01:04:11 我们下一个是班就是最佳进步奖，这个我们是颁给那个那我没有忘记，这个非常准确，是颁给欧阳小元，这个我们也刚才说了，他那个来 • 发言者 12 01:04:27 先拍照。好好好。 • 发言者 1 01:04:37 这个我也刚才说了，你先坐。 • 发言者 12 01:04:39 就是其实 • 发言者 1 01:04:42 技术进步就是从你去年做到这和今年做到这，其实说实话进步是不是所有人都有的，这个它是明显的跑了一截，所以我们这个也是给予了肯定。这个希望你开心，当然也希望你真的能往后的日子能保持专注，也能保持热爱，保持好奇。好吧，大家也鼓鼓掌。这个是真的非常中肯的祝福话语。那我们下面颁一个就是我们这个奖其实是政委搜了好久这个名字，因为我们想解释一下就是这个奖是能意思就是能完美的胜任我们后期的各种的类型的。是完美的胜任，不是说你能做是做的最好的，就是我们课程微电影MV快剪，类全都能完美的解决， • 发言者 12 01:05:37 这个说实话。 • 发言者 1 01:05:38 那我们这个名字真的是当时在这个电脑上搜了半天，叫后期独挡一面讲，但是有点拗口，但是但是就是我解释了一下，但是和这个名字可能不太搭，但是我们搜了半天可能觉得这是政委手写上去的，可能是名字称上也是我们独有的，应该其他的没有这个讲。 • 发言者 2 01:06:00 就是 • 发言者 1 01:06:02 对这是那个 • 发言者 12 01:06:03 李不 • 发言者 1 01:06:05 续集，我可能谢谢。心急。好。 • 发言者 12 01:06:17 好好好，谢谢。 • 发言者 1 01:06:20 那我们这个其实从技术层面来说，政委也是给予了非常高的评价，就是也能开始就是有些可能比较难以沟通的课程，他也跟我说人家也就是也其实相当于承担了一种沟通的角色，也非常的包括他也说有些也是搞到半夜那种也很辛苦，当然我们期待你也能够继续发光发热，攻坚克难。那我们这个奖可能是荣誉，或者就是当然我先说一下，就是我们最佳新人也好，最佳进步也好，当然是一种肯定，当然也有鼓励的成分，但是我们从这个后后面这三项包括训练 • 发言者 12 01:07:04 就是 • 发言者 1 01:07:05 完全出于肯定，就是没有没有鼓励的成分。然后这个叫最佳员工奖，这个是比较就是我感觉是我们含金量比较高的，就是也是我和政委非常达成一致的一个就是这个我们会颁给我们就是各个方面，就是无论从纪律执行，还有职业态度技术能力，包括出活这种，我这颁这个奖，我不是说我单纯的考虑某个部门，我是所有的都考虑的，大家不要误会，我只考虑的。某一个部门或者怎么的，我是把所有的名字都列在上面，我们甚至进行了认真的讨论来颁这个奖。 • 发言者 1 01:07:47 然后这个奖金也会稍稍微多一点点，就是 • 发言者 12 01:07:52 李海腾你给我发个视频，你给我发个视频。再错了可就尴尬了。 • 发言者 8 01:08:00 应该是那个女生吧。 • 发言者 12 01:08:03 那行， • 发言者 1 01:08:04 情商比较高，情商比较高，那我会颁给游腾宇。 • 发言者 12 01:08:13 Okayifhowever,好像挡住了。 • 发言者 1 01:08:25 对我们这字体还是选了我比较喜欢的苍耳青和可以。然后还有最后一个那办完就没了，但是我们这个是有竞争性的，不是每个人都有的，但是我们在评的时候也是就是相同级别的框出两个人或三个人来。 • 发言者 2 01:08:45 就是 • 发言者 1 01:08:47 我们如果你没拿到，并不代表你就是能力不行，但是至少证明你不突出这一点是能证明的。就是我们你比如说颁某个奖是两三个人的这样的一个就一个窗窗定，就是可能2选1可能3选1。那大家希望大家也不要颁完，最后一个也不要有落差，这个奖我们叫特别贡献奖，这个是其他公司也有这个名字的。那我们会颁给对我们运营层面是比较重要的一个人，当然这个可能大家也能理解，我们可能理所应当的就要颁给李海涛， • 发言者 2 01:09:23 就是 • 发言者 1 01:09:25 在工厂。这个我们从奖金上来说也是就几个单项奖中最多的这个3 • 发言者 8 01:09:37 口罩戴上 • 发言者 1 01:09:38 没必要吧。好可以了。那其实我们就是这个仪式感说实话也是大家要求，也是我们之前没有这个意识的，就是我们之所以办了林业藤，就是因为他的辛苦程度就是是最大的，但是就是我指的是可能大家就是半夜或者周六周天，当然大家也回也侵占到他是最多的，也是最操心的，大家包括执行层面，谁要去救火这种谁人家不满意了，人家去赌一赌。或者是上传下达，对我们运营是非常的一个重要的意义的。这个所以我们就办完了，大家也不要没有得到的，也不要有落差，我们这个就是有这个就是有竞争的，这个我们也说了我们的算法就是2选1或3选1。 • 发言者 1 01:10:34 不，你有明年要有拿的这个想法。但是我也刚才也解释了，我们无论从年终奖的数额还是这种颁奖上，我们对后期可能是就从执行部门，我们对后期是有所侧重，这个是我们唯一愿意解释的。大家应该也好接受的一点。好了对我们这个颁奖有反对的吗？反对也无效。可以的，那我们希望大家能开心，也不要因为我们大家讲的不开心， • 发言者 2 01:11:12 这个 • 发言者 1 01:11:16 那我们最后就是抽奖，抽完奖大家就就散会了，就是吃饭应该人家说你去吃是吧？然后那那个陈德丰也去，然后李国宇去吗？ • 发言者 8 01:11:28 我看时间。 • 发言者 1 01:11:30 那其他人还有安排吗？就是有，如果你那我们今天也算个福利，如果你今天晚上之前就是今天你去看个电影或吃个饭，只要在一定额度之内，我们也可以酌情报销。但是你要如果我们报的话，我们可能来年就不一起吃饭了，如果不报的话，我们来年把这个饭补上。当然可能自己来考虑可以来找我可以拒绝报销，拒绝你。就是包括自己的，你比如说下午和男朋友看个电影，吃个饭花个两三百这种，可以报销，就近只限于今天，过了今天就没了。那我们就抽奖1、 • 发言者 2 01:12:08 23456789、 • 发言者 1 01:12:14 10十一十二十三十四15，15个，那我们讲的话是我们一些充值兑换的一些这个可能值个小200，我刚才看了一下好像一百七八吧应该是。这个是79块钱49块钱观影券是价值30块钱，当然还有一个七八十的那种洗头膏。可能你今天拿不着，就是只能年后再拿。但是奖都是小奖，这个也图个乐呵。我昨天本来是因为有8个奖品还是几个奖品，我只做了8个，我数着就8个，我总觉得哪里不对，应该致一下空奖。那怎么抽呢这个东西？是一个字。放袋子里。 • 发言者 1 01:12:57 这就 • 发言者 8 01:12:58 那个茶叶蛋。 • 发言者 1 01:13:00 好的，那就传一下好了，来你也拿一个传一下，一会再一起开，没事，你可以拿一个开一个好不好？没有没没有，我也不知道是哪个对哪个。你就抽就好了。对，我还写了一个就找我发100块钱红包，如果你谁抽到这个我就会发给他。这个还好，我们可能就占用了大家一个半小时不到的时间， • 发言者 8 01:13:36 是不是还交尾。那 • 发言者 10 01:13:43 他们挑的对。 • 发言者 8 01:13:48 我们其实在这你还能学会给我们就最后一次了。不需要这么开心。没有。这我有这。他说全都要。一等奖。我 • 发言者 7 01:14:10 不要我全都要 • 发言者 8 01:14:11 还真是一等奖最大奖。都有。一等奖。 • 发言者 1 01:14:19 乌鸦嘴。 • 发言者 8 01:14:22 你自己刷一下。你介绍吧。我们俩他妈就连着ok.一起开吧，随便一年费用。放一起放一下。 • 发言者 1 01:14:37 可以，那一等奖是谁的？自己喝送礼都不错，谢谢老板。 • 发言者 8 01:14:45 奖票 • 发言者 1 01:14:46 这这个不用谢，这个不用谢。这是你的运气，然后二等奖是谁的？充电宝是谁？ • 发言者 7 01:14:53 对。 • 发言者 1 01:14:55 来给我。好好运。对价值79元的。然后那个三等奖是谁？冠军券那个。 • 发言者 8 01:15:08 不对， • 发言者 1 01:15:09 还有那个洗头膏是谁，洗头膏是谁。洗头膏是谁？可以的，那他说今天能寄到是吧？反正到时候找林远腾要一下好了。找林远腾要好了，反而也应该是价值七八十的那个，我觉得也挺贵的。应该相对就洗头膏，他没寄来那个，然后那个观影券是谁？几个师傅。一个应该可以随随意兑换。所以谁谁还有给我。你不有一张了吗？ • 发言者 11 01:15:49 对我这不又中了吗？ • 发言者 1 01:15:51 那你送给别人吧。谁还有换一换一串什么ok.然后还有那个我自己写那个发100块。 • 发言者 8 01:16:02 100、 • 发言者 1 01:16:03 100块。是吧？你看是你说的是林海龙出的，他不要了， • 发言者 11 01:16:09 你怎么能这么说呢？是你自己抽到的。 • 发言者 1 01:16:12 那现场发100块钱红包， • 发言者 7 01:16:15 那肯定的。 • 发言者 1 01:16:16 哈哈那肯定不行。 • 发言者 13 01:16:19 你不行发个拼手气发在群里， • 发言者 8 01:16:21 大家都看到。 • 发言者 13 01:16:22 那反正是林总让给我的发给100 • 发言者 1 01:16:24 块钱我先发你我会再发一个对。等一下。 • 发言者 7 01:16:36 行行。我 • 发言者 13 01:16:37 收到就发。 • 发言者 7 01:16:40 王总。红包就先放一放，每个月的工资都还没达到，我刚才唉。谢谢。唉最重要是这个。 • 发言者 1 01:16:46 反正这样我们反正今天就结束了，那个反正最后吧最后就是让林彦腾发个200块钱红我会转给你的，你不要担心，反正林林彦腾发个200块钱红包在群里。那过程中那个我会再转你，因为我微信里没钱了，或者那啥林彦腾你转给他100好了，我到时候转你300你来管我要行，反正那个就今年就结束了，这个应该大家还行吧。 • 发言者 8 01:17:14 可以。 • 发言者 1 01:17:15 其实我们真的也包括台词也好，这种证书什么玩意儿，我们真的也是比较认真准备了这个当然我们从更人性化应该提前放假了，这个但是也考虑到活上可能就没有。那反正从一个就是希望大家能注意安全，新年快乐，这个其他的应该就没了吧。应该就可以结束了，大家觉得还行吗？可以也不敢说不行。好的，那应该大家还有什么想说的吗？最后一次机会有什么要补充的吗？ • 发言者 8 01:17:50 没有了是吧？ • 发言者 1 01:17:52 没有了。没有补充的，你没抽中是吧？没事。 • 发言者 7 01:18:03 镜头最后喊一个信息。好， • 发言者 1 01:18:04 新年快乐， • 发言者 8 01:18:06 nice准备321起。 • 发言者 1 01:18:10 好勒。 | D4: # 复盘目标与结果概况 本次年度总结复盘会围绕公司2023年发展状况展开，重点汇报了营业额、开票额、年终奖总额等核心数据，并对各部门员工表现进行评价。会议明确了短视频账号在多个平台（微信视频号、小红书、抖音、B站）的粉丝增长情况，以及商务部门的业务成果（约300万项目量）。尽管公司面临成本控制不佳（全年支出390万，利润率约24%-27%）和人员配置不足的问题，但整体业务总量呈上升趋势，员工收入和年终奖均有提升。会议还设置了奖项颁发和抽奖环节，强化了团队激励与仪式感。 # 亮点事项 **短视频账号运营突破**：2023年6月20日发布的户外拍摄视频成为关键转折点，微信视频号粉丝从700增长至8万，小红书从2000+增长至6.4万，抖音从2000+增长至5.7万，B站从3.1万增长至7.6万。这一成果得益于郭东辉的坚持，其在项目受阻时主动说服潘老师调整策略，结合外部资源（如Forty加入）推动账号发展。 **员工个人能力与团队协作**： - 刘腾宇在技术执行和职业态度上表现突出，被评价为“后期技术标杆”，其工作质量在客户反馈中获得高度认可。 - 张文倩在跨平台沟通和项目执行中展现综合能力，完成多项高难度任务（如宁波项目、财经宣传片），并具备学习新技能（如三维制作）的潜力。 - 林海腾在运营层面承担上传下达职责，有效协调部门沟通，推动问题解决，成为公司内部的重要枢纽。 **年终奖与激励机制优化**：公司首次引入含证书、设计规范的实体奖品（单价40元），并制定明确的年终奖发放标准。例如，满一年员工以基本工资为基准，结合贡献度调整额度，部分员工年终奖达20万以上，整体年终奖总额较去年增加1312万。 # 不足事项 **成本控制问题**：全年支出390万（含人员工资、外援费用、设备租赁等），利润率仅24%-27%，成本控制能力被多次指出为“最大问题”。根源在于老板对资源调配和管理介入不足，导致人员冗余与效率低下的矛盾未能及时解决。 **部门协作与资源分配**： - 商务部门与后期部门存在认知偏差，商务认为技术工作可由任何人完成，而技术部门则认为商务依赖“一张嘴”推动业务。这种跨部门协作的不信任感影响了整体效率。 - 拍摄任务密集但人员配置不足，导致高强度加班（如后期团队后半年频繁加班）。老板承认是“判断失误”，未及时补充人力，加剧了员工负担。 **年终奖分配争议**：部分员工因年限不足或贡献度未达预期未获得高额奖励，但公司未完全量化评价标准，仅以“基本工资为基准”和“贡献度”作为模糊依据，可能引发公平性质疑。 # 改进计划 **成本控制优化**：2024年将重点强化成本管理，具体措施包括减少外援依赖（如内部人员可承担基础拍摄任务）、优化人员配置（根据业务量动态调整团队规模）。 **跨部门协作机制**：计划通过“组织协调”提升商务与执行部门的配合效率，明确责任边界，减少因沟通不畅导致的资源浪费。 **激励机制细化**：年终奖标准将结合具体项目贡献（如粉丝增长、课程变现进度）和工作年限，同时探索“红包+实物奖品”的组合形式，增强仪式感。 **员工能力提升**：针对后期团队，计划通过内部培训和项目实践提升综合技术水平；对商务部门，将加强主动沟通与客户开发能力的培养。 **运营目标调整**：短视频部门2024年核心目标为“账号变现”，老板承诺投入更多精力推动，同时减少对员工休息时间的侵占。 | E4: 5 | F4: 4 | G4: 5 | I4: =(E4+F4+G4)/3 -> 4.6666667 | J4: 2.1 细节遗漏，员工评价和部门评价的细节内容遗漏 | K4: 2026年团队年终总结报告 一、年度核心数据概览 营收情况：2023年公司营收同比增长100万元，整体业务实现正向增长。 开票总额：全年累计开票额达528万元，为实打实的业务收入。 年终奖总额：本年度年终奖转账部分总额为22.6万元，较去年增加约12万元。 人力成本支出：全年人员工资、外援配音、字幕、设备等实际支出达390万元，成本控制压力显著。 利润率：当前净利润率约为24%~27%，处于较低水平，需重点关注优化。 员工规模与留存： 干满一年员工人数从去年的4~5人提升至12人，团队稳定性增强。 最高个人年度收入（含年终奖）突破20万元，平均到手月薪超1万元。 注：公司结余虽有百万余元未收回账款支撑，但到账资金呈下降趋势。若无增量，运营将面临严峻挑战。 二、高频词捕获与术语演进分析 高管演讲词频TOP5术语（发言人1为主） 术语演进观察 2022年 → 2023年 “加班应对” → “系统化运营”：从被动应对任务转向强调数据分析、流程协调和跨部门协作。“零星产出” → “账号矩阵发展”：短视频平台由无明确成果发展为多平台粉丝量级跃升，具备变现潜力。 三、战略执行清单 承诺强度分级 强承诺（含明确目标或数值） 弱承诺（模糊表述） 四、部门与个人评价摘要 短视频运营部（郭东辉负责） 整体表现：高度认可，克服达人配合困难，推动账号从0起步实现快速增长。 关键成果： 微信视频号粉丝从719增至8万（约7.9倍） 小红书粉丝从2,000+增至6.4万 抖音粉丝从2,300增至5.7万 B站粉丝从3.1万增至7.6万 里程碑事件：6月20日外拍视频成为转折点，开启涨粉周期。 变现进展：课程体系初步成型，直播间平均在线超百人，具备商业化基础（当前完成度7.5/10）。 存在问题：前期多次萌生放弃念头，内部资源支持不足。 未来期待：2024年实现账号正式变现，管理层将加大投入。 执行部门（后期/编导/拍摄） 整体评价：认可度高，尤其肯定技术能力与职业素养。 进步亮点： 后期团队分层消失，整体效率趋同，多数成员可独立承担复杂项目。 加班现象普遍，尤其上半年长期高强度作业，反映人力配置不足。 成本问题根源：招聘滞后导致现有团队超负荷运转，属管理层判断失误。 奖励倾向：明确表示年终奖与奖项侧重后期岗位，因品质要求更高。 商务部门 业绩成果：全年获取项目合同额约300万元，基本达成预期。 代表人物：张启表现出较强主动性，主动联系客户、拓展资源。 现存问题：部分项目推进缓慢，沟通链条拉长。 管理反思：老板承认支持力度不够，承诺未来提供更多协助。 五、个人表彰与成长记录 最佳新人奖 古叶子 入职时间：约2023年10月（试用期后转正） 核心优势：懂技术、通英语、责任心强，政委给予极高评价 工作态度：主动提出优化建议，细致认真，难招人才 奖励形式：证书 + 红包（金额高于普通新人） 张扬 入职时间：满半年左右 核心贡献：带来职业化风气，能力与态度匹配预期 特别评价：“2023年最有价值招聘” 奖励形式：证书 + 红包 最佳进步奖 欧阳小源 显著提升剪辑能力，胜任更多类型项目 学习能力强，态度端正，进步幅度被广泛认可 奖励形式：证书 + 红包 后期独当一面奖（非官方命名） 刘腾宇 技术标杆，出活稳定、质量上乘，客户直接表扬 纪律性强，几乎无迟到请假，工作安排可靠 老板称其“像干了50年的老员工”，年终奖将“翻倍” 奖励形式：特别表彰 + 显著高于基准的奖金 特别贡献奖 林海成 角色定位：运营中枢，上传下达的关键桥梁 实际作用：缓解上下沟通障碍，协调紧急事务，承担额外操心 老板评价：“对我们运营层面非常重要” 奖励形式：最高单项奖金 + 专属证书 六、文化与机制建设 新增仪式感举措： 首次设立正式奖项与纸质证书（单价40元，皮质材质） 所有奖项经老板与政委认真讨论评定，强调公平性 设置抽奖环节（含茶盒、充电宝、观影券等），营造轻松氛围 福利政策补充： 当日消费报销：员工可在当晚餐饮或观影消费200~300元内申请报销（仅限当日） 红包激励：随机抽取“找我发红包”彩头，由老板额外支付 开放沟通机制： 鼓励员工现场表达工作内容，争取年终奖调整机会（存在500~1,000元浮动空间） 允许社恐员工使用预设台词：“明年继续努力即可” 七、问题与待确认事项 八、总结与展望 2023年公司在业务总量、团队稳定性和品牌影响力方面取得实质性进展，依靠“增量”实现了可持续运营。尽管成本控制不佳、管理响应滞后等问题依然突出，但通过强化仪式感、优化激励机制、识别关键人才，组织凝聚力明显提升。 2024年核心方向： 推动短视频账号商业化落地 改善人力配置，减少无效加班 提升管理层关注度与支持效率 建立更透明、可预期的晋升与奖励机制 正如郭东辉所言：“最大的敌人是自己。” 坚持与自我突破，是团队最宝贵的资产。 待办 林彦城在群里发送200元红包，并由发言人1后续转账补偿 为今天晚上发生的电影或餐饮消费提供限额内报销，需在当日提交 安排抽奖环节并发放奖品，包括茶盒、充电宝、观影券等 章节 00:00:24 会议议程与年度总结介绍 发言人1介绍了本次会议的整体议程，包括回顾公司过去一年的发展状况、主要业务数据（如营业额、开票额、年终奖总额等），并说明将不再逐一公布个人绩效。随后提到各部门将进行简要评价，每位员工可发表自我评价或回应。同时预告了后续的颁奖与抽奖环节，强调增强仪式感的重要性。 00:04:22 公司经营数据与财务表现汇报 发言人1详细通报了公司在2023年的关键经营数据：营收同比增长100万元，全年开票额达528万元，年终奖转账总额为22.6万元。同时指出成本控制存在严重问题，总支出高达390万元，利润率仅为24%-27%，形势不容乐观。尽管如此，公司整体业务量和员工收入均有所提升，干满一年的员工人数从去年的4-5人增至12人，团队稳定性显著增强。 00:09:11 年终奖发放标准与激励机制说明 发言人1解释了年终奖的发放原则：新入职员工视情况发放千元左右红包；满一年员工以一个月基本工资为基准，并根据贡献适度上浮；长期优秀员工有机会获得数万元奖励。强调奖金分配结合实际贡献与综合表现，鼓励员工主动争取认可。同时表示明年将继续评估是否保留该制度。 00:12:05 员工个人工作评价与部门反馈 会议进入员工逐一评价环节，发言人1对多位成员进行了中肯点评。红叶子虽低调但技术扎实、责任心强；郭东辉作为运营骨干，在账号增长方面取得显著进展；刘腾宇被高度肯定为执行力最强、最可靠的技术人员；欧阳在剪辑能力上有明显进步；徐玉玲工作细致高效；张文倩表现出色，胜任复杂项目；旭景仍是后期技术标杆；秦德峰拍摄任务繁重且尽职尽责；徐武安驻场表现良好；宋金义、张扬等新人也展现出高潜力与专业素养。 00:46:16 团队整体表现与跨部门协作反思 发言人1总结执行部门整体技术能力提升明显，后期团队已无明显层级差距，工作效率普遍提高，尤其上半年高强度加班完成大量项目。承认因招聘不及时导致人力不足，属管理层失误。同时指出商务部门全年承接项目约300万元，成果达标，但管理支持不足。呼吁加强沟通主动性与职业化表达，避免简单拒绝任务安排。 00:54:46 部门总结与未来期待 发言人1对各业务板块提出展望：短视频部门整体满意，期待未来实现账号变现；执行部门认可其辛苦付出，承诺明年优化组织协调，减少加班压力；商务部门虽达成目标，但需进一步提升业绩，管理层也将加强支持与关注。整体希望各部门在保持现有优势的基础上持续突破。 00:56:00 奖项颁发与仪式感建设 为增强团队凝聚力，会议正式设立多项荣誉奖项。‘最佳新人奖’授予红叶子与张扬，表彰其快速融入与卓越贡献；‘最佳进步奖’颁给欧阳，肯定其技术水平的飞跃；‘后期独躺院长’称号授予技术全面、完美胜任各类后期工作的员工；‘最佳员工奖’综合纪律、执行、态度等因素评选而出；‘特别贡献奖’则授予在运营管理中起关键上传下达作用的林海成，奖金最高，体现其不可替代价值。 01:03:04 抽奖活动与会后福利安排 颁奖结束后举行抽奖环节，奖品包括价值约178元的茶盒、79元的小米充电宝、观影券、洗头膏及现金红包等，设有空奖增加趣味性。一等奖由员工抽中最大奖。此外，公司宣布当晚餐饮或电影消费可在额度内报销，或选择来年补聚餐，体现人性化关怀。 01:06:01 会议收尾与新年祝福 会议接近尾声，发言人1确认流程无遗漏，感谢大家参与。通过群内发红包形式完成最后互动，并提醒注意安全，提前预祝新年快乐。全体成员确认无补充内容后，会议圆满结束。 术语 出现次数 相关语境 成本控制 8次 多次强调成本过高、管理不力，归因为“老板问题” 后期 7次 聚焦执行效率、技术能力及奖励倾斜 增量 6次 强调业务总量提升是维持运营的核心基础 拍摄 5次 涉及工作强度、人员参与度及外包替代可能 仪式感 4次 回应员工建议，首次设立正式奖项与证书 承诺内容 责任人 关键节点 验证方式 来源 发放总额22.6万元年终奖 发言人1（老板） 会议结束后转账完成 实际到账金额核对 对话文本 设立五项年度奖项并颁发实体证书 发言人1 当场颁奖 是否全员参与、获奖者名单公示 对话文本 明年重点推进短视频账号变现 发言人1 2024年内启动 是否上线课程销售或直播带货 对话文本 补贴加班人员额外1,000~2,000元 发言人1 年终奖发放时体现 是否在奖金中体现差异化补贴 对话文本 提升商务部门项目承接量至300万以上 发言人1 2024年度考核 实际签约金额统计 对话文本 承诺内容 责任人 说明 来源 “适时推进组织架构优化” 发言人1 未明确时间表与具体措施 对话文本 “明年可能会继续加强支持商务” 发言人1 缺乏量化标准和支持方案 对话文本 “希望每个人都能参与拍摄” 发言人1 无强制要求或培训计划 对话文本 “成本控制问题明年再议” 发言人1 推迟决策，无短期行动项 对话文本 项目 状态 说明 成本控制改进方案 未知/待确认 明确表示“明年开会再说”，无具体路径 组织架构是否调整 不一致 口头提及“有些公司架构重要”，但本公司暂无动作 拍摄岗位全面普及计划 弱承诺 提倡人人参与拍摄，但无培训或激励机制支撑 外援拍摄替代测算 未落实 提出设想，认为自拍成本更低，但未执行 政委真实姓名 未知/待确认 多次提及“政委”，但未说明其全名或职位归属 | L4: 3.5 | M4: 5 | N4: 5 | P4: =(L4+M4+N4)/3 -> 4.5 | Q4: 1.1幻觉 标题时间2026年，开票金额528万；1.3 实体提取错误，摘要中‘像干了50年的老员工’ | R4: 年度发展状况与数据报告 营业额与开票额：2023年营收同比2022年增长100万，开票额为528万（实打实开出去的票额）。 年终奖：总额确切为22万6千元；比去年多12万多；发放标准参考：刚入职两三个月或半年以内的员工，发约1000元红包（去年为600-800元）；干满一年的员工，一般以一个月基本工资为基准，无大纰漏会比基准高甚至更高；干满一年且公司非常满意的员工，往年实际拿到约两三万，若条件允许（年限够、公司满意、体量在、成本控制好）有大几万预算。 成本控制：存在严重问题，2023年成本（包括人员工资、外援、配音、字幕、租机器等）达390万；利润率约24%或27%，非常不可观；根源问题在于老板对成本关心关注不够、不够雷厉风行、问题未及时解决。 人员工资：2023年有两三个人（含年终奖）拿到手工资达到20万多；平均到手工资为一万块钱多；2023年平均人工支出比2022年相对提高，平时工资拿到手的总额多了约25万。 公司整体情况：2023年公司总量提升（这是能召开此次会议的最大原因）；员工拿到的钱在提升；成本也在往上跑（负值）；公司结余到账来说是往下跑的，还有百来万没收回来，实际是稍微缩水的；老板个人比去年少拿约10万块钱左右。 账号数据表现 视频号：截至1月1日，粉丝数8万。涨粉起始于6月20日第一条外出拍摄视频。 小红书：2023年1月粉丝数2000+，截至目前6.4万。 抖音：2023年粉丝数约2300人，截至目前5.7万。 B站：2023年粉丝数3.1万，截至目前7.6万。 重点项目进展 涨粉：各平台粉丝数均有显著提高。 账号变现：课程已上架（10分满分的话应该是拿上上架，表述不清晰，推测为已成功上架）。 直播：视频号上已直播4场，最后一场为新年直播。平均在线人数较高，前100名平均在线人数能达到一定水平（具体数据未明确）。目前直播形式在课程方面存在不足（表述不完整）。 个人认知与能力提升 认知收获： 说服他人（如老师）需站在对方角度。 坚持做事过程中会有委屈和放弃的想法。 混日子比充实的日子更可能让人陷入困境。 能力提升： 系统化分析能力：处理多平台账号、上架、开店、内容及直播内容等事务时，学会了分开处理并以数据支撑决策。 经验积累：主要在获客方面获得经验（具体事例描述不清晰，“包丢了，失踪，跟老师。但是我不去。轻轻往桌子上一敲就碎了，我就很容易就扒拉。慢的去把这个是这样的一个进入到我的这个”）。 学习习惯：晚上8点到9点会抽时间刷直播间（如坎哥）学习内容。 部门评价与期待 短视频部门 整体评价：公司满意，认可其工作及克服困难的过程。 存在问题：受其他原因限制发挥。 明年期待：账号开始变现；老板将投入更大精力并给予足够重视。 政委情况：虽有些问题未解决，但已尽力。 执行部门（含编导、后期、拍摄） 整体评价：认可大家的辛苦程度；今年项目未做砸，整体满意度尚可。 成本问题：成本飙升是老板问题，与员工无关。 明年期待：老板加强组织协调，提升效率；关注员工工作开心程度，减少压力，尽可能少侵占休息时间。 商务部门 今年结果：从结果看基本达到预期，实打实项目金额约300万左右（可能更多）。 明年期待：结果上要更好；老板反思今年在支持、管理、关心方面的不足，明年改进。 会议流程与安排 部门评价环节：分短视频、商务、执行（文案、拍摄、后期）等部门，每个部门进行简单评价；每人进行两句评价，以肯定性为主，问题性留到明年；评价时个人可以回应几句（也可无台词），若有未被看到的工作或价值，可能有500 - 1000元的年终奖涨幅；回应内容可包括自己的工作内容，以便跨部门了解。 证书发放：往年没有，今年认真对待，有皮质证书（含设计费40元一本），但并非每个人都有，会说明评价标准。 抽奖环节：最大奖为价值约200元的茶盒；另有两个价值79元的小米充电宝；几张观影券；两个价值约七八十元的洗头膏（未寄到）；一个“找我发100元红包”的奖；存在空奖。 员工评价（部分） 红叶子：10月份转正（8月入职，待了几个月），性格低调，说话不多；政委给予非常高评价，认为其是很难招到的既懂技术又懂医的人才，有把事情做好的精神头，对待项目意见和想法认真（如填工资表时会写如何把项目做得更好）。 郭东辉：干满一年的运营，有非常丰富的经验；克服了本不应他面对的困难（包括达人那边）；公司某种意义上限制了其发挥，对此公司应表示歉意；负责的账号目前虽未变现，但比去年有很大发展，有变现潜力，对公司软实力有很大帮助。 员工评价与反馈 刘腾宇 优点： 职业性、专业性评价最高，沟通能力强，能准确理解并表达。 纪律性好，按时上班，按时完成工作，几乎不迟到，请假严格按规定并提前安排工作。 技术能力强，反馈好（如宁波城市项目罗峰对其工作的肯定），让人放心，能胜任急活和重要活，人效最高，做事好且效率高。 更高期待：综合的后期技术水平希望能更高，以完美胜任各种类型工作。 年终奖：在既定标准基础上，因林海腾的肯定再拉一档，会让人比较惊喜，可能比其期待的数翻倍（具体数额未透露）。 欧阳 优点：工作态度认真，有一定学习能力且进步明显，职业能力和职业态度没问题。 提升空间：沟通能力需进一步提升。 期望：保持进步和对工作的热爱。 徐玉玲 优点：工作仔细认真，“一遍过”的情况多，技术层面有进步（如从剪课程到能剪宣传片），做课程类工作既有效果又有效率，好评多（如杨晶项目中被指定完成）。 更高期待：希望能更开心一点（其他未明确）。 张文倩 优点：比较灵光，综合能力强（需沟通能力和专业水平），表现超出期待，能完成较难的工作（如宁波的项目）。 提升空间：因年龄和工作年限，经验和感觉上与职场老人有欠缺。 期望：从灵光性来看有进步空间，能为公司发挥更大价值。 旭锦评价与期待 后期技术标杆，2022年起虽部分工作分散，但仍是技术最好的人员，品质最高。 曾期待其参与项目，因社恐等原因尊重其意见，仅在必要时参与后期相关会议。 更高期待：解决公司认为较难的问题。 秦德峰评价与期待 元老级人物，后半年拍摄密集，曾两个月连轴转无休息。 除个人拍摄外，还负责安排拍摄人员，占用个人时间多，收入尚可。 从运营层面关心公司，如提议办理停车券、设备更新等非本职工作。 更高期待：具备更强的执行能力（项目、沟通谈判等）。 拍摄与后期相关讨论 拍摄参与建议：后期人员可尝试参与拍摄，提升个人市场价值，公司不阻止且期待大家参与，至少能应付基本拍摄即可。 年终奖与奖项侧重：年终奖及奖项侧重于后期，后期拿到的钱比前期少一截，公司掌握了拍摄与后期收入的平衡，此为老板主观意志，仅对此点进行解释。 职场沟通要求：面对领导安排工作，直接说“没空”是不职业的，应解释手上工作或勉为其难安排。 徐武安评价 比较灵光，眼里有活。 曾独自在警察学院驻场，初期被认为经验欠缺，后期获得认可，未搞砸工作，拍摄任务多且辛苦。 拍摄和后期技术水平过关，拍摄技术水平好于后期。 宋金义评价 入职两三个月，由政委招聘。 第一个任务为宁波两分钟小宣传片文稿撰写，效率高，与张文倩工作内容相同（编导职位），初次表现即获认可，能解决问题，后续负责监狱、财经等项目无问题，段位高，该岗位明年或发挥更大价值。 张阳评价 公司邀请的人才，入职约半年，职业态度和工作能力有目共睹，基本达到公司期待，公司给予了有诚意的待遇。 若其出现问题，可能是老板或制度管理、沟通问题。 被认为是2023年公司最有价值的招聘，但需防止骄傲。 郭阳评价 新入职两三个月，技术段位较高，参与剪辑的财经宣传片达到行业标准，超出预期。 会做包装等其他同事可能不了解的工作，有望解决公司二维三维外包问题。 李海腾评价 对运营层面作用重要，承担上传下达工作，传达员工声音。 负责繁重的后期安排工作。 加班相关说明 年终奖考虑了加班因素，计划补贴一部分（约一两千）。 加班主要原因是公司判断失误，未及时招聘合适人数，商务业务断断续续导致错觉无需招多人，人脉资源不确定也影响招聘。 李博宇评价 入职满一年，拍摄水平在公司较高，能胜任稍高难度工作。 后期有灵性，能进步、听懂指导（如理工项目剪辑经指导后完美交差）。 更高期待：提升沟通能力，避免项目拖延。 张启评价 干了一年商务，表现高于预期，性格外向（原以为会害羞）。 工作有主观能动性，能主动联系客户、打电话。 更高期待：公司将给予更多支持和帮助（此前支持较少）。 年终奖与红包说明 具体数额不公布，总额有一万多块。 年终奖、红包以实际到手为准，口头提及的数字可能因记混等原因不准确，实际可能更高。 若发现员工有违法乱纪行为，将不发放。 颁奖环节 奖项设置与规则 共6人获得5项奖。 奖项包括：最佳新人奖、最佳进步奖、后期独躺院长、最佳员工奖、特别贡献奖。 最佳新人、最佳进步奖包含肯定与鼓励成分；后期独躺院长、最佳员工奖、特别贡献奖完全出于肯定。 评选过程严肃认真，公平公正，与获奖者非亲非故。 部分奖项存在竞争性，在相同级别中进行二选一或三选一，未获奖者不代表能力不行，但说明不够突出。 各奖项获奖者及评价 最佳新人奖（2人） 红叶子：政委给予高评价，有技术、有把活做好的心态，懂英语；红包相对厚一些。 张阳：工作能力、工作态度和实际作用得到大家认可，无信息差。 最佳进步奖：欧阳小元，技术进步明显，希望其保持专注、热爱与好奇。 后期独躺院长：能完美胜任后期各种类型工作（课程、微电影、MV、快剪等）；技术层面获郑总高评价，承担沟通角色，工作辛苦；期待继续发光发热，攻坚克难。 最佳员工奖：含金量高，综合考虑纪律、执行、职业态度、技术能力、出活等各方面；奖金稍多。 特别贡献奖：叶成，对运营层面重要，承担最多夜间及周末工作，操心多，在执行层面负责救火、上传下达等；奖金是几个单项奖中最多的。 颁奖相关 颁奖前询问是否合照，不愿意可举手说明。 证书字体选用“苍耳青荷”。 抽奖环节 奖品设置 充值兑换的奖品（价值约178元）。 79元的奖品。 49元的观影券（价值30元）。 七八十元的书包（年后领取）。 写有“找我发100块钱红包”的奖项。 抽奖过程与结果 共15个抽奖名额，可能存在空奖。 抽奖方式：将奖品放入袋子传递抽取。 一等奖：某奖品（未明确具体名称，提及“自己喝、送礼都不错”）。 二等奖：充电宝（价值79元）。 三等奖：观影券；洗头膏（价值约七八十元，需找林彦腾领取，当天可能未寄到）。 抽到“找我发100块钱红包”奖项者，可获得100元红包。 其他福利与安排 今日福利：今天晚上之前看电影或吃饭，在一定额度内可酌情报销（如两三百元）；选择报销则来年不一起吃饭，不报销则来年补饭。 群红包：李海鹏在群里发200元红包，由老板事后转账给李海鹏（老板当时微信没钱）。 后续安排 各部门进行简单评价，每人说两句肯定性评价（问题性明年再说）。 个人在被评价时可回应几句，内容可包括自己今年干的活、取得的成绩等，以争取可能的年终奖涨幅（500 - 1000元）。 郭东辉介绍所负责账号的粉丝等情况。 发放皮质证书（说明评价标准，非人人有）。 进行抽奖活动（奖项包括茶盒、充电宝、观影券、洗头膏、100元红包、空奖）。 明年开会讨论成本控制问题。 明年开会讨论年终奖是否发放及额度问题。 刘腾宇：提升综合后期技术水平，以胜任更多类型工作。 欧阳：提升沟通能力，保持进步和工作热爱。 徐玉玲：保持工作状态，尝试更开心地工作（具体未明确行动项）。 张文倩：积累经验，提升专业感觉，为公司发挥更大价值。 徐武安总结自己的工作。 张阳明天具体说明自身问题。 公司明年继续推动每个人参与拍摄。 公司为商务张启提供更多项目支持和帮助。 未领到书包的获奖者年后领取书包。 抽到洗头膏的获奖者找林彦腾领取洗头膏。 员工今日产生的符合条件的电影票或餐饮费用，找老板进行酌情报销。 老板向李海鹏转账，以便李海鹏在群里发200元红包。 若选择不报销今日电影票或餐饮费用，公司来年安排补饭。 内容由 AI ⽣成，仅供参考 | S4: 4 | T4: 4.5 | U4: 5 | W4: =(S4+T4+U4)/3 -> 4.5 | X4: 1.1 幻觉，同比增长100万，开票金额等。2.2比例失调，抽奖过程，评价内容比重过多
A5: 4 | B5: 江涛 | C5: • 发言者 1 00:10 装备了。调出来的时候我们生活 • 发言者 2 00:17 还让你上学或者不含不含那三个月工资。再加15%的就是15个群体。但是他那个比如是不是刚才说的就是流失额流转，所以去不上退的时候，快递他原来我们交的，那他不知从后边才来的，他都交费了。交费当时是什么呢？当时是我的公司管理工作。什么时候能达到10,200人，这块不能不太清楚其他的职业吧。能推进去。都可以。就退回去吧，我再推进点推，但是他出去他是上网的。从而选择一个地方可以。我们还有10多年的这个项目。 • 发言者 2 01:04 我找找啥什么安排什么还真不清楚，我一个工作点我们就可以作为呢当时是公司在这公司他就是一到C从银行的东西这么多，唉但是呢我就是说我如果达不到一个集团，今天一个是不会的。我从明天这20户为啥没有员工呢？装备是因为它更低了。那个哪些那个区长你登记了。百分:1低，要不唉按1%百分:1%也是一些了，那想法一样，那个12来块钱发行，12、10+271点广，那样现场的话当时应该完成马上就推什么。推了不行了。他不听了。 • 发言者 2 01:50 大家哪个那不是先跟我一起以后，后来慢慢就是这个协调的。这个是什么？完全说是高安街，然后联系的高安街，我现在到处得去上班几个，天天来他也没关系。我们要支持。那个钱是肯定受不了，昨晚能退。唉人家也不出来，没办法放心。说不定呢让我刚才今天上午说我那个所以说这个应该说是吧，那你又不清楚，要来以后再聊一。领导数据。好长时候那个怎么说。他当时因为家庭工人水平比例更低了，对了比例更低了。他是他不是说17号就分开单方的吗？ • 发言者 2 02:37 他也是你也是到你那里是工厂，那个谁你他在谁李艳南李艳南集团中你这不用他原来11%点多，所以这个光一期的时候还能上千五，完到百分之十七八。一个控制吃饭而行，而且是完全是唉那么通报了百分之十七八号，然后呢就是押金我那个办公楼那个出入来处理是吧？那我就一块录唉去一块录，可能通报这边那边查明了什么事情，我们俩就那吧在一起的时候，然后你再去做了，完之后就知道我得会使那个对方10.5差不多了，百分之二三三10分钟了。 • 发言者 2 03:22 有问题了。这里边还参与过时间，咱这个问题可能还涉及这个开户费用比较大。嗯嗯。是吧？这个原来我一样的这些什么是我这个供暖，因为咱是第1次起初的时候，从建设一直到后期，不光是我们营销的问题，到目前为止整个园区就没有验收过。咱讲什么要给钱放一边，咱就说开户费，开户费的话是应该是由地产来出一笔钱，然后和他出完这个钱，然后把管道直接交接给供暖公司。但是现在呢煤炭流程来处理这个事情，到现在为止都没有完工，也没有具备也没有验收，所以就导致了现在大部分都认为是物业的工作，但实际上我们很低调，你还不踏实一个地方先别想了，他就随便把这个他打电话咋办？ • 发言者 2 04:18 你说咱这个其实如果是个其他，其实当时交了吧，交了配套费是吧？交了咱所有的费用都交了，什么都交了。都交了都 • 发言者 3 04:35 交清楚了， • 发言者 2 04:37 咱说就是说我是我说的那意思是开发商交进去他那个公司了。那个咱不知道了是吧？我那就不清楚了，这是你这是个标准，不能单纯单调的。唉那个他那个不清的老板骗他钱都交了，全9亿的一个都交了不一样，你说咱医院公司收到的钱不一样，他说我的钱他也有点他就永远是 • 发言者 1 05:02 在公司。 • 发言者 2 05:04 有这个事情，这个不签他特殊费，这个事情不管我就反正不可能。那你不想让他说开会会议，咱就是往里一定要扩大发到维修上，其实咱去这个网关的时候嘛，它可以细节查也可以，好之后一样你简单我们讲讲讲一下。你在网易云那么你假如不愿意把门打错了，人家打错了咱就好，人上这里公司也跑过这里看看上海这户看到底还能不能供，还能能不能办。 • 发言者 3 05:36 行。 • 发言者 2 05:37 做了项目。这他这个心也就要千万，大部分，当时的话不能光直接擅长的处理是最好的是吧？因为啥？ • 发言者 4 05:49 就主要是业主们还买房满怀希望，他人家业主们不愿意退，希望越大， • 发言者 2 05:54 唉人家当时人家还 • 发言者 4 05:55 盼着想想能够为什么呢？所以那谁接着也 • 发言者 2 05:58 没有一份钱的，当时第1次管理都是说到平方点，他放在平方就小就打结算了。算了吧，二期应该叫人家补助，差不多能到29%，我的不知道晚上多少人找我也行。我挣的钱呢你全部给我说我有钱，我不会工作。这这个我当然说我也做了，他后来也不是他收钱了以后，中间说18天没完事你都要然后没推进呢在这。到最后叫人家在公司的时候发优势。你觉得不舒服，对手机钱包里有12块钱，就是那个那时候上课的能觉得值得推荐，他不是牵扯到了3万，还有一个那个关了不知道了。 • 发言者 2 06:40 那个钱可能是应该交三个月的时候，也是装4个月的，那个钱是业主自发组织。两个业主热心业主。竖起来点。说是死了一些，而且他们的公司消费的时候也不能清楚直接交上400块钱。这个钱也不能往上推了，已经开始。那么一批人招13万。那天我都讲了啥，23年了。收费。好不开。你现在那个还是涉及不到那个集团责任上去。安排那几个数。实际上那种集团协助央行的操作表的话，协调成成长领导代表。然后2727270原来37心里面有可能2点不做，两点不做，2点是不做，当时一共是两 • 发言者 4 07:31 个人家质量的报名的。人家质量的报名的货，就是交钱的货，就你交了费的人家质量这一部分交了钱的货，所以说一共也就是二期三期加起来就量了20来户， • 发言者 2 07:43 不是你家量了，你说日期以后这个那时候他这个比例这些单企业的比例。在公司里面。必必须得去做这个公司。看第一看他的公司，看他怎么刷。他怎么说他怎么样你怎么跟我说，当时与我说的他说不出去，然后他就给他就这个哪个你把我们这那个群里这个大家都给他说那不可以。那有几十号你就达不到，你本来50户吧，你达到了10户。又达不到人家不提供，你拿这个物业费也好弄也好。这媒体他说明白了。那你拿他的东西他直接过来给你拿，以前你反正简单了。 • 发言者 2 08:30 刚才说其他你还不知道，你说不知道你现在你家里热了吧。热了不知道你这。不知道那还挺感兴的， • 发言者 4 08:40 我这个热了我那就是行为慢。我那管子少，一部分 • 发言者 2 08:46 就是这个20、30的业主，有一部分是确实就是很小一部分是想要想今年是想文化。更重要的一部分是啥？是单是担心啥呢？就和刚才你口里说的那个东西是不是派出去工作，是不是这管道咱们做业主，然后明年如果还能用上好多业主就会到位，他讲的观众讲的情况，他们他干他干一下工作是他之前他对不对？其实今天这个时候吧，就是明天这个时候，如果说是咱工业设计明文的时候，咱们整个公司协调就是不是只是今年，但是肯定因为这个要有这个问题的话，但是可以可能更好解释一下，就是由于今天有点不存在这个问题，昨天了。 • 发言者 2 09:26 你说明天上你这个公司，你这个公司那我说这个你不能不是不是这样吗？还有这个我说只要肯定会叫要不你这边有活吧。闺女没叫可能是不是没叫。对，那个演出也就没演说都没用。都没按说是客户也没交。虽然说如果突然明天公关怎么说吧，在哪里，这个那东西不是就他整个就客户就有人和我说，你当时就知道他们的时候呢，再就是他们这个其他人不知道。一个是那时候请你打这个软件上比较没有网。第三系 • 发言者 5 10:05 主要当时是后面第三不去说你有个也不会去什么一些什么，但是他有说话的用呀说话。 • 发言者 2 10:14 不知道行了，我们说还是还就难了，那你不大问题今年开始了，这个客户让我刚才我从底下说的，这和配电室主要是一共三级，他家里一级班长就得排出来是吧？那么你排出来然后才能在家呀。行，这个其他我做完今天。把大家都召集到这来呀，还是没有解决更好的解决那方面问题。这一些有一些一大堆一大堆问题吧，不忙回家就坦诚相待，有啥说啥搁一块都商量，大家都委员会和他的物业放在一块。第1样我想说一句话，你都不要暴露一个敌对一个情况， • 发言者 2 10:57 就长期我说话成立业主委员会，最早最早一开始上，我一开始上我没有打出这个那你成立一家老板很好，一开始嘛你得多一开始提到事嘛，后续我就怕算计了就知道哪些问题，这个问题是和我女朋友是一样的，这个情况你们都处理，都把这个好的态度放一块咱们但是老板也是，万一大人这个情绪存在一些问题怎么办？咱不管这边还能不能处理到一块说话不能听，你还能不能继续的都得一块共事是吧？能还能不能在一块就把这事搞好下是吧？到这一块商量，任何人也不要有私心。 • 发言者 2 11:36 大娘是叫你们来商量事的。听得到坐下来坐坐下来商商量事，看他去怎么办，去商量不成，该咋去商量不成。不要谈矛盾有啥目的。行，你觉得那会有啥你啥乱七八糟。 • 发言者 4 12:09 那下午我开个头我先说两句，现在就是前一段时间，本来小区的这个有业主自发弄了个接龙王，然后差不多有接龙有200来二。百来个业主，然后就是说主要议题就是说想开这个业主大会。业委会甭管是业委会还是哪个业主，他都没有权利说是去做任何决定，包括什么撤换物业或者是开除物业，咱都没有那个权利。但是呢业主大会能这个就是表决，也有可能就说大部分业主愿意留下物业来，这也有这个可能对吧？也有这种这个啥，所以说我的建议呢就是尽快的召开这个业主大会，就是让全体业主来表决。我的意见就是这么简单。 • 发言者 2 13:11 从他大学的教育群用于工作群一共有几个群， • 发言者 4 13:16 工作我们业委会工作组就就是一唯一一个群，然后准业主分了5个群。差不多， • 发言者 2 13:24 唉你说咱这个然后一品正常的。你就说业主正常的，你说这个工作群嘛有几个不能应该有一个才对吗？委 • 发言者 5 13:34 会组织的工作群是6、 • 发言者 4 13:36 6个对6个对， • 发言者 5 13:38 一开始成立了筹备组的时候6个人。每个人联系一一部分。 • 发言者 2 13:43 我们联系完了以后，你不用接触是一共6个，对6个，你这个巡视从哪你这个 • 发言者 4 13:50 监督这个是从哪个钱，这是这个接龙的群是在我们最开始的时候，业主就是业主们自发组织的一个业主群，也就老邱哥。建的群主唉最早的这个业主群。 • 发言者 2 14:04 也就是说现在从这个群里监督的要求说成立要求这个开这个也就是这个水是刚建的，是原来就有的这个水。 • 发言者 4 14:12 呦得5、6年了，从开开始交房就有这个群了。 • 发言者 2 14:28 行，下去其他的问一下。你反正你们说的话是一个问题，就把这个狗狗就开个研究。研究开个研究的大会，你开个大会是啥目的呀？ • 发言者 4 14:44 要知道就是大家讨论一下小区目前大家 • 发言者 2 14:47 都把那个啥程序你知道吗？讨论。讨论你们。讨论讨论，对。一共有多少年？ • 发言者 4 14:55 因为那接龙是有200代人的，他 • 发言者 2 14:58 就接那个东西我也没加，我没法进行二百零这一块就不要讨论了，就有决心明白吧？因为你讨论过， • 发言者 4 15:05 你看你怎么讨论，你讨论出来肯定 • 发言者 2 15:08 有一个结果，也不做讨论应该就超。明白了，我说的神经病明白了就可以找找，那不就成了，那叫超人知道吧？所以说你想着你看，所以说你这个找个太监鬼，你得有他，你咋不有个三基层，我想这个人民来啥来啥去啥去形成，你这样你要说把窗门失控了，那不叫把人家说还不说这样说，那样你咋死得其反了。对是吧？那你可能就死在哎呀软 • 发言者 4 15:42 业委会的意思就是说不是说让所有的业主就是到现场，我我们打听那个意思，那个我就该介绍呗，就是 • 发言者 5 15:51 咱这个我看看那群里他们不打组织， • 发言者 2 15:54 就就是说他开这个业主大会，但是你这这个你你5个。你5个都同意。 • 发言者 5 16:02 对，还有这个开 • 发言者 2 16:03 这个医疗单位这个事吧，我们有5个就是群业中开始乡政府我们我也开这个会开这个会吧，主要是也就把他预测的问题我们考虑到到底是以讨论为主还是以表决为主，就是。沿着我们最终的结论也是以表决为主。然后表决的这个问题，我们按当时的时候大体上一类，我想问一下这不你不敢都同意不同意？你们同意的不是你哪一个。个人兄弟。嗯。对，实际上说话的对， • 发言者 5 16:59 说话那个可以的会议一听见了，不是说话不一样。你这个根据这个接龙的这些人的心声呢，我总结看看，第一是要求说是讲开会，第一是要求这小区存在的问题不一样，能不能整改，然后一说整改不了，就说这怎么达不到这个一些东西。达不到一些这个效益的时候呢，然后就说是化工业化工业的东西，并不是说不要这个物业来了，然后说原物业也可以那个投标，然后招标或者是怎么样达到咱现在小区存在的这个问题。那现在小区存在问题呢，我看看群里那个就说一下问题，11个是吧？ • 发言者 5 17:36 那个谁对你看这11个人，你说那11个提高看看，我看看有没有， • 发言者 4 17:44 你完全可以再转发一下，那个你可以说一下，你不用 • 发言者 5 17:48 转发你直接说一下，有什么问题就行，就说有啥。 • 发言者 2 17:53 问题开始他就说你才一参加这群，就他提过11个问题，对，不要求无下有来无外出这11个问题， • 发言者 5 18:01 你能不能该 • 发言者 2 18:01 能不能那个什么就不能，你知道那知道那11个问题，他不知道你这个我说一下按照正常的一个流程。比方说你们要召开业主大会或者要组成决议的话，事先要和物业公司要进行一个沟通的，但是我们事先没有接到任何目标，然后至于在这个业主群里面去发什么接龙也好，肯定是有组织的，对吧？你们组织的议题是什么？我们也不知道，我们也没有参与过。但是我在这只是郑重的说一声，鉴于目前我们双方所存在的，包括成立之初和工作过程当中存在的有一些违法情况，我们已经在今天上午的时候沟通集团法务是起诉会在本月进行起诉，但是起诉周期之间你们没有行使表决权的义务和责任吗？ • 发言者 2 18:45 可以。你们没有办法行使权利，我想把这个事情说清楚，因为你无论你找哪个律师，你们可以自己去咨询，也可以自己去问对吧？还有一个欠费的人员不能成为业主代表。顶名了也不能成为业主代表，这些东西都存在，我们都依法追究责任。我们在这儿也正式说明一下，我们会在本月正式起诉。我来我走了是你说的。那你不不用你问我为你庆祝一下，然后有我的不是不是因为你来支持好的，我希望也给我们业主留一个，当然了最后会让你尽情的这个让你谢谢。那个你昨晚还有一个口号，你看现在看手机了，那个按你的意思说你要求你去做，我们肯定是要依法维权，因为从目前的情况来说谁呀？ • 发言者 2 19:27 我们起诉的话，首先第1个我们已经在业主群里面掌握了很多的一些证据和依据，首先从证据和依据上来说，你说明白你吃苦行不行，不能给他们麻烦，我们对业委会整体我相信也都会隐形了，欠费周期超过一年的业主，你得你想起诉咱的起诉业委会，我们已经上午跟高级人民法院已经沟通了。我们这都有沟通记录，我们已经你想着因为你找业委会存在有啥问题吗？我们说了上午的时候我给高主任打电话了，我也给你这边打过电话了，从选举就存在很多违法行为，一直到后期再决策，一直在后期在业主群里面去煽动的时候，这里面都不符。 • 发言者 2 20:22 和业主委员会行使的权利的职责，而且还有撬我们的门。而且我们上午的时候，我们银河高级人民法院9:52，我们通了电话，我们会有诉讼。第四的话你上游物业，你要求你要起诉这个业委会，对我们要起诉业委会，包括保洁业主代表我们一块，你不得你演演出得掉。我们今天上午和滨城区人民法院也沟通了，我们也和高级人民法院都致电了。电话都不通过一样，但是你说你想是属于研究院部分研究代表，对。这个不是我个人的理由，是集团的就得你把你们你们他没有他们的权利，你们的权利，因为大公司的都有自己的法律环境。 • 发言者 2 21:23 但是起诉过程当中可能会影响你们个人经营。 • 发言者 6 21:34 我说到了这个咱 • 发言者 2 21:35 也不为啥咱得把你们做到一块儿，得抓紧什么的，抓紧时间你都得说明白了，如果说是你就还有什么错误指向你，不得痛快你都做不到最后谁是谁怎么想的。最终往哪落是吧？他上了一块，但是你也要走法律程序是吧？至于这个其实对这个法律程序上咱就不很咱就不很懂了，你这个亚委会这个就是说中中间一些程序，你开这个会一些程序，这个你的可不能马上说到大可不可能不能开。 • 发言者 5 22:08 也为我们开发就这个成熟，你要押金业主大会开与不开，现在不定这个事，这是必须的事。所以说你今天咱们今天就上两课，就是刚才说的那个一些东西能不能达到那种现状，因为一些缺失一些缺失的问题，确实能不能改善一下子。能改善一下子，咱们继续那个什么。 • 发言者 4 22:31 能改善早改善了，唉 • 发言者 5 22:34 你说的是不是？ • 发言者 4 22:37 是这10条是从咱交房到现在这个 • 发言者 2 22:42 姑娘你店里边这个成绩他现在是从做谈事我知道，但是很严肃的地方。你能把来记住这个柜子是个非常严肃的。你不要管他经常跟我说，我也不知道你那个啥，你那个你刷刷那个纸条用纸条你得搞，我知道能不能整改来， • 发言者 4 23:02 我给正好领导们也都在这里，包括业主代表咱就咱就细数一下咱这个小区。这些年来的这个问题。首先第1条就是说这个每家每户这个入户的这个庭院门柱灯，从来没有开启过，这都是业主们应该应得的利益，应得的服务从来没有开启过。第2个就是内部水系，咱这个内部水系，人家很多业主也是加钱购买的这个水系旁的这个房子。对吧？这本身水系旁的这个房子本身就价值高，但是呢自从卖完房子到现在从来都没有开启过一次。对呀，所以说人家这个水系这个服务也没有一直再就是第3条咱这个门口这个售楼处门口这个迎宾水系，这个水系，现在小区里面有非常多的业主在讨论这个事，因为这个水系是一个小区的一个门脸是吧？ • 发言者 4 24:03 也是一个面子。再一个就是水嘛就是财对吧？行好好好，我就打电话说说这里，唉就是这个水汽迎宾这个水汽从来没有开启过。然后第4条监控几乎全部损坏，基本上就是没有好用的监控，包括上个月咱小区进贼了，包括110派出所还是刑警大队都没有从咱这个监控上获得任何的这个数数据，这是一个非常严重的问题。第5个就是这个是一个监控室服务问题，这个监控室从交房的时候，咱小区配备的就是说在监控室里面是要有24小时有人值班的，每位家庭每位这个业主家里边这个可是门铃都有一个一键直达功能，家里边有如果有什么紧急的事干嘛的，就可以按这个按这个门铃监控室这个值班人员就可以接到就可以紧急处理一些问题。 • 发言者 4 25:02 但是自从王艳芳上任以后，这项服务就已荒废了。再一个就是监控室里边大家也都知道这个监控大部分都坏了，他在那里也就是看那么一两个还能用的也没啥用，也没有人值班了，这都是一些缺失的服务。再就是咱小区这个绿化，这是被大家诟病最多的一件事，这个绿化每年你是需要维护和保养的。对吧？这么些的树死了这么些，头几年的时候还知道营养针维护，你看看自从去年死了多少树，特别是小区一进小区这个两边就我光我知道就死了三棵了。 • 发言者 4 25:50 这些都是全体业主的财产。不维护我们去问的时候，就像我们家门口有一个，我当时就打电话给这个物业管家，我说这棵树已经生病了，现在已经明显的已经有问题了，你们是不是派人过来看看？结果物业管家就这么跟我说，我们经理说了，明年看看他发的那个能不能发芽，能不能长绿叶，这是真事，我没有夸张在等，等到明年我说你等到明年的时候，这树不就死了吗对不对？所以说这是这不是一个正常的这一个服务的这么一个这么一个这么一个态度是吧？ • 发言者 4 26:31 我觉得这不对。这么多年了，一直都是就是自从咱小区围上这一圈这个围墙以后，北边这一块一直是用这个烂铁皮这么挡着，一个是影响美观，再一个也不安全。事实上这个就是说在一直有铁皮这个这一段时间，在最西边有一个缺口，是社会上任何人都可以从这个缺口进来，进出都没有问题，这是很多业主都知道了不安全。然后呢业委会成立以后呢，就跟这个物业责令整改，但是呢物业拆除铁皮以后，就再也没有任何的更这个更新的动作了。甚至是哄骗业主说已经定制了围挡了，你们等这些我们很快就能给你安装上，结果呢直到今天这个围挡都没装上，后来我们证实根本就没有定制这个事儿。 • 发言者 4 27:37 就是纯粹就哄骗业主。进了这个盗贼这件事以后，物业应该以最快的速度来重视这件事。一个是修好违这个监控，再一个就是修好这个围墙对不对？因为这是关系到全全体小这个整个小区这个安全问题，人家说话的时候你不要打扰人家，有你说话的时候来我给 • 发言者 2 28:03 你不要解释， • 发言者 4 28:04 你不要解释等我说。完了，你让刘主任刚才说了，他会给你时间让你说的。你现在让我先都说完。然后这个咱小区甭管是哪个小区，这个安全必须要放在第1位，对不对？这是所有业主的共识，你没有这个围挡，你让这些业主怎么能安心的过一个这个年呢对不对？经常有这个业主就在群里说，又看几个不认识的人在小区里面晃荡。对不对？你现在你这个文档没有全编入的人，随便一个人就可以随意的进出咱们这个小区。是不是？这像这种非常 • 发言者 2 28:50 好， • 发言者 4 28:50 好像这种安全问题必须得也必须得重视，在第1位。是不是？然后就是说这个第8条就说咱小区这些民生的这些附属问题，比方说快递柜直饮水机宽带的覆盖，暖气的开通开户这些等等这些问题。正常来说都是应该由物业去负责去联系给业主们，这是提供一些最基础的服务，对不对？但是呢事实上这么多年来从来都没有任何的进展，我们有很多业主也是多次的去询问，和要求，但是没有任何的作为，最终呢这些所有的问题都由我们业委会全程去办理了，这个大家也都知道。 • 发言者 4 29:39 第9个雨水倒灌这个问题是非常严重的一个问题，从2019年这有很多业主都是亲历每家每户都有不同程度的财产损失。然后业主们也都跟物业唉经理物业包括管家都无数次的反映，就是要求出个完完整的这个解决办法，但是一直到现在也没有任何的这个进展。明年如果开开这个就是说再有大雨的话，有可能海淹最后一个第10条，物业人员这个配备配比，正常情况下，我们小小区最初的时候，大家也都知道物业里面光办公室里就有接近10个工作人员，现在大家也都看到了，物业办公室里面加上物业经理一共就4个人，从维修人员呢从最初的5个人减配到如今呢只有两个人，其他有光线什么打扫卫生门卫之类的，严这个人人员配备。 • 发言者 4 30:53 配比严重不足，应该是这个接这个物管办应该是监督的，这个是我们也之前也有提出过来，差不多就是这么10条，当然还有一些其他的细分的一些条目，一些什么。也都有讨论，相对来说不是那么的这个重要和迫切，唉差不多就有这么10条。好我发言完了。 • 发言者 2 31:22 然后我就把这11个问题一个给大家在这里做个解答嘛，因为我之前这几个问题之前跟业主沟通过，但是呢很多业主呢都没有把这个问题去传达给业主们。首先来说第1个入户门门柱灯。没有亮这个问题。这个灯不是说没有亮，而是现在我们园区里面的能耗的成本，物业公司已经没有办法运营，而就此问题物业公司也本着自己的经营原则，也即使呢要有被成员做了一个沟通，也做了一个交流， • 发言者 6 31:57 对吧？徐哥， • 发言者 2 31:58 而且还不止一次对现场的一个经营情况给他报个反馈，而业主委员会呢也不只是一次给我们承诺支持物业的工作全员缴费，其次是帮着物业公司去收费，然后收上来的费用。当时我们在做这个会议要求的时候也说过了，收上来的费用以后，我们拿出一部分钱来及时做修复。第2个问题关于水系的问题，水系从交付开始一直到现在就存在严重的质量问题。一直到现在所有的泵都是没有办法正常运转的，这个的话已经由地产来进行一个维修，不属于物业的责任，这个走法律程序也不属于物业的工作，因为本身是地产配套没有完成。 • 发言者 2 32:27 第3个问题，第4个问题监控损坏问题，我们已经在会上沟通过。第1个修的就是监控。因为没有费用已经超出了运营承担，物业公司从进入这个长坡到进来，我不知道你们都是个体，你应该也会算过一笔账，人员的薪资是多少，园区的保护收入是多少。20多个人包括20多个人的人工成本一年是多少？我们园区的整个保护收入可以公开调查账目账目一共保护收入100来万，光人工成本就占到了100多万，而且这还不包括垃圾清运费工缺能耗费用维修费用税费，包括办公运营成本费用这些。 • 发言者 2 33:28 都是我还在内，每年都是亏损，都随时都可以去查账，因为你的户数是固定的，钱数固定的，你通过这个一减就能看得清清楚楚。第5个监控视服务，可视对讲这一块，说民警来了，我们没有拍到任何的监控，我们业委会成员我不知道你这个信息从哪里得到的。在警察进入我们园区的时候，物业公司第一时间已经将拍摄的画面截取给了派出所，给了刑警，看一下乐乐。这是当时刑警调取监控的照片和记录，我不知道咱们之间信息是有偏差的，你的信息从哪里过去，有没有查证，有没有核实。 • 发言者 2 34:12 在第一时间我们给了刑警，也给了派出所，关于绿化死亡后不为处，我们的业委会成立的时候是在今年10月份，而业委会的备案也是在今年的10月份过了，10月份往后的时候都已经是冬季，我来的时候就是冬季这个时候你就算让我换，我可以换死了，谁承担。 • 发言者 4 34:43 继续说说，完了以后又把跟你说死了， • 发言者 2 34:46 谁承担，我觉得这是专业性的问题了。对吧？北边的围墙一直是空着，北边的围墙在这我再郑重的说一遍，北边的文桥在物业服务范畴里边，它是不作为物业服务范围内的，它是红线以外。而且那个地方现在又涉及到法律的官司本身也属于违建。我物业公司有权不处理这个事情。这本身也不属于我物业公司的范围。我们本着为业主着想的态度来积极解决这个问题。确实也协调了施工单位去厂家定做，但是因为费用太高，人家确实不给咱弄。现在一直在拖着我们那个费用由物业公司来承担，但我这个事情也跟业委会沟通了不下5次了。 • 发言者 2 35:34 我说过现在物业费外面欠的账是170多万回40万，我解决这个问题，因为我账上一分钱没有。如果我上门有钱的情况下，这个问题我早就给你拿出钱来去解决了，我没有钱。但是在这种情况下，咱的业委会成员还在业主群里面，去告诉大家不要缴费。明前跟我说帮着大家去缴费来解决园区问题，但是背后的却告诉人家说不要让大家缴费，这些记录我们都有，我们已经和法院那边联系了。我们会走法律程序，阻碍经营， • 发言者 7 36:15 造成物业公司经济损失，它阻碍正常经营，我们以这个理由会正式起诉。 • 发言者 2 36:23 第八， • 发言者 7 36:23 民生覆盖，宽带快递柜燃气燃气宽带民生。根据建设条例和前期配套要求，这属于地产的前期配套的问题。如果后期要开通，物业公司可以帮着来开通，但费用由业主来承担。这些都有法律规定，这不是我物业公司前期的工作，这是地产前期配套，政府都有相关的制度的。第9个雨水障碍一直没有解决。雨水倒灌这个问题，整个园区地势四周偏高，中间偏矮。车库到设计的时候全都是往里斜坡向下， • 发言者 2 37:08 这个的话你得找找地产前期设计和建设是不是符合设计规范和建设规范。对吧？都是地产，那你的壕沟排水量就在那摆着呢。对不对？那排水量在这里面下的雨水量那么大，超出了它的承载范围，这不是我能解决的问题。对不对？我就算加个机械排水，但是它的水费超出一定程度以后它才能排水。是不是？人员配备不足，我刚才已经说过了，前期人员人员配不足，是因为地产当时债主给了一批补亏款，但是这个款到现在为止还没结账。刚才也给你们算过了，现在项目上就是20来个人，这20来个人一个一年的成本就100多万，你们自己有没有算过这笔账？ • 发言者 2 38:01 光维修费今年就花了几十万，喂。上完了你们看看人家怎么现在怎么一句话都没听懂。那我接着就是集团的问题。了，也就是说他原来我原来还没有上面提这些问题，需要用钱来解决的。目前就这么回事，听明白了。这个东西都知道要点了。你提供钱解决，这就是给钱的问题。 • 发言者 4 38:53 我先我先接着刚才吴经理说完这个我先接着聊， • 发言者 2 38:58 现在确实是集团的问题。这我都明白了。你这确实集团的问题。 • 发言者 4 39:04 首先这个物业服务是没有滞后性的，这个东西，这件事我可以非常确定，你咱整个全滨州小区也没有说是必须得先收上钱来，我才给你服务。 • 发言者 2 39:17 对不对？这个我先说一下， • 发言者 4 39:20 你不要先说。了， • 发言者 2 39:21 你刚才说的时候我们不要背后销售服务，在任何一个法律上都有明确， • 发言者 4 39:26 那就没什么谈的，必要我们小区要求的就是必须得正常服务，我不刚才给我不管你，我不管你， • 发言者 2 39:32 我们已经走法律程序了，你认为你的你慢慢走， • 发言者 4 39:35 你慢慢走，我支持你。法律场景。第2个包括我们之前讨论的这几条，它不是说你你们几个人来了小区以后才发才有的这些问题，我就举个最基本的例子，门柱灯内部水泄迎宾水泄监控。这些等等这些问题是从交房一直到现在是一个时序性的问题，你怎么说你来了以后，因为最近你没有钱才出现了这些问题吗？ • 发言者 2 40:04 是这个事我跟你说对不对？你别再正常办事了行吗？第1个点我看我我不说今天下午来是干啥的，就是我首先说咱这个方法就是这个成立业委会，成立业委会今天下午的时候你们来干啥的？就是他这个行业都安排好了， • 发言者 6 40:23 放在一块把 • 发言者 2 40:24 这个业委会这个原理的问题放在一块，看看还能沟通沟通上去了。妥善的解决吧。今天我是为这个事这个事刘主任怎么说呢，就是完全说咱的观点就是成立业委会召开业主大会，这个事这个叫做成立完业委会召开业主大会，这是一个正常流程，并不是说是非得说是就要求换物业要求什么的是吧？这也就说是他这个成立也拿这个招聘业务大会这个事，他还换主意和沟通这个事没有多大的问题，因为这个因为具体这个物业工作的不到位的地方，然后小区业主和物业也反映都反映过了，也反映很多，那就是今天换。 • 发言者 2 41:05 到这里不应该再通过我们再去和业主再去考虑一下这种问题，因为你也看不懂你你们你们可你们可以起诉你们，我觉得这个如果说是法律意义上，如果说是在诉讼期间，我们这个业务大会不能啥不能召开是吧？法律意义上如果有这条的话，我们小区有很多律师有这条的话，我们可以等着不召开业务大会，但是如果我觉得话，如果说是只要没有这一条，我觉得作为这一步的业务大会该怎么着该怎么着是吧？对，我就是社区的，我反正出来我你们应该是有权利的阻挡我们权利的大会，但是你们有权利当面也会可以把也会当面的要说的这个问题你就可以去说去，没问题服务。 • 发言者 4 42:01 我个人感觉咱今天下午也没有什么讨论的必要了，我们就是全体包括物业代表，还有我们业委会，就是说基本上就是定下来，一个是开开这个业主大会，再一个基本上决议就是换掉这个物业也没有。发生于吴经理的意思也很明确了，那就大家现在做个表决投个票。就完事了，我觉得这个会没什么继续下去的必要了，服务他肯定是不会给我们服务了。这说的很明确了，对不对？这么些年这些遗留问题他也不承认，他也不会是去说去解解决的， • 发言者 2 42:37 你说你这样认为是啥？我们把事我们把事情程序知道吧？我知道我知道，他希望你们把事办好，但是你也看到了 • 发言者 4 42:44 已经到这一步了，已经不可能。调和了， • 发言者 2 42:49 底下的位置不是不让你们背道而驰，我知道你是好意， • 发言者 4 42:53 你是想让我们互相再调解调解，但是年年看到了像是已经到这种情况了，确实没有什么调解调和的必要了，就是换掉他。就是换掉他，只要是业主们同意换掉他没有问题，他们该起诉他们的，我们唉我们是该怎么走，我们的流程唉换掉我们 • 发言者 2 43:14 没有问题我们都同意，但是前提是把费用结清可以， • 发言者 4 43:17 没有问题，你起诉嘛又没有。人跟你男人一起起诉， • 发言者 2 43:22 去起诉的话你们没法换物业公司，因为在案件存续期间是没有办法， • 发言者 4 43:26 那你抓紧吧抓紧时间法律条文唉抓紧去起诉去， • 发言者 2 43:30 需要拿，你可以随便咨询一个法律， • 发言者 4 43:32 你知不知道我们业委会成立之日，你就自动已经自动解除和你们的物业合同关系了， • 发言者 2 43:39 你以前追问题你想象不出来，假如说今天这个会你不坐一块，还就从背后都做，就是你顶我顶我想是吧？你看有事就专门该该报的时候就报，出来就行了，知道吧？你你出不来问题永远解决不了问题。 • 发言者 4 43:55 刘主任就像你那天你 • 发言者 2 43:57 去小区创完他到了一定时候了，到了一定时候你到了一块，我说这一块不是让你们撒谎，我的意思出了问题来看看他还能打吗？还能救助这个事。是吧？ • 发言者 4 44:10 你看当时他物业说给我们定制围栏，让他拿出证据来，把电话号码拿出来，我们现场验证。第2个那天刘主任在现场的时候，跟咱主任当着面给他布置下任务，买半热带给小区业主们装半热带嘛， • 发言者 2 44:29 他办了没有，他们可能是把这一个 • 发言者 4 44:31 装的时候甭管怎么了，他当时是答应了你，咱不管咱不要给他找理由去，是答应了吧，是没办法对不对？你像这种物业我们不想用。明白吧？我虽然不能代表全体业主，我也不能代表业委会，我仅代表我个人想法， • 发言者 2 44:47 我不想用他就说实话真心对，唉对， • 发言者 4 44:50 就代表个人看法，但是我可以这么跟你说，我也99%的业主支持我。 • 发言者 2 44:57 对。他只是你要是市场要有对吧？ • 发言者 4 45:01 是我说的是只是我本人，我不干这业委会，我不干我虽然是业委会成员，但是我不干业委会， • 发言者 2 45:07 不不算业委会。 • 发言者 4 45:09 就说我不就说让业委会担我说的话的责任，我就这么个意思。唉我仅代表我个人就说我现在说的这话都是仅代表我个人， • 发言者 2 45:21 我业主的身份，实际上我们有事的话，90%的这个业主是应该是尊重，但是他相关业主物业会负责， • 发言者 4 45:29 他不是说现在这个物业服务已经是太差了，你。已经让人忍无可忍了，你知道吧？你要之前我们几个业主喝茶都得监视我们业主的行动，你你让我们怎么我们在小区的生活是没有， • 发言者 2 45:43 你不要把矛盾再往深一步拉的，我不说啥人品问题，咱不能不不别说全是什么。那不好了，谁叫那个什么，你是多少号楼，我是59号51号59号20。所以其他特点不一样，我还想把这个专业给我的原因汇报了，到了一块就要2000万准备快上去了，他就发现问题这个点解决现在查清楚就是没有钱办不了事， • 发言者 4 46:14 不是不是刘主任你还是给我们，你听你也在。 • 发言者 2 46:50 唱完不成咱们班来去，怎么是他们去不是吗？出现了以前的位置你得存在他那有钱 • 发言者 8 46:59 他怎么不能改呢？ • 发言者 2 47:00 反正咱说出的退的不要问问题，刘主任我说一句吧，好的。 • 发言者 3 47:05 咱这个问题既然没有钱上山退不动改不了，那就是永远这样。对，现在讲不见服务，业主们不是在说我怎样就是打别的业主不愿意交这个物业费。父母安康就是整改工作没整改，他肯定不愿意交。不愿意交物业就没有钱，没有钱就是觉得这个情况越来越糟。越来越糊涂。你这样有法解决吗？你不用说这大事者领导们来咱去做工作， • 发言者 2 47:38 做不下来。 • 发言者 3 47:39 你就是区领导甚至市领导，你这样我跟你一样烦恼。哪个领导说能不想拿回他的物业，他说他接下来本来他对也不叫或者说瞎救也不救，能帮助吗？这种事情不好吧。 • 发言者 4 48:00 我再说一个我个人观点，这个物业费的问题，我们就是说在最终解决之前，我们还有个提案，就是说从交房到现在之前我们交的物业费他没有达成的服务，我们也有可能会就是集体去起诉他，要返还一部分费用， • 发言者 2 48:21 说实话应该说就是把那个物业和业主的价格有些不对称磕磕绊绊的问题，我们现在的体重怎么到了一种就是不敢不可调整的。 • 发言者 3 48:34 这个情况很尖，锐那 • 发言者 2 48:35 有视频也有照片，不光知道你就这么啥。 • 发言者 8 48:40 问题太严重了，现在是。 • 发言者 2 48:44 嗯嗯。原来我就不至于这 • 发言者 3 48:46 有啥这么大问题你都不想。 • 发言者 2 48:49 不想。这唉呀你们做这个程序跟他们说了什么？我们 • 发言者 7 48:56 上午说给求助人已经说过了。 • 发言者 2 48:59 我给等于今天说你昨天说的我现在前两天他如果今天有多少做多少程序，是不是 • 发言者 7 49:05 今天上午我今天上午的时候我就给他打了电话，我打了他电话以后，我又给集团打了法务电话，集团法务会在今天操作这个手续，我们已经在跟法院那边打电话沟通这个事儿。我先给所有人打了一遍电话以后，我才给集团法务沟通的这个事情。其实他们在群里面做的这所有的动态，很多业主都已经反馈出来了，我们都已经截屏，然后都已经邮政了。 • 发言者 8 49:31 那这是不是窥探业主隐私？那我不影响业主的正常生活，那 • 发言者 2 49:37 你可以为了相对的 • 发言者 8 49:39 我们就反诉就可以了，只要他起诉我们就反诉拿出证据来。 • 发言者 2 49:43 人家都在这都法律合适了，那你这对 • 发言者 3 49:47 都到法院了，对，那你。 • 发言者 8 49:49 这小区的生活你觉得对小区的公司服务满意吗？说句实话 • 发言者 5 49:54 有很多地方是不满意的，我问你咱们平常先生说就确实这个东西是真是啥的，唉看这个地方当然这里这么一些问题是一是一个问题，不是他的这一个就一点都没有了，就说嗯。是一些不可控的一些反正是我的范围是全球第一，我能不让说话，不让说话就别人攻击怎么样怎么说，现在我感觉那东西我也不让他上吃的东西什么。嗯 • 发言者 2 50:31 怎么样。你给谁也没啥需要。多少。 • 发言者 4 50:34 对，没有了。 • 发言者 2 50:38 我有啥需要说的。 • 发言者 3 50:41 我刚才我一开始跟谁说， • 发言者 2 50:43 邱主任说的是一样的，我是一直单方面一直把他们双方之间的矛盾，我还要你们是一家人一家一会给校区服务是吧？ • 发言者 7 50:52 最终咱们是都是业主是不是 • 发言者 2 50:54 咱就直接使用是吧？服务物业不。就是服务给咱服务嘛 • 发言者 7 50:58 是不是？ • 发言者 4 51:00 那现在服务你是服务你业主，你物业本身 • 发言者 5 51:04 是应该对把一些双方的人， • 发言者 2 51:06 我是一个就是出现一些负面影响， • 发言者 4 51:08 我一个就是往下好像我也不愿跟你们强调这个。尽量是，但是物业这个物业经理我这不是说针对个人，这个物业经理确实说话非常欠妥，就像那天进贼了，我们抓着贼的这个老师给他打电话，他上来就是你小区进贼了，让你派个这个人，过来帮忙或者逮贼或者干嘛，这不很正常吗？咱物业经理第1句话就是你交物业费了吗？你没交物业费我们不给你服务。跟我也说你不交物业费，我们上家吃饭去，然后16个004也就跟人家说，你这话16个104人家那个业主就说了，你不交物业费我们就上你家去，我说这话我负责领导们都在这里， • 发言者 7 51:50 你从哪得到这句话，业主有录音。拿出来让他拿出来看看我是不是这么说， • 发言者 4 51:55 你正常起诉就行了， • 发言者 7 51:57 你不是你如果你这句话给我拿出录音来， • 发言者 4 52:00 我不管你跟我说了要上我们家吃饭，这个事你承不承认？ • 发言者 7 52:05 你承不承认我就问我承认我上你家吃饭去， • 发言者 4 52:08 这不就算吗？就和黑社会一样说你不交物业费我们都 • 发言者 3 52:12 先吃饭，别吵架去，别吵， • 发言者 4 52:14 不是吵不吵 • 发言者 5 52:15 他不承认吵啥小买卖，就说有啥就别在那说。 • 发言者 4 52:23 这个事就是说我就这么讲，没有调停必要了， • 发言者 3 52:26 这个要拿错了。那个目录那让你说过他们做的事情我都不会了。 • 发言者 4 52:32 对呀，出那个谁出来不是给你打电话也是这么说的吗？ • 发言者 3 52:35 对不对？ • 发言者 5 52:37 那咱别吵，咱就说有些问题吧，那就是注意这个业主大会，咱说业主大会目的开与不开钱都炸不开，那都全都炸毁了，我一直说不通不如说开这个事，然后我就说这事，然后说到一定该开的时候咱就开开了，咱就咱就和那个那个叫物业也打个招呼，咱怎么开怎么开个议题是啥？当时说了以后就是话在那说了。 • 发言者 3 53:01 还是他今天来下午来我不说了吧，他说我到还得看你双方冷静看，能不能还是还能再激光往中间给你们透透，把这事还往好的方向发展吧，这是哪里会这一下会知道吧？ • 发言者 8 53:14 现在都调到就激起人民内部矛盾了。有些从筹备组开始，业委会一些热心业主就给人家造谣，说人家物业公司还说到我了，说我有物业公司说我有时间拿个物业当会计上，我在这里刘春我可以拿个身份证来搞好对象的身份证来上工上。大大方方的去查，我房子要是明天查询我也没事了。 • 发言者 3 53:38 第一也没有必要，第二我也没有权利就是 • 发言者 8 53:42 因为我没有我们是出的钱是有意图，这就有个人福利，所以相信这个世界上有无私奉献的人， • 发言者 3 53:49 所以我现在吧我你10点了现在哪里到这里开会，我现在还建议啥？我建议这个刚来这咱就这后边在公园。里面公园里面生出个妈妈这种人。你看这个这就是我们 • 发言者 2 54:05 实际上这个办事处领导文案这个牺牲这个时间过来，实际上这个到推荐给妈妈是很多牺牲时间，目的就是为了啥？为了这个小区好起来对不对？ • 发言者 3 54:16 唉他们的问题也是为了 • 发言者 2 54:18 把这个专业也没不要要眼光和这个不一样，也是 • 发言者 3 54:25 这是他的目的。 • 发言者 2 54:26 然后现在呢 • 发言者 3 54:27 到这个地步， • 发言者 2 54:28 我要这你这个物业也得自己反思反思。为什么呢？一开始前几年为什么很好，交的物业都很齐会提出对不对？你反思这个人置办商品，你这个大块东西，你怎么去反思自己，我怎么是造成的？这个我不说是吴经理，你这是干了 • 发言者 3 54:47 多长时间， • 发言者 2 54:48 以前这么多经理 • 发言者 3 54:50 不是你造成的。 • 发言者 2 54:52 不要为了什么你自己造成的。他是累积起来的历史的 • 发言者 3 54:58 多方面的原因造成的，有底层的原因，当然也有问题的原因， • 发言者 2 55:01 你比如你比如说你说话你就没记住，还得跟你交。也不是咱俩没有这个话，他不是买自己的。对不对？所以说呢你说起诉你走法律程序呢，每个组织每个个人的权利，你就是我们这个业主也好，还是业主会也好，你就是绕开这个业主大会，这是他的自身权利，都有自己的比如说你不可以行驶。对。但是尽量的还是把这个行驶权能够都沟通的合法化，你要是不合法化的，如果说就说你滥用一些权利，但是我可以想象 • 发言者 3 55:37 你既然滥用权利， • 发言者 2 55:38 肯定要受到法律的惩戒。我就说这个这还得感谢你当时 • 发言者 3 55:44 准备了给我们这个时间，为啥说拿2万的最多，我商量的最好，我为啥到坐在这里选择哪个位置，现在我看情况确实我怎么寻思你们这个中间这个隔阂越来越越多的。 • 发言者 2 55:59 有多少产品？ • 发言者 3 56:00 北京我想让你上给你干什么，就是要比较好的，我各方各方面他都能看出来。你还有什么能力远都远远都 • 发言者 2 56:10 唉呀。 • 发言者 3 56:14 都属于哪个公关了是吧？就都属于哪个公关，你把它处理，包括那小区物业都需要让他出去以后和谐稳定，你只有这样你都好亮干你好像123456了是吧？有那次就好了呀。 • 发言者 4 56:30 咱们明白。肯定也是为我们好吧，咱反正说那么多了，让邱主任做个总结吧，总结咱就说把这个事就定下来，该怎么那啥咱说多少其实也没啥意义了，对吧？怎么咱开会怎么都在讨论这个结果来。我是跟着这个组织走组组织的，我们组织的这个决议我没意见， • 发言者 5 56:54 我刚才说了。 • 发言者 2 56:56 好好我。 • 发言者 5 56:58 我在学校 • 发言者 3 57:00 应该说，实际上我建议还是这个咱这物业拿出来这个真实行动来，你要想在那继续干下去的时候，你没有那真实行动来这赢得这个业主的这个各方面的这个心。 • 发言者 7 57:15 意哥我现在就跟你说一句话，心里不想去了， • 发言者 3 57:19 我现在已经入不敷出，外面欠着物业费，我什么都算，我们拿太多领导再有领导再有我委会还有咱这一些比较站在中立的，不对你们有偏心。或者说偏偏什么的，这个业主们也考虑你这部分的难处，你也得体谅这业主们的这个良苦用心。我这么说，现在呢你看三天两水两头的停水也进水，院墙也这样，架空也这样，你那小区嘛别那大路上的雪都干干净净的，咱们小区还那雪还那么厚，确实市政服务有待于进一步的提高。 • 发言者 7 57:59 我这么说哥，这个咱一个也是来物业公司态度不是一次两次的明确表态过，光业主欠物业公司的钱就100多万，当时我给业委会的所有成员说过，我说要求不多年前回40万，我拿出钱来给你修一部分，然后 • 发言者 3 58:19 那个时候还有咱有充足的资金， • 发言者 7 58:22 我那个时候说一下，我刚才已经跟你说的很清楚，外面欠物业公司170多万，不是说那个时候其实在之前公司一直是亏损的，没有钱。只是说当时亏损的额度少一点而已，今年的亏损额度直接拉大了。 • 发言者 3 58:39 你现在你叫业委会也好，叫领导们也好，争取，咱这个现状不改变，就叫他们再去交这个物业费。 • 发言者 7 58:48 很难呀，我这么好的跟你说一直在重复一个问题，业主欠物业公司100多万170，14万，如果他欠1万块钱无所谓，10万块钱无所谓对吧？恰恰应该有钱， • 发言者 3 59:02 但是要你的服务更好，这是个前提。 • 发言者 7 59:05 我刚才也跟你说了，你刚才说出血这个事情上出血的时候，人一直都没有停下来，一直都出着为你 • 发言者 3 59:14 看你不出去也不行，你不见效你 • 发言者 7 59:17 有没有对接对接，看看其他小区里面完全的血清理的，在滨州市有几个小区能听到咱现在这个样子， • 发言者 3 59:23 像我住的那个基本上住的人都能至少能人他的面积有多大是吧？那当时不是我们 • 发言者 2 59:31 都要查出来了。 • 发言者 8 59:32 掉了我只能清那个三期，光一期的时候干到2、3、3期是靠经济转化的。那有照片。多。然后 • 发言者 3 59:40 他现在讲这个矛盾越积越越加锐了，越积越加锐你更难解决，吴经理。 • 发言者 7 59:47 你等于我刚才这么说吧，我就扔一句话给大家。也不是说 • 发言者 3 59:52 你刚才你看法律大家可以就这样，你还是说你还是说这个地产据说那时候我也不大很清楚，你这地产行物业，你这物业怎么现在的没有地产你进不来，对不对？你在签合同的时候，我首先签合同的时候，我签这个售楼合同， • 发言者 7 01:00:11 就逮着我这么跟你说，我这么跟你说。 • 发言者 3 01:00:14 你这个2块5一个平方2块5，那是一定规定，你那个时候也没有物业业主会也没有， • 发言者 7 01:00:20 我也不怕合作人，我这人说话上来就直接你说一说地产公司把物业带进来，物业就要承担这个责任，是这个意思吧？不是。 • 发言者 3 01:00:29 不是这个意思，不是这个意思，不是这个意思，我是什么意思呢？你刚才说一个集体说推到这个地产公司上， • 发言者 7 01:00:36 你既然是推到地产公司，确确实实是他的问题， • 发言者 3 01:00:38 我跟你说我说完了，既然地产公司能把你来带去带进来，为啥你不能去把他签回来？我现在跟你这么说， • 发言者 7 01:00:48 我已经跟他们所说的已经不下5六遍甚至10遍左右了，地产公司现在申请破产，你让我拿什么去找他？ • 发言者 3 01:00:56 申请破产就没有办法了吗？ • 发言者 7 01:00:59 有办法呀，业委会集体提出 • 发言者 3 01:01:02 的问问量 • 发言者 7 01:01:04 最好的办法， • 发言者 3 01:01:05 姑娘唉 • 发言者 2 01:01:06 行了。还是你放完母亲的这个中间的某某某的隔阂越来越深，不但不好吧往好赚钱那个原因反而越来越深。今天咱的结果不很好。我就说实话不知道。行，他妈那今天到到此为止了，你再给我传回去。也解决不了啥实质性问题，就说这个智慧化耽误时间，你在网上说的啥等等走出一直呼吸之后等等都经常性的在在都 • 发言者 3 01:01:38 都理解对方互相交换，吴经理。您 • 发言者 2 01:01:43 都有物业的地方吧， • 发言者 3 01:01:46 从办事处这边你再努力一把， • 发言者 2 01:01:49 再把咱们服务了，往去听哥我就这么说吧。我不小了，我也只是一个打工的， • 发言者 7 01:01:56 公司已经现状运营情况。不止一次跟情主任沟通过我们也都流过相关的录录相像据对吧？不是我们不想不录相沟通， • 发言者 3 01:02:05 而且都了录你这班你邱你再把你这把光 • 发言者 2 01:02:10 提 • 发言者 3 01:02:10 这把你这边能理解，咱也能理解沟通，能理解同志们说实话。 • 发言者 2 01:02:15 我提这个问题，我11个结果咱还能说逮住， • 发言者 3 01:02:18 就是说有一个完不完不完好的三个地方能说你出去吃也出了8页， • 发言者 5 01:02:24 也是也不是业主委员会，你能出来群里自发能出来一点， • 发言者 3 01:02:27 你说什么也当的，也是一种认可的。情况给你办了是吧？找哪个回去，你这话说的都是为了工作，没必要把个人喊起来沟通， • 发言者 2 01:02:37 能强调一下都是为了工作， • 发言者 3 01:02:39 你也是为工吧，他们是为为了那个业主，咱不是为了工作，咱今天我说一句话， • 发言者 7 01:02:44 你走的时候我就说一句话，就是你们啥情况，我说我自己心里很清楚，群里的信息我也都看你们拿这十几个问题也好，还干嘛也好，你们上了钱也好还是怎么着，能不能解决这十几个问题解决不了的时候，你们怎么对这400个业主怎么收场你就别管了。你干什么？ • 发言者 4 01:03:07 那我们就正常推进这个业主大会了，领导们我们就不再跟 • 发言者 3 01:03:13 你们再那个啥了。就是我和他 • 发言者 2 01:03:16 关系就是啥意思？ | D5: # 全文摘要 会议围绕小区物业管理问题展开讨论，主要涉及业主委员会与物业公司之间的矛盾。双方就11项具体问题展开辩论，包括门柱灯未启用、水系未开放、监控损坏、绿化维护缺失、围墙安全隐患等问题。物业公司强调因资金紧张无法提供服务，而业主委员会则认为物业服务质量低下且存在违规行为，计划召开业主大会表决更换物业公司。会议最终未能达成实质性解决方案。 ## 物业管理问题讨论 - 小区存在11项长期未解决的物业管理问题，包括门柱灯未启用、水系未开放、监控损坏、绿化维护缺失、围墙安全隐患等 - 物业公司表示因欠费170多万元导致运营困难，无法承担维修费用 - 业主委员会指出物业服务质量低下，包括对绿化问题的敷衍态度、监控室无人值班、围墙整改拖延等 ## 业主大会筹备 - 业主委员会计划召开业主大会，讨论是否更换物业公司 - 物业公司表示在法律程序未完成前无法召开业主大会 - 会议中提到有200多位业主参与了相关讨论 - 业主委员会表示99%的业主支持更换物业公司 ## 法律程序进展 - 物业公司已与高级人民法院沟通，计划本月正式起诉 - 起诉理由包括业委会成员阻碍正常经营、欠费业主不能成为代表等 - 业主委员会表示支持法律程序，但认为物业已无法提供正常服务 - 双方都提到有相关沟通记录和证据 ## 问题根源分析 - 物业公司认为问题根源在于地产公司，包括前期设计缺陷、配套未完成等 - 业主委员会认为物业应承担服务责任，不应将问题推给地产公司 - 讨论中提到地产公司已申请破产，物业难以追责 - 双方都承认问题已积累多年，矛盾日益加深 ## 后续建议 - 物业公司建议双方冷静沟通，寻找中间解决方案 - 业主委员会表示将推进业主大会流程 - 会议主持人建议双方保持理性，避免激化矛盾 - 会议最终未达成实质性解决方案 | E5: 3 | F5: 3 | G5: 4 | H5: 0 | I5: =(E5+F5+G5)/3 -> 3.3333333 | J5: 1.2 事实错误：原文只提及仅代表发言人个人观点99%业主不想继续用当前物业，是否真的有99%支持该观点是不确定的 1.4 逻辑错乱：只是有200+业主接龙想要组织业主大会，不能推断有200+业主参与了讨论 2.1 核心遗漏：没有介绍11项问题具体是哪些 2.3 冗余：小区存在的问题就是业主委员会支出的，物业管理问题讨论1、3条表达的是相同的内容 3.4 内容重复多次：下去存在的长期未解决的物业管理问题在摘要和问题讨论这出现两次，且详略程度一模一样 | K5: 会议背景 小区长期存在基础设施未启用、物业服务不到位等问题，业主与物业矛盾持续升级。本次会议由业主代表与物业方共同参与，就小区十余项历史遗留问题进行当面对质。核心焦点集中于服务缺失责任归属、欠费与服务的因果关系，以及是否召开业主大会表决更换物业。会议最终未能达成调解共识，对立态势明确。 小区现存问题通报（业主方陈述） 基础设施长期未启用 入户庭院灯自交房以来从未开启。 小区内水系及售楼处迎宾水系均未运行，影响小区品质与业主权益。 安防系统严重缺失 监控系统几乎全部损坏，上月小区发生盗窃案时无法提供有效影像支持。 监控室自王艳芳上任后已无24小时值班，可视门铃一键报警功能失效。 绿化养护失职 多棵树木死亡，业主反映病树未及时处理，物业回应“明年看是否发芽”，未采取主动维护措施。 安全隐患突出 北侧院墙长期以铁皮围挡，西端存在缺口，社会人员可随意进出，存在重大安全风险。 物业曾承诺定制新围挡但未兑现，经核实并未实际下单，涉嫌哄骗业主。 民生配套缺位 快递柜、直饮水机、宽带覆盖、暖气开通等基础服务多年无进展，均由业委会自行推动解决。 雨水倒灌频发 自2019年首场大雨起，6至15号楼共经历三次严重积水，造成业主财产损失，至今无系统性解决方案。 人员严重减配 物业办公室工作人员从最初近10人缩减至4人，维修人员从5人减至2人，服务能力大幅下降。 物业方回应与解释 运营成本与收费困境 园区年饱和收入约100万元，而仅人工成本即超100万元，加上能耗、维修、税费等，公司长期亏损。 外部欠款达174万元，账面无资金支撑维修与服务升级。 问题归责说明 庭院灯未亮：因能耗成本过高，物业无力承担，需业主缴费支持方可修复。 水系无法运行：水泵存在严重质量问题，属地产前期配套缺陷，非物业责任。 监控损坏：维修报价超出运营预算，无法承担。 雨水倒灌：园区地势设计为中间低四周高，排水系统容量不足，属地产设计问题。 北侧围墙：位于红线外且涉及违建官司，不在物业服务范围内。 对业委会行为的指控 业委会成员在业主群中鼓动拒缴物业费，阻碍正常经营，已造成实际经济损失。 已掌握相关证据，包括群聊截图与沟通记录，并将于本月正式提起法律诉讼。 起诉对象包括部分业主代表，理由为“阻碍经营”与“滥用权利”。 双方立场冲突与争议焦点 服务与缴费的先后逻辑 业主方认为：物业服务应具前置性，不能以“先交钱再服务”为前提，否则违背物业服务本质。 物业方坚持：当前亏损严重，必须有资金回笼才能恢复服务，缴费是服务恢复的前提。 历史问题责任归属 业主方指出：门灯、水系、监控等问题自交房起持续存在，非近期才出现，不应以“没钱”为由推诿。 物业方强调：部分问题属地产遗留，自身接手时已存在缺陷，不应由现物业公司全责承担。 业委会合法性与行动权 物业方声称：部分欠费人员及顶名人不具备业主代表资格，选举程序违法，业委会不合法。 业主方反驳：业委会依法成立，其成立之日即视为原物业合同自动解除，有权组织业主大会。 关键决策与共识 关于召开业主大会：业主方决定继续推进召开业主大会，表决是否更换物业，不受物业起诉威胁影响。 关于物业去留：多数业主代表明确表示“换掉他”，认为当前物业服务已“忍无可忍”，无调和可能。 关于法律行动：物业方确认将在本月正式起诉业委会及相关代表；业主方表示将反诉，要求返还未达标服务期间的物业费。 全局行动项汇总 AI洞察 物业与业主陷入“服务差→拒缴费→更没钱→服务更差”的恶性循环，单靠一方让步难以破局，需第三方介入资金监管或临时托管。 物业将多个问题归责于地产，但作为服务提供方，仍需承担协调与推动责任，完全推责削弱其专业形象。 业委会虽有群众基础，但若无法解决“欠费者能否参选”等程序合法性问题，可能被司法途径推翻，存在组织风险。 待办 业委会准备集体起诉物业公司要求返还部分未达标的物业服务费 确认法务程序是否影响业主大会召开，并咨询小区内律师意见 物业公司需提供北边围墙未修复的详细法律依据和协调进展说明 物业公司就监控损坏、绿化维护、水系未开启等问题提出具体整改计划 业委会整理并提交关于物业服务质量不达标问题的书面清单 业委会与物业公司沟通召开业主大会的流程和议程安排 发言人2提议召开业主大会并由全体业主表决是否更换物业，需尽快推进 章节 00:00:22 会议开场与议题引入 会议初期，发言人1与其他参与者开始提及费用缴纳、手续办理等问题，初步暴露出小区在物业管理和财务交接方面的混乱情况。讨论涉及资金流向、服务未兑现等疑点，为后续深入讨论物业问题埋下伏笔。 00:01:38 物业费用与服务履行争议 多位发言人围绕物业费是否已缴纳展开争论，强调业主已履行缴费义务但未获得相应服务。同时指出园区基础设施长期未能验收，供水、管道等问题本应由地产方负责，但至今未解决，导致责任归属模糊，矛盾逐渐显现。 00:05:12 业主维权行动与业委会筹备 讨论转向业主自发组织接龙并推动召开业主大会的行动。发言人2介绍已有约200名业主参与，旨在通过合法程序表决是否更换物业公司。同时明确业委会尚无决策权，需通过正式业主大会形成决议，体现业主群体对制度化治理路径的诉求。 00:19:52 法律对抗升级与起诉威胁 物业公司宣布已启动法律程序，将以业主代表在群内煽动言论、阻碍经营为由提起诉讼。同时警告欠费业主不具备代表资格。业主方则反击称将集体起诉物业公司要求返还多年未履约期间的物业费，双方均表明走司法途径的决心，协商基础彻底破裂。 00:22:45 小区现存十大核心问题陈述 发言人2系统性地列出小区长期存在的十大问题：包括庭院灯从未开启、内部水系与迎宾水系常年停用、监控设备大面积损坏、绿化维护缺失、北侧围墙安全隐患、雨水倒灌频发、人员配备严重不足等，全面揭示物业服务缺位的现状，引发集体共鸣。 00:31:35 物业公司回应与责任推诿 发言人3代表物业公司逐条回应问题，将多数问题归因于地产配套缺陷或资金不足。强调物业长期亏损运营，人工成本远超收入，并指出部分设施不在服务范围内（如北侧围墙属红线外违建）。同时声称已向警方提供监控证据，否认服务失职。 00:39:07 服务与缴费关系的根本分歧 双方就“先服务还是先缴费”产生激烈争执。业主方坚持物业服务不应以缴费为前提，质疑物业公司以欠费为由拒绝服务的正当性；而物业则强调收不上费用导致无法维持运营。矛盾焦点从具体问题上升至服务逻辑的根本对立，调解空间被压缩。 00:42:10 信任崩塌与换物业共识形成 随着对话推进，业主代表明确表示对当前物业失去信心，即便个人不具全权，也坚信绝大多数业主支持更换物业。指出对方承诺未兑现（如围栏安装）、态度恶劣（如‘不交费就不服务’），已构成不可调和的矛盾，决定依法推进业主大会流程，不再接受调解。 00:53:02 矛盾根源探讨与历史积弊反思 发言人1尝试引导反思矛盾成因，指出问题非短期形成，而是地产遗留、资金链断裂、管理滑坡等多重因素叠加所致。呼吁各方认清现实，避免互相指责。同时提及业委会成员遭造谣攻击，反映社区治理环境恶化，内部信任体系濒临瓦解。 00:56:44 会议总结与后续行动定调 会议尾声，中立方建议物业拿出实际行动赢回信任，否则难以继续留任。物业重申欠费困境，但未提出可行改进方案。最终业主方坚定表态将依法推进业主大会，完成投票程序，彻底结束当前物业服务关系，会议在高度对立氛围中收场。 行动项 负责人 时间节点 正式启动业主大会召开程序 发言人2、业委会成员 立即推进 物业方向法院提交起诉材料 发言人3（物业代表） 本月内 业委会准备反诉材料，主张退还未服务期间物业费 业主代表群体 待定 核实并公开物业所称“已定制围挡”的证据真伪 业委会 已要求立即提供 | L5: 4 | M5: 3 | N5: 5 | O5: 0 | P5: =(L5+M5+N5)/3 -> 4 | Q5: 1.2 事实错误：物业表示欠款170万回40万，不是欠款174万 2.1 核心遗漏：提及了十余项物业问题，但只列出了不足十条 同样，问题归责说明也只提及了五个问题 待办不合理 格式太差，主次不分，很难阅读 | R5: 决策会议：业主大会启动与物业更换 第一层：核心信息 [会议标题] [决策型] 小区治理与物业服务争议：业主大会启动及物业更换决定 [一句话摘要] 业主大会因约200名业主联名要求将于本月启动，同时决定起诉业委会代表并更换物业公司，因物业服务长期缺失且争议无法调和。 [结论与决策] 已确定: 业主大会本月启动（依据200名业主接龙要求）。 起诉业委会代表（依据高级人民法院通话记录）。 立即更换物业公司（因服务缺失、安全事件处理不当及物业经理威胁业主）。 待进一步讨论: 业主大会召开细节（参与规则、议程）。 业委会权利边界（决策权限、业主资格）。 物业费欠款174万元责任归属及返还方案。 [待办事项] 召开业主大会 → 负责人：待确认 / 截止：待确认 咨询律师 → 负责人：待确认 处理欠费业主问题（欠费人员禁入业主大会） → 负责人：待确认 修复监控系统 → 负责人：待确认 / 截止：待确认 修复北围墙缺口 → 负责人：待确认 / 截止：待确认 起诉物业公司返还费用 → 负责人：业主 / 交付物：证据（录音、服务记录） 更换物业公司流程启动 → 负责人：业委会 / 优先级：高 第二层：关键脉络 [讨论脉络] 议题1：业主大会争议与法律行动 Speaker 6报告约200名业主接龙要求召开业主大会。Speaker 1称业委会计划本月启动但未实施，同时宣布起诉业委会代表（已与高级人民法院沟通）。核心矛盾：业委会被质疑决策超权及选举合法性。 议题2：物业服务缺失问题 业主列举十条服务问题（监控损坏、围墙缺口、雨水倒灌等），物业回应资金短缺（年收入100万，人工成本超100万），并称围墙/水系属地产责任。安全事项（监控、围墙）列为优先整改项，雨水倒灌需联合地产评估。 议题3：物业更换决策 Speaker 6指控物业经理拒接安全事件电话并威胁业主，全体委员支持更换物业。物业（Speaker 1）辩称欠费174万致亏损，业主方反驳服务缺失是欠费主因，提议集体起诉返还费用。 [关键提取] 重要数据： 约200名业主联名要求召开业主大会（Speaker 6）。 物业年收入约100万，人工成本超100万（Speaker 1）；欠费总额174万元（Speaker 1）。 2019年至今雨水倒灌致三次财产损失（Speaker 6）。 知识要点： 业主大会是唯一决策机构，欠费业主无参会资格（Speaker 1、6）。 物业服务范畴以合同和红线地带为界，围墙/水系问题属地产责任（Speaker 1）。 第三层：深度洞察 [未解决的分歧] 业委会合法性争议： Speaker 1主张业委会存在违法行为需法律纠正；部分发言者回避起诉必要性（如Speaker 4转移话题）。 物业责任与资金矛盾： 业主坚持物业对全部问题负责，要求“服务先行“；物业称资金不足且部分属地产遗留问题，坚持“收费优先“。 [值得关注的信号] 反复争论：Speaker 1多次强调法律行动，其他发言者转移话题（如Speaker 4），显示沟通障碍。 执行矛盾：Speaker 1宣称“本月启动“业主大会但又称“未启动“，暗示执行不力；围墙修复承诺未兑现（Speaker 6：“哄骗业主说已定制”）。 内容由 AI ⽣成，仅供参考 | S5: 3 | T5: 3 | U5: 4 | V5: 0 | W5: =(S5+T5+U5)/3 -> 3.3333333 | X5: 1.2 事实错误：是起诉业委会，不是起诉某一代表 物业表示欠款170万回40万，不是欠款174万 2.2 比例失调：概括会议主要讨论的物业问题以及物业对其的解释篇幅太小 待办提取不合理 格式太差，通篇不是按逻辑顺序或时间顺序排列的 ，很难阅读
A6: 5 | B6: 李腾飞 | C6: • 发言者 1 02:06 就是 • 发言者 2 02:06 都是一些比较基础的问题，因为我挑的这4个这个博士生，我自己代表这个多模态大模型和具身智能的这个融合这个方向。然后呢雄辉呢是这个于洋老师的博士生，他是这个强化学习做得非常厉害，然后呢薛寒博士呢是卢策武老师的博士生，然后呢他是在这个数据的这个收集以及这个柔性物体的操作方面非常的有心得，然后志龙呢也是于洋老师的博士生，他是在这个具身模型世界模型方面非常有建树，然后我非常期待志龙和这个赵昊老师能在这个世世界模型上能够有一些这个碰撞，就是其实是两个领域，因为志龙呢是从这个做强化学习那一套这个据世界模型来入手的。 • 发言者 2 02:50 所以呢我们先从我自己最熟悉的方向来来说起，就是在这个那第1个问题就是说其实请老师们和这个博士生们都分别回答一下，就是大家认为就目前其实具身智能呢分就是发展了一下，就是包括大模型呢大家其实介绍过这个大脑大模型，然后小脑大模型，然后有端到端的纯端到端的从头到尾都是端到端的模型。以及呢其实目前呢国际上有非常好的一些工作，包括以派灵为代表的这些，他们可能收集了6000多个小时这个数据，那最终训出来一个很work的一个端到端的模型。 • 发言者 2 03:38 那么在这一块就是想问一下各个老师们，还有这个同学们的意见，就是还是说我可以有一个粘绕的一个model,还是说我前面其实整体是端到端的，但是前面一部分我可以是fix住的，然后后面可以是一个这个Action的一个refiner,那么先请老师们回答一下。 • 发言者 3 04:24 我应该是这个现场最不懂具身的。那么各位老师都是可能在计算机方向深深耕多年的，然后我在这个机械方面和传感器方面有所其实这个问题我想反弹回去。我想请问一下各位老师和同学就具身的身体想请问一下大家，到底它会收敛成什么样子？是说像人一样的人形机器人呢，还是像科幻片里面的更不像人的，比如说我记得有个电影叫星际穿越，里面那个机器人就是一个大方块，然后遇到什么情况它可能自己会变形变成各种各样的样子。然后在我们机械领域呢可能有点没那么主流，我们会谈到一个叫机械智能的东西，比如说有的老师做这个抓取工作，大家想了各种各样的方法，让这个物体抓的稳抓的牢。 • 发言者 3 05:13 但是我们机械上可能会通过采用一些我们的软手就有非常强的摩擦和顺应性。抓取一个物体的时候，我们甚至能把这个误差比较大的时候，我们也能抓得很牢。所以在这些方面可能我就想请教一下各位老师，大家是从这个算法和软件的角度，那从硬件的角度大家有些什么？比如说对我们这个给大家服务的学科有什么期待？对。 • 发言者 2 05:44 那博士生们提一下期待吧。薛博士。我觉得就是嗯 • 发言者 4 05:53 可能硬件上就需要它的寿命，然后可靠性要比较高。就是因为我们在具身智能实验的过程中，特别是训练一个var a,然后你要大规模的在真机中evaluation,你会发现如果你的机器人很容易你的模型预测一些撞桌子之类的事情，撞几次它就坏了，然后其实很难去可靠的去sky up.对，所以就是我觉得这是一个非常重要的一个要求，对，但是可能现在现有的设计了很多工业机械臂或者是传统应用的很多臂，它其实并不是为这种设计考虑的，对我们需要一些比如说个人柔顺的一些硬件解构，然后能让支持我们能够更scale up的去做这个value的evaluation,对。 • 发言者 2 06:39 嗯。那我也简单说一下就是对于这个就是硬件的期待，其实我一直的一个观点就是具身它一定是一个软硬件协同优化的一个范式，特别是比如那个松龄他们的产品就是这个就是发布了两代其实你大家用过的话会发现就是它的第2代的这个b呢，你在姚操包括策略部署的时候呢，会比这个它的第1代要要好很多。那包括然后就是夹爪，夹爪特别是我和这个任老师也有学术合作，就是我们会发现包括比如说加了这个凝胶的这这种夹爪呢，它一个是可以反馈触觉，一个是它加很多东西会更稳。 • 发言者 2 07:21 固还有更好的这个摩擦力，所以我理解这个其实就是一个协同进化的一个部分。大模型玄学learning的人，就是但aloha可以说给我们续了一波命，因为它的这个出现呢我们就有了很多的这个收集数据的方式，然后大家开始就像清华呢它是这个收集了也是几千条数据，据说这个苏杭老师花了300万呢，这个预算，然后呢像这个派零它是多少个几千个小时这个数据，然后包括有了这套体系之后，我们也和松林合作了这这个部分。所以呢其实这但然后呢这个aloha的这个硬件呢，提升了之后呢，我们这个软算法呢又提升了对吧？ • 发言者 2 08:11 现在以派零为代表的这种大模型，它这个性能非常惊艳，然后可能后面还会有无数轮的迭代，所以可能最后迭代成什么样子，可能会也有可能会超越人类，这是我的观点。那就是还是recalL1下我刚才那个问题就是这个最深的这个大模型的这个问题，那还是请这个刚才分享的过程当中讲了大模型的两位老师，掌声行老师和王岳老师。来分享。因为 • 发言者 5 08:49 我好像没有分享。大模型方面的内容。但是我觉得刚才这两个问题，我觉得我想把两个问题连在一起去谈一下这个事儿。一个是硬件，自带，一个是模型最后的收敛。如果像刚才大家这个所畅享的那样，如果有一个大模型，它能够直通最底下一直到最上面。那么其实在某种程度上就把我们硬件迭代的可能性给消除了。因为一旦我们有新的硬件出现，尤其是像软体这样的机器人出现的情况下，你的硬件你的前面的大模型很有可能要完全重新训练。那又要用新的软体的结构去完成所有的data. • 发言者 5 09:29 所以我觉得它似乎不应该是一个应该或者说从上一直最上一直到最下是一个模型的形态，那至少可能也是两个层面的。那我觉得举一个不那么恰当的例子，就比如说有一天我一个手断了，我的大脑仍然能够帮助我去做一些比如说我原来泡一杯咖啡，可能左手拿个杯子，在里面讲， • 发言者 3 09:56 那现在 • 发言者 5 09:56 呢我可能右手拿这个杯子去放咖啡，那事实上我已经是一个构型变调的机器人。但是我的大脑仍然工作的很正常。那这个时候我的但是什么东我的什么东西变了呢？我的这个底层控制的这个模型这个小脑发生了变化。因为我的断了所以我整个人的惯量发生变化的dynamics.变化，我同样控制我的右手去做那些精细动作。我的身体就要发生改变。而且不能再像过去那样，我控制双手一样去控制我的右手的动作。所以从这个角度来说，好像应该是一个至少也应该上下层能够分的东西，大脑没有发生改变，小脑应该adaptive到你的肢体。 • 发言者 5 10:37 我感觉是这个样子。那我想总应该也是软体的这一部分的控制这方面的dynamics发生相应的变化，而不是把我的大脑也换了。这是我个人的观点。 • 发言者 2 10:56 好，谢谢王老师。 • 发言者 3 10:59 好，可以 • 发言者 6 11:00 针对刚才穆老师的刚才的问题的话呢，觉得就是可以回顾一下那个在非机器人领域就是人工智能领域的这个发展历程。通往这个agi还有很长的路要走，像我们做人工智能的时候，经常会从人的第一性原理出发，就是思考一下我们整个人这个大脑。它这么多的神经元，然后这么多连接，它这么低的功耗，这么高的效率，还有这样的memory的机制等等，它到底都是怎么实现的，我相信现在的这个大模型肯定还远远不能让人的大脑这样的这样一些能力。 • 发言者 6 11:53 所以说从那个人工智能角度来说，现在的大模型应该不是我们人工智能的这个终极的这样的一个大脑大模型他们大多数还是针对这个多模态大模型把它就是微调到这个机器人的这个任务上去，那我相信它应该也不会是一个最终的解决方案。然后像刚才赵浩老师讲的世界模型，有可能会更进一步，像the queen他也在多次的报告中提到了这个人脑的这个世界模型，那我它的话应该会比我们现在的这个基于多模态大模型泛化微调的大脑大模型，端到端大模型可能更接近。 • 发言者 6 12:39 这个人类这个水平的这样的一个面，向具身智能的大模型的这个形态，但是它也可能不是最终的形态，因为最终的话因为人脑还有这个叫或者是新完全新型的这个网络架构出来，现在确实还是很难预测的。然后刚才说机器人形态的话，可能就是我觉得一种的话肯定还是说从第一性原理出发嘛，因为我们现实中的这些桌子椅子都是对人而设计的，所以肯定会有一类机器人是那种人人的形态的机器人。可能是双足可能是轮式的，但是他也会有灵巧手。嗯嗯像今天我还看阿罗马斯克的那个那个采访说他们公司花了一半的精力做那个灵巧手， • 发言者 6 13:25 实现22有自由度灵巧手，就所以这些肯定还是会有人形的，这个机器人在很大的一个比例，但是特种机器人因为它不仅要像人还要超越人嘛。车厂，甚至这个微电子的这样的一个制造厂，他们有很多各种各样形态的机械手臂都已经实现了97%以上的这个自动化都是用机械臂在那边做工作那种，就是完全是特种的机器人，也是大量的存在于这个工业生产制造中的，所以我觉得可能就是人形机器人和特种机器人将来都会存在。嗯嗯对。我来讲两句，我这个 • 发言者 7 14:10 来发表一个暴论，给大家一点这个留下一点印象。Ok.我觉得这个很有意思，那个我刚才就想到我从我的产产业角度，从我个人比较关注的一个角度来讲，我先说一件事儿，就是现在军人智能融资很火的，是吧？然后比如说大家可能话其实10个亿没有那么10个亿的话，我是说比起整个市场的cap来说没有那么多，就大家为什么要投这个巨人智能这个赛道？是因为它被认为是手机和汽车之后的第3个万亿级的市场，那如果是一个万亿级市场如果，你投的比如说ok你赌这一家是以后5%10%，市场份额，那你投5000万算什么呢？ • 发言者 7 14:55 对不对？对吧？就挣了不知道多少倍，不知道多少倍。所以说现在之所以大家如果大家不了解产业的话，其实10个亿很少的，然后比起来首先10个亿比起自动驾驶或者是就很少，自动驾驶比起大模型又很少，大模型比起互联网又很少对吧？那互联网时代的话，我不知道大家有没有，如果跟我一个年纪的看，当年对吧？美团或者滴滴融资的时候对规模会大很多，对，其实所以说整体而言军事智能比起自动驾驶还很小，自动驾驶比起大模型还很小。大模型比起互联网还很小，所以说我并不说它就应该这么小，它但是它这么小是因为现在它还非常早。 • 发言者 7 15:40 非常早，所以说就是过几年因为弱的说一句，资本界基本上也认为过完这个年就是智能融资会开始冷一些冷一些，然后会进入一个低谷以后，第2波我预测它会和当年自动驾驶融资规模差不多，然后第3波会到大模型的规模，然后第4波会到互联网的规模，在这4波中它什么时候到来取决于技术突破，什么时候到来，这四未来的三波变革会带来三波形态，就是本体的形态和大模型的形态的改。变对，我觉得这个预测要终局是比较比较远的，就是10、10个亿人民币其实很少，我刚才说互联网很大，那互联网比起二级市场其实还是很小，就整个风投市场比起二级市场还是很小。 • 发言者 7 16:39 所以说真正要军事智能要改变产业的话，至少还有3~4波。然后这三波到4波的这个技术变革导致的产业变革会深刻的改变。那个大摩就具身大模型的硬件和整个云端的这个模型的形态。这个暂时是无法预测的，我觉得ok.Ok ok, • 发言者 2 17:10 这个赵老师分分析的非常的深入，然后呢紧接着就来到了赵老师熟悉的领域，就是这个事件模型，因为赵老师呢有一个非常经典的图，就是说这个从各个维度来评价这个世界模型。然后呢就是因为赵老师可能从这个computer vision的角度出发去讨论这个世界模型，包括比如说是否是需要重构出来，所有的pixel是否需要重构出来的这个3D,包括其实现在我们可可以在a clear上看到这个投稿已经有4four d的这个Word model了。 • 发言者 2 17:41 那另外一个部分呢就是说其实很多像我一样，就是博士一开始呢做强化学习的这个同学，我们的这个其实因为强化学习里面，有V1V2V3，他这个那么一般来讲他都要有一个action,也就是说我take了一个action之后呢，他将产生什么样变化，而不是说像sora一样，我就一个文字他就出一个什么样的变化，那这个action呢可能是离散的，其实目前我觉得Word model做的比较好，特别像你比如说李菲菲之前的一些工作， • 发言者 2 18:13 但是比如连续的就是比如像我们机器人说我这个joint state发生什么变化，那这个呢可能是志龙的这个研究领域，他有一个非常经典的一个代表工作，一以及呢就是说在训练这个世界模型的时候，如果说我们同时重构出了这个image也好，video也好，或者这个3D的match也好，或者说整个负D的flow也好，那么就是这些模态的这个生成和引入呢，从lstm开始训那个就是说其实有个4090能跑好几个实验，所以在这方面呢也是希望听一下这个两位的这个声音。 • 发言者 7 19:10 要不您先说对，我今天老师就是讲的报告也非常好，然后我是 • 发言者 8 19:16 刚博士入学，然后也是从一个初学者的入门的角度来跟大家讲一下我是怎么看，其实比较有意思的一点。我记得老师老师上说的是三个维度，第1个是要有3D要有空间，第2个应该是有物理规律还是呃应该是有物理规律，然后最后一个是可交互，其实在我们强化学习领域，我们可能是有点反过来看的。我们希望Word model的它的第1个要素就是可交互。比如说在Word model这个概念其实是强化学习，如果你往前回溯的话，大概在1990年91年，在我们的强化学习之父萨特的那本那篇叫dyna Q的文章中他就提出来了。 • 发言者 8 19:59 对于这个Word model或者model的概念，它其实的概念就是一个黑盒black box,然后输出是下一时刻的一个situation,就下一时刻的观测它是一个可交互的一个概念。然后紧接着呢可能到18年像Smith huber教授或者是图灵奖得主杨乐坤他们所定义的Word, model的时候，他们的Word model有两个组件，一个叫表征，一个叫转移表征，就是把视觉或者是一些类似的模态输入压缩到一个隐空间。 • 发言者 8 20:30 转移就是在这个隐空间下我有当前的观测，有当前的action,如果是机械臂的话，可能就是机械臂的那个无论是位姿控制还是关节控制的那些控制，object的一些改变的影响，对这可能是我们领域所强化学习领域所一开始所追求的Word model,它第1个要义就是可能是要可交互的，因为我们的最终目的还是要学一个策略，只有可交互它可能才能学策略。然后紧接着呢我们是希望强化学习，它有一个非常好的物理世界模型，有一个非常好的物理规律的体现，现在的这部分世界模型它在这方面的欠缺是非常明显的。 • 发言者 8 21:03 然后看到赵老师今天的工作，他的理解也是变好了很多，我们也很欣慰，因为我们也非常需要一个物理规律理解的非常好的世界模型来供我们做一个策略优化。然后最后可能是我们可以引入更多的比如说3D信息或者是其他模态的触觉，各种各样的感知信息来进一步的完善我们的世界模型，达到一个我们世界模型最终的一个形态，它可能就是我们一个客观世界的一物理规律的一个反应吧。然后这个可能是我们强化学习这边的理解，谢谢老师。Ok. • 发言者 7 21:50 行好，我也说实话我不知道怎么回答这个问题，首先我自己的学术观点我已经表达过了是吧？Ok就什么才是world models,然后这一块在计算机视觉领域基本上是共识，就是我们计算机视觉发展这么多年，就是为了重建这个物理世界动态的去重建它，然后这个东西当然和il领域中的这个呃这个对就state就state其实就是可能包含a和那个把a把Action也加进去和reward也加进去，ok也不谋而合吧，也不谋而合，对就是我觉得cv界追求的这个东西可以作为可以作为RL中的world models的一个工具吧，也可以被调用的工具。 • 发言者 7 22:34 但是因为我们发展这么多年一直在慢慢的发展，它现在肯定还是bready,首先肯定还是bready,然后因为三维计算机视觉整个圈子也比较深，整个技术栈也比较长，所以您很难去让做RL.同学在博士阶段博士生阶段就完全的去学习它，所以导致学术界大在RL领域，大家不会去太关注三维表征，太关注三维表征。Ok这是一个现状，这是一个现状，这是一个现状，就是我所以我总结一下，就是one models这个概念，在L和这个CV界可能大家关注点略不一样，一个更加端对端一点，一个更加解耦关注更加解耦的表征一点。 • 发言者 7 23:24 这个是一个现状，是由这个学术发展阶段导致的现状。比较深刻的学一个我自己最近也在思考的一个问题，就是我们到底需不需要inductive bias? Inductive bias这个在CV界大家经常讨论的就是你在学一个模型，你学得好的时候是不是需要inductive bias?对就是gpt的成功或者说imagenet的成功，其实是告诉大家不需要inductive bias.对，然后然后在cv发展的历史上这样说不太好，就朱松纯老师是这个引入了非常多的inductive bias和他的学派，对，但是很长时间内就特别的丢在那个时代，就就会被对那个比下去了比下去了。 • 发言者 7 24:11 但是就比如说unison, unison是最近这个我觉得非常有意思的工作，但是unison呢他就真的需要inductive bias,他非常需要就是我的第一性原理讲的也很明白是吧？就是你不把occupancy给生成出来以后，你很难就直接在视频上去consistency,所以我一直其实我就关于这个梦。问题，我一直梦想着我能写一篇paper叫data bias trade off,我一直梦想中能写这样一篇paper,就是我觉得在large scale machine learning中，如果数据到了一定的程度以后，它需要的indexBias会变少，但是数据少的时候你需要的index bias会更多，我觉得这是一个基本的第一性原理。 • 发言者 7 24:51 对我觉得用性这种东西在现在在new things上做，我们为了把它点刷高，那就是需要three d的inductive.Bias,但是在未来数据变得越来越多，工业界把它scaling scaling up以后可能大家就不需要了。更加端对端的方式会更好，所以在整个学术界一直是一个对一直是螺旋前进的状态，就比如说在90年代的时候是吧，90年代的时候，这个我们做recognition做understanding,朱书成老师这个非常复杂的index,inductive bias Android graph这些render field这些理论会很有用，但是后来唉imagenet来了对吧？ • 发言者 7 25:37 在Rock更新审核understanding的阶段，我们会发现不需要inductive bias, a large scale learning比较重要，但是它是现在我们又出现一些新的machine learning model,它非常难学，然后我们又进入了一个引入1~6814会很有用的阶段，很有用的阶段，然后可能过一阵子它又会变得不那么重要，所以我觉得如果有志于做学术的同学来讲的话，我觉得这个还挺有意思的，我们可以在历史上多梳理，对就world models. • 发言者 7 26:10 呃它到底需不需要这个three d inductive bias,我觉得我让我们拭目以待，我觉得整体而言还是由数据决定的。数据决定ok.要不我补充一点， • 发言者 8 26:24 我你先 • 发言者 7 26:26 王老师。抛砖引玉了。 • 发言者 5 26:30 我其实对我的model我因为我刚才做，我也是偏向于做强化学习的，所以我的model的角度跟强化学习也比较接近。但是在讨论这个问题的时候，我想我又想举个例子，假如说我们现在一个有一款游戏，它有一个主角它能够从这个楼上跳下去，并且在路上非常稳的落地，比如像刺客信条这样的主角，然后现在呢假如说我们去cosplay这个人，然后在物理世界里面也做了一个这样的动作，然后他从这个楼上跳下去一定就完了，对不对？所以这是一模假定这个人cosplay的非常漂亮，跟这个游戏game当中graphics渲染出来是一模一样的。 • 发言者 5 27:07 那么好那就意味这个世界模型现在的观测是一模一样的。他们一起有一个主角跑了过去，从这个窗口跳了下去，但他们会面临不同的结局。在游戏里面的那个很稳的落地了，然后在现实生活中那个就挂了，那是不是一个世界模型可以同时acquire两个这样的dynamics呢？我个人的观点是不太行的。因为这个问题本身是一个完全歧义的问题，因为他们要一模一样的输入，但是他们却要不同的输出。所以我觉得一个世界模就所以我觉得这个问题最后落到的是强化模型强化学习。 • 发言者 5 27:44 在谈论世界模型的时候，像以前我们玩atari game,我们玩my super mario这些游戏，我们从来没有追求过CAD representation.但是现在我们为什么要追求three d,刚好跟vision的Word model交叉在了一起，是因为我们要给机器人用，然后机器人是在physic世界Physics世界里面的一个robot,所以我们才刚好跟vision的这个Word model两者交叉在了一起。 • 发言者 5 28:17 那所以我谈这个东西的观点是什么东西是有可能构建成一个模型的，那我觉得Word model很有可能是做不到的。因为完全有可能是一个歧义的问题，但是policy有可能是做得到的，因为我们作为一个玩家，我们完全可以在游戏当中玩这个事情，但是呢我们也完全会在真实世界里面避免我们从楼上跳下去。那但是我们都是同一个玩家，都是同一个大脑同一个policy.所以我个人的观点是Word model到最后肯定不是一个它应该是很多，但是policy有可能是一个，因为我们人能够玩这样的事情，这这个是我的一个观点看待，这个也是纯粹个人的一个见解，看大家是什么。 • 发言者 5 29:05 什么是不是认可。 • 发言者 9 29:08 我来给讨论加点料，我来提点反对意见。让讨论激烈一点。首先我想说一下那个刚刚说的一个就是我们尝试用inductive bias来区分说强化学习的Word, model和CV里面的Word, model我们认为CV里面是不带inductive bias,所以它是更好的，但我觉得不一定就是是这么一个意思，我说的是带 • 发言者 7 29:36 微润里面是带一些three d的inductive bias.ok okanyway你先ok ok • 发言者 9 29:43 对。Okany anyway就是从我整体从那个Word more那为什么是那为什么您认为强化是不带吗？ • 发言者 7 29:55 就我可能看的不太多，比如dreamer这些paper可能是不带的吧，就是一个生成。就它没有three d的。就没有voxel,也更没有光照纹理材质这些东西。是吧？ • 发言者 9 30:10 ok是最后那我明白那个我自己的话就是我会更侧重于说我们我自己对于这个CV的这个Word model和我们强化讲的Word model的理解，我更倾向于强化我的Word model,它是一个有针对性的任务下的一个Word model,整体来说如果我们cv的Word model做的足够好，可以用于做强化，但是为了解强化的任务，是否需要像CV这样的一个Word model,我总觉得它是不必要的。因为我们从强化的目标来说， • 发言者 9 30:33 我们目标只有一个Word model,能让我们更好的学策略，那更好学策略实际上最最后只有一个目标，就是我能够在在这个用这个model model在用我的策略去做这个交互，我产生的那个不管是奖励或者说那可能说是一个latent state,一个role是就ok了，那它是不是一一定要有action呢？一定要有对所以可能我和志龙感觉我我们整体是这种观点，然后对然后我再浅的再加点料，就我和我关于那个王老师的刚才的观点， • 发言者 9 31:19 就是咱咱们刚刚举的那两个例子就是说，比如说那个我们说我们讨论说这个是不是需要有统一的模型，不需要有，因为那个不能有，因为那个我们的我我们整体需要解耦的，因为不然的话我们的不不同的物理结构，对应的模型就应该是不一样的。是吧？那但是我们是不是也可以考虑说不同的物理结构，它最后会有一个相同的统一的表征。就这样子的话是不是我们依然说它是一个统一的模型， • 发言者 5 32:07 但是对我觉得你就是说的这个你我大概也猜到你会这么说，你的这个点大概就是在我的model里面再加上一个condition, this is the game or this istrue. • 发言者 9 32:18 对，我刚才也想说。 • 发言者 5 32:20 这个还加上这个condition, • 发言者 9 32:21 我们说policy能够识别，那为什么Word • 发言者 5 32:24 model不能识别这个呢？就是那就所以最后变成的问题就是从工从这个复杂度的角度来说，我们原来可能是M个独立的世界模型。现在呢我们要把M个独立的世界模型装到一个非常那必然是非常高维的，对有一个controllable condition的世界模型，对，那我们那从我个人的感觉，从这个可实现的角度，似乎是M,个模型会更简单一点。对是的，而且我不知道现在有没有atari game,能够靠一个我的model去建模所有的atari game.似乎没有做这样的。 • 发言者 5 32:57 是的， • 发言者 9 32:59 而且理论上这个肯定选可能要无限长才能调整，这个卷呢？是对，其实我是同意您的观点，我只是说基基于您的例子找个反ok,但我们同样这个表达的话，是不是我们的policy也需要分成n个呢？ • 发言者 5 33:13 Policy我我的观点是这样子，policy,因为physics有其实在policy里面能够体现的，还有一种形式是一个更长的observation窗口。Ok一个更长的observation窗口，所以呢我觉得这个 • 发言者 9 33:29 它本质上也是一种condition. • 发言者 5 33:31 对它本质上是一种condition,但是它不需要我们显示的加进去，对，所以我觉得如果我们有一个通用的policy,我们能够get就像我们去玩一个游戏，只不过我们过去玩游戏这个时间长一点，我们可以get到这种 • 发言者 9 33:44 那如果按这个逻辑，我们是不是又可以套回到我的Molly,我们有一个历史的condition,嗯嗯历史的observation和是如果我们把我把家那所以 • 发言者 5 33:51 我说这是一个工程难度的问题，是你把它加了一个非常长的，到最后我觉得如果我们现在用一个model,用一个gpt model去regression,用我们的atari games,那大概率它应该是强记，最后应该是一个强记。我这是我个人的一些见解。 • 发言者 9 34:09 Ok ok • 发言者 2 34:10 好，果然这个问题如我所预想的一样，激发了这个大家的热情，讨论的非常的有inside,那我们就着刚才提了很多次强化学习，那么强化学习和模仿学习作为这个整个具身智能策略学习的两大主流的流派，其实就是曾经强化学习达到一个顶峰，然后呢但是其实强化学习SIM到real等等，它还是有落地上，大家其实进行了一些尝试，就是有一部分人说可能就是不太有work,然后呢另外一部分人就是说以拉阿罗这些为代表的这个他们收集了海量数据之后呢，串出来的模仿学习呢一定程度上展现出来了一些可落地的这个性质。 • 发言者 2 34:47 但是呢其实在这个Coral上派零团队他们也是说了他们在收集了上千个小时可能近万个小时的数据之后，他们也明显的看到了就是基于这个模仿学习的这个瓶颈依然是存在的，并不是说反正从他们的实验结果，这但这只是他们说就是这个scale之后呢，并不是说如大家所想的就那么的这个有这个性能提升，然后呢我们也对比一下就是语言模型，语言模型呢实际上最后还是有一个环节就是RLHF,那么他去调整，那么可能之前比较早期只做这个价值观的调整。后面呢就是随着这个o one的这个引入呢，就是大家会发现这个思维链包括一些mcts mcts对吧？ • 发言者 2 35:41 这个算法被大家广泛的熟知，就是alphago那一批做围棋的这个部分，那所以呢这个地方也就引出了我们今天的这个问题，就是大家觉得就是未来就是说我们真正走到落地，特别是这个嗯对产业的这个嘉宾，对这个我们整整整个这个就是最终的这个方案，肯定我理解呢就是il和il不一定说一定要割裂开谁优谁劣，但是会有一些方案对吧？就是比如说先模仿学习pre train,然后il再翻腾，或者il作为这个il的一个数据的收集的这个部分，比如说success了，那么我们作为专家数据进行补充进去。 • 发言者 2 36:34 那这个关于这个最终这种策略学习的最终路线呢，请这个业界的嘉宾然后做强化学习的。Ok我先 • 发言者 10 36:48 就是我从我个人见解来讲一下，就是我刚刚也提我们公司在做这个事情的时候，其实采用的是模型强化，然后加机理融合的方式去做。其实就是现在的阶段来讲，监督单独的单独的这个监督学习，包括强化学习都有自己的一个缺点。比如说我们监督学习在做具身智能任务的时候，它的这个动作空间是非常大的，然后我们通过强化通过监督学习方式去学的时候，其实监督学习的这个数据的分布其实是完远远不足以去做这样高维的。一些动作的。那在这个数据量相对欠缺的情况下，我们才去采用这样融合的方式去做。 • 发言者 10 37:16 然后另外一点呢强化学习没有去完成的，完全覆盖这个任务的点，也在于它其实强化学习是强依赖于一个比较好的仿真环境的。一个纯强化学习的一个这样的路线的话，其实也是不能做到很好的symptom的迁移的。所以刚刚王老师也有提就是我们会去做一些实物的强化学习，那你要去做这样一个实物强化学习的过程中，其实你要做的事情就是你要把强化学习的这个决策的规模以及它要做的任务的设定去限制的很好才行。如果直接去学到一个，比如说从上层的观测到最终电流的这样一个控制的， • 发言者 10 38:03 其实是依然是非常困难的，因为它里面会涉及到不同的频率的决策，然后以及不同的规模的一些分层。那如果能把强化学习的这个决策空间以及它的任务，比如说就是我们刚刚提的state action队去做到一个很好的限定的话，那我们其实可以在比如监督学习任务中已经做得很不错了。比如说我自己的强化pc的工作中有去考虑做任务的分层，我上层去让强化学习去做一些上层的决策层面，那他在一些选择或者是一些决策层面能是能做到比较好的性能之后， • 发言者 10 38:36 我用底层的一个执行去可能是基于传统方法，比如mpc或者是这种甚至是我们导航中常用的dwad, TB这样非常可能非常low的一些方法，他也能做到整个框架性上的一些性能的提升。所以我理解现在在现在这个阶段，比如说监督学习数据量有限，然后仿真环境不够好，然后这个传统模型都不还不够能泛化性比较好的这个前提下，我们去做一些这是我从我们实际部署过程中的一个经验来做的一个结论，就是但是也是比较偏我们可能偏工程一些，然后学术界可能会有一些不同的见解。 • 发言者 9 39:36 我先吗？我没有太多不同见解，我很同意你的观点，说实话我唯一不同的观点是你说的最后一句话，我不觉得收敛到最后可能强化能够或者模仿能够单独完成，这个我觉得比较好的解就是现在这种混合多种情况的方式。首先第1个点是你底层一个比如说我们的以前的pid就很很多场景已经传统的方法能够解好了，你就没必要从scratch再把这个部分重新替代一遍，这个是没有必要的。然后第2个呢我们说强化和模仿我，我们看历史发展的规律，除非你那个问题不够复杂，但是你看那些复杂问题最后都怎么解的，都是先模仿 • 发言者 10 40:17 后强化， • 发言者 9 40:19 就是你看那个比如说阿尔法star,再比如说gpt,很难，你就是强化，虽然看起来我们最后能够收敛到最优解，但是如果你from scratch的去跑一个强化，他最后需要的这个样本的复杂度，有时候也不是我们实际可接受的，这个时候如果如果我们人类能通过模仿带来一个好的鲜艳的信息何尝不用呢？我觉得他也没有坏处，也不会说因为你带了模仿就导致你强化做的不好，好像虽然有些学术界有些学术界的论文宣称先模仿再强化会不好，但是实际上我觉得一些工程手段能把它解应该是能把它解决的，所以我整体还是觉得说一个复杂任务应该先模仿再上强化，然后单独的模仿。 • 发言者 9 41:06 不行，因为我们都知道，就是你要做最后的那个expert behavior,比如说自动驾驶，这样你可以说模仿是最优解且模仿就够了。但如果说我们现在面临的这个场景，可能人类的那个行为也不一定是最优解的话，这个时候可能就需要再强化再做优化。比如说再或者说比如说语语言模型，我们除了追求它能够average我们的数据集，我们希望能够达到superhuman的这个Intelligence,那这个时候可能我们要上一些强化，让他到达博士的水平，超越博士的水平，那对然后单独对，所以说我觉得单独模仿要到到达专家是不行的，除非你的到达任务就是专家反过来说单独强化也是不行的，因为除非你那那个任务足够简单，那个这个强化风scratch可以训练，否则的话我觉得现在这个记录训练我觉得还是蛮practical的。 • 发言者 2 42:02 王老师在王老师这个回答之前，我补充一个关于王老师的问题，这个刚才王老师做报告我没来得及问，就是这个因为王老师介绍了就是有一个这个拔插的任务，然后就是就是也一直在这个随着这个应用，然后也一直在训练，但是在真机这就涉及到一个非常重要的问题，就是如果我们以RL作为最后一个环节的话，那么它涉及到一个真机的这个过程当中，一些复杂任务的这个reward如何获取，因为我们在仿真里面我们有上帝视角的一切，但是在真机上呢我们可能各种detection各种传感器都会有偏差。所以这个问题也是想请教一下王老师。 • 发言者 5 42:44 对，我觉得你刚才说到这个问题比较关键的地方，那为什么我刚才talk的时候特别从控制，然后先讲控制，再讲规划，再讲一起。这么一种讲法，其实是因为在控制领域呢，天然我们刚才一直在说everything you need is pid.那pid这个东西其实有一个非常重要的元素叫做反馈，因为它没有反馈它就做不了控制。那这也就意味着其实所有曾经pid能做的系统，它必然有一个反馈在里面。因为没有反馈就做不了嘛，所以它必然有一个反馈在里面。 • 发言者 5 43:17 那如果它必然有一个反馈，我就可以完全拿这个反馈作为我在后面执行过程中的一个reward.这是这样的一个原因，只是我过去可能用pid做这个问题做的效果不够好，那么现在呢我通过强化能够把这个效果做得更好。但是如果pid能做，它必然有反馈在里面，所以我强化必然走得成，这个是我是这样的一个观点。那其他人我觉得刚才您提的那个RL跟模仿学习的这个事情，前面其实两个你Q,我们三个都做强化学习的。3那必然结论是强化学习对吧？ • 发言者 5 43:53 所以我觉得这个问题你不妨我觉得个刚才做这个模仿学习的几位老师，可以更更好的回答一下这个问题吧。 • 发言者 2 44:13 静波和李欣来回答一下。我来是就是说一点， • 发言者 11 44:19 反正我们这边研究的一些感感受就不一定是不一定是结论，就是首先比如说像这种人形角色的控制，其实我觉得这两件事好像并没有一个很很大的一个冲突，比如说你想学一个人类的运动先验，有一种就是基于比如像deepmind mate make,这种就是基于强化学习优化的魔方学习。就我觉得这两件事儿好像并没有一个很本质的冲突。就是我只是想要一个运动的鲜艳而已，就是我只是为了ok我怎么样去比如说我的那个控制对象，比如说在我的数据里面我找不到， • 发言者 11 44:53 比如说我想比如说控制这个比如说做pd CTRL the p target是什么，或者是什么的力是什么，就是我没有这样的数据。我希望先获得这样的数据，然后somehow我去建模一个latent.我就可以就这个latent你可以你如果有这个现成的数据，那你就可以从Imitation learning就是说这种surprise learning角度去做，然后呢你如果没有，那你就可以比如说你可以先用deep每每个这种就低于2的东西先获取到，然后你也可以用BC的一些形式把它给做出来。 • 发言者 11 45:32 对然后你有了这样一个latent之后，你比如说你再去完成一些任务，我觉得就是说他可能就相当于一个偏离散空间的这么一个状态，就是ok那我就可以通过RL的形式很快的找到这个对应的latent去完成一个这样子一个任务。对。所以说在我的视角上来看，就是其实并没有什么所谓的L或者L之争，我只是想要那个状态而已。对，然后那具体他完成什么任务，ok你有你有数据。那你就可以用surface软件去做，你没有数据。比如说你像进入人类的数据，它想让它去做一些很复杂的运动，它没有这样子的。那你就完全可以用L的形式来去把它给做出来，对。 • 发言者 2 46:21 Ok好，那接下来来到我们的圆圆桌的这个最后一个问题，然后也是recalL1下我们这个主题scaling law,那这块呢就涉及到这个数数据的这个采集，然后呢薛寒博士还有杨老师，杨立新老师呢他们两个是在这个真机的这个数据上收集非常有经验，然后赵浩老师呢和我我们是这个用仿真来生成数据的这个流派，那我们两个流派也叫这个对抗一下，那先请杨老师分享，在杨老师这个回答之前，我也是请补充一个小问题，就是因为刚才这个没来得及问， • 发言者 2 47:02 因为我是主持人，也就是这个因为其实您那个oak link, vevr就是非常高质量，然后但是呢其实就是我理解一定会有一些比较好的经验，因为像比如open embodiment X呀joy的这些数据集，大家公认他们的这个数数据质量是比较导一下我们比如松陵他们后面会再采很多数据，那么怎么样就是说保证这个数据的高质量。 • 发言者 11 47:48 好谢谢。首先非常感谢你对ok的赞赏，然后我们从数据质量这一块面来说的话，首先您说的像open X这种，它其实融合了很多家不同的数据就是说它的那个相机视角是一个完全没有办法固定的。对它我每个相机可能放的位置不同，然后放的有些是放末端的，有些是放那个本体之外的。然后我们从采集数据这一块，尤其是在训模型，尤其是训2D模型这一块，我们发现视角其实是非常会影响这个模型policy的表现的。所以我们自己在采集的时候， • 发言者 11 48:22 首先视角这一块我们会控制的非常好，包括标定这一块，就我觉得一个系统搭起来，尤其是多模态的这种采集的话，标定非常重要很多时候就是以手眼标定来说，就这个事情感觉。已经是一个做机器人领域觉得应该解决的问题，但其实到现在也有人在发文章，然后也其实解决的不太好。像open ai，x这种数据集它其实是不关注物体的，就是它的它基本上捕捉出来的数据只有本体的信息。对本体的可能是末端或者是本体的关节的角度，或者关节的力矩等等的， • 发言者 11 48:55 它缺少了这样一个就是我理解世界的话，我肯定不只仅仅是只有这个本体本身还有物体的运动，所以我们orkin可从采集数据的角度出发呢，也就是说我们一定要把物体运动给记录下来，不管以什么样的方式，当时我们的设备有限，所以我们只能采集刚体和关节体。就这种物理变化的过程，我可能没法用一个mesh来表示，但我可能可以用一些更自由的方式表示。这也是我们在不断推的，就可能说随着技术的进步，我们的数据质量也会越来越高。 • 发言者 11 49:40 对，这是我们的两个心得。好，谢谢。那好，那 • 发言者 4 49:47 我想分享一下我这边在做一些相关工作的时候的一些体会吧。首先先说一下我自己的流派，我是我现在是all in这个reward采集这条路线的，对，但是呢reward采集具体用什么样的本体去采集，我觉得这是一个可能有待发展的问题。为什么这么说呢？就是因为我之前是做柔性体操作，做了很多比如说叠衣服呀，就是把一团揉成一团的衣服，然后把它给展平，然后把它叠好就是这种非常高难度的任务，也是派领他们在他们demo中展示的一个代表性的一个任务。 • 发言者 4 50:17 就其实你仔细发现生活中其实有很多这样的任务，比如说你去系鞋带，比如说你把你的衣服拉链给拉上，然现有的simulation呢，他如果真的想把它模拟很好呢，他其实需要一些非常先进的图形学的技术，比如说一些IPC等等之类的一些技术，但是呢这些技术他现在对算力的要求非常的高，然后后呢全世界能够做这些先进仿真技术的人其实非常少，比如说像ucla的蒋正凡夫老师，他就做过很多这种这种仿高性能仿真技术，我觉得就是如果有更多的人在这个仿就是真正准的物理仿真上投入资源的话，可能这些柔性体的问题才能解决，但是我觉得这可能目前来讲进展还是比较慢的，对。 • 发言者 4 51:13 然后我觉得对于现实的应用来说呢，就是如果我们在仿真技术没办法就是很好的模拟这些数据，那么其实reward去采集这些数据其实是一个更低成本的一个方案，相比那些仿真算法高性能仿真算法高昂的算力相比，其实reward是相对更加的低成本，你的现实生活中身边就每个人每家每户都有很多衣服有很多场景，对，所以说在这个阶段呢就其实reward数据呢它大自然就是一个最好的仿真器，对，然后这是一个我占这个reward的数据这个一个原因，对。 • 发言者 4 51:50 然后我觉得就是就是能够在人身上的某种可穿戴式设备。就是我觉得就像派林那样去搞一堆GDP小操作，我们现在收集的1万个小时，我们可能即使以现在这个大家能融到的资的情况，哪怕把这个东西再多个一两个数量级，我觉得已经很可怕了，对吧？就是花了这么多钱，我觉得可能即使这个量级依然不能够达到，就是大家想要的这个GDP gp two gpt two那个级别，然后离gpt3可能还还有很远，就光这样肯定也是不够的，对，所以我觉得真的想用scale up. • 发言者 4 52:36 需要就是我们日常这个设备本身可以有各种各样的形态，比如说我觉得一个终极的形态可能是脑机接口或者是机电之类的方式，就是能够真正的无感去采集数据，然后它是多模态的，它的触觉力觉视觉听觉这些信息都是内生的都有的，我我觉得这是一个终极的标形态。那如果在现阶段呢，我觉得通过某些可穿戴式设备，然后呢在人们在做这事情的过程中，然后去采集数据，我觉得这是一个比较能scale的方案，对，然后也有很多人会想到就是利用互联网视频的数据，但是其实我也其实专门的研究过这个事情，其实我发现就是人们在互联网上发的东西和机器人所需要的数据其实很不一样的。 • 发言者 4 53:23 我举一个例子，比如说互联网上你去搜叠衣服，这个是这个关键词你搜出来会发现有很多就是大家教你怎么去叠衣服这个事情，那你想我是不是只要把这些视频给学一下，然后我就学会叠衣服，其实并不是就是你会发现人类那些网上的视频，他叠衣服都是一个非常平的状态，然后教。你开始叠，但是机器人他见到的衣服状态可能是从洗衣机里拿出来揉成一团那个状态或者一堆衣服散在一起，但是没有人会专门拿手机拍视频教你怎么把这个衣服从洗衣机拿出来，不会拍视频，就是教你怎么把这衣服从混乱的状态把它展。 • 发言者 4 54:05 平人，这是就是人类从小就可能很小就会做的事情，没有人会把这些东西发到网上去。很常见很容易完成的事情，却是我们机器人最缺少的数据。对，所以我觉得就是我们必须要补上这一个环节，所以想要就是在初始阶段拿到一个比较好的一个仿的是毛豆的话，我觉得就是要让很多的人就我们可能不能就是专门的只是让我们这些学者或者一些公司我们去雇人去一波一波踩数据，也许这样也是远远不够的，就我们需要一种方式能够比如说像大家就是像玩手机一样，我们日常生活中的一部分就可以顺便有采集到数据。 • 发言者 4 54:48 然后这些数据真的汇总到一起，我们可能才能获得一个真正的对。这是我的一些想法，对。 • 发言者 2 54:57 感谢那赵那那个是这样，这个正好是是不是刚才这个谈的这个对互联网数据的这个问题我是高度赞同，然后我本人呢非深受这个ego four d这个数据的毒害，这个数据集我在做我自己的paper的时候，洗这个数据集洗了三个月三个月，导致我的领导一直认为我你这三个月什么产出没有。然后甚至我展示不出来一个learning rate,就是learning occur我就一直在洗，然后呢就确实是有很多大量的是跟我们训练一个有效的这个policy无关的数据，所以呢其实在大家列的这个数据金字塔里面，这个互联网数据也是在最底层的，它的质量可能也是比较低的。 • 发言者 2 55:39 然后再往上呢就是这个当然上往上一层可能是仿真生成的数据，那仿真生成的数据可能分几种吧，一种就是这种传统的仿真的数据，比如说我们周扣这些，比如说我们可以强化去训一个policy,这个policy给他任意的一个初始的状态，让他去收集一个数据。那这些数据呢就是其实可能就是到real的这个概括比较大。然后当然我们目前做的一些工作呢，就是能够希望就是说其实就是两两块嘛，一个就是说如果我们SIM呢能够逐渐的逼近real, • 发言者 2 56:11 那么就那么确实是可以弥补这个GAP.那另外一点就是当然这个大家可以立即站出来，有很多个例子来反反对我刚才这个话包括这个比如柔性物体现在仿真解决的非常差，但是这个问题呢是这样，就是其实并不是解决不了，只是说一个是算的可能他需要这个graphics的人，他们其实可以做到那种烟雾的这个模拟，但是他们认为我们做机器人这些衣服的这个布料什么的这些模拟呢，海绵的模拟他们认为就是在他们那个这个顶会上发出来paper, • 发言者 2 57:01 所以他们看不上我们这个research,然后我们这边呢完全不懂那个这这些计算，所以可能这个我理解这在这一块可能未来会有一个这个发展。然后我在这留一个小引子给赵浩老师，就是这个因为赵浩老师也在光轮智能做专门做这个仿真的手机科学家，当然其实现在像这个isaac SIM,就是isaac lab,他们整个这个系列呢开放了一些就是支持柔性物体仿真的这个接口，当然目可能是目前最好用的了，就是要比其他仿真架构更好一些。 • 发言者 2 57:23 那我的问题就是说我们未来比如中国的强依赖英伟达的这个生态吗？还是说我们可以有一些国产的这个产品出来能够支持我们这个仿真。然后另外一个部分就是说仿真数据呢和真实数据并不一定是相斥的，就是因为因为像我们这个实验结果就是说当然你用robotain去生成数据，就是你用你生成300条数据，然后你训完一个策略直接去real world的测，就是只要它变一点，就基本上就是成功率还是很低。但是呢这300条SIM的数据加上那么20条或者就是少量的这种真机数据， • 发言者 2 58:15 你会发现它那个成功率有一个很显著的提升，而且我们用的这个fenton的方法是非常原始的，还是pretrain一个model,然后用那个真机的数据很快的。的翻翻翻的几次，因为这个做真机实验，这个我我们其实做真机实验的同学都坐在后面，这个熬了好多个通宵，这个确实是就是多少个任务，你看我们这个他们松龄都跟我说说要照顾一下实习生的这个身体健康，所以呢就是当然所以说就是说踩大量的真题数据，它确实是有很大的这个effort. • 发言者 2 58:56 然后呢比如说可穿戴式设备这种收集确实是一个非常好的方案，然后但是其实可能它的这个精度上呢相比遥操数据呢就是cover这个GAP,就是最终才能走向一个比较好。所以我觉得仿真数据能帮上忙的一点就是说我们可以有海对一个任务，我们可以有海量的simulation的数，据这些simulation的数据包含了物体的随机的位置，随机的orientation任意的初始状态，以及呢我们可能收集几十条这个真机数据，我们配在一起，它可以训练出来一个比较好的一个policy.那我就分享了 • 发言者 7 59:51 唉好，那这个我再说点我的想法第一就是我觉得还是case8case嘛要不要用用真实数据还是用仿真数据，肯定还是看成本嘛是吧？还是看成本，对，我觉得成本的话还是要case by case的去看，那么最大的一个分类就是自动驾驶还是具身对吧？我觉得现在主要还是局限在室内的服务机器人这个狭义的具身上的话，那确实真机数据收集起来还是有一些可行性的，但是在自动驾驶中确实还是不一样的，因为你车上车会非常麻烦，然后你真的corner case你要让人去对吧？ • 发言者 7 01:00:31 去鬼探头在车下这个就太危险了，对，所以还是看成本，我觉得就是是真实数据还是仿真数据还是要抗成本这块。另一块的话就是case by case讨论，另一块的话我们在说仿真数据和真实数据的时候，现在说的都是有标注数据，我觉得还是加入第3个domain,就是无标注的真实数据，我觉得无标数的真实数据比毕竟这个segment anything是吧？这个东西拿了best paper嘛是吧？这也是我们CV界最近最大的一个进展，所以我觉得之前大家一直经常讨论的是这个到底是百分之多少的真实数据和百分之多少。的仿真数据是吧？ • 发言者 7 01:01:14 有人说1:9，有人说2:8，有人说5:5什么这种这种观点都有，我觉得20的这个2025年了，马上2025年了，大家不要讨论这个已经讨论这么多年的问题了，我觉得2025年我们要迈向在既用真实的和仿真的有标注数据的同时，在自动驾驶和军人智能领域推广到大规模的利用无标注数据，就像segment anything和depth anything这样，我觉得这个会成为2025年的主题。至少是我至少是我的主题，对。Ok. • 发言者 2 01:01:53 还还有我那个留的影子这个国国产的仿真系统， • 发言者 7 01:01:57 国产仿真系统，国产仿真系统这个产业问题就更复杂了，产业问题的话，比如说有一个朋友叫那个宋应对吧？宋应他们大家可能也都认识，他们也在圈子里也挺social的，他们他们赌的就是以后会被卡脖子嘛是吧？所以他们在做这个国产替代，我觉得这个生意business by business当然是很好的。然后具体而言的话，具体而言的话是有人在做这个生意，exactly,然后暂时工作人员不会去直接touch这个声音，对哈哈。 • 发言者 7 01:02:35 Exactly,然后被标准化以后，应该也对应该也没有什么大问题，最后技术上会是比较统一的，但是business上会是一个很加复杂的问题，因为他们赌的就是会脱钩会卡脖子嘛是吧？这就是另一个问题了。Ok好，我就大概简单说这么多。 • 发言者 2 01:03:04 好感，那感谢各位老师还有各位同学的这个精彩发言。然后看大家还有要补充的。要发言的吗？那那个没有的话，那感谢各位老师，然后那个那我们这次的那个圆桌论坛就结束了，也感谢各位听众来等一下。那各位老师我们合张影就是那个那感谢各位听众来。参加我们这个会议，相信今天这个我觉得今天整个从报告到这个圆桌论坛的质量，还是能匹配得上一个顶会的这个workshop的质量的，然后也希望大家能都值回票赞。 | D6: # 研讨背景与议题 本次研讨聚焦具身智能与大模型融合的技术路径探索，参与人员涵盖多模态大模型、强化学习、柔性物体操作、仿真数据生成及产业应用等领域的专家与博士生。核心议题包括：端到端模型与固定模块的结合方式、具身智能硬件形态的未来趋势（人形机器人 vs 特种机器人）、世界模型是否需要三维归纳偏置（inductive bias）的争议、强化学习与模仿学习的协同策略，以及仿真数据与真实数据的采集成本与质量平衡问题。 # 核心观点 **1. 端到端模型与固定模块的结合** - **观点A**：发言者2提出，当前国际上以PaLM、Aloha等为代表的端到端模型已展现落地潜力，但需解决数据规模与硬件可靠性问题。例如，清华团队耗资300万收集数千条数据，PaLM则使用数千小时数据训练。 - **观点B**：发言者5认为，若采用固定模块（如PID控制）作为底层反馈机制，可为强化学习提供基础reward信号，从而降低训练复杂度。例如，控制领域天然依赖反馈，仿真数据可直接复用这一特性。 **2. 具身智能硬件形态的争议** - **人形机器人派**：发言者6指出，现实环境（如桌椅设计）为人服务，人形机器人（双足或轮式+灵巧手）将成为主流。阿罗马斯克公司已投入50%资源研发22自由度灵巧手。 - **特种机器人派**：发言者6补充，工业场景中97%的自动化依赖非人形机械臂，特种机器人需超越人类形态以适应极端环境。 **3. 世界模型与三维归纳偏置的分歧** - **强化学习视角**：发言者8强调，世界模型需具备可交互性（如Dyna Q的黑盒模型），并优先关注物理规律的建模。例如，李菲菲团队的工作在离散动作空间中表现较好。 - **计算机视觉视角**：发言者7认为，CV领域追求端到端的三维重建（如4D世界模型），但受限于学术发展阶段，博士生难以全面掌握三维表征技术。 - **争议点**：发言者9反驳，认为强化学习任务下三维表征并非必需，仅需状态-动作映射的隐空间即可。 **4. 强化学习与模仿学习的协同策略** - **混合方案**：发言者10提出，当前阶段需融合监督学习、强化学习与传统方法（如MPC）。例如，上层决策用强化学习优化，底层执行用PID控制。 - **分歧双方**： - **发言者9**主张“先模仿后强化”，认为复杂任务需模仿提供先验，但需保留强化优化空间（如自动驾驶需超越人类行为）。 - **发言者11**认为两者并无本质冲突，核心在于获取有效状态表征，可通过行为克隆（BC）或强化学习灵活组合。 **5. 数据采集的仿真与真实数据之争** - **仿真数据优势**：发言者2提到，仿真数据可覆盖随机初始状态（如物体位置、朝向），与少量真实数据结合后成功率显著提升。例如，300条仿真数据+20条真实数据可优化策略。 - **真实数据痛点**：发言者4指出，柔性物体操作（如叠衣服）依赖高性能仿真技术（如IPC），但算力成本高昂。当前更倾向通过可穿戴设备低成本采集真实数据，例如脑机接口或触觉-视觉多模态记录。 - **无标注数据趋势**：发言者7预测，2025年将转向大规模利用无标注真实数据（如Segment Anything的范式），而非纠结标注数据比例。 # 达成共识与解决方案 **1. 软硬件协同优化是具身智能发展的必然方向**：发言者2与发言者4均认可，如Aloha硬件迭代推动算法进步，柔顺夹爪设计提升数据可靠性。 **2. 仿真与真实数据需互补而非对立**：发言者2与发言者4同意，仿真数据可覆盖长尾场景，而真实数据需通过可穿戴设备规模化采集，尤其针对柔性物体操作的缺失环节。 **3. 混合策略是当前落地的可行路径**：发言者9、10、11均支持结合模仿学习与强化学习，例如用BC获取状态表征后，再通过RL优化策略。 # 未决分歧与后续探索 **1. 世界模型是否需要三维归纳偏置**：CV与RL领域对三维表征的必要性存在分歧，需进一步验证大规模数据下端到端模型的性能极限。 **2. 人形机器人与特种机器人的占比预测**：发言者6虽提出两类机器人并存，但具体比例及应用场景需产业数据支撑。 **3. 国产仿真系统的替代可行性**：发言者7提及国产仿真生态面临技术与商业挑战，需宋应团队等产业力量推进标准化与脱钩风险应对。 **4. 强化学习的真机reward获取难题**：发言者2提出真机传感器偏差影响reward设计，发言者5建议依赖底层反馈机制，但具体实现路径待明确。 | E6: 4 | F6: 4 | G6: 4.5 | J6: 1.4：具身智能硬件形态的争议部分对于发言者的观点理解错误 2.2比例失调，发言人2只是提出观点的人，而不是一个发表观点的人 3.1部分标点错误 | K6: 会议背景 围绕具身智能与大模型融合发展的核心议题，多位高校学者与产业界专家就未来5-10年巨神智能系统的形态、策略学习路线、数据采集范式等关键方向展开深度研讨。讨论聚焦于大脑/小脑架构是否收敛、强化学习与模仿学习的融合路径、真实数据与仿真数据的协同机制三大主线，形成多组技术判断与产业预判。 未来巨神智能系统架构：大脑与小脑的解耦与协同 系统形态争议 发言人3（王老师）：提出“大脑不变、小脑可变”的类比观点——如同人类大脑可控制不同身体形态（如假肢），智能系统应保持高层知识稳定，底层控制模型需适配具体硬件。 发言人4（郭磊老师）：认为当前大脑大模型+微调至机器人任务的模式非最终解，世界模型可能更接近人类水平，但受限于ANN架构，未来或被SNN等新型网络替代。 发言人7：质疑单一统一世界模型的可行性，指出不同物理环境（如游戏vs现实）存在动力学歧义，难以用同一模型建模。 架构演化趋势 软硬件协同进化被广泛认可 发言人1（主持人）：以松灵机器人两代产品为例，指出夹爪加入凝胶反馈后显著提升抓取稳定性，体现硬件改进反哺算法性能。 发言人2：强调高可靠性硬件是实机训练前提，现有工业机械臂在寿命与稳定性上更具优势。 端到端模型的局限性 发言人3：担忧纯端到端模型会抑制硬件创新——若模型与特定硬件强绑定，新形态（如软体机器人）将无法接入。 发言人1：引用PaLM-SayCan案例，指出6000+小时数据训练出的端到端模型虽有效，但仍依赖高质量数据供给。 策略学习路线：强化学习与模仿学习的融合路径 主流技术路线分歧 监督学习瓶颈 发言人8：指出监督学习在高维动作空间下数据分布不足，难以覆盖全部任务场景。 纯强化学习落地困难 发言人8：强调强化学习依赖高质量仿真环境，现有Isaac Gym等平台在力反馈、柔性物体模拟上仍不完善。 发言人3：提出真机Reward获取方案——复用PID控制系统中的反馈信号作为强化学习奖励函数来源。 融合成为共识 先模仿后强化为优选路径 发言人7：主张复杂任务应“先模仿再强化”，模仿提供初始策略，强化实现超越人类水平的优化（如语言模型从拟人到超人）。 发言人8：建议分层决策框架——上层用强化学习做任务规划，底层用传统方法（如MC、DWA）执行控制。 混合架构必要性 发言人7：认为除非任务极简单，否则单一方法无法胜任；传统方法（如PID）已解决的问题无需从头学习。 发言人9（薛涵博士）：指出模仿与强化本质目标一致——获取有效状态表征，二者无本质冲突，可灵活组合使用。 数据采集范式：真实数据、仿真数据与无标注数据的协同 真实数据采集挑战与创新 现有数据集缺陷 发言人9：批评Open X数据集视角不统一、缺乏物体运动信息，影响2D模型性能。 发言人2：指出互联网视频数据（如叠衣教程）多为理想化场景，缺少机器人所需的混乱初始状态数据。 高质量采集实践 发言人9：Allink数据集通过固定相机视角、精确标定、记录物体运动提升质量，并探索4D高动态捕捉柔性体变化。 规模化采集设想 发言人2：提出终极方案为无感可穿戴设备或脑机接口，实现日常行为中自然采集多模态数据。 仿真数据的价值与局限 仿真瓶颈 发言人1：指出图形学领域对布料、海绵等机器人所需仿真看不上，导致进展缓慢。 发言人2：高性能物理仿真（如IPC技术）算力要求极高，全球掌握者极少。 仿真与真实协同策略 发言人1：提出“海量仿真+少量真机”微调范式，300条仿真数据加20条真机数据即可显著提升成功率。 发言人5：呼吁2025年重点转向大规模利用无标注真实数据（如Segment Anything启发），打破有标注数据依赖。 国产仿真生态展望 发言人5：承认英伟达USD标准可能促成技术统一，但商业层面存在脱钩与卡脖子风险，宋颖等团队正布局国产替代。 关键决策与共识 架构方向：未来巨神智能系统更可能采用大脑与小脑解耦架构，支持硬件迭代与算法独立演进。 学习范式：“先模仿后强化”+分层决策是当前最可行的策略学习路径，传统控制方法应作为底层执行模块保留。 数据战略：必须构建“高质量真机数据+高保真仿真+大规模无标注数据” 三位一体的数据体系，推动scaling law持续生效。 全局行动项汇总 AI洞察 当前争论的本质是“通用性”与“专用性”的权衡：统一模型追求通用但面临工程不可行，分治架构牺牲部分集成度换取可实现性。 数据将成为下一个战略制高点——高质量标注数据的竞争正在演变为多模态、无标注、持续采集的能力竞赛。 “小脑可变”隐喻揭示了具身智能的核心矛盾：智能体既要适应无限多样的物理世界，又要保持认知的一致性与连续性。 章节 00:00:12 多模态大模型与具身智能融合方向介绍 会议开场由主持人介绍本次讨论的核心方向——多模态大模型与具身智能的融合，并引出四位博士生及其研究背景：熊辉专注于强化学习，薛涵在数据收集与柔性物体操作方面有深入研究，志龙聚焦于巨身模型与世界模型。主持人提出对未来五到十年巨身大模型形态的开放性问题，包括是否仍会存在大脑与小脑的区分、是否趋向端到端统一模型等，开启后续讨论。 00:03:09 硬件设计对智能系统演进的影响探讨 讨论转向硬件层面，发言人指出机器人系统的寿命与可靠性是实际应用中的关键挑战。当前工业机械臂虽具备一定稳定性，但在复杂任务中仍面临预测不准和控制不可靠的问题。随后强调软硬件协同优化的重要性，以松林产品的迭代为例，说明夹爪结构（如凝胶材料）改进带来的感知与操作能力提升，体现了硬件进步推动算法发展的正向循环。 00:04:57 数据驱动的大模型训练与阿罗哈平台的作用 发言人分析当前大模型训练依赖大规模真实数据的趋势，提及阿罗哈（Aloha）平台为机器人领域提供了高效的数据采集手段，激发了清华、苏航团队等大量数据收集工作。派灵等机构通过数千小时数据训练出高性能端到端模型，显著提升了算法表现。硬件升级进一步促进算法迭代，形成‘硬件-数据-算法’的正反馈机制。 00:06:11 世界模型的收敛性与模块化架构思辨 围绕世界模型最终是否会收敛为单一整体模型展开深入讨论。有观点认为，若模型完全通联底层硬件，则将限制硬件创新空间；类比人类大脑即使肢体缺失仍可正常运作，暗示控制模型应与身体解耦。因此更倾向于“知识上层稳定、下层适配肢体”的分层结构，尤其在面对软体机器人等新型形态时，小脑部分需具备可扩展性。 00:07:36 人工智能发展路径与机器人形态展望 从AI发展历程出发，反思当前大模型并非终极形态。尽管多模态大模型经微调可用于机器人任务，但其效率与功耗远不及人脑。世界模型可能更接近人类智能机制，但仍非终点，未来或出现脉冲神经网络（SNN）等全新架构。关于机器人形态，人形机器人因适应人类环境而占重要地位，但特种机器人已在工业制造中广泛应用并实现高度自动化。 00:09:57 产业视角下的技术演进与市场周期判断 从产业发展规律切入，提出机器人被视为继手机与汽车后的第三级市场。然而当前仍处于早期阶段，类比互联网发展需经历多轮高峰与低谷。技术变革将引发深刻产业重塑，预计未来还将有三至四波重大起伏。当前大模型热潮只是第一波，后续仍将回归基础技术创新，形成螺旋上升的发展态势。 00:11:48 世界模型的技术维度与强化学习交叉 聚焦世界模型的具体构建维度，涵盖是否需重建像素、3D结构及物理规律建模。从强化学习视角看，世界模型的核心在于可交互性——输入动作与观测，输出下一状态。典型框架包含表征与转移两部分，在隐空间内完成状态演化预测。当前进展在物理规律理解上有提升，但仍不足，需融合3D、触觉等多模态信息以逼近真实世界动态。 00:15:30 世界模型的歧义性与策略统一性之争 通过‘游戏角色跳楼成功 vs 真人跳楼失败’的对比案例，指出相同观测输入却导致不同结果，暴露世界模型在跨物理规则场景下的歧义问题。由此推论：单一世界模型难以兼容多种动力学机制，而策略则可通过上下文识别情境（如‘这是游戏’），在同一policy下做出合理决策。因此，未来更可能是多个世界模型配合一个通用策略。 00:25:00 模仿学习与强化学习的融合路线探讨 深入讨论策略学习两大流派——模仿学习（IL）与强化学习（RL）的优劣与融合可能性。当前趋势显示纯模仿存在瓶颈，纯强化样本效率低且依赖仿真环境。实践中采用监督学习+强化学习+传统方法的混合模式更具落地性。复杂任务宜先模仿获得初始策略，再通过强化优化至超人类水平，形成‘模仿起步、强化精进’的主流路径。 00:32:45 真实数据采集挑战与未来规模化方案 聚焦数据采集难题，对比仿真与真实数据的利弊。仿真难以准确模拟柔性物体且算力成本高，而真机数据质量更高但获取困难。Open-X等开源数据集存在视角不统一、缺乏物体状态标注等问题。高质量数据需严格标定与完整环境记录。未来规模化依赖可穿戴设备或脑机接口实现无感、多模态数据采集，弥补互联网视频中缺失的日常操作数据。 行动项 负责人 时间节点 探索可穿戴设备用于无感数据采集的原型设计 发言人2 待定 推进Allink数据集增加4D动态捕捉与柔性体标注 发言人9 待定 研究基于PID反馈构建真机强化学习Reward机制的通用接口 发言人3 待定 评估国产仿真平台在柔性物体模拟上的可行性与替代路径 发言人5 待定 | Q6: 示例：1.1：xxx内容在原文中未提及；3.2：xxx标题无法概括段落内容；xx内容在xx段落中重复出现2次 | R6: 总结 讨论背景与参与人员 讨论主题围绕多模态大模型与具身智能的融合展开。 参与人员包括：Speaker 1（主持人），以及在强化学习（熊辉）、数据（薛涵博士）、世界模型（志龙）等领域有专长的博士生和老师。 具身大模型未来形态探讨 核心问题：未来5~10年，具身大模型会是大脑和小脑分离的形态，还是纯端到端的形态？ 国际相关工作：以派林（PerAct）为代表，收集了6000多个小时数据，训练出有效的端到端模型。 世界模型的不同视角与要素 强化学习领域视角： 可交互性：世界模型的核心要素，输入为观测和动作，输出为下一时刻的观测，服务于策略学习。Sutton在1990/91年的DeepAQ文章中已提出相关概念。 物理规律：当前世界模型在物理规律理解方面欠缺，需要如赵老师工作中展示的能更好理解物理规律的世界模型来优化策略。 多模态信息：可引入3D信息及其他感知信息完善世界模型，最终目标是反应客观世界的物理规律。 计算机视觉（CV）视角：赵老师的4D world model，从CV角度出发。 世界模型的统一性与多样性： 观点一（志龙）：世界模型可能不是单一的，而是多个。例如，游戏世界和现实世界的物理规则不同，需要不同的世界模型，但策略可能是一个，通过长历史窗口等方式体现物理差异。 观点二（反驳）：可以考虑不同物理结构下有统一的标准，或在世界模型中加入条件（如“This is a game or this is a real world”）来实现统一模型。 策略学习：强化学习与模仿学习的融合 强化学习的挑战： 动作空间大，监督学习数据分布不足以覆盖高维动作。 强依赖良好的仿真环境，现有环境在力反馈、柔性物体操作等方面不足。 直接学习从上层观测到最终电流控制困难，涉及不同频率决策和分层。 模仿学习的现状：以派林为代表的团队收集上千甚至近万个小时数据后，发现基于模仿学习仍存在问题。 融合方案： 工程实践路线：模型强化+激励模合，结合监督学习、强化学习和传统方法。例如，上层决策用强化学习，底层执行用传统方法（如PID、RPC、DW、ET）。 先模仿后强化：复杂问题倾向于先通过模仿学习获取良好先验信息，再用强化学习优化，以达到超人类智能。除非任务简单且专家数据足够，否则单独模仿难以达到最优。 数据采集与Scaling Love 数据质量与标定： 视角对模型policy表现影响大，多模态采集中标定至关重要。 需记录物体运动，不仅是机器人本体信息，还包括物体信息。随技术进步，数据采集应涵盖刚体、关节体、变形物体、柔性体等。 仿真数据与真实数据： 仿真的局限：如叠衣服等任务，现有仿真技术（如IPC）对算力要求高，掌握先进仿真技术的人少，进展慢。 真实数据（in vivo）的优势：成本相对较低，可在现实生活中采集。但互联网视频数据与机器人需求不匹配，缺少机器人所需的从混乱状态到有序状态的过程数据。 数据采集的未来方向： 终极形态：可能是脑机接口或机电等方式，实现多模态（触觉、力觉、视觉、听觉）信息的内身化。 现阶段方案：通过可穿戴设备在人们日常活动中采集数据，或雇人采集，但规模可能不足。需探索让数据采集成为日常生活一部分的方式。 数据混合策略：结合仿真数据和真实数据，如用300条仿真数据加上20条真实数据可带来显著提升，具体比例需case by case（如室内服务机器人与自动驾驶场景不同）。 后续安排 撰写一篇名为《Data Bias Tradeoff》的论文，探讨大规模机器学习中数据量与归纳偏置（inductive bias）的关系。 探索在世界模型中加入条件（如环境类型）以实现统一模型的可能性。 研究如何将强化学习的决策空间和任务设定进行良好限定，以更好地与监督学习和传统方法融合落地。 开发更先进的物理仿真技术，降低对算力的要求，吸引更多人投入研发。 设计并推广可穿戴设备，实现日常活动中的数据采集，以解决数据规模和质量问题。 针对不同应用场景（如室内服务机器人、自动驾驶），研究仿真数据与真实数据的最优混合比例。 深入研究互联网视频数据与机器人需求的差异，探索从互联网视频中提取有效机器人训练数据的方法。 内容由 AI ⽣成，仅供参考 | X6: 示例：1.1：xxx内容在原文中未提及；3.2：xxx标题无法概括段落内容；xx内容在xx段落中重复出现2次
A7: 6 | B7: 潘奕利 | C7: • 发言者 1 00:10 现在 • 发言者 2 00:10 公布法庭纪律在合议庭评判请诉讼各方参与人全体航行人员起立。你是对法庭的尊重。二诉讼各方参与人与全体旁听人服从法庭的指挥，尊重执法礼仪。遵守法庭纪律，不得实施下列一鼓掌喧哗。二吸烟禁食。三拨打或接听电话。四对庭审活动进行录音录像拍照或使用移动通信工具的传播途径活动。五其他危害。秩序的成为。三注重参与人发言或提问。应当经达成许可。是旁听人员不得进入审判活动区，不得随意站立走动，不得发言评论和记录。五在执行过程中，诉讼参与人或者旁听人员扰乱法庭秩序，情节较轻的，审判长可以口头警告制止训诫等。 • 发言者 2 01:15 不听制止的，可以指令法警情节严重的告诉院长批准后可以对行为人处以罚款或者拘留。6诉讼参与人或者旁听人员未经许可录音录像摄影或者通过邮件微信转型，方式，传播庭审情况的法庭。录像和摄影器材，责令相关人员删除。有关内容。拒不擅自的，法庭可以采取必要手段强制删除。严重的犯法 • 发言者 1 01:48 秩序构成犯罪的， • 发言者 2 01:49 依法可以60、7，本案庭审中请诉讼各方参与人与全体旁听人员自觉遵守司法礼仪及法庭纪律。全体起立。请审判长。请坐下。本案各方当事人均已到庭，法庭准备工作就绪，可以开庭，报告完毕。 • 发言者 3 02:37 现在开庭。上诉人国家开发银行应与被上诉人云南东源电力股份有限公司云南东源曲靖电力有限公司，招引金融租赁有限公司金融借款合同纠纷一案。不服。云南省高级人民法院2018云民初88号民事判决。向本院提起上诉。根据中华人民共和国民事诉讼法第134条，第1款第169条的规定，本院依法组成合议庭。对本案公开开庭审理。现在核对各方当事人出庭人员身份，请上诉人国开行陈述出庭人员身份和诉讼代理权限。谢谢审判长， • 发言者 4 04:00 上诉人国家开发银行的委托代理人是两位，一位是邓劲松，一位是刘双俊，两位均是北京德恒昆明律师事务所律师，代理权限为特别授权代理，谢谢。 • 发言者 3 04:15 请被上诉人东源煤电陈述出庭人员身份和诉讼代理权限。被上诉人代理人是吴学成，蝗虫镇 • 发言者 5 04:31 云南勤业律师事务所律师，代理权限为特别授权代理。陈述完毕。 • 发言者 3 04:41 请被上诉人东源煤业陈述出庭人员身份和诉讼代理权限。东源煤业集团的 • 发言者 6 04:51 代理人是云南东源煤业集团有限公司员工李新海，代理权限特别特别授权代理。 • 发言者 5 05:00 东源煤业还有另外一个授权代理人是吴学成。云南秦业律师事务所律师，补充完毕。 • 发言者 3 05:12 请被上诉人东源曲靖电力陈述出庭人员身份和诉讼代理权限。 • 发言者 5 05:22 东源曲靖电力公司的出庭人员和东源煤电股份有限公司的出庭人员一致，陈述完毕。 • 发言者 3 05:32 请被上诉人招银租赁陈述出庭人员身份和诉讼代理权限。 • 发言者 7 05:41 招银租赁代理人两位，一位是万海龙招银租赁的员工，另外一位是陈志超律师，上海盈泰律师事务所，两位的代理权限都是代理，回答完毕。 • 发言者 3 05:53 各方当事人对于其他方今天出庭人员的身份有无异议？ • 发言者 4 06:02 上诉人国家开发银行没有异议， • 发言者 5 06:05 东源公司方面没有异议， • 发言者 6 06:08 东源没异议，公司没有异议。 • 发言者 7 06:13 招银租赁没有异议。 • 发言者 3 06:44 经本田核对，各方当事人出庭人员的身份均符合法律规定，可以参加今天的庭审活动。鉴于东源煤电东源煤业曲靖电力都委托有共同的诉讼代理人，三方是否在以下的诉讼程序中合并发表意见。 • 发言者 5 07:09 合并发表意见。 • 发言者 6 07:20 嗯 • 发言者 3 07:22 既可以共同发表意见，特殊情况下东源煤电公司也可以单独发表意见。本案受理后分别向各方当事人送达了受理案件通知书。应诉通知书和合议庭组成人员告知书等一系列诉讼文书。各方是否已收到，是否在开庭前三日收到开庭传票？ • 发言者 4 07:55 上诉方都已收到。 • 发言者 5 07:58 东源公司方面已收到。 • 发言者 7 08:00 招银租赁收到。 • 发言者 3 08:06 对二审期间的诉讼权利和义务，各方当事人是否清楚？ • 发言者 4 08:13 上诉人清楚。 • 发言者 5 08:14 东岩公司方面清楚， • 发言者 7 08:16 招银租赁清楚。 • 发言者 3 08:20 本案由审判员李少平担任审判长。与审判员魏文超黄年王海峰葛洪涛组成合议庭。法官助理张瑞，中华人民共和国民事诉讼法第44条的规定，各方当事人对合议庭组成。本合议庭特向各方当事人释明了以下事项。根据干预过问案件两个规定，本院已经建立了法院内部人员外部人员干预案件处理的 • 发言者 4 09:05 合法的这种文件上的判断，可以得出在当时那么2013年的3月份，东源煤电应该取得了价值，所有的价通过邮件的形式这个传到这个国开行的那么请法庭注意一下它的这个文件的格式叫做东源公司融资情况统计表。然后在这一栏的它写了一个资金，提供人国家开发银行云南省分行，抵押物是恩洪电厂设备在建工程，抵押手续的办理情况是正在办理，这一栏是这样描述的。那么在涉及到跟我们相关的招银金融租赁有限公司的下面描述是这样的。招资金提供人是招银金融租赁有限公司，抵押物是恩洪电厂设备资产。 • 发言者 4 09:55 那么抵押手续的办理情况是已登记，情况统计表在上面，从文件本身来看，他向国家开发银行表达了两个概念。也就是说恩洪电厂的一部分设备资产是招银租赁的，已经登记过了，这个我们理解接受但是作为国家开发银行，你需要办理抵押的恩洪电厂设备和在建公司正在办理那么从上面来看，招银租赁和我们的针对的设备是完全不同的，我们只能得出这样的理解，而不能得出对方所说的已经告知过我，那你应该备注招银租赁的东西，招银租赁的抵押物已经办理过了，而不是像这样并列性的这么一个描述，所以我们从这份邮件上得不出刚刚东元公司所说的这么一条结论，所以我们认为呢对方所说的这个告知这个是不成立的。 • 发言者 4 10:55 第二，针对招银租赁反驳意见。作为这个国家开发银行作为一个金融机构，那么它的尽职调查是有限的，而不是无限的。也就是说作为我们来讲，我们要贷款给谁，那么谁提供抵押物，那么我们就调查谁，这个是一个法定的概念，而不是关联的企业。因为作为东源公司或者是刚刚提到的云南煤化工集团涉及的关联企业几十家，那是不是我们每一家都要去筛查一遍，这个是没有办法做到的。而我们根据法律上的一个规定，那么企业它是不同的。刚刚代理人说了一个母公司和子公司的关系，对我们来讲母公司也罢，子公司也罢，它都是独立的企业法人，所以我们只能根据法律的授权，只能根据就是我们金融贷金融机构的权利，针对抵押人抵押人是谁取经，电力公司进行调查。那么调查了没有这一项登记，那这个任务已经完成，我们履行的手续已经完成，而对方要求我们把相关的所有企业都要去进行调查，这个是不可能做到的，这第1点。 • 发言者 4 12:02 第2点，关于这个设备的问题，这个设备呢我们想说一下，这个设备是企业的通用设备，它不是唯一的，而且在这个设备当中呢也没有一个唯一的标识码，唯一的权属证明它不像汽车，不像房产，它有一个唯一的编码或者身份证，那么这样的话我们调查当然就可以调查，但是这个设备是没有的，所以在这种情况下，我们能做到的就只能是对抵押人名下的融资租赁系统进行调查。第2个我们调查以后，当时因为显示没有任何登记，那我如何来证明我当时的调查行为， • 发言者 4 12:48 我们也向法庭说明过了，到目前为止，到今天为止，如果登上这个系统，同样没有曲靖电力公司的一个调查的结果，那么我们如何提交所以我们想提醒法庭的第2点，第3点关于这个审计报告和这个评估报告的问题。在建工程的价值是5.7亿，拥有的机器设备的价值是5.1亿。那么在这种情况下，他后面做一个表述是什么呢？没有由于这个可能企业内部管理的原因，上述的是属于曲靖电力公司的上述的设备和工程都没有纳入到资产负债表。企业没有纳入到资产负债表，并不等于企业不拥有上述的资产，而这个评估报告已经非常明确了。 • 发言者 4 13:39 同时我们结合这个抵押权确认的一个方式。第二工商登记手续完成已经完备。第三评估报告已经非常确认了上述资产的存在第四现场设施设备的存在。第五，东源煤电没有任何告知我们的行为。那么在这种情况下，我们完全有理由确信我们的抵押权是完整的，是没有任何瑕疵的。所以对方提了一些我觉得是超过了一些我们作为金融机构能够做到的事情，我们不是一个法律调查机构，我们只是一个金融贷款机构，我们只能按照我们业内的通常的人民银行规定的有关程序来完成。 • 发言者 4 14:37 实际上我们已经完成了全部完成。所以呢我们这个反驳的意见就到此，谢谢。 • 发言者 5 14:51 法庭第2代理人的话呢补充几点意见吧，好。 • 发言者 8 14:54 就第1点的话呢还是针对于东元方所提出到的一个告知义务的这个问题，因为我们也注意到，那么有一个细节的话向法庭做一个强调，那么在2015年的12月2日所发的该份邮件的话呢，它不是针对于咱们抵押物。要上面所涉及到的一个融资租赁的这么一个告知的这么一个邮件。从这个邮件的正文部分，以及邮件的附表当中的话呢，均没有任何的文字能够载明东元方向，我们告知过，那么抵押设备当中存在这么融资租赁的这么一个情形，那么这是第1个点。 • 发言者 8 15:18 第2点的话呢该份邮件的话兆英租赁所提交的该份东元公司融资情况统计表之外呢，那么还有另外的有9份报表9份报表，而这个邮件的话呢它是当时国开行进行相应的一个常规的例行的贷后审查，那么由东元方所提供的相关的一些资料。第3点的话呢是从该份统计表当中呢，刚才也提到了作为招银租赁的这一栏当中所记载的融资的额度，那么以及上面所显示的抵押的类型的话呢，是不动产抵押跟本案当中招银租赁所主张的融资租赁的话呢是两个法律概念，那么从这份邮件当中的话呢看不出东元方。向我们告知过认履行过任何的这么一个告知义务。 • 发言者 8 16:24 那么国开行的话呢在办理抵押登记时候，对下设备当中可能存在的融资租赁事宜的话呢，那么也不知情曲靖电力公司的话呢也没有向开行履行过相应的告知义务。这是第1个特第1点。第2点的话呢就是关于设备的这个问题，因为我们也注意到刚刚我们的第1位代理人也强调了，我们的抵押设备或者我们本案当中所诉争的抵押设备的话，它是一个通用设备。通用设备。并且的话呢我们也注意到在招银租赁一审向法庭所提交的证据，那么建招银租赁的证据第7页，有一份回租设备清单。 • 发言者 8 17:08 这份回租设备清单呢仅载明了设备的名称和生产厂家对设备的型号的话呢均没有任何的一个提及。另外的话呢还有一个点是在这份回租设备清单当中所记载的设备的出厂日期是2012年的3月1日，而本案当中经过国开行进行现场调查核实到的，抵押设备的铭牌当中所记载的生产日期呢均在2013年以后，那么部分设备是2013年的11月，部分设备是2013年的12月，那么还有部分设备是2014年的3月份。那么从记载的这个时间来看的话呢，那么也看不出是同一设备，那么这是属于从设备的这个情况。 • 发言者 8 18:08 第3个点的话呢是在办理抵押登记时，那么除了我们之前所谈到的一个是工商部门的一个出资的这么一个证明，那么另外的话呢我们向法庭所提交的证据的54页和58页，也有东源煤电公司曲靖电力公司对该些设备的一个权属的一些相应的一些证明材料和股东会的一个决议。那么在这些材料当中的话呢均能显示本案当中所诉争的抵押设备它的所有权的话，呢是曲靖电力公司，那么根据融资租赁的一个司法解释，以及人民银行所出具的相关的一个登记的一些情况来看的话，在国开行已经对设备的所有权尽到了一个审慎义务，经审理查明所有权，那么确属曲靖电力公司的情况下，国开行的一个融资租赁登记的核查义务呢仅限于曲靖电力公司。 • 发言者 8 19:17 不能任意扩大到东源煤电公司。没有任何的一个融资租赁信息的这么一个登记。那么该份核查表的话呢是见我们证据的108页，我们一审的话呢也向法庭做了一个提交。那么因此的话呢开行在对抵押物进行核查的时候，包括融资租赁登记信息进行核查的时候呢，已经按照了相应的法律法规和行业的相应的规范履行的相应的一个义务。那么开行的对抵押物的这个取得的话呢是构成法律上的一个善意取得。第4点的话呢是针对于招银租赁所提到的报表的问题， • 发言者 8 20:09 我们在强调两点，那么招银租赁的代理人提到了，那么在曲靖电力设固定设备一栏的一个价值是0，那么这里的话呢是有一个财务记账的一个问题。因为曲靖电力公司那么它的一个整个的一个生产设备厂房还没有正式的一个投产，另外的话呢是从招银租赁一审向法庭提交的2013年和15年的审计报告当中，建招银租赁的证据82页和证据95页当中的话呢，虽然是合并的一个报表，但是在82页合95页的话呢也明确载明曲靖电力公司的注册资本是4个亿，并且的话呢是已经是实缴已经是实缴。 • 发言者 8 21:07 那么也即在招银租赁所提交的该两份审计报告当中呢，已经对设备的出资事项呢已经进行了载明。因此的话呢站在上诉人的角度来讲，我们认为招银租赁的话呢有理由或者是知道或者是应当知道设备进行出资的这么一个情况，这是第4点。第5点的话呢是关于招银租赁的这个融资租赁模式的问题呢，那么简单提简简单强调一点，因为招银租赁的话呢一直在强调的一个售后回租的一个占有改定占有改定。但是从本案当中是上诉人所提交的相关证据来看呢，相应的设备在办理融资租赁的时候的话呢，还没有取得还没有取得。 • 发言者 8 21:56 也即本案当中动员方的话呢，还没有取得融资租赁设备的一个所有权，还没有发生的一个占有。像法庭做一个强调。最后一点的话呢是关于上海中院的一个一审判决内容，跟本案有关抵押权的审理是否冲突的问题的话呢，上诉人认为的话呢是不冲突，一方面的话呢在上海市中级人民法院的判决当中呢，那么它仅限于是动员方对相应设备的一个返还的义务没有明确载明，那么确认该些设备的所有权。的话呢归招银租赁所有。第2个方面的话呢是本案当中上诉人向法庭所主张的是该些设备的一个抵押权。 • 发言者 8 22:56 从权属的一个范畴来讲，但是本案当中所审理的，那么主要是该些设备的一个底担保物权担保物权。而担保物权跟所有权从法律规定的角度来讲的话，那么是可以并存的。那么即便本案当中招银租赁取得了设备的一个所有权，但是对设备当中是否存在在先的一个抵押权，这个设备的权属是否存在相应的一个瑕疵的话呢，我们认为是两个权利范畴。我们认为的话呢本案当中上海中院的一审的判决呢对本案的审理的话呢，不构成一个实质性的这么一个障碍，那么不存在招银租赁所提出来的，需要通过再审或者是抗诉来进行权利救济的这么一个情形，补充完毕，谢谢法庭。 • 发言者 7 23:54 好。 • 发言者 3 23:56 东园坊有无反扒意见？ • 发言者 5 24:00 好，我放那个简要发表。一点反驳意见。第1点呢是针对刚才国开行第2代理人提到的，我方提供的相关材料只是一个贷后审查的材料，这个我方是认为不符合客观事实。应该说从时间节点来看呢，我们发发送的这个邮件是在2015年12月2日，而双方签订私自增财产的那个抵押合同呢是在2015年12月22日，从时间节点来看呢是肯定是吻合的。然后贷后审查要求提供相关报表呢，其实它应该是在年中有相关的报表，那么那个应该是在次年的年初才会提供相关报表，因此我们认为这个只是一个贷后审查正常提供材料，我们认为与客观事实不符。 • 发言者 5 24:53 然后事实上我们可以看到在我们的融资情况统计表里边，两家公司的抵押设备它的设备名称是完全相同的，而且我们查看了这个邮件的相关的截屏的话，抵押设备的那个这个部分的嘛是用红色予以标注，就是清晰的突出的，就是这个地方是有用红色来区了别的那个抵押设备的。那么国开行作为一个专业的一个金融机构，当他发现他即将要办理的抵押设备名称和其他家的抵押设备的名称完全一致的时候，你起码你要起到一个注意的一个义务吧。再加上我们用红色已经给你标注清楚了。 • 发言者 5 25:50 那么我们认为当发现抵押设备资产一致的情况下，都应该进一个适当的核查，避免双方的设备在办理抵押的时候出现重复的情况。 • 发言者 7 26:09 但是 • 发言者 5 26:10 从整个庭审来看呢，国开行没有提供相关证据，证明他们已经做了一个区分。因此呢我们认为从我方提供的相关材料应该引起国开行的注意义务，然后从而呢做一个区分，以免今天在庭上发生诉争这么一个情况发生。我方就发表到这里，谢谢话题。 • 发言者 3 26:38 招银租赁有反驳意见。 • 发言者 5 26:42 招银租赁补充3点意见。首先是我们认为国家开发银行没有尽到应尽的审查义务，不构成善意。依据这个国开行提供的第5组证据的第1项，这个国开行是提供了2018年9月份一份对曲靖电力公司的融资租赁的查询证书，但实际上这一份查询证书是不符合要求的。因为根据2014、93号这中国人民银行关于融资租赁登记系统的规定，国家开发银行应当是在抵押的时点进行一个融资租赁的登记查询。那就是说国开行应该是提供2015年12月份，它在操作抵押的时候，这个时点它在查询人行征信中心的一个查询结果。 • 发言者 5 27:40 这个结果不管是以设备的名义进行的查询，还是以电力公司名义进行的查询，第2个就是对于国开行提到的不能扩大它的审查义务，我们提请法庭注意到就是首先国开行作为贷款人，它的借款人是东源煤电，而它的抵押人恰好是同一案件的抵押人，那实际上第3个法律关系就是它的借款人和抵押人是构成100%的全资的控股关系。那所以在同一个案件不是这个东源煤电它是有双重身份的，它不仅仅是抵押人的全资的控股的母公司，它同时是这个贷款案件的借款人，所以我们觉得国开行对这个东源煤电的审查义务是应当具备的。 • 发言者 5 28:47 那第2点补充的意见就是我们对电力这个东源煤电的一个出资行为的一个我们的一个观点。东苑煤电的这个出资行为是一个无权处分的行为，因为招银租赁在2012年即取得了这个租赁设备的所有权，那开放银行是在1115年进行的一个抵押登记，他的这个出资行为实际上是一个无权的一个处分行为。那工商抵登记实际上公示的是一个出资行为的公示，而不是对这个动产的一个公示。所以我们认为这个国开行东源煤电对设备出资给电力公司这个行为是无权处分，电力公司是没有取得设备的所有权，那我再补充第3点，就是关于国开行提到的，我们在2012年操作融资租赁业务的时候，我想曾经的一个概念是设备的交付到货与设备的最安装调试，它实际上是两个概念。 • 发言者 5 30:20 只要设备交付到货给了东源煤电，那实际上东源煤电就已经取得了这个相关设备的所有权，那同时招银租赁也在这个交付的时点，也同时获得了租赁设备的所有权。所以我们认为招银租赁是在12年就已经取得了设备的所有权。那国家开发银行的抵押权它是在2015年操作时间是在我们后面，而且开发银行在抵押这个时点没有进行相应的审查义务，它是不构成善意的。我们的这个意见汇报完毕。 • 发言者 3 31:06 对于第1个争议的焦点，各方有无新的辩论意见？没有了，审判长。 • 发言者 5 31:17 动员公司没有了，专业做的没有。 • 发言者 3 31:23 根据各方发表的意见，我有两个问题还想再请问一下。这个生产设备作为动产那么各方怎么理解中国人民银行征信中心的融资租赁登记的性质？以及这种登记行为产生的法律后果？希望各方简要的回答一下。好。 • 发言者 4 32:00 这个中国人民银行颁布了一个融资租赁登记的一个办法，还有向各大金融机构发放一个通知，我们认为呢它是一个行业内的强制性的一个规范，行业内强调是对金融系统内部的一个一个规范，它的目的呢主要是为了解决这个因为动产它本身的属性具备，什么叫可移动性。第2个叫我们认为还有一点叫做不明确性。因为动产设备呢它是由各大厂家生产的一些机器设备，这种机器设备呢很多都是通用设备，那么在这种情况下，实际上而且也没有一个类似于咱们公民的个人身份证号码呀，或者这个像刚刚讲汽车的这个车牌号这样的，所以它具备这种可移动性和不明确性。 • 发言者 4 32:53 那么人民银行颁布这个包括这个银行贷款机构进行动产抵押的时候要求进行查询，这样呢是为了防范内部的这个金融风险。防止出现了这个动产设备呢多处抵押，最后抵押权这个抵押或者融资租赁出现冲突的情况。所以呢就这个理解呢我们认为呢首先它是一个强制性的行业内的规范。第二呢我们认为呢就是说它是为了防范金融风险，融资租赁相互之间冲突，或者融资租赁和抵押之间和动产抵押之间出现相互冲突的这么一个系统，我们认为它还是有效了，一定的程度上防范了这个金融风险的发生。谢谢。 • 发言者 3 33:50 好，法定那个 • 发言者 8 33:53 第2代理人的话呢补充一点意见吧。那么针对这个登记的这个性质上来讲的话呢，因为我们认为动产的这个抵押登记的话，不管是根据中华人民共和国物权法的一个规定，还是动产抵押登记管理办法的一个规定呢，我们认为动产抵押登记呢它是一个法定的这么一个物权登记，那么是对外的话呢是具有一个相应的排他性。作为融资租赁登记的话呢，融资租赁登记的一个性质的话呢，那么更多的是一个行业性质的，那么不是一个法定意义上的一个物权登记。 • 发言者 8 34:15 那么我们这边补充一点， • 发言者 3 34:29 东院方。 • 发言者 5 34:39 对院方有什么好的，对这个问题呢我方是这样理解的，就是融资租赁登记呢它只是一个行业的一个指导性规范意见，它不是一个强制性的一个规范，然后呢它也不当然的产生相关的物权的后果。呃我我方是这样理解这个问题的，陈述完毕。 • 发言者 3 35:02 招银租赁你们怎么看？你们搞这个更是 • 发言者 7 35:07 对对于这个央行的融资租赁登记，我们认为根据物权法定的原则，它并不是一个法定的物权登记这样一个措施。它只是一个权利的公示，它是强化了一个动产权利的外观，它可能会产生一种对抗效力，就是如果说经过了登记以后，那么在一旦产生争议，在考察是否善意的时候，它有一种对抗效力。但是呢这个登记并不影响所有权的这个设立转移等这些法，这个物权法的法定效果，这个是不影响的。那么央行的这个规定呢，它主要是央行作为一个银行业的监管机构之一，对于各大政策性银行国有商业银行，还有股份制银行，也包括这个邮政储蓄银行这个行业内的一种行业性的强制性规范。 • 发言者 7 35:59 它并不构成法律效力上的这么一个约束力， • 发言者 5 36:07 好， • 发言者 3 36:09 下面呢请看我们合议庭其他成员有无提问。 • 发言者 5 36:15 好。我也有个问题呢想问一下国开行和招银租赁就是央行的这个金融租赁融资租赁登记系统有几种查询的方式？这些查询的方式 • 发言者 9 36:29 是否能够保证查询到登记的结果？先请国开行回答一下。 • 发言者 4 36:45 谢谢，我们现在能够产能够使用的就是一种查询方式，就是查询单位好。谢谢。 • 发言者 9 36:55 招银租赁你们的意见。 • 发言者 7 36:58 这个登记平台应该来说是可以通过两种方式进行查询，一个呢是根据公司的名称进行查询，看一看这个公司是否有涉及到融资租赁的情况。第2个呢是可以根据设备的情况进行查询。就是输入设备以后然后进行查询。那当然这个涉涉及到如果以设备进行查询的话呢，那可能如果涉及到一些种类物，那这个后续涉及到一些区分的问题，如何通过一定的登记因素来区分这些设备的唯一性和自己这个项目的关联性。那这个可能会产生一个问题。 • 发言者 5 37:31 就是对设备进行查询的话，就要求租赁公司或者这个对这个设备的特定化要做到很详细，这是对它的这个唯一识别码的这个登记需要相当的明确， • 发言者 9 37:46 你们作为这个系统的登记这一方，在登记的时候，这些识别码都已经登记清楚了吗？ • 发言者 5 37:54 我们只要是这个设备具有唯一的识别码，我们一般都会登记。 • 发言者 9 38:00 我是说的案涉的5套设备， • 发言者 5 38:02 案涉的这5套设备由于它当时是这个刚刚交付，所以它在这个设备是没有这个它是一个种类物，没有这个唯一的识别码，所以当时我们没有进行登记。好的。嗯。行， • 发言者 6 38:19 我问一个问题，那个国家开发银行那个你们在那个 • 发言者 10 38:34 贷款前那个这个审查的时候，风险控制这个相关需要的资料里面，有没有你们内部的这个一些规定说必须要去查，如果没查到，也要把没查到的这个单子作为风控材料的一部分。来准备。 • 发言者 4 39:03 首先呢我们在做这个动产抵押的时候，是按照这个央行的规定，肯定是要调查这个这个系统的，就通过这个融资租赁系统来需要做一个筛查。那么在筛查以后呢，实际上因为没有这方面的记录，所以呢我们在当时贷款办抵押的时候，我们就没有保留这个筛查的这个记录，因为本身没有嘛，那我觉得就没有必要，而且我刚刚也讲到今天也没有 • 发言者 10 39:31 你说内部没有这样的一个规定制度是吧？没有查询到结果，需要在这个单元再 • 发言者 4 39:36 对，因为没有查询到结果。嗯。 • 发言者 10 39:40 然后再问一下，这个你们这个认为去查了这个电力曲靖电力的这个登记信息是吧？你们认为你没有查到这个登记的这个结果，设备融资租赁登记的结果，然后你以此想免责的这个逻辑，你简单再说一下。 • 发言者 4 40:05 Err下。好，首先呢是这样的，就是说我们作为金融机构，我们要按照央行的规定来查询这个融资租赁系统，那么根据这个融资租赁系统记载呢，就是刚刚对方也提到了，因为它这个是通用设备，通用设备呢而且我们就不可能查设备，因为这个设备那就系统上就非常多了，这是第1个问题。第2个问题作为我们来讲，我们首先确定的是我们的抵押人是谁。那我们的抵押呢就是曲靖电力公司，那么查了曲靖电力公司，当时实际上我们当时查了以后呢， • 发言者 4 40:37 因为它是一个手段之一，就是说我们还有其他的刚刚讲了办抵押登记诸如此类审资料审查之类的，那么它只是其中一个手段之一，我们查了以后再系统上就没有记载说这个曲靖电力公司它的设备有其他融资租赁的情况，没有系统。我们做了一个截图，做了一个截图，那么也没有显示说曲靖电力公司的这个设备有融资租赁的情况，那么到目前为止也没有，那么我们的逻辑关系是什么呢？就是说在当时到现在都没有，那么实际上我们作为一个查询的行为，我们本身来讲就没有必要说我去截一个没有的东西，没有的这个结果，我来证明我当时做了，实际上到今天为止，我刚刚讲的我们逻辑观今天也没有这么一个结果，说明我们的这个行为是没有任何过失的。像现在的结果也证明了对方刚刚所说的一个观点是必须我要证明我当时去查了，实际上查不查到今天结果都是一样的，你都没有登记，所以我们想说的是这么一个逻辑关系，谢谢。 • 发言者 10 41:51 张颖助理我问你一下，那个你们在那个融资租赁登记系统里面登记了那个设备的唯一标识码吗？或者说那系统里面是不是设备的唯一标识码是不是必填项？ • 发言者 7 42:07 设备的唯一标识码不是必填项，因为在这个项目里面所涉及到的设备呢，它不像汽车一样有一个发动机号码或者说车架的号码，它没有这个识别的唯一的识别码，所以我们在本案登记的时候 • 发言者 6 42:22 没办法填写。 • 发言者 7 42:24 这样一个识别码。 • 发言者 10 42:25 那现在的那个设备不是已经安装了吗？现在的设备上比如发电机上都没有唯一标识码吗？ • 发言者 7 42:33 发电机上没有的，它这个发那个铭牌上面只有它的型号，然后还有一些这个设备本身的一些参数，那这些呢可能是只要是达到这样一个好像是15万伏发电机，只要是上海电气出厂的，这个设备，它的铭牌上面都是一样的，应该是 • 发言者 10 42:52 另另外两方是这个情况吗？ • 发言者 4 42:55 是没有一个唯一的识别码。 • 发言者 10 42:59 好的， • 发言者 5 43:00 就我补充一点是我们当时在做初始登记的时候，是把我们的租赁物清单是作为附件整体的上传到了这个人行的征信系统，那这个附件清单里呢除了有设备名，称有数量有原值有净值出厂时间生产厂商，而且还有它的存放地点，所以那实际上我们的这个存放地点清晰的显示是在n红矿区煤矸石电厂，而这个煤矸石电厂呢只有两台设备，实际上就是汽轮机两台，这个发电机两台，锅炉两台，实际上是没有额外的设备了。所以我们觉得这样的一个描述已经是足够清晰，而且能够足够引起这个相关金融机构的足够的重视了。 • 发言者 10 43:51 好的，我问一下。那我问一下那个国开行和招银租赁，就是刚才大家都提到了一个查询的通知，这个查询通知呢里面也规定了在银行业就金融行业办理动产抵押之前呢，应当到人民银行这个登记系统里边，对融资租赁的情况进行查询。那么你们两方认为就是在多大程度上违反这个规范，才会导致最高人民法院关于审理融资租赁司法解释第9条第2款规定的这样一个法律后果。也就是说你们认为 • 发言者 5 44:29 这是一个 • 发言者 10 44:30 基本的查询义务，还是一个全面审慎的查询义务？各位好。 • 发言者 4 44:36 谢谢，我们认为这个是一个基本的一个查询业务，因为首先来讲呢，这个也就是说作为金融机构在做动产抵押的时候，根据这个人民银行的规定，我们觉得都应该查询这套系统。第2个根据最高人民法院这个关于融资租赁司法解释第9条第3款之规定呢，我们认为它就是说你必须作为金融机构第三方来讲，你要取得善意的权，你应该对这个融资租赁的这个抗辩权的话，应该进行一个查询。那么这个呢涉及到这个抵押和这个本案结合本案，那么涉及本案的一个抵押和一个融资租赁所有权的情况， • 发言者 4 45:05 我们认为呢作为这个国家开发银行本身来讲，那么我们的审查义务也就是说针对的是我们的这个抵押人，那么这个审慎的这个调查义务我们已经完成。所以呢从这个层面来讲，我们觉得这个 • 发言者 10 45:36 专业助理。 • 发言者 7 45:39 关于这个问题招银租赁认为这是对银行业的一个严格要求，就是严格的一个义务，只要银行没有进行查询，那么就不应当构成善意，不管查询的结果如何，因为根据同业这个规范的要求，银行在办理抵押的登记的时候呢必须要进行查询，那如果没有进行查询，那就已经违反了行业的规范要求和行业的惯例。那第2点呢是关于多大程度上来进行查询，那我们认为这个在每个案件中所考察的程度呢是不一样的。那在本案中如前我们所述的在东源煤电安宏煤电安宏煤矿区发电厂只有这一个，所涉及到的发电设备也只有这两台，所以我们认为综合各方面信息能够确定细征的5台设备的唯一性和特殊性。 • 发言者 7 46:20 那么在这种情况下，我们认为已经达到一个足够引起国开行这个引起他注意的这么一个程度。以上是我们招银租赁的一个看法。 • 发言者 10 46:42 我再接着问一下就是这个通知的规定，要求查询呢其实就是银行业对风控的这样一个呃业务性的规定，对。那如果说是一个银行在发放贷款之前，通过其他途径了解到了动产这个将要被动产抵押的这个物呢属于融资租赁物，是否就相当于不需要查询，就已经对这个风控的情况进行了了解和掌握。 • 发言者 4 47:15 这个如果说以贷款银行再提前通过其他渠道了解到呢，那可能会导致下面的贷款的审批各方面的一些不同的意见。但是我们理解呢这个就说这个动作刚刚讲的是一个基本义务，基本义务就是必须要做的。那么从人民银行的这个规定来看，就是作为动产抵押的时候，每家银行都要做同样的事情。是这个融资租赁这个调查的情况。第2个刚刚从这个对方所说的这个全面的这个审查的一个这这个义务的情况，我们理解是这样的，首先我们为什么认为它是一个基本义务回答刚刚这个审判长这个问题。因为这个基本的义务呢我们认为就是说你只要做了这个动作，这个动作完成了，那么根据完成的结果，你就可以得出自己的结论，那么这是个基本的。 • 发言者 4 47:52 第2个它的做要做到多大程度呢？我们认为你作为一个贷款金融机构来讲，你只能做到把你所需要的贷款人，或者说如果这个设备是有唯一标识码的，你可以输入查询有没有，那你的动作就完了。所以我们认为这个调查的审核的这个系统它所起到的作用，第1个风险提示。第2个作为查询来讲，你只是输入登录有没有记录这样就够了，所以我们认为它就是一个基本的义务，谢谢。 • 发言者 8 48:32 法庭这个问题我补充一点吧。对于刚刚说到的这个查询主体的话呢，因为我们也一直在强调跟本案当中跟国开行建立这个租抵押合同关系的这个主体是曲靖电力公司，那么作为开行的这个根据人行的一个相关规定或者司法解释的相关规定的话呢，开行的这个核查义务的话呢仅限于曲靖电力公司，但是国家开发银行在办理本次抵押的时候的话呢，那么也对这个抵押物的所有权进行了一个合理的一个审慎义务。刚才在发表辩论意见的过程当中的话呢，那么我们也向法庭做了详细的一个说明，那么在我们对抵押设备的所有权经核查都能够明确为曲靖电力公司的情况下的话呢，我们的义务的话呢也仅限于对曲靖电力公司名下的融资租赁登记事项那么进行核查。就补充这点，谢谢老丁。 • 发言者 10 49:27 找云租赁。 • 发言者 5 49:32 对于合议庭提提到的这个如果已经知道有租赁是否还需要查询这个登记系统，我们的观点是这样的。金融机构在接受抵押物之前呢，需要对这个你接受的抵押物进行一个权属的一个这个确权也好查询也好，就是说首先这个抵押物是不是抵押人真实拥有，就是他是不是所有权在他这里。第2块就是这个抵押物之上还有有没有其他的权利瑕疵？比如说我不可能接受已经存在抵押，权的抵押的抵押设备继续做抵押，所以我觉得首先是要进行一个这样的权属的确认。 • 发言者 5 50:09 那第2块就是如果通过其他渠道知道这个你抵押设备可能存在租赁的话，我觉得这个还是要进行一个查询。这个确实客观存在的，以决定我能否接受这个抵押物。 • 发言者 7 50:37 我们招银租赁补充一点就是关于第2个问题，通过其他方式查询到以后呢，我们认为仍然要通过央行的这个系统进行查询，这个呢主要一个考量央行的这个规定出台的一个背景，就是因为在实务中大量存在这样的权这个权利争议，然后以及司法程序过程中呢遇到这样大量的案例，所以说才出台了这样一个规定。那么在解决争议的时候，对方那个银行是否通过其他的方式获知了融资租赁这一点在解决争议的时候是没有办法予以来证明的。所以只有通过一个确定的标准才能够去才能够这个衡量双方是否构成了善意。 • 发言者 7 51:09 那么这个确定的标准目前来看就是央行的这个通知规定就是必须要通过央行的这个规定进行查询。那当然了如果有其他的证据，司法解释的层面，还是从央行的通知规定的层面，都归这个要求银行必须做这样一个动作。 • 发言者 10 51:51 好的。我也问一个问题，就是因为这个动产的租赁融资租赁它会因为它自身的属性的问题，也会产生一个所有权和占有的分离，也就会引起来一个交易安全。因为这个问题呢融资租赁司法解释的第9条专门进行了规定，其中第1款呢它是说构成善意取得的情形。第2款呢它是列举了排除善意取得的情形。其中就包括呢大家一直在争的查询的问题，也包括刚才王海峰法官问的事前其他方式知晓的问题。这都与本案呢联系很密切。我想问的问题是各方对这个第2款的举证责任，的分担是怎么理解的？ • 发言者 10 52:47 就在本他举证责任归谁，在本案当中呢应该是怎么分担？ • 发言者 4 52:54 这个我们认为通常意义上来讲，这个举证责任呢还是按照谁主张谁举证的原则来确定。那是在本案当中呢我们觉得就是说关于这个例外情形的这么一个规定的话，我们觉得首先来讲呢这个应该说还是按照这个原则来处理。只是说在里面来讲，我们现在双方争议的一个焦点是这个对这个条款和本案结合实际的一个理解问题。也就是说我们作为我们国开行作为一个金融机构，我们需要查询的是谁，查询到什么程度的问题。那么根据这个司法解释的这个有关融资租赁的规定呢， • 发言者 4 53:33 它针对的主要它也有要求进行查询，但是它上面的写的要求的是说我们和陈志文进行交易的时候，那么实际上我们如果涉及到和承租人交易或者贷款的话，我们就是指定电力公司，所以现在来讲可能作为这个上诉人和被上诉人争议的焦点是应该是查询的范围和查询的主体。 • 发言者 10 54:03 动员方。 • 发言者 5 54:07 我方 • 发言者 10 54:09 对此 • 发言者 5 54:11 没有意见 • 发言者 10 54:12 招银租赁。 • 发言者 7 54:15 关于融资租赁司法解释第9条的规定呢，我们认为还是原则上应该依据民事诉讼法谁主张谁举证的原则，然后综合考量各方的义务内容和各方掌握证据的优势，综合来进行判断。因为这个第9条呢它是一个列举式的，列举了三种明确的方式和第4款有个兜底条款，我们认为关于1、2、4应当由出租人进行举证来进行证明。关于第3项应当由第3人本案里面呢也就是国开行应当证明在办理抵押的时候，向央行的登记系统这个进行了查询。所以我举证原则呢我们认为是124有出租人， • 发言者 7 54:56 第3项应当是由第3人这个原则性上的一个规定。这里我们多说一句，就是因为国开行一直在强调说查询的一个内容一个范围，国开行一直强调说仅限于曲靖电力，我们认为这一点呢从善意上来说是不成立的，因为从金融行业的一个惯例来看，的权力来源，比如说我们在办理的时候，我们会查询购买合同购买发票，那么国开行在办理抵押登记的时候呢，其实也应当查询购买合同购买发票，那么在本案中他因为涉及到了出资，所以说我们认为国开行应该扩展到调查东源煤电，调查东源煤电，获得这些设备的权属是否是完整的没有瑕疵的。 • 发言者 7 55:54 好，我们简单回应一下，回答完毕。 • 发言者 3 56:06 这个当然了这个本案呢案涉这个融资租赁物还有这个动产机器设备，那么在我们国家目前没有统一登记制度的情况下，我们可能就由于这个对不同的登记制度的情况呢会有不同的看法，那么双方如何看待因不同登记机构产生的登记信息？特别这些信息如果冲突了，那么你们有什么意见和建议？嗯 • 发言者 4 56:47 实际上呢作为这个今天我们可能涉及到的是两个问题，第1个是这个人民银行的融资租赁登记系统，第2个是动产抵押的这么一个冲突和矛盾的问题。首先呢我想作为这个各自的机构，如果人民银行作为一个银行的银行，它出它按它设计的这个融资租赁系统，应该说从它的角度来讲，已经做到考虑到了诸多的风险。应该说是做到了我认为应该是相对一个合理的一个程度。作为这个工商银行，不是作为这个工商局作为动产抵押的一个这个登记机构，目前来讲国家工商总局是颁布了一个动产抵押管理办法，那么我们也是根据动产抵押这个办法来办理的动产抵押。 • 发言者 4 57:37 那么从国家工商局颁布的这个办法执行上来来讲也没有问题。动产抵押登记和人民银行融资租赁系统这个一个巨大的这个因为信息的不统一出现的一个矛盾。那么我们双方的争议，我们和招银租赁出现的这个诉讼和争议也是由此而来。就我们的理解应该说这个由于这个系统信息的不完整，它可能不是哪一个部门的问题，是整个系统的问题。就包括我们在研究这个国家工商总局颁发的这个动产抵押办法，动产抵押办法的第2条规定的是由动产所在地的， • 发言者 4 58:24 由这个企业住所地所在的县级工商行政管理部门，就现在市场监督管理部门进行登记。在这个规定上应该说从我们的原来的理解上是没有问题的，现在就我们作为碰到一些案例当中也出现一种其他的情况，也就是说企业的住所地发生了变化，原来我是在比如说我们刚刚讲，原来我是在曲英曲曲靖市麒麟，多重动产抵押的情况，对于这个像对于交易安全和金融机构贷款来讲，也存在相应的风险。这个我讲的是动产抵押的问题。第2个就我们涉及到的这个融资租赁的这个情况，我们就我们来讲，我们的确是调查了这个曲靖电力公司，但是融资租赁系统没有任何的显示。在这种情况下出现了这个系统之间的这种相互的隔离。 • 发言者 4 59:29 所以我们认为呢应该说就各个专业的区域来讲，比如说作为央行作为它专业机构的金融机构的角度，或者说工商局作为动产抵押，的机构谁都没有错，但是由于整个体系的相互隔离和信息的不流畅，没有形成一个相互的连通的情况，我们估计呢在未来有关动产抵押也会带来这个首先交易上的风险。第2个由于金融机构或者说这个融资租赁机构对于动产抵押的这种担心害怕，因为动产抵押出现了很多问题，它也会导致在企业需要资金的时候，很难取得金融机构的同意。 • 发言者 4 01:00:16 特别像我们国家现在提的是一个制造业立国，那么机器设备就是很重要的企业的一项资产。所以它会形成一个恶性的循环。所以我们认为呢就目前来看呢应该说这个应该是整个的这个系统性的一个相互的信息的一种整合。这种整合以后呢实际上就是说整个市场的这个有序性规范性完善以后，那么所有在这个市场里面的包括金融机构，的融资租赁机构和企业才能够各取所需，导致市场一个充分的有效的资金的一个流动。所以我们认为呢实际上就本案来讲， • 发言者 4 01:01:03 我们虽然是和招银之间这个进行了租赁之间进行了一个很大的一个争议，但就整个系统来讲，我们觉得就是因为条块化的这种分割导致了这个整个市场秩序的一个不稳定，而且它对潜在的企业的这种未来企业，刚刚我讲到的这个整个动产抵押的这块市场的这个信誉坏了以后，实际上对于企业的发展也是很不利的。互联互通的话，对于整个市场持续经济的发展，我们认为是有帮助的。好谢谢。 • 发言者 5 01:02:03 好，那个从本案的情况来看呢，确实是在登记上 • 发言者 10 01:02:09 以及查询上出了一些问题， • 发言者 5 01:02:11 那么系统的一个整合或者是相互 • 发言者 10 01:02:14 的一个衔接确实有必要， • 发言者 5 01:02:16 但是东研公司这边呢那个因为不是这方面的专业机构，也提不出成熟的一个相关的什么 • 发言者 10 01:02:25 建议和意见。 • 发言者 5 01:02:27 是这么一个情况。好。 • 发言者 6 01:02:30 所以 • 发言者 7 01:02:31 关于这个问题呢，我们认为现在这个金融主体和市场主体所面临的一个客观情况呢是规范不统一，登记的机构呢也不统一，实际操作呢可能千差万别，这样呢最终导致了一个信息不对称。那这样一个客观状况呢距离我们希望说能够规范金融秩序和市场秩序那存在比较大的一个差距。那为了解决这样一个客观状况所造成的风险，那我们认为可以从几个方面然后进行来着手。第1点呢是从立法层面来统一对金融主体和市场主体的一个要求。也比如说我们在本案中一再争议的这个央行的通知， • 发言者 7 01:03:11 其实这个央行的通知呢是关于银行业的一个规范，但是它对融资租赁业它并没有一个效力比较强的要求，因为它只是说提倡融资租赁公司进行登记，但是在务中呢各大融资租赁公司是否进行登记，那这个可能是没有办法去强求，也很难不一而足的了。但是我们也应该认识到这个立法程序呢，它其实是一个非常复杂可能时间比较长的这样一个程序。所以我们认为从第2点呢为了能够尽快的实现这样一个效果，可以发挥行业协会的这个作用。比如说银行有银行同业协会，那融资租赁呢也有融资租赁行业协会，那包括信托各个金融这个主体都有自己的一个协会。 • 发言者 7 01:04:00 那这个协会呢它虽然是一个自治组织，但是它对于规范这个行业内后续对后续有一些指导的这个意义方面呢，这个自治协会是有很大的作用发挥空间的。所以如果说行业协会能够从整个行业的层面提出一些倡议，或者甚至是一些不成文的要求，各个会员单位然后来认可的一种规定，那我们认为至少可以形成一个行业惯例，那这样呢我再产生争议的时候也可以有一个评判的标准，那没有法律的规定的情况下，那至少有一个行业惯例。第3点呢我们认为是从操作和技术的层面儿， • 发言者 7 01:04:53 因为造成双方的信息不对称，目前来看最主要的一个原因是主管的机构是不一致的。比如说我们前面提到的融资租赁的登记是央行的平台抵押的登记呢是目前由市场监督管理局进行管理规定，两个平台的信息呢目前是不互通的，那当然最理想化的一个程度是登记的平台，然后来这个实现这样一个目的。但是这个呢因为涉及到行政机关跨部门的一个合作，还有一个技术上的一个难度，可能短时间之内的这个比较难以实现，但至少少我们从技术上可以去实现一种信息的互通，那这个我们认为从技术上来说呢是没有什么难，是没有什么难点的。其次呢从登记主体的角度来说，我们认为也有比较大的改进空间。 • 发言者 7 01:05:48 那目前银行还有融资租赁公司作为比较专业的金融机构，基本上都可以做到按照同业的要求和行业的管理，在主管机构的平台进行登记。但是呢这个企业主体很多时候呢这个是没有登记的。那比如说为什么在融资租赁司法解释的第2款有一个规定是说在工商机关做抵押登记，因为在融资租赁行业在摸索所有权和抵押权不要产生冲突的时候呢，曾经尝试过在市场监督管理局做抵押的登记，就是把这个抵押物抵押给出租人自己，但是呢这个操作在实务中呢遇到很大的障碍，有很多的市场监督管理局对于这样一个登记不予认可。 • 发言者 7 01:06:32 他们认为抵押权就是抵押人把自己所有的物那这样所以在实务中操作的时候呢碰到很大的难这个难点，这个呢也是央行为什么推出这样一个登记的背景和原因，所以我们认为企业也可以发挥它的一个主动性，做一个抵押登记或者所有权的登记。那如果说本案中假设在本案中东源煤电曾经也在工商机关做了这样一个抵押登记，就是我们融资租赁它也在市场监督管理局做了一个登记，那这样就不可能从根本上杜绝了，国开行查询不到。涉及的融资租赁这样一个情况，那么从根本上就可以杜绝这个风险。 • 发言者 7 01:07:31 所以我们认为呢这个企业也可以利用自身的一些这个途径发挥它的主动性，那这样大家所有的市场主体，无论是金融主体还是企业还是我们的行政机关，包括我们的司法机关，大家一块合力来寻找这样一种途径，避免这种风险的发生。以上我们招银租赁的简单看法。 • 发言者 6 01:07:53 好。 • 发言者 3 01:07:55 下面进入第2个争议焦点。一审判决对案涉借款的罚息复息的计算以及起算日期是否认定错误，请国开行发表辩论意见。 • 发言者 8 01:08:14 好的，法庭。针对第2个争议焦点的话呢，上诉人国家开发银行认为一审的认定有误，那么第1点的话呢是本针对本案的利息，本案的利息呢从一审二审那么以及庭前会议审理查明的一个事实来看呢，本案当中东源煤电的一个利息的支付时间呢是截止到2017年的12月20日。那么相应的利息的话呢是理应从2017年的12月20日开始计算，而在上诉人在一审向法庭也提交了相关的证据，那么在2018年的6月13日，国家开发银行的话呢，向东源煤电股份有限公司东源煤业集团有限公司发送了两份关于偿还云南恩洪矿区煤矸石综合利用电厂上大压小项目贷款本金的函。 • 发言者 8 01:09:06 那明确要求被上诉人呢于2018年的6月13日归还相应的一个借款。我们在2018年的6月13日发出了相关函件之后呢，本案的一个借款的一个到期日呢，因为2018年的6月13日罚息的起算时间的话呢，因为2018应从2018年的6月13日开始起算。那么关于本案的一个复利的话呢，在上诉人国家开发银行与东原煤电借款合同的第6条，也对相应的一个复利的一个计算标准以及计算的一个内容的话呢也做了详细的一个约定。那么因此的话呢我们认为上诉人的一个本案当中所涉及到的利息呢，应从2017年的12月21日计算到2018年的6月12日。利息合计21,795,727. • 发言者 8 01:10:11 68元。罚息的话呢是应自2018年的6月13日，计算到东源煤电，东源煤业向人民法院申请破产受理之日，即2019年的2月19日，期间的一个罚息为41,050,579.57元。复利的话呢是2018年的3月21日，计算到2019年的2月19日，复利的话是为1,918,206.23元，陈述完毕。 • 发言者 3 01:10:50 请董元芳发表辩论意见。 • 发言者 5 01:10:54 好的，关于那个上诉人提出的那个利息到2018年6月13日以后就已经宣布贷款提前到期，要按照相关的罚息进行计算呢。那个我方认为这一主张不符合双方的合同约定，因为双方在借款合同第24条第2款第2项里边已经明确约定，在借款人违那个违约以后呢，那个确实国家开发银行有权宣布贷款提前到期，但是在合同里边同时设定了一个义务，就是国家开发银行在宣布贷款提前到期的时候，应该是给东元公司发一个通知，然后要求限期偿还，就是在合同里边有非常明确的一个限期偿还的这么一个要求，那么我们认为限期偿还和立刻偿还是完全不同的两个概念。 • 发言者 5 01:11:55 那么本案的被上诉人立刻就要偿还。所以呢我们认为主张2016年2018年6月13日，贷款全部到期，作为贷款全部到期日呢，我们对此是有疑义的，认为没有合同依据。然后从公平的原则来说呢，因为本案涉金额是比较大的，光是本金就是将近8.37亿。你当天发通知就要求借款人当天就要全额偿还，这个严格来讲还是没给了一个合理的时间。还是有违一定的公平原则。所以呢我们不认可说那个贷款到期日是计算到2018年6月13日，这个是第1点。 • 发言者 5 01:12:48 第2点呢是关于那个复利的计算，复利的计算呢那个现在按照上诉人的主张呢是要求那个预期的利息也要计算复利，对此呢我们认为不应当予以计算，主要基于三个方面的原因。第1个方面的原因，从法律规定来看，人民币贷款人民币贷款相关规定呢那个已经明确说了，不好意思，请稍等一分钟。 • 发言者 9 01:13:23 不要着急。 • 发言者 5 01:13:25 人民币利率管理规定第21条中就明确的规定，对贷款期内不能按期支付的利息，按合同利率按季计收复利贷款利息后改按利罚息利率计收复利。那么我们认为这个规定呢说的很明白，它针对的仅仅只是对贷款期内不能按期支付的利息，而不是贷款逾期以后不能按期支付的罚息，这是法律的相关规定。那么合同从合同的约定来看呢，那个双方在合同第6条第4款里边关于合同的约定也是说的贷款人对借款人不能按期支付的利息计收复利，然后接着是表述为其中是一个包含关系，其中对不能按期支付的逾期借款或挪用的挪用借款的利息，这表述的也是利息，那么都没有提到罚息。 • 发言者 5 01:14:24 所以呢我们认为1将罚息作为计算复利的基数呢是没有合同依据的。然后再从那个司法实践来看呢，我们也注意到最高人民法院在201在2015年和2016年都有相关的民事判决书，对罚息是否能作为复利的计算基数呢有相关的判例，那么相关案例中呢也是支持被上诉人东源公司主张的这个想法的，也就是说罚息不能作为复利的计算基数。所以呢我们认为这一点不能上诉人呢该上诉请求呢不能成立。然后在上诉人的上诉请求里边呢，其中提到一句话就是要寄收要以2018年3月21日起的复利为本金再计算复利，那么我们认为复利再计算复利的这种计算方法是完全没有合同依据的，也违反相关的法律规定。 • 发言者 5 01:15:31 我们认为这一部分复利呢也应该予以相应的扣除。好，谢谢法庭。 • 发言者 3 01:15:45 请招银租赁发表辩论意见。 • 发言者 7 01:15:50 招银租赁不是国开行和东源煤电之间借款合同的当事人和参与方，我们尊重合议庭的审查结果。好。 • 发言者 3 01:15:58 那么各方是否还有反驳意见？要国开行 • 发言者 4 01:16:05 针对刚刚对方说的第1个问题，我们想做一个事实上的一个简要的描述。2017年12月21号的时候，对方实际上东源煤电公司已经逾期没有支付，他支付的利息计息日应该是2018年3月份到3月份的时候，他已经欠息了。在这个时候实际上这个对方已经构成了严重的违约。第2个在20在2018年6月13号发函之前，关于云南煤化工的破产以及这个东源煤电的无没有履约能力，这种信息实际上已经在云南省来讲大范围传播，作为国开行当时在了解到有关情况以后，行使的一个合法的，我们认为就是一个不安的一个抗辩权。 • 发言者 4 01:16:46 那么在这个时候主张收回贷款，我们认为是合理的。那么事实上来讲有没有合理的期限？我们认为不是在本案当中不应该是一个讨论焦点，因为即使对给了对方合理的期限，对方到目前为止也没有偿还。所以呢而且按照当时我们合同的约定，如果正常情况下，因为这个履约你先你迟延一段时间履约，那么这种情况下我们来考虑合理的期限，我认为还值得讨论，但在本案当中实际上从2017年年底到2018年期间，由于这个破产，而事实上也已经破产了，像对方也没有任何的履约能力，那么在此前提下，我们认为讨论这个给不给合理的期限，对于本案是没有意义的。 • 发言者 4 01:17:35 第2个关于这个第2个问题就是关于这个罚息复利这个问题呢，我们想提醒这个对方注意一下，因为我们在今天请求里面非常清楚利息是从什么时候到什么时候罚息复利，刚刚我们的另外一个代理人做了明确的阐述，所以对方所说的这个复利的复利是不存在的，我们主张的就是利息罚息和复利。 • 发言者 8 01:18:19 第2大点补充两点吧，就关于罚息的复利的话呢 • 发言者 6 01:18:23 在 • 发言者 8 01:18:25 国家开发银行与东源煤电的合同的第6条第4款的话呢做了明确的约定，对不按不能按期支付的预期借款或挪用借款的利息的话，按相应的罚息利率计收复利，那么在合同当中的话呢是已经是明确做出了相应的一些约定，上诉人所主张的对罚息部分按照罚息利率计收复利的话呢是有明确的一个合同依据，并且的话呢也不违反我们国家的相应的法律的一个强制性的一个规定，那么理应充分尊重。双方当事人的一个意思自治，那么按照合同的约定进行履约。 • 发言者 8 01:19:03 那么对该问题的话呢我们也向法庭做一个强调，东源煤，东源煤电是没有向法院提起上诉的。没有提向法院提起上诉的。在一审判决一审判决的话呢是对上诉人主张的罚息的复利部分的话呢是已经获得了一个支持，本着一个不告不理的一个原则的话呢，那么本案当中的话呢，也对于罚息部分的复利的话呢，也理应依法支持上诉人的一个请求。我们就补充这点，其他的没有了。好。 • 发言者 5 01:19:37 好，针对那个国开行的代理辩论意见呢，我方补充一下。首先第1点呢是那个我们不否认有严重的违约行为，你们有权国开行有权宣布所有贷款提前到期。但是呢我们提出来的是你宣布提前贷到期的话，应该给一个合理的时间，而且合同约也约定，应该是限期偿还。那么那个这是第1点。第2点呢关于复利，国开行认为在合同约合同中有明确的约定，我方认为合同约定是不明确的，因为刚才提到的这个条款呢，第1它是一个包含关系，它表述的为其中第二呢他没有说罚息计算复利，而是说利息计算复利，那么我们认为合同约定是有争议的。 • 发言者 5 01:20:21 那么按照最高人民法院相关司法解释呢，不管是我们刚才提到的限期，他因为限期也没有说限多少天，然后呢也不管是这个合同第6条第4款，那个相关的利息还是指罚息，那么我们认为在双方现在是双方都出现了一个理解上的一个不同。那么这个合同呢是国开行提供的一个格式文本，那么按照国司法解释，关于格式合同文本相关的那个解释呢，是认为当对合同条文出现不同的理解的时候，应当由格式合同提供一方承担相关的不利的对格式合同提供一方做出不利的解释。 • 发言者 5 01:21:05 那么我们认为第一限期你好， • 发言者 3 01:21:29 合议庭有其他有没有提问？ • 发言者 6 01:21:38 嗯 • 发言者 3 01:21:40 下面进入第3个争议焦点。东源煤电东源煤业是否应当连带给付违约金？请国开行发表辩护意见。 • 发言者 8 01:22:00 好的，法庭。上诉人认为本案当中东源煤电东源煤业的行为的话呢，是已经是构成了一个违约，那么应当向国家开发银行支付相应的一个违约金。第1点是在上诉人和被上诉人之间的借款合同第24条第3项的话呢，是明确约定对被上诉人发生违约时应承担的一个违约责任的话呢进行了明确，那么属双方当事人的一个意思自治。对双方的话呢是均具有法律约束力。根据该项的一个约定，在被上诉人出现违约事项时的话呢，那么理应按照理应向上诉人的话呢是支付那么千分支1的这么一个违约金。 • 发言者 8 01:22:44 那么第2点的话呢是本案中东源煤电没有按照借款合同第13条及第14条的相关的约定呢，配合上诉人办理相应的账户管理及柜台前移的相应的一些手续，其对于本案中被上诉人的违约事项，那么需被上诉人主动到上诉人。处理相关的处理相关的一个事项，那么并且进行相应的一些办理。对于被上诉人是否办理是否违约等相应的一个举证责任的话呢，是应当是在被上诉人一方，不在上诉人一方。本案中的罚息复利违约金的一个金额的话呢，也没有超过法定的一个最高的标准。 • 发言者 8 01:23:34 因此的话呢上诉人的话呢理应依约向 • 发言者 3 01:23:45 请中原银行发表好的一件。 • 发言者 5 01:23:50 针对 • 发言者 4 01:23:52 上诉人的意见呢我们做以下回复。 • 发言者 3 01:23:56 第一呢是上诉人呢没有举证证明 • 发言者 4 01:24:02 东源煤电存在违反柜台前移和账户管理的这么一个举证， • 发言者 11 01:24:10 在本案的一审庭审过程中，二审庭前会议中，今天的庭审过程中呢，国家开放银行始终没有向人民法院进行举证，因此呢这个举证不能的后果呢应由其自行承担，这是第1点。第2点呢如果国家开发银行认为东源煤电存在违约行为，按照合同的约定，国家开发银行呢必须对东源煤电的行为进行限期纠正，如果东源煤电不予纠正的，国家开发银行才有权主张违约金。但是实质国家开发银行提起诉讼之日呢，始终没有向东源煤电发出过任何纠正任何行为的这么一个书面的函件，或者进行过任何的告知。 • 发言者 11 01:24:58 因此呢我们认为国家开发银行驳回其上诉请求，完毕。好。 • 发言者 3 01:25:31 招银租赁发表辩论意见。 • 发言者 7 01:25:34 招银租赁不是该解释时的参与方，我们尊重合议庭的审查结果。好。 • 发言者 3 01:25:40 嗯。各方还有无反驳意见，国开行。 • 发言者 4 01:25:46 没有了，谢谢。嗯。 • 发言者 3 01:25:49 这个东方东元方 • 发言者 11 01:25:52 东元也没有了。这个 • 发言者 3 01:25:56 我们合议庭法各位法官有什么嗯那么我们三个主要的争议焦点呢调查和辩论到这儿。那么各方当事人对于本案还有什么其他的补充意见？ • 发言者 4 01:26:27 没有了，审判长。 • 发言者 8 01:26:30 没有了， • 发言者 5 01:26:31 没有 • 发言者 7 01:26:32 专业组里没有。好。 • 发言者 3 01:26:36 对各方当事人的意见法庭已充分注意并记录在案。在评议时将给予充分的考虑。今天的法庭调查和法庭辩论，就到这里。根据中华人民共和国民事诉讼法第9条，第142条的规定，人民法院审理民事案件应当根据自愿和合法的原则进行调解。判决前能够调解的可以进行调解。调解不成的应当及时判决。在本案开庭审理之前，由于本案这个案涉金额巨大，法律关系复杂，合议庭呢多次到案发地，就是包括设备所在地，进行调查走访。那么同时也在进行了召开了庭前会议。 • 发言者 3 01:27:57 那么在调查走访和庭前会议中，我们认为通过调解能够实现个案审判，与调结构。去产能供给侧改革的高度统一。实现个案审判与绿色发展理念的统一。实现个案审判中债权保护与债务人利益保障的统一。我能够达成调解。这个在此法庭再次询问你们是否愿意在法庭主持下进行调解。国开行 • 发言者 4 01:29:13 国开行愿意在法庭这个明确基本的事实和这个双方的责任以后呢，进行调解，并且考虑希望法庭提出合理的这个能够让双方接受的调解方案，谢谢。 • 发言者 3 01:29:30 董元芳。好的，法庭那个 • 发言者 5 01:29:34 在就调解发表相关意见以前呢那个想占用合议庭一点时间，对动员公司的一些情况了吗 • 发言者 10 01:29:46 做一些介绍，希望法庭能够予以准许。好。 • 发言者 5 01:29:52 东源公司呢是这样，它是以那个煤炭开采和那个煤炭经营为主营业务的这么一个国有企业， • 发言者 10 01:30:01 那么那个在近些年呢那个受宏观经济下行等因素的一些影响呢， • 发言者 5 01:30:06 那个下游的化工 • 发言者 10 01:30:08 钢铁甚至于火电这些这么一些行业了嘛，都出现了一个需求的一个严重的一个萎缩。那么就导致我们每相关的煤炭整个行业呢的景气度了嘛就下降的比较厉害。那么由于需求下降，产品的那个价格呢也是掉的非常厉害，从而就导致了东源公司的一个经济上的一个严重困难。然后其实在2015年下半年的时候，东源公司就出现了一个资金链断裂的这么一个情况，整个企业呢应该是出现了一个举步维艰亏损严重，然后债务负担非常沉重。的这么一个问题。 • 发言者 5 01:30:50 我们也做了一个统计， • 发言者 10 01:30:52 就是在2019年2月19日那个宣那个人民法院受理破产重整的这个时点呢，那个东源公司它光是负债就已经高达76.2亿元， • 发言者 5 01:31:03 应该说是公司 • 发言者 10 01:31:04 的整个情况是非常常困难的。 • 发言者 5 01:31:07 然后那个到了2016年的时候呢，那个 • 发言者 10 01:31:10 东研公司这边也因为国家有一个整体的一个去产能的这么一个政策，东研公司也是积极响应，但是呢由于去产能那个公司的整个生产能力下降又 • 发言者 5 01:31:22 涉及到要安置 • 发言者 10 01:31:24 职工13,000多人了吗？整整体加剧了那个东研公司的一个经营的那么一个困难，然后职工呢应该说也非常的困难，这。边可能最困难的时候出现了有将近半年没有发工资的情况，不仅没有发工资相关的社会保险了吗？也是出现了一个严重的拖欠。那么对于职工来说，尤其是医保这一块了吗？应该说都是非常担心的。那么这个确实职工这职工的情绪各方面都非常低落，整个企业状况也非常的糟糕。那么在这么一个困局下呢，那个东研公司也是积极的在想办法，比如说做一些转型升级的这么一些努力，包括呢那个优化相关的资源配置，淘汰落后的产能，甚至于那个僵尸企业的出清了吗这些。 • 发言者 10 01:32:20 措施都积极的但是确实是有点积重难返吧，企业尽管做了很多的尝试和努力，那也最终也是避免不了走入破产重整的这么一个程序。那么也确实那个希望那个各各家债权人能够理解那个动员公司的这个处境，不是不想还钱，确实是这个整个负债情况非常糟糕，没有能力还钱。基于这么一个现状呢，那个我们就还是说是法院提出的这个调解的这个想法呢，我们也是积极的响应，非常的支持，也谢谢法庭。就说呢那我们那个但是呢我们也希望就是说在调解的过程中，要考虑东源已经进入破产重整这么一个程序了吗？ • 发言者 10 01:33:19 能不能把相关的债权予以考虑。然后呢我们也希望在人民法院的主持下呢，那个作为一个既不损害债务人利益的情况下，最大限度的保障债权人利益的一个实现，我们觉得我们是有这个愿望的。最后呢那个我们也代表东源公司对我们那个在座的国开行以及那个招银金融助力公司呢表示感谢，谢谢你们那个在过去企业经营过程中给予企业的一个支持，以及目前企业进入破产成重整程序以后，你们给予那个整个破产工作的一个支持。我们对此表示感谢。我们那个衷心希望通过和解呢那个大家实现利益的一个最大化。 • 发言者 10 01:34:10 好，谢谢法庭。 • 发言者 3 01:34:14 招银助力。 • 发言者 5 01:34:17 考虑到东源煤电目前的实际情况，招引租赁同意调解。希望合议庭在查明事实以及结合综合考虑各方的违约情况过错情况的情况下，这个主持调解。好。 • 发言者 3 01:34:35 最高人民法院关于人民法院民事调解工作若干问题的规定，第8条规定，当事人可以自行提出调解方案。组织调解的人员也可以提出调解方案，供当事人协商参考。中华人民共和国民事诉讼法第93条的规定，人民法院审理民事案件在事实清楚的基础上，分清是非，进行调解。下面合议庭将休庭对争议问题进行评议。并请各方当事人协商调解方案。现在休庭。全体起立。请审判长。请坐下。现在恢复开庭。刚才合议庭根据审查查明的事实，和各方的诉辩意见，对三个争议点进行了评议。 • 发言者 3 01:36:32 结合联系我国动产担保及融资租赁登记不完善的现实背景。统一处置争议的5套设备在内的整体设备。能够最大化保护各方当事人的利益。合议庭在此基础上提出了调解方案，并在休庭时征求了各方当事人的意见。下面我宣读调解方案。以确定各方债权债务1国开行对东源煤电的债权扣除破产中已经清偿的本金外，利息罚息复利的计算方式为利息。2017年12月21日至2018年6月12日期间，利息合计2179.5727万元。罚息2000、2018年6月13日至2019年2月19日期间合4105. • 发言者 3 01:38:07 0579万元。福利2018年3月21日至2019年2月19日期间，合计191.8206万元。以上三项共共计6474点4513万元。2在东源煤电东源煤业破产重整程序中，已确定的招银租赁对涉案6项设备享有所有权。对应的债权数额是1377.4137万元。确定国开行对93项设备有抵押权。招银租赁对6项设备有所有权，招银租赁和国开行对以以上案涉全部发电设备整体盘活处置。并从变现款中实现各自的债权。在本案调解书生效后20日以内，在由国开行向本案的一审法院提出执行申请，启动司法处置程序，变现的价款双方各得50%。 • 发言者 3 01:39:46 实现的费用双方各担50%。国开行招引主力未实现的债权待执行。法院出具体本裁定后，按照破产重整计划中的预留方案实现债权。若破产管理人对招银租赁的债权不予纳入预留方案，有东源煤电按照此前招银租赁在东源煤电破产重组程序中有担保清偿方案予以清偿。如果司法变现不能国开行和招银租赁的权益，通过前述方法实现实践后均放弃对上述案涉设备的权益。由东源曲靖电力自主生产经营。4对上述案涉设备上的管理费用由东源曲靖电力承担。 • 发言者 3 01:41:03 东源曲靖电力无条件配合司法处置。各方对一审判决第2项第4项无争议，按照其判项内容在调解书中确认。61审诉讼费用中对于国开行诉请部分按照一审判决执行。对于招银租赁诉请部分的诉讼费用，由二审法院按照规定，根据争议财产对应的债权数额计算后，由国开行承担。二审诉讼费用由法院依法确定后，由国开行和东源煤电各承担50%。7本协议签订后，各方之间就本案涉及的问题不再存在任何争议。各方当事人对调解方案有无异议或者修改意见或者补充意见？ • 发言者 4 01:42:21 国开行没有异议，也没有修改意见。 • 发言者 10 01:42:25 东营公司方面没有异议，也没有新的修改意见。 • 发言者 5 01:42:32 噪音租赁没有异议。嗯。 • 发言者 3 01:42:38 鉴于各方对调解协议条款均无异议，请各方诉讼代理人依次在调解协议正式文本上签字。经本院组织调解，各方当事人自愿达成的调解协议。不违反法律规定，本院予以确认。并在庭后根据中华人民共和国民事诉讼法第97条的规定出具调解书。调解是高质量审判。调解是高效益的审判。各方当事人在分清是非的基础上，众谋合作共赢的大局意识。让个案的争议得以更好的解决。云南煤化工集团东源煤业东源煤电的破产重组得以圆满收官。企业得以重生并良性发展。 • 发言者 3 01:47:03 金融债权已得到充分保护。通过本案的审理，我们还发现本案设计的生产设备等动产抵押权与融资租赁物所有权的冲突，是司法实践中的普遍性的难题。金融风险防控还有较大的空间，其根本的原因是我们国家还未建立统一的动产登记制度，现有的动产融资租赁登记系统和动产抵押登记系统尚缺乏有效的衔接。未从根本上防范和解决此类矛盾纠纷。我们将根据最高人民法院关于加强司法建议工作的意见的规定，向有关部门提出司法建议。共同推进国家治理的现代化。 • 发言者 3 01:48:18 今天的庭审到此结束。阅看庭审笔录并签名。如有遗漏和差错可以申请补正。现在闭庭。 | D7: # 庭审概况 本案为国家开发银行（上诉人）与云南东源电力股份有限公司、云南东源曲靖电力有限公司、招银金融租赁有限公司（被上诉人）之间的金融借款合同纠纷案，不服云南省高级人民法院2018云民初88号民事判决。庭审由审判员李少平担任审判长，与魏文超、黄年、王海峰、葛洪涛组成合议庭，法官助理张瑞参与审理。庭审围绕三个争议焦点展开：一是抵押权与融资租赁权的冲突问题；二是罚息复息的计算及起算日期是否认定错误；三是东源煤电与东源煤业是否应连带给付违约金。最终，合议庭在查明事实基础上提出调解方案，各方当事人达成调解协议。 # 原告诉称与被告辩称 | 方 | 诉讼请求/答辩意见 | 事实与理由 | | --- | --- | --- | | 上诉人国开行 | 要求确认抵押权有效，主张罚息复息计算正确，要求支付违约金 | 1. 2015年12月2日东源公司邮件未明确告知设备存在融资租赁情况<br>2. 东源煤电未履行账户管理及柜台前移义务构成违约<br>3. 国开行已履行审慎核查义务，抵押权成立 | | 被上诉人东源公司 | 反对国开行主张的罚息复息计算方式，认为违约金主张不成立 | 1. 2015年12月2日邮件中红色标注设备名称，应引起国开行注意义务<br>2. 东源煤电已进入破产重整程序，无力承担高额债务<br>3. 东源煤电与东源煤业为独立法人，不应承担连带责任 | | 被上诉人招银租赁 | 支持东源公司意见，主张设备所有权归其所有 | 1. 东源煤电出资行为构成无权处分<br>2. 国开行未履行查询义务，不构成善意取得<br>3. 设备所有权与抵押权可并存，不影响各自权利 | # 举证与法庭调查 ## 证据提交 - **国开行提交**： 1. 2015年12月22日签订的抵押合同 2. 2018年9月的融资租赁查询证书 3. 2018年6月13日要求偿还贷款本金的函件 4. 证据54页、58页：设备权属证明材料及股东会决议 5. 证据108页：融资租赁登记核查表 6. 证据68页：利息罚息复息计算明细 - **东源公司提交**： 1. 2015年12月2日邮件及附件《东源公司融资情况统计表》 2. 2013年、2015年审计报告（证据82页、95页） 3. 东源煤电与东源煤业共同委托代理人证明 4. 东源煤电破产重整相关文件 - **招银租赁提交**： 1. 2012年融资租赁合同及设备交付证明 2. 证据7页：回租设备清单 3. 证据137万元债权确认文件 4. 2019年2月19日破产重整受理文件 ## 法官询问要点 1. **融资租赁登记性质**： - 国开行认为人民银行规定属行业强制性规范，仅需核查抵押人曲靖电力公司 - 招银租赁主张登记具有对抗效力，登记虽非法定物权登记，但可作为善意判断标准 - 东源公司认为登记属行业指导性规范，不当然产生物权后果 2. **查询方式与标准**： - 国开行确认仅使用单位查询方式 - 招银租赁指出可通过单位名称或设备信息查询 - 法官强调登记系统间信息不对称问题，建议行业协会推动行业惯例形成 3. **罚息复息争议**： - 国开行主张按合同约定计算，利息2179.5727万元、罚息4105.0579万元、复利191.8206万元 - 东源公司认为罚息不应计算复利，且未给合理期限 - 法官询问合同条款解释争议，指出格式合同解释应倾向非提供方 4. **调解可行性**： - 法官指出本案涉及去产能政策背景，企业经营困难 - 东源公司补充说明职工安置困难及破产重整情况 - 各方均表示愿意调解，但强调应考虑破产重整程序 ## 辩论交点 - **抵押权与融资租赁权冲突**： - 国开行强调已履行审慎义务，设备属曲靖电力公司所有 - 东源公司指出邮件中设备名称一致且红色标注，应引起注意 - 招银租赁主张设备交付即取得所有权，国开行未尽查询义务 - **利息计算争议**： - 国开行主张2018年6月13日贷款到期，罚息应从该日起算 - 东源公司认为合同约定需限期偿还，且罚息不应计算复利 - 法官指出需结合合同条款与司法实践，格式合同解释应倾向保护债权人 - **调解方案讨论**： - 国开行同意调解但要求合理方案 - 东源公司强调破产重整程序中的债权处理 - 招银租赁同意调解但要求确认所有权优先地位 # 庭审结果 本案达成调解协议，主要内容包括： 1. 国开行债权确认：扣除已清偿本金后，利息2179.5727万元、罚息4105.0579万元、复利191.8206万元，共计6474.4513万元 2. 招银租赁债权确认：1377.4137万元 3. 涉案设备处置：东源曲靖电力公司93项设备抵押权归国开行，6项设备所有权归招银租赁，双方同意整体盘活处置，变现款各得50% 4. 诉讼费用承担：一审诉讼费用按判决执行，二审诉讼费用由国开行与东源煤电各承担50% 5. 后续债权实现：未实现债权待执行法院裁定后，按破产重整计划预留方案处理 6. 司法建议：合议庭将就动产登记制度不完善问题向有关部门提出司法建议 | E7: 5 | F7: 4 | G7: 4 | H7: 0 | I7: =(E7+F7+G7)/3 -> 4.3333333 | J7: 3.2:部分小标题概括性一般；2.2:对庭前会议等背景环节比例略低 | K7: 本次庭审围绕金融借款合同纠纷展开，涵盖了抵押权与融资租赁物所有权冲突、罚息复利计算及违约金承担等核心争议，并最终在法院主持下达成调解协议，明确了各方债权债务的确认与实现路径。 出庭人员身份核对 各方当事人及代理人身份确认 上诉人国家开发银行委托代理人邓劲松、刘双俊，均为北京德恒昆明律师事务所律师，代理权限为特别授权。 被上诉人云南东源电力股份有限公司、云南东源曲靖电力有限公司共同委托代理人吴学成、黄城镇，系云南勤业律师事务所律师，代理权限为特别授权。 云南东源煤业集团有限公司委托代理人李青海（公司员工）及吴学成，代理权限为特别授权。 被上诉人招银金融租赁有限公司委托代理人万海龙（公司员工）、陈志超（上海银泰律师事务所律师），代理权限为全权代理。 合议庭组成人员公示 本案由审判员李少平担任审判长，与审判员魏文超、王年、王海峰、葛洪涛组成合议庭，法官助理张瑞。各方对合议庭成员无异议。 案件基本事实与程序事项 案件来源与审理程序 本案系上诉人国家开发银行不服云南省高级人民法院2018云民初88号民事判决提起的上诉，案由为金融借款合同纠纷，涉及云南东源电力股份有限公司、云南东源曲靖电力有限公司、招银金融租赁有限公司。 法院依据《中华人民共和国民事诉讼法》第134条第一款、第169条规定依法组成合议庭公开审理。 诉讼文书送达情况 各方当事人均已收到受理案件通知书、应诉通知书、开庭传票等诉讼文书，且均在开庭前三日收到，程序合法有效。 诉讼权利义务告知 法庭已向各方释明二审期间的诉讼权利与义务，各方表示清楚。 争议焦点一：抵押权是否构成善意取得 国家开发银行主张其已尽审查义务 国开行主张在办理抵押登记时已对曲靖电力公司名下设备所有权进行合理审慎核查，包括查阅工商出资证明、股东会决议及相关权属材料（证据54页、58页），确认设备所有权归属曲靖电力公司。 提交2018年对曲靖电力公司融资总额的核查表（证据108页），显示该公司名下无融资租赁登记记录，主张已履行行业规范要求的查询义务。 强调企业法人独立性原则，认为无需对母公司东源煤电或其他关联企业进行全面筛查；设备为通用设备，无唯一识别码，调查范围应限于抵押人本身。 主张评估报告显示曲靖电力公司在建工程价值5.7亿、机械设备价值5.1亿，虽未纳入资产负债表，但不影响权属存在，结合现场勘查与审计报告，足以确信抵押权完整无瑕疵。 招银金融租赁反驳国开行未尽查询义务 指出国开行提供的2018年查询证明不符合规定，应在2015年抵押时点进行查询，而非事后补证。 强调借款人东源煤电与抵押人曲靖电力公司存在全资控股关系，国开行应对东源煤电的设备来源进行延伸审查。 主张其已于2012年通过售后回租取得设备所有权，并在央行征信中心融资租赁登记系统完成登记，上传包含设备名称、数量、原值、净值、出厂时间、生产厂商及存放地点（恩洪矿区煤矸石电厂）的完整清单，足以引起注意。 认为东源煤电将属于第三方所有的设备作为出资注入曲靖电力公司属无权处分行为，不发生物权效力。 关于融资租赁登记性质的辩论 国开行认为央行融资租赁登记系统属行业内部强制性规范，目的在于防范金融风险，具有对抗效力。 招银租赁主张该登记虽非法定物权登记，但在判断“善意”时具关键意义，银行未按规范在抵押前查询即不构成善意。 东源方认为登记仅为指导性规范，不当然产生物权后果，但承认其在争议中可作为判断善意的重要依据。 技术性问题讨论 双方确认涉案设备为通用发电设备，无发动机号或车架号类唯一标识码，名牌仅标注型号与参数，增加识别难度。 登记系统支持以公司名称或设备信息两种方式查询，但种类物需依赖详细登记要素才能区分。 招银租赁承认部分设备因交付初期未设唯一编码，未能登记具体识别码，但存放地点描述清晰明确。 争议焦点二：罚息与复利计算是否正确 国家开发银行主张一审认定有误 利息应自2017年12月21日起算至2018年6月12日，合计2179.5727万元。 因被上诉人违约，国开行于2018年6月13日发函宣布贷款提前到期，故罚息应自该日起算至破产受理日2019年2月19日，金额为4105.0579万元。 复利依合同第六条第四款约定，针对逾期利息按罚息利率计收，期间为2018年3月21日至2019年2月19日，金额为191.8206万元。 东源方反对立即到期与复利基数扩大 虽认可合同赋予国开行宣布提前到期的权利，但强调须给予“限期偿还”的合理期限，不能要求当日清偿，主张以通知发出日作为到期日显失公平。 反对将“罚息”本身作为复利计算基数，指出《人民币利率管理规定》第21条仅允许对贷款期内欠息计收复利，逾期后仅能对本金计罚息。 合同条款表述为“不能按期支付的利息”，未明确包含罚息，且格式合同应作不利于提供方的解释。 明确反对“复利再计复利”的计算方式，认为无合同与法律依据。 争议焦点三：东源煤业是否应连带支付违约金 国家开发银行主张违约金成立 依据借款合同第24条第三项，被上诉人违约应承担日千分之一违约金。 指控东源煤电未依约配合办理账户管理及柜台迁移手续，构成违约，举证责任应在对方。 东源方抗辩违约金请求不成立 国开行始终未就“未配合办理事项”提交任何证据，应承担举证不能后果。 即便存在违约行为，合同亦要求先行发出纠正通知，而国开行从未履行该前置程序，直接起诉主张违约金不符合约定条件。 法院引导调解与背景陈述 法院推动调解动因 鉴于案涉金额巨大、法律关系复杂，合议庭曾赴设备所在地调查并召开庭前会议，了解到各方均有调解意愿。 强调调解有助于实现个案审判与去产能改革、绿色发展理念融合，兼顾债权保护与债务人重生。 东源方陈述经营困境 受宏观经济下行影响，煤炭行业长期低迷，导致企业营收锐减、债务沉重。 截至2019年2月19日，负债已达15亿元，职工人数逾13,000人，曾出现半年未发工资、社保医保严重拖欠情况。 已采取转型升级、淘汰落后产能等措施，但仍难扭转局面，现处于破产重整程序，缺乏偿债能力。 表示并非恶意逃债，恳请债权人理解现实困难，支持通过调解化解纠纷。 招银金融租赁表态支持调解 考虑到东源煤电实际经营状况，愿意在查明事实基础上参与调解。 法院宣读调解方案 债权数额确认 国家开发银行对东源煤电的未清偿债权合计6474.4513万元，含： 利息：2179.5727万元（2017/12/21–2018/06/12） 罚息：4105.0579万元（2018/06/13–2019/02/19） 复利：191.8206万元（2018/03/21–2019/02/19） 招银金融租赁对涉案六项设备享有所有权，对应债权额为13774.1137万元。 设备处置机制 明确国开行对93项设备享有抵押权，招银租赁对其中6项设备享有所有权。 双方同意对全部案涉发电设备进行整体盘活处置，变现价款由双方各得50%，相关费用各担50%。 国开行应在调解书生效后20日内向一审法院申请执行，启动司法变现程序。 债权补充实现路径 若变现款不足或无法变现，未实现债权按破产重整计划中的预留方案继续清偿。 如破产管理人不予纳入预留方案，则由东源煤电依此前担保清偿方案予以清偿。 实现债权后，双方放弃对案涉设备的一切权益，设备由东源曲靖电力公司自主生产经营。 其他安排 案涉设备日常管理费用由东源曲靖电力公司承担，其须无条件配合司法处置。 一审判决第二项、第四项内容在调解书中予以确认。 诉讼费用分担： 一审中涉及国开行诉请部分按原判执行； 涉及招银租赁诉请部分由二审法院依债权比例核定后，由国开行承担； 二审诉讼费由国开行与东源煤电各承担57%。 协议效力 本协议签署后，各方就本案所涉事项再无任何争议。 AI洞察 动产担保与融资租赁权利冲突暴露制度短板：本案核心矛盾源于我国尚未建立统一的动产权利登记体系，央行融资租赁登记系统与市监局动产抵押登记系统互不联通，导致“一物二押”风险难以规避。 金融机构合规操作存在灰色地带：尽管央行明确要求抵押前查询融资租赁登记，但实践中银行常以“系统无记录”或“仅查抵押人”为由推责，反映出行业自律与监管执行间的落差。 破产重整背景下司法调解更具现实合理性：面对企业严重资不抵债、职工安置压力巨大的现实，法院通过调解统筹债权实现与企业重生，体现了司法裁判从“刚性裁断”向“综合治理”的功能延伸。 待办 国家开发银行在调解书生效后20日内向一审法院提出执行申请，启动司法程序变现案涉设备 章节 00:00:19 法庭纪律与开庭准备 会议开始时，主持人宣布恢复法庭纪律，要求全体人员起立以示对法庭的尊重，并强调庭审活动中应遵守的行为规范，包括禁止鼓掌、喧哗、使用通讯工具及擅自录音录像。随后确认各方当事人到庭情况，完成身份核对和诉讼代理权限确认，为正式开庭做好准备。 00:05:48 案件基本信息与当事人身份确认 审判长宣布本案为国家开发银行因金融借款合同纠纷提起的上诉案，依法组成合议庭公开审理。会上逐一核实上诉人国家开发银行及被上诉人云南东源电力股份有限公司、云南东源曲靖电力有限公司、招银金融租赁有限公司等各方出庭人员的身份及其代理权限，并确认无异议，同时告知合议庭成员构成及相关诉讼权利义务。 00:07:45 抵押权争议：告知义务与尽职调查范围 上诉人国家开发银行代理人主张其已履行合理审查义务，指出对方未明确告知设备存在融资租赁关系，且在2015年邮件中关于融资情况的统计表仅为并列信息，不构成有效通知。同时强调金融机构仅需对抵押人名下资产进行核查，无需扩展至关联企业。招银租赁则反驳称其已在系统中登记相关信息，国开行未尽查询义务，不应构成善意取得。 00:14:07 设备权属争议：通用设备识别与登记问题 双方围绕涉案设备是否可识别展开辩论。国开行指出设备为通用设备，无唯一编码，无法通过型号精确比对；而招银租赁提交的回租清单虽缺型号信息，但提供了出厂日期（2012年），早于国开行所称抵押设备生产时间（2013年后）。此外，招银租赁强调已在人民银行征信中心上传完整租赁物清单，包含存放地点等关键信息，足以引起注意。 00:16:27 抵押登记合规性与善意取得认定 国开行主张其在办理抵押时已尽审慎义务，审查了工商出资证明、股东会决议等文件，确认设备所有权归属曲靖电力公司，并依据行业规范进行了融资租赁登记查询。尽管未能提供当时查询记录截图，但仍主张行为合规。招银租赁则认为，未在抵押时点查询央行登记系统即属重大疏忽，不能构成善意取得，且东源煤电将他人财产出资属于无权处分。 00:19:29 担保物权与所有权并存问题及司法判决协调 国开行提出即使招银租赁享有设备所有权，亦不影响其抵押权作为担保物权的存在，两者可在法律上并存。同时指出上海中院一审判决仅判令返还设备，并未确权，故不构成本案障碍。招银租赁回应称所有权优先于担保物权，尤其在已登记情形下应受保护。法院进一步探讨了不同权利之间的冲突解决机制。 00:22:26 融资租赁登记系统的性质与查询义务标准 各方就中国人民银行征信中心融资租赁登记的法律性质展开讨论。国开行认为该登记为行业指导性规范，不具备强制物权效力；而招银租赁坚持其具有对抗效力，银行未按规查询即违反风控义务。法院询问具体查询方式，确认可通过企业名称或设备信息查询，但种类物识别存在困难。争议焦点在于是否必须查询以及查询程度如何界定。 00:36:01 举证责任分配与审查义务边界 针对司法解释第九条规定的善意取得条件，各方就举证责任展开辩论。出租人主张应由第三人（银行）证明已查询登记系统；国开行则辩称已尽合理审查义务。争议还涉及审查范围是否应延伸至母公司东源煤电的权属来源。法院关注是否存在格式条款解释规则适用问题，即当合同理解发生分歧时，应作不利于提供方的解释。 00:46:52 动产担保制度缺陷与系统整合建议 国开行指出当前动产抵押与融资租赁登记分属不同系统（市监局与央行），信息不通导致交易风险上升，影响企业融资能力。建议推动立法统一登记制度，发挥行业协会作用形成行业惯例，并通过技术手段实现跨平台数据互通。同时呼吁企业主动登记以增强权利外观，共同防范权利冲突，促进市场信用体系建设。 00:56:47 罚息复利计算与违约金争议 国开行主张一审判决对罚息、复利起算时间认定错误，认为应自2018年6月13日发函宣布贷款提前到期日起算，利息计至该日前，罚息自此日起至破产受理日止，复利亦应相应计算。东源方反对立即到期主张，认为需给予合理偿还期限，且合同未明确允许对罚息计收复利，相关请求违反法律规定及公平原则。关于违约金，国开行主张依约支付千分之一违约金，但东源方指出其未履行催告纠正程序，且无证据证明违约事实，故不应支持。 01:11:47 调解意愿表达与企业困境说明 各方均表示愿意接受调解。东源方详细陈述企业因宏观经济下行陷入经营困境，负债高达15亿元，职工工资及社保长期拖欠，已进入破产重整程序。强调并非恶意逃债，而是无力清偿，恳请债权人理解。招银租赁基于现实情况也同意调解。法院肯定调解有助于实现债权保障与企业重生的平衡，符合绿色发展理念与供给侧改革方向。 01:19:01 合议庭调解方案宣读与协议确认 法院综合查明事实与各方意见，提出调解方案：明确国开行债权总额约6474万元，招银租赁对六项设备享有所有权，对应债权1.37亿元；双方共同处置全部发电设备，变现款各得50%，费用均摊；若变现不足，则依破产重整预留方案清偿；管理费由曲靖电力承担；诉讼费用依比例分担。各方当场确认无异议，签署调解协议。法院予以确认并将于庭后出具调解书，标志着案件圆满解决。 | L7: 5 | M7: 4 | N7: 4 | O7: 0 | P7: =(L7+M7+N7)/3 -> 4.3333333 | Q7: 2.3:章节部分保留较多原文叙述,略显冗余；3.1:个别标点如逗号过长句偏多 | R7: 会议笔记： 案件基本情况 案件性质：国家开发银行与云南交易金融借款合同纠纷上诉案 审理法院：中华人民共和国最高人民法院 原审判决：云南省高级人民法院2018云88号民事判决 审理程序：公开开庭审理，依法组成合议庭 出庭人员身份核实 上诉人国家开发银行委托代理人权限为特别授权代理 法庭询问各方当事人是否收到开庭前3日送达的二审诉讼请求材料 抵押设备相关争议 讨论15 10亩电铲设备在建工程抵押手续办理情况 招银租赁提交的回租设备清单仅载明名称，无型号信息 抵押设备品牌均为2013年12月后生产，而调查显示2012年3月1日已有抵押记录 国家开发银行主张已对设备所有权尽到审慎审查义务，提交了18亿设备权属信息材料 招银租赁强调售后回租设备的所有权问题，援引上海市中级人民法院相关判断 设备抵押登记与审查 争议设备是否存在在先抵押权及权属瑕疵问题 要求提供相关报表，审查两家公司抵押设备名称一致性问题 国家开发银行被指在办理抵押时未充分审查设备权属 讨论设备唯一识别性问题，现有附件清单包含设备名称及部分参数 涉及5套发电设备，其中发电机2台 借款罚息与利息计算争议 合同到期日为2018年8月，实际计算至2018年6月12日 国家开发银行宣布贷款到期时未给予合理期限，直接要求当天全额偿还 双方对罚息计算存在争议，涉及合同第六条和第二十一条规定 被上诉人主张按最高人民法院相关司法解释及2015-2016年民事判决案例处理 国家开发银行未按合同约定向东源煤电发出限期纠正通知，直接主张违约金 调解方案 明确2018年3月21日至2019年2月19日期间债权数额为8206.23万元 招银租赁对涉案六项设备享有所有权，债权数额1377.437万元 案涉全部发电设备整体变现补偿，实现各自债权 调解生效后20日内向一审法院申请启动变现程序，费用双方各担50% 变现款不足或不能时，按东源煤电破产重组程序中清场方案处理 程序事项与法庭总结 庭前已召开庭前会议，调查走访相关情况 法庭认为通过调解能实现个案审判中的债权保护 指出案件根本问题在于我国尚未建立完善的动产抵押登记制度 各方当事人对调解协议基本达成一致 后续安排： 各方确认调解协议内容 调解生效后20日内向一审法院申请启动变现程序，并按规定分担设备变现相关费用 二审法院按规定处理一审诉讼费用 AI建议： AI建议 AI已识别以下会议中未得出结论或缺乏明确行动项的问题，请注意： 抵押设备权属争议尚未完全解决，需进一步审查设备所有权证明材料 设备唯一识别性问题未明确解决方案，可能影响后续变现程序 借款罚息计算标准存在理解分歧，需明确适用的合同条款和法律依据 国家开发银行是否履行了合同约定的通知义务仍有争议 动产抵押登记制度不完善问题需向有关部门反映，推动制度建设 内容由 AI ⽣成，仅供参考 | S7: 3 | T7: 3 | U7: 3 | V7: 0 | W7: =(S7+T7+U7)/3 -> 3 | X7: 1.3:债权数额1377.437万元与原文13774.1137万元数值提取错误；1.2:将'东源煤电'误写为'交易'；3.1:存在'15 10亩电铲设备'等乱码表述；2.1:未明确最终调解方案细节
A8: 7 | B8: 申家坤 | C8: • 发言者 1 00:11 我们可以开始了吗？可以了。好的，那我们开始开会。尊敬的合作局金昌柱以及公司国内的领导，那么根据我们验收工作安排，我们现在召开我们原占比二玉米面加工厂项目的中期验收会议。由于时间关系和工作安排，那个我们在昨天与那个合作局和金昌处的对接过程中，考虑到今天会议的时间的确定呢，以及这个有限的会议时间，我们提前召开了这个我们验收组以及参与单位的一个预备会，把截止目前完成的工作的情况呢，也做了一个梳理和内部通报，以期呢为这个参建单位提前争争取整改和完善的时间。 • 发言者 1 01:08 那么根据我们之前的计划和安排，由我来代表这个一会呢由我来代表验收组吧，截止目前工作的开展情况和存在的问题做一个简单的汇报和评述。然后呢请我们的管理组以及技术组就存在问题的逐渐整改情况做简单的做一个汇报。那么会后呢后面呢再请我们有关的领导做指示，那么会后呢继续安排我们剩下的一个点的这个现场验收工作。那么截止今天为止呢，我们以这个已经完成了卢萨卡点除弹料加工调试以外的所有唉验收工作。蒙蒙泽这个点呢已经完成了， • 发言者 1 02:12 这个应该说是全部的一个一个验收工作，就是提前，因为正好我们的带料调试的厂家工作人员也在现场，尽管我们这次台带料调试工作是按照原计划是列入下一期来，重新开展验收，但是正好利用前方的资源呢，我们的验收组以及技术组，顺带把整个流程试生产，包括外方人员的操作手，整个产品的生产过程过了一道，那么现在呢应该谨慎，就是我们某皮卡点的现场验收工作，因为某皮卡点的内业工作呢，内业资料呢是提前拿到了卢萨卡这个点，唉由于时间关系呢，我刚才说了我们的议程就是要尽量简化，把问题会议的问题解决了，所以呢现在由我来代表检查组验收组就我们截至目前的工作开展情况做一个简要的汇报。 • 发言者 1 03:33 根据对外援助成套项目，依据项目参建各方的合同以及相关规范标准，我们检查组于实际上是提前在18号19号就提前介入了项目的前期这个摸排和了解工作。那么我们于20号召开了首次会议，紧接着了安排了这个目前为止两个点的检查验收工作。那么从工作的方式场景来说呢，我们是分为了内业检查和外业检查两个方面。从专业的角度来分了这个建筑工程安装工程和设备这个机电设备这个专业方向的工作。下面呢我就简单就这几个方面的检查情况给会议以及各位领导做一个汇报。 • 发言者 1 04:35 内业方面呢我们主要是管理组技术组基本门够按照项目合同从开工到过程中组建整个项目的执行团队。并且按照这个相应的流程和程序开展相关工作。那么截止目前呢，由于受疫情及项目特殊情况的影响，目前主要人员呢还基本能保证，都在前方岗位上，唉包括我们的验收工作推迟，这个疫情确实有一些变化，能满足目前工作验收和后续工作的需求。我想这个是履约的这个人员组成情况。第二大部分呢就是有关流程性程序性和这个管理文件和这个管理办法的编制和执行。 • 发言者 1 05:47 那么项目执行团队能够按照有关的合同及相关规范和标准，针对本项目编制有关施工组织计划管理计划，还有相关的实施细则以及各项专项预案，分别从工程质量安全环境治愈健康以及合同管理实验检测等方面，开展相关工作。那么我们检查验收组呢也是根据工作情况分组和分时段对项目执行过程中的有关的内业资料，就是程序性文件执行检查和整改闭合管理这样一个流程呢进行了资料查与。和现场抽检以及问询和交流。那么了解了整个项目在供工程执行过程中的一个管理流程和相关资料的收集整理，以及项目各工艺工序检验和审批的一个流程。 • 发言者 1 07:09 目前为止呢基本评价为满足项目的有关标准和规范的要求，嗯第三一个内容呢内容资料主要是配合外衣抽检，查阅工程质量检查验收的控制性文件。就是过程性的检验人员，包括工艺工工序的报检及实验检测资料。那么项目执行过程中，施工单位就是技术组和管理单位能够严格按照项目从开工到工艺工序的流程，完成和完善过程中的每一个工序的检查质检报检和验收。评定这样一个程序，那么相关资料呢也按照分类和与这个工程组成这个检验批这些相匹配的收集和整理，这个是内业之内的第3个方面。 • 发言者 1 08:21 外业检查外业检查呢也主要是分第三一个呢主要是机电设备的调试运营，包括安装后的调试。建筑部分呢就是由于项目比较分散，当然目前我们母批卡项目还没去，就对卢萨卡现场的这个厂区以及蒙泽厂区的建筑部分的检测呢，从因为作为竣工验收组呢是成果性交付的验收，那么主要是通尤其是过程性的很多隐蔽性的工程呢只能通过查阅文件。那么现在还能检测的东范围呢，我们根据施工单位的质检和管理单位的这个抽检的这个评定的频率呢，按照规范和标准呢，在全方位和全领域的一定的百分比的量上来，我们抽检了和量，测了现场可以操作的一些过程一些范围。 • 发言者 1 09:36 目前来看呢整个项目是其中呢也有一些做的比较好的。首先呢在原材料的使用上，包括蒙卓在内的主要建筑工程，除了国内采购出口的这个建筑材料，有完全根据合同根据这个履约的要求，集中从国内采购发货到现场有外来很多主要的这个主材，包括预制构件年广场地砖都是从卢萨卡大规大规模的成建制的有一定质量管控体系的。其中这个供货单位呢也是我们在这边原来这个合作平台里面的单位集中预制采购，从200多公里以外拉过去的，所以呢整个项目的这个内在品质通过查验资料外在表观通过现场抽检和检测，那么应该说是达到了一个很好的标准。 • 发言者 1 10:38 由于这个资料完整的整理结果没出来，今天我们也不下最后的结论。我想这个是建筑部分。建筑安这个安装部分呢主要是一个是以钢结构为主的，还有呢就是设备的安装。那么同样钢结构的这个部分呢，嗯所有材料应该都是从国内定制发货到现场，因为从设计开始我们的有一些材料当地就采购不了，那么从施工工艺吊装的这个精确度，到我们现场查看的一些这个外观质量等等，应该都是满足规范和标准要求。因为我一会儿针对一些不足或要完善的，我单独再来汇报，那么这是这个是钢结构部分。 • 发言者 1 11:39 设备部分呢就是执行单位，就是技技术组的执行单位与国内的中粮西安设计院以及它的相关厂家签订了应该是专项的这样一个供货合同，根据过程的了解以及厂家的交流，包括查阅资料呢，本项目的设备呢是参照了中国的标准集合，因为当时设计团队也派人到前方来了，解了这个加工厂的原材料供应的情况，包括这个已取了玉米的样，然后呢也根据就是我们输出的从输入和输出的角度，从输从输出的这样一个产品，分类分为三类这样一个标准和要求。 • 发言者 1 12:36 应该算是专门定制了这么编制了有关这个设备并按照这样一个专项技术和规范来生产。啊。生产了这样三套的这样成套设备。在下这个设备进场和安装过程中呢，厂家也一度高峰期拍了十几名。厂家工作人员到现场指导和安装，那么目前为止流到前方的厂家的团队，还有市民，加上我们技术组和这个管理组，驻厂的这样一个专家成员，唉对整个就是以蒙泽这个具备条件这个点，的整个调试试车调试试运行弹料加工，产品整个流水线还在继续培训和交底。 • 发言者 1 13:30 那么就在昨天我们离开现场以后呢，应该是今天相关管理人员和技术人员，现场人员已经到达现场，继续对这个点进行一个就是全流程的这样一个生产调试。所有的验收组呢对工艺设备呢进行了逐台的复核，复核设计和规范以及施工图纸的要求，并对工艺设备进行了投料试运行。刚才说了，因为这个点正好条件都具备，工艺设备呢运行正常，工艺流程满足生产要求，产能也能符合设计指标。因为那天我们也是打着表计算了这样一个产能的。这个生产产能。 • 发言者 1 14:22 唉安装正确运行正常现场进行了相关的检测。机电设备的安装和国家和这个都能达到。国家质量检验的有关标准，这个是关于机电这一块。嗯这个呢是整体的一个评价。那么针对以上这三块呢，我们也提出一些整改项的要求。第1项就是关于人员履约和这个合同履约的这个专项来。由于受疫情影响以及本项目作为epc项目的特点，唉那么包括从我们的管理组到技术组，尤其是管理组是涵盖了这个应该说是是涵盖了是因为是与设计方进行的这样一个联合中标项目，而且我们是在签约以后呢是先要完成设计。 • 发言者 1 15:24 工作，唉加上呢三个点受以及受中期又受到这个疫情的影响。按照合同和履约呢，我们检查组的过程中呢，可能对个别同志的进出场时间以及护照和这个呢还需要施工部和管理组进一步的来完善和提高，以期让我们在整个验收报告的时候呢能够达到一个闭合条件。嗯因为其中呢也有个别岗位的人员，因为各种原因有这个有这个申请，换这个申请这个更换的这样一个流程，那么请两个参加的部门呢，我们会后形成验收报告之前，也要完善相关的这样一个把这个资料的整理把这个闭合。我想主要的呢是这一块。 • 发言者 1 16:28 另外呢就是作为因为呢我们投标和合同文件的时候对数量也有要求，可能我们之前在检查验收的时候，这个数人员统计数量，尤其是技术组，对包括厂家的服务人员和一些人员呢可能没有计算进去，这个呢下来完善一下，因为他作为团队人员，你们是EPC项目嘛，所以呢应该也是可以计入的。另外呢就是个别特种人员的证件和那个在有效期上，因为可能出国以后国内的这个嗯延期或者说他们更新没有及时到位，这个呢下来也请我们执行单位跟国内做人力资源做一个对接，是不是延期了，没有及时更新还是怎么了，把这些东西完善。 • 发言者 1 17:23 我想主要履约方面主要是这个原因。关于内业资料，包括我们的质检资料，包括我们的这个流程性文件和过程性检查文件，就是程序性文件。程序管管理文件和过程检查文件以及整改唉就内部检查整改的这个文件，唉应该说都有了，在各个方面就我刚才提到的主要控制范围都有，唉但是呢在分类整理以及少量的这样一个质检和管理机构的验收上来，唉的签字的规范性和一些分类整理，还需要进一步规范和完善。因为按照时间的安排呢，我们认为目前为止呢整个项目的竣工文件应该是达到了一个基本组卷。 • 发言者 1 18:21 和成册的一个要求，但是经过跟合作组根根据执行单位的交流呢，全部集中到罗萨卡点来，但是呢其中有一个点因为又太远，又把它集中过来，就还是在分散这个过程。所以呢验收后或者验收这段时间以后呢，请我们执行单位抓紧按照这个项目执行的有关标准和规范，包括国家的有关规范，来及及时把这个资料汇总到卢萨卡，分类成册，按照竣工文件的这个这归档要求来及时组卷。我们因为我们正好验收组也在前方嘛，哪怕我们正式验收完了，有需要的话找到我们也会按照这个验收的流程和标准，去补充和完善这方面的工作，跟大家一起核实。 • 发言者 1 19:19 其中包括竣工图的嗯那么就接下来就现场，现场呢就是还是这三个板块嘛， • 发言者 2 19:41 建筑板块呢就是我们经经过我们的验收和现场查看呢，唉基于项目的整体品质和包括投资的这个 • 发言者 1 19:52 这个这个内控目标，整个项目应该说存在缺陷的地方还是非常少，但是呢难免也有一些小的地方，包括涉及到这个时间也久了，我们有的点可能因为原计划的验收时间是在几个月以前，那么我们在正式交付之前呢，对一些有局部损伤的，包括这个膜这个装饰装修的位置，唉这些要做一些检查，包括卫生也要打扫。最后移交给外方。那么特别是马上雨季来了，也要再次检查我们整个厂区，包括办公区的这个排水。不管是我们那个屋面排水还是室外通道方面有没有阻塞，这些要做一次最后的清理和排查工作。 • 发言者 1 20:50 嗯在就是这个因为按照合同呢，整个园厂区的绿化工作是交给站方自己来执行的，我看我们也做到了基本一些培土这些要求。那么有一个点这这里也不不得不提一下，就是我们在某个厂区呢发现这个有少量的应该是在非主要通道范围内的这个混凝土路面呢，有少量的开裂现象。那么这个呢也可能是跟当时的这个基础碾压和这个混凝土扬升的这个过程有关，那混凝土这个路面的开裂纹这个呢也是个通病。但是呢我就提醒施工方在处理这个裂纹的时候要认真要小心。 • 发言者 1 21:47 我看了一下可能当地工人做了一下，但是效果不好，要把它重新清理，用防水的这个来全部封管，确保这个裂纹不再受到水的侵蚀，全部封闭掉，这个我想主要是建筑部分。安装部分呢我们看了就是大的构件结构型的安装是完全没有问题的。那么但是局部一些，包括我们昨天在设备现场看到，这个监控的那个管线有少量的就是因为那个设备启动的时候它有震动嘛，我们在监视那个有一个加工设备那个转子，它是应该是通过转速转速来唉采集一些数据，那个管管线的接头处有脱落，这个呢伴随着设备的调试呢，也请我们施工组要全面的检查，一个是保证这个的有效性，另外一个呢是安全性，刚才说结构性应该是没有问题，但是小的东西也可能引起机械的故障。 • 发言者 1 22:57 另外呢就是嗯我们到那个屋顶和那个嗯储料仓的顶部的那些廊桥的那这些都做了查看。也有两个问题，一个是罗萨卡这个点呢，就是我们在加工的那个提升，桶往上的位置，可能赞比亚的雨比较特殊，不光是雨量比较大，而且呢有时候风比较大，那个雨水完全是有可能倒灌的形象。所以呢可能接下来以后请你们检查一下，包括即便是按照原设计施工的，如果说不足以解决这个水的问题，那么要考虑因为那个不大，只有几二二32、30见方这样一个通道往往上所以把那个位置要考虑一下， • 发言者 1 23:52 可能传统的我们做法就跟国内一样一个烟囱一样，然后上去以后有个盖子，但是水要倒管，一个是增加，这个覆盖的面积或者什么，通过技术措施把这个问题解决掉。那么还有呢就是刚才提到的那个我看了一下有那么几个点，可能要稍微加密一下，你比如说卢萨卡这个点，我们走到廊墙的最端头，嗯。在横向上在分布只有三个竖条，剩下全是横条。那么我们建议不管设计师有是没有，中间再加两个竖条，总从视觉上感觉会更加安全一些。那么包括这个那些地方，那那些位置呢使用频率不高，但是呢一旦要使用的时候，它就是为我们检查也唉这个检这个是巡检和这些维护的工作人员提提供安全保障，所以呢这一块也请我们后面再做一次检查和完善。这个是我想说的现场需要整改的几个点。 • 发言者 1 25:05 当然如果磨皮卡我们现场在发现什么问题呢，及时会跟这个参建单位沟通。最后一个需要通报呢就是关于财务部方面的使用，那么我们财务验收专家呢也对本项目的财务的资料进行了查阅，也跟他们的相关人员真的沟通。本项目的这个财务从账户的设置，资金的往来，银行开户等等这样一个过程呢，完全符合财务处理的有关规范和标准。因为我们也知道中基公司呢在这儿也是也算是第1个项目嘛，也是唯一的一个项目，所以也没地方去挪用资金，所以这一点呢也是做得比较好了。 • 发言者 1 25:56 由于时间关系，我们这个资料的整理和这个通报的内容不尽完善，那么好在我们的过程中呢也及时跟相关单位做了沟通和检查完以后内业整理的时间呢逐步来完善和整理这样一个检查验收工作中遇到的问题。刚才我讲了作为竣工验收这样一个环节呢，更多的我们是成果性交付验收。那么过程性管理除了依托我们有经验的承包商的质检体系，加上我们这个联合中标的管理单位的这样一个规范标准的这个验收过程来把关以外呢，我们还引入了中期验收的这样一个过程，应该说对项目的过程性执行呢都是有所管控。 • 发言者 1 26:43 那么执行过程，尤其是对成品交付，从功能和品质上做一个最终的评价。目前已经近期的工作了，我们感觉到还是很不错的能满足规范和标准要求。当然最终的评审结果呢还要看我们最后一个点的工作开展完，各个工作组再来汇总相关的信息，我们最初做最后做出一个评价，时间关系呢我这的汇报先到这儿。下面呢我们请这个管理组田组长这边，就我刚才说的问题简单也说一说你们因为我们这有些问题是在检查过程中就已经提过了，这几天的一个几一个符符合闭合，整改情况。嗯。 • 发言者 3 27:46 刚才这个王总提的这些问题呢，就是说我们马上在会后呢会根技术组这边一一起把这个问题呢再细化，再再检查。最后呢我们就说这个在布置一个这个通过进行一个方案的处理，最后把这个这些问题呢最后把圆满的解决掉。好， • 发言者 1 28:14 那我们请技术组龚总这边还是你们组长，有龚总那来也可以，你们俩谁都可以过来说吧，好。 • 发言者 4 28:22 这个尊敬的合作局领导，经商处领导，还有验收组各位专家，针对呢这个验收组专家检查出来问题，我汇报三点吧。第一第1点关于人员履约和合同履约的，这里面涉及到人员的统计和护照的统列的统计。呢我们现在已经在开展这项工作，因为随着这个验收过程嘛，我们有些后台的同志国内同志我们也在加紧的把这收集所有参与我们项目到我们现场的人员的这个护照证书1、1收集，第2点是关于内业资料，我们一定严格按照验收组专家的要求及这个援外援外项目执行手册管理办法的规定，在验收完成第一时间第一时间将三个厂区的资料全部汇汇总于卢萨卡，包括竣工图进行分类汇总，分类组卷及编码。 • 发言者 4 29:16 第三一点关于现场实体的这个整改，我们现在编制，其后我们严格按照这个方案编制要求进行逐一整改和落实，谢谢。 • 发言者 1 29:38 好的，我们现场的汇报工作就这样，我们现在请嗯请先请金山处的领导还是做一个对我们这个工作做一个评价和指示。好的， • 发言者 5 29:56 谢谢王总，咱们听得见吗？ • 发言者 1 29:59 唉听得见。 • 发言者 5 30:02 好的，谢谢咱们验收组的这么辛勤的工作，然后也谢谢龚总和田组长，然后进行了一个补充的汇报，我这边没有什么特别要说的，就是再麻烦大家辛苦几天，然后顺利的把咱们验收工作完成，按照咱们经合局的领导的具体指示就好，然后谢谢大家。 • 发言者 1 30:21 好的，谢谢。那我们先现在请合作局的领导和我们做讲话。 • 发言者 6 30:31 没有不叫讲话了，就是发表1点这个咱们我这我们这边的建议吧，刚才听了验收组的关于目前这个咱们两个厂区验收的这个汇报，总体感觉情情况还是比较好的。存在的问题呢也不太多，主要集中在这个合同履约以及这个施工资料方面。呃这个关于这个资料方面呢，还是请这个咱们相关方施工单位以及管理组尽快的能够补充相关的资料，跟尤其是跟验收组做好这个沟通和对接，争取就是不要再存在这个遗留未决事项，因为我们这个之前也有过这种情况，就是这个验收报告。都已经报到我们这儿来了。 • 发言者 6 31:19 然后我们在就是在了解一些这个问题的时候，跟各方在沟通的过程中发现这个确实有一些问题，现场几方和验收组并没有沟通清楚，导致这个验收报告的有些表述呢也不是特别的准确。所以说咱们在争取在这个阶段，就是把所有的问题以及未决事项都跟验收组该提供资料的提供资料，该沟通的沟通，咱们争取就是不要这个出现这个遗留的和未决的这种事项。然后第2个就是关于这个刚才提到的蒙泽蒙蒙泽厂区有一个就是混凝土路面，存在开裂现象是吧？ • 发言者 6 31:59 对现场的这个管理组和总包单位还是要重视一下。因为这个这个施工完完成没多长时间，然后就出现了这个开裂。具体还是要分析一下它的这个原因。特别是结合赞比亚当地的这个气候特点，要制定一个就是切实可行的这个整改方案。这个事情我觉得管理组和总包单位共同吧共同会同共同研究。制定一个科学合理的这个整改方案。因为说如果说这个项目移交给外方，移交给外方投入使用之后，你很快如果又再出现这个路面开裂的话，这个对外影响也不太好。 • 发言者 6 32:50 对吧？现在不知道是什么原因，是他当地气候的原因，还是说咱们施工施工工艺的原因，还是说这个原料的这个材料的原因。现在因为现在刚才也没有说到特别细，所以这个成因我觉得现场各方还是要分析一下这个到底是什么原因，然后需要采取什么措施去解决，避免以后再出现这样的问题。 • 发言者 1 33:18 这个下来我们这边会会同几个单位，再把我们过程中收集到的情况做一个专题的技术研究，因为位置呢也是比较偏的在角落里面。另外一个呢面积也不是很大，如果嗯嗯最不利的情况，我们就是把它弄了来个这个绝不影响整个项目的这个按照验收组的要求，我们也希望不能因为这个来影响整个项目的最终评价，下来我们会专题再跟他们做一个对接，因为我们是分组的，所以呢昨天时间也比较紧，回来以后了解不进完善。这边我这边会来负责，追溯这个事情。 • 发言者 6 34:06 所以你就是现在主要是分析一下这个问题的原因在哪，因为现在可能出现开裂的可能只是很小的一部分，你很小的一个面积也有可能其他的这个部位还没有反映出来。这个问题就表象还没有反映出来，是不是也存在这样的隐患，我们现在他就怕这个就是说一旦移交给外方，我们再出现大面积的开裂可能就不太好了。 • 发言者 1 34:31 好的，谢谢 • 发言者 6 34:33 领导的支持好吧？然后就是咱们研究出了这个技术方案之后，还是要尽快整改。争取在咱们这个默思会之前，最迟要在咱们出报告之前要完成整改，咱们在报告里面要形成一个闭环，要给他闭口是的好吧？这个出报告之前完成整改之之后，咱们验收组还要进行一个复核。嗯嗯。然后对最后一个就是说，因为这个项目确实这个工程实体完工已经挺长时间的了，因为是这个带料调试一直没法进行，所以验收咱们就推后了，刚才咱们验收组也提到了，因为这个时间有点长，所以有些地方可能这个成品保护呀这个也有疏忽的地方吧是吧？ • 发言者 6 35:17 咱们在这个交给外方之前还是要继续做好成品保护，有一些有破损或者有这个这个什么地。方要做好这个及时的做好这个修补吧。好吧，我就这几点，我们就这几点意见。 • 发言者 1 35:43 好的。谢谢那个金昌住合作局领导对我们工作的一个只是和下一步的工作的一些意见和建议。我们那个公司国内林总你那儿有没有跟大家说一下工作做个指示。林总你那边听得到吗？可能。来了。唉听得到， • 发言者 7 36:23 不好意思，刚才没开声音，这个你们说的我都听到了，也感谢这个商务部经商局的领导对我们的工作的那个支持，我也没什么更多说的，说就我们要按照这个商务部经常说的那个指示，把这个验收任务原本的完完成，这是第1个。第2个是11根据这个合同的这个那个规章制度，标准来进行那个仔细的验收工作，要仔细来。第3个就是说我们这个我们这个项目应该是在当地的站票的那个一个民生工程，所以说我们在验收过程当中可以尽可能多提醒当地的那个那那些用户的一些建议。 • 发言者 7 37:05 第4个就是说那个刚才这些这提到这些问题，就希望这个参加单参建单单位要重视，特别是那个商务部领导提出的要随时那个要保持。是那个监测吧。第4个就是说这个我们因为我们公司是在站标识是有几十年的那个历史，所以这个请那个商务部经常就要放心，我们这个验收组尽管可能工作时间是比较短时间或者十几天，但是我们一直会在那边，如果有什么问题的话，参政单位可以学习跟我们那个现场专家联系，有任何问题我们可以协助那个参政参建单位一起来。 • 发言者 7 37:52 来做。可以承诺。那个最后一个就是那个安全问题，希望大家那个在这个验收过程当中那个这个安全这个除了这新冠这以外，还有这个交通安全，那么现在赞比亚那边是雨季大雨季了，你们可能那个姆皮卡那边还没去吧，那条路我知道我去过很多趟，应该是那个路况不是很好，所以你们如果要下去的话，应该一定要注意那个安全好吧？唉我就做我就讲这些，谢谢大家。 • 发言者 1 38:21 好的，谢谢林总。好，我们最后呢我这儿利用那个结会的时间呢补充一个问题，因为首次会议时提到关于这个不可预见费的使用和具体符合的一些证据，我们从检查中呢也看到了这个本项目有动用不可预见费的情况，我们的专家组呢也跟施工单位做了一些沟通，可能在一些内容上还要进一步完善和来这个把资料收集整理也清楚一点，而且呢跟这个因为不可预见费的原则上是在原合同原设计这个原投资控制的基础上，要增加动用这个费用，所以呢有关的依据证据和数据呢都要必须做到充分无误。 • 发言者 1 39:17 这个呢也还会遇到这样的问题下来了，我们会利用后续的时间把这项工作也做专门的对接好，最后呢也得感谢我们这个就是国国家援外局，还有经参处给了我们验收组这样一个学习的机会。就是经过这两三次的验收，我还是深深的感触到这项工作的重大意义，不仅是在经济领域，也代表这个两个国家的友谊，更多的也是展现中国制造中国的这个外交以及民族复兴的这样一个国际影响的一个过程。所以呢也也要感谢为这个项目做出努力和奉献的这个两个参与单位， • 发言者 1 40:15 其实不止两个了，就是合同上的管理机构和技术组以及相关的同事，我们到现场来发现，很多同事已经两年多三年没回家了，还是在继续的坚守在这个岗位上，尽管现在这个形势比较特殊，疫情以及国际经济形势的影响，但是我们有理由相信这个好的这个会到来，那么我们检查组和相关工作人员呢也有信心将剩余的工作刚才林总也提了要求，因为这个点也是最远那个点。会后呢我们将及时安排接下来的工工作情况，也会通过适当的渠道跟我们后方的领导们这个汇报我们整个工作的进展情况，感谢大家。 • 发言者 1 41:07 因为时间关系，我们正式的会议看就到这儿了吧，领导们还有什么指示的没？嗯 • 发言者 7 41:27 没有。 • 发言者 1 41:28 没有了，国内我们合作局领导那边还有什么交代的吗？没有，我们就先散会了。因为我们可能还得留下来安排后续的工作。现场参会人员还能留下来。好， • 发言者 7 41:48 大家辛苦下面。 • 发言者 1 42:09 喂线上的国内领导会议还有什么要求吗？唉。 • 发言者 6 42:16 我们还没有要求了，在可能信号不太好，刚才一直没有听到您讲话。 • 发言者 1 42:24 也没什么特别的内容。我就补充一下关于那个不可预见费的使用，我们这边因为首次会议专门提到了吗？我们其实验收组已经开展了这个工作，我们接下来也会继续跟踪和完善这方面的内容，因为他们也有动用不可预见费的情情况。唉第二第这后面说了就是因为这个项目的重要性嘛，目前又在这种特定条件下，我们整个前方工作组将依据有关规则和方法标标准和规范，在后方的指导下，有信心把后续的工作按计划推进和完成，也请领导们放心。嗯 • 发言者 6 43:10 好的，更多的情况咱们可以放在末次汇报，包括不可预见费什么的，放在末次汇咱们可以再进行一个沟通。 • 发言者 1 43:18 是的。 • 发言者 6 43:22 嗯嗯行，刚才那个因为听到林总也说了，因为下一个点咱们验收组马上就要去某皮卡那边，因为这个路途也比较遥远，交通也不好，还是希望咱们验收组一定要注意这个交通安全以及那个这个防疫。的疫情的这个防控，好吧？咱们争取安安全全平平安安的回来，好的完成顺利的完成任务。 • 发言者 1 43:47 好的。 • 发言者 6 43:49 那我们那个好勒，我们这边没有这个 • 发言者 1 43:52 我们整体会议就先开到这儿，因为我们现场组还要留下来讨论后续工作的安排。 • 发言者 6 44:01 好的。 • 发言者 1 44:03 好，谢谢大家。 • 发言者 7 44:06 好的好的，大家保重 • 发言者 6 44:08 唉行。 | D8: # 项目概况 本次会议为原占比二玉米面加工厂项目的中期验收会议，验收组已完成卢萨卡点除带料加工调试外的全部验收工作，蒙泽点验收工作已全部完成，某皮卡点验收工作尚未开展。会议重点通报了项目在人员履约、内业资料整理、现场实体整改等方面存在的问题，并对后续验收工作安排进行了部署。 # 进度追踪 | 模块 | 进展 | 状态 | | --- | --- | --- | | 项目验收 | 已完成卢萨卡点除带料加工调试外的验收工作；蒙泽点验收工作已完成；某皮卡点现场验收尚未开展 | 🟢正常 | | 人员履约 | 管理组和技术组人员基本到位，但个别人员进出场时间、护照信息及特种作业人员证件有效期存在不完善情况 | 🟡低风险 | | 内业资料 | 项目内业资料基本齐全，但存在分类整理不规范、签字不规范等问题，需进一步完善组卷工作 | 🟡低风险 | | 外业检查 | 建筑板块发现少量混凝土路面开裂、廊桥结构安全性等问题；安装板块发现监控管线接头脱落等细节问题 | 🟡低风险 | | 财务验收 | 财务资料符合规范要求，账户设置、资金往来等流程完整 | 🟢正常 | # 风险预警 | 风险/瓶颈 | 等级 | 影响 | 责任人 | 应对计划 | | --- | --- | --- | --- | --- | | 某皮卡点验收工作尚未开展 | 🟢正常 | 项目最终验收结果需待该点验收完成后确定 | 验收组 | 会后立即安排现场验收工作 | | 人员履约相关资料不完善 | 🟡低风险 | 可能影响验收报告的闭合性 | 管理组、技术组 | 会后形成验收报告前完善相关资料 | | 内业资料分类整理不规范 | 🟡低风险 | 可能影响竣工文件的归档质量 | 管理组、施工单位 | 按项目执行标准和国家规范及时组卷 | | 混凝土路面开裂问题 | 🟡低风险 | 存在移交后继续开裂的风险 | 施工单位、管理组 | 分析成因并制定科学整改方案 | | 廊桥结构安全性问题 | 🟡低风险 | 可能影响巡检和维护人员安全 | 施工单位 | 加密结构设计并进行整改 | | 不可预见费使用依据不充分 | 🟡低风险 | 可能影响费用使用的合规性 | 施工单位 | 后续时间进行专门对接完善资料 | # 后续计划 *核心交付物*：完成某皮卡点现场验收工作，形成完整的验收报告 *验收标准*：确保所有整改项完成闭合，内业资料组卷完整，外业检查无遗留问题 *关键时间节点*：会后立即安排某皮卡点现场验收工作 *资源协调需求*：需协调前方验收组专家持续参与后续工作，确保验收质量 *特别提示*：需注意赞比亚雨季期间的交通安全及疫情防控措施，确保验收工作顺利进行 | E8: 4.5 | F8: 5 | G8: 5 | I8: =(E8+F8+G8)/3 -> 4.8333333 | J8: 1.1：部分风险等级及影响由原文推断得出，不算完全的错误和幻觉 | K8: 会议背景 根据对外援助项目验收工作安排，召开玉米面加工厂项目中期验收会议。验收组已完成卢萨卡、蒙泽两个实施点的现场检查与内业资料核查，整体工程满足规范要求，设备试运行正常，产能达标。会议通报了合同履约、内业资料整理及现场施工等方面存在的问题，并明确整改要求和后续工作安排。 验收工作进展汇报（发言人1） 总体进度 卢萨卡点：除带料加工调试外，其余验收工作已基本完成。 蒙泽点：全部验收工作已完成，利用厂家人员在场契机，同步完成了全流程试生产及外方操作培训。 MP卡点：尚未开展现场验收，为后续重点任务。 验收方式与组织 检查组于18-19日提前介入摸排，20日召开专题会议部署任务。 工作分为内业与外业两大部分，涵盖建筑工程、安装工程、机电设备三大专业方向。 内业检查情况 合同履约：管理组和技术组基本能按合同组建执行团队，主要人员均在前方岗位，受疫情影响有所延迟，但整体满足当前工作需求。 程序性文件：参建单位编制了施工组织计划、管理计划、实施细则及专项预案，覆盖工程质量、安全、环境、职业健康、合同管理等领域，流程完整。 过程资料管理：施工单位能严格执行工序检查、质检、报检、验收评定程序，资料分类整理与设计图纸匹配，符合标准要求。 外业检查情况 建筑工程 主要建材（含预制构件、地砖等）由国内集中采购发运，质量可控。 现场抽检显示建筑品质良好，表观与内在质量达到标准。 安装工程 钢结构材料全部国内定制发货，吊装精度与外观质量符合规范。 机电设备 设备由技术组联合中粮西安设计院及厂家专项定制，参照中国标准并结合当地原料特性设计。 厂家曾派十余人高峰支援，目前仍有4名技术人员驻场。 在蒙泽点完成投料试运行，工艺流程顺畅，产能数据达标，运行正常。 存在问题与整改建议 人员履约问题 因疫情及EPC项目特点，部分人员进场时间滞后，个别岗位存在更换申请未闭环。 技术组统计中未完全纳入厂家服务人员，特种作业人员证件更新不及时。 要求会后完善资料闭合，确保验收报告时人员信息完整有效。 内业资料问题 纸质资料、程序文件、过程检查记录基本齐全，但分类整理不够规范。 因验收时间未定，资料仍分散存放，未集中归档。 要求验收完成后尽快将三个厂区资料汇总至卢萨卡，按竣工文件标准分类成册，完成竣工图绘制与签章。 现场施工问题 建筑方面： 少量非主通道混凝土路面出现开裂，可能与施工碾压或养护有关。 要求重新清理裂纹，使用防水树脂或沥青封灌，防止雨水侵蚀。 雨季将至，需全面排查厂区排水系统，清理屋面及通道堵塞。 安装方面： 监控管线接头在设备振动下有脱落现象，需全面检查加固。 卢萨卡提升桶位置存在雨水倒灌风险，建议增加遮蔽面积或采取技术措施。 卢沙海廊桥端点防护竖条稀疏（仅3根），视觉安全感不足，建议加密至5根以保障巡检安全。 财务管理情况 财务专家查验账户设置、资金往来、银行开户等，均符合财务规范。 中基公司本地唯一项目，无资金挪用风险，管理规范。 其他事项 不可预见费已有动用情况，相关依据和证据需进一步补充完善，确保支撑充分。 验收组将持续跟进，协助参建单位完成整改与资料闭合。 整改响应汇报（发言人3） 人员履约与资料统计 正在收集所有参与项目人员的护照及证书信息，包括国内后台支持人员，确保统计完整。 内业资料归集 承诺在验收完成后第一时间将三个厂区资料汇总至卢萨卡，并按援外项目管理办法进行分类归档。 现场问题整改 已安排技术人员逐项梳理不合格项，编制整改方案，严格按方案落实整改。 合作局领导意见（发言人2） 资料沟通闭环 强调验收阶段必须与验收组充分沟通，避免遗留未决事项。 曾有案例因现场各方沟通不清，导致验收报告表述不准确，本次务必杜绝。 混凝土路面开裂问题 出现开裂时间较早，应高度重视，分析成因（气候、工艺、材料）。 要求管理组与总包单位共同研究，制定科学整改方案，防止移交后大面积复发。 最迟在验收报告出具前完成整改并形成闭环，验收组需复核确认。 成品保护 项目实体完工已久，因带料调试推迟导致验收延后，部分成品可能存在破损。 移交前须加强成品保护，及时修补受损部位。 公司国内领导指示（发言人4） 验收原则 严格按照商务部指示和合同标准完成验收任务。 细致开展验收工作，确保质量。 用户反馈 本项目为当地民生工程，验收过程中应多听取外方用户建议。 质保与监测 对路面开裂等问题属质保范围，需持续监测。 后续支持 江西国际承诺长期支持，现场专家将持续驻守，参建单位可随时联系协助解决问题。 安全提醒 注意新冠防护及交通安全，尤其前往MP卡点道路条件差，雨季行车风险高，务必谨慎。 关键决策与共识 整改闭环：所有发现问题须在验收报告出具前完成整改并经复核，形成闭环。 资料归档：三个厂区资料须在验收完成后立即集中至卢萨卡，统一分类归档。 不可预见费核实：相关动用依据须补充完善，确保数据充分无误。 安全管理：高度重视雨季交通与防疫安全，确保验收组人员平安完成任务。 全局行动项汇总 AI洞察 项目整体执行质量较高，尤其设备定制化程度深、运行表现良好，体现“中国制造”输出能力；但细节管理（如资料归档滞后、成品保护疏忽）反映出对“交付闭环”的重视仍需加强。 路面开裂虽为局部问题，但领导层高度关注其潜在扩散风险，反映出国别项目对“移交后口碑”的敏感度远高于一般工程。 多方强调“沟通闭环”，暴露出以往援外项目中“验收组—参建方—后方”信息链断裂的共性痛点，本次会议试图通过前置沟通机制予以规避。 待办 参建单位补充完善不可预见费使用的依据证据和数据，确保资料充分无误并与验收组对接 验收组在末次会前完成对整改项的复核，确保所有问题闭环处理 管理组和总包单位共同分析蒙泽厂区混凝土路面开裂原因，并制定科学合理的整改方案 在卢沙海点廊桥端点横向防护通道加密竖条，提升巡检与维护人员的安全保障 对卢萨卡加工厂提升桶上方通道雨水倒灌问题进行技术评估并采取增加覆盖面积或其他技术措施解决 施工组全面检查设备监控管线接头，确保设备调试过程中管线连接牢固、安全有效 施工方对混凝土路面开裂处进行彻底清理并使用防水树脂或沥青封灌处理，防止受潮扩展 执行单位汇总三个厂区的内业资料至卢萨卡并分类成册，按照竣工文件归档要求及时出卷 管理组和技术组完善人员履约和合同履约资料，确保在验收报告形成前完成闭合 章节 00:00:14 会议开场与议程介绍 会议由发言人1主持，宣布中期验收会议正式开始。介绍了参会单位包括合作局、平台局及公司国内领导，并说明因时间紧张，已提前召开预备会梳理工作进展。本次会议旨在汇报项目中期验收情况，安排整改并部署后续现场验收工作。 00:02:43 验收工作总体进展情况汇报 发言人1代表验收组汇报了卢萨卡点和蒙泽点的验收完成情况，指出除带料加工调试外大部分工作已完成。利用前方资源对试生产流程进行了演练，并介绍了检查工作从18号起分内业与外业两个方面展开，涵盖建筑工程、安装工程及机电设备等专业方向。 00:05:45 内业资料检查情况总结 重点汇报了三方面内业检查内容：一是合同履约情况，管理组和技术组基本满足人员在岗要求；二是程序性文件编制执行情况，相关计划和预案齐全；三是工程质量控制文件核查，施工单位能按流程完成报检和验收，资料整理总体符合标准。 00:06:31 外业检查结果与工程质量评价 外业检查分为建筑、安装和机电设备三大板块。建筑材料多为国内采购，质量管控严格；钢结构和设备均按设计定制，施工工艺达标。设备由中粮西安设计院联合厂家专项生产，现场调试运行正常，产能达到指标，整体工程质量良好。 00:11:31 存在的问题与整改建议（一）：人员与资料管理 指出人员履约方面存在个别岗位人员更换未及时报备、特种作业证件更新不及时等问题。内业资料虽基本齐备，但分类整理不够规范，竣工图归档尚未完成，需在验收后尽快汇总至卢萨卡点并完善签字盖章流程。 00:14:25 存在的问题与整改建议（二）：现场施工细节优化 现场发现局部混凝土路面开裂，需用防水材料封灌处理；监控管线接头脱落存在安全隐患；部分厂区排水系统需清理以防雨季堵塞；提升桶位置有雨水倒灌风险，建议增加防护措施；检查通道竖条间距过大，建议加密以提升安全性。 00:19:10 财务与过程管理总体评价 财务验收专家确认项目资金使用合规，账户设置和资金往来符合规范。作为成果性交付验收，引入中期验收机制有效加强了过程管控。整体执行情况良好，最终评价将在最后一个点验收完成后综合得出。 00:21:23 参建单位整改回应与后续安排 技术组代表发言人3回应问题，承诺正在收集人员护照信息，将统一汇总三厂区资料，并针对不合格项制定整改方案逐一落实。验收组将继续跟进闭环管理，确保问题解决。 00:22:29 主管部门意见与工作指示 金川处领导肯定验收工作成果，强调要避免遗留事项，确保验收报告准确。投资局领导特别关注路面开裂问题，要求分析成因并制定科学整改方案，在末次会前完成闭环。同时提醒做好成品保护和安全防范。 00:27:03 公司领导总结发言与会议收尾 公司林总表示将严格落实商务部指示，认真完成验收任务，重视民生工程意义，听取当地用户建议。承诺将持续提供支持，并强调雨季交通安全和防疫注意事项。最后发言人1补充不可预见费使用需完善资料，会议在确认无其他指示后结束。 行动项 负责人 时间节点 完善人员履约资料（含厂家人员、证件更新） 管理组、技术组 验收报告前 三个厂区资料汇总与分类归档 技术组、管理组 验收完成后第一时间 编制并落实现场问题整改方案（路面、管线、防护等） 技术组、总包单位 验收报告前 补充完善不可预见费使用依据 施工单位、验收组 后续对接完善 MP卡点现场验收安排 验收组 会后立即组织 | L8: 5 | M8: 5 | N8: 5 | P8: =(L8+M8+N8)/3 -> 5 | R8: 会议笔记： 项目验收工作进展 已完成算法点和量下一期工作 设备生产按专项技术标准执行 设备进场安装及调试已完成第一流程 项目竣工文件已达到验收要求但因验收时间未定未最终确认 存在的主要问题 人员问题：受疫情影响，个别特种人员资质有效期存在问题 内业质量：质检资料分散，质量不尽人意 现场问题：蒙泽厂区混凝土路面存在开裂现象 财务问题：项目账户设置需核实，不可预见费使用需完善 验收工作要求 按照合同和规章制度标准进行仔细验收 重视当地用户建议，作为民增工程需保证质量 验收过程中注意交通安全和疫情防控 确保验收报告准确，避免遗留未决事项 问题整改安排 人员和合同问题：会后细化检查，加紧收集现场人员护照数据 资料问题：验收完成后第一时间提交三个小时的资料 路面开裂问题：分析原因，结合赞比亚气候制定整改方案，出报告前完成整改并闭环 成品保护：工程实体完工时间长，需做好成品保护和修补工作 后续安排： 会后细化检查人员和合同问题，加紧收集现场人员护照数据 验收完成后第一时间提交三个小时的资料 分析蒙泽厂区混凝土路面开裂原因，结合赞比亚气候制定整改方案，出报告前完成整改并闭环 做好项目成品保护和修补工作 跟踪完善不可预见费使用和核对 验收组注意交通安全和疫情防控 AI建议： AI建议 AI已识别以下会议中未得出结论或缺乏明确行动项的问题，请注意： 未明确路面开裂问题的具体责任方和整改完成时限 不可预见费使用的具体标准和核对流程未明确 项目账户设置问题未提出具体解决方案 分散的质检资料如何集中整理未明确具体措施 验收时间仍未确定，影响项目整体进度安排 内容由 AI ⽣成，仅供参考 | S8: 3 | T8: 4 | U8: 4.5 | W8: =(S8+T8+U8)/3 -> 3.8333333 | X8: 示例：1.1：幻觉“设备生产按专项技术标准执行”“项目竣工文件已达到验收要求但因验收时间未定未最终确认”；1.2 过度总结“质量不尽人意”。2.1 核心遗漏，遗漏内外业检查的具体内容；进展部分缺少细节。3. 由转写错误导致的语句不通顺有点多
